package com.jxphone.b.a;

import java.net.URL;

public final class a
  implements c
{
  private final URL a;

  private a(String paramString)
  {
    this.a = new URL(paramString);
  }

  // ERROR //
  public final boolean a(String[][] paramArrayOfString)
  {
    // Byte code:
    //   0: new 22	java/lang/StringBuilder
    //   3: dup
    //   4: sipush 128
    //   7: invokespecial 25	java/lang/StringBuilder:<init>	(I)V
    //   10: astore_2
    //   11: aload_1
    //   12: arraylength
    //   13: istore_3
    //   14: iconst_0
    //   15: istore 4
    //   17: iload 4
    //   19: iload_3
    //   20: if_icmpge +50 -> 70
    //   23: aload_1
    //   24: iload 4
    //   26: aaload
    //   27: astore 16
    //   29: aload 16
    //   31: arraylength
    //   32: iconst_2
    //   33: if_icmpne +31 -> 64
    //   36: aload_2
    //   37: aload 16
    //   39: iconst_0
    //   40: aaload
    //   41: invokevirtual 29	java/lang/StringBuilder:append	(Ljava/lang/String;)Ljava/lang/StringBuilder;
    //   44: bipush 61
    //   46: invokevirtual 32	java/lang/StringBuilder:append	(C)Ljava/lang/StringBuilder;
    //   49: pop
    //   50: aload_2
    //   51: aload 16
    //   53: iconst_1
    //   54: aaload
    //   55: invokevirtual 29	java/lang/StringBuilder:append	(Ljava/lang/String;)Ljava/lang/StringBuilder;
    //   58: bipush 38
    //   60: invokevirtual 32	java/lang/StringBuilder:append	(C)Ljava/lang/StringBuilder;
    //   63: pop
    //   64: iinc 4 1
    //   67: goto -50 -> 17
    //   70: aload_2
    //   71: invokevirtual 36	java/lang/StringBuilder:length	()I
    //   74: istore 5
    //   76: aload_2
    //   77: iload 5
    //   79: iconst_1
    //   80: isub
    //   81: iload 5
    //   83: invokevirtual 40	java/lang/StringBuilder:delete	(II)Ljava/lang/StringBuilder;
    //   86: pop
    //   87: aload_0
    //   88: getfield 19	com/jxphone/b/a/a:a	Ljava/net/URL;
    //   91: invokevirtual 44	java/net/URL:openConnection	()Ljava/net/URLConnection;
    //   94: checkcast 46	java/net/HttpURLConnection
    //   97: astore 11
    //   99: aload 11
    //   101: sipush 8000
    //   104: invokevirtual 49	java/net/HttpURLConnection:setConnectTimeout	(I)V
    //   107: aload 11
    //   109: iconst_1
    //   110: invokevirtual 53	java/net/HttpURLConnection:setDoOutput	(Z)V
    //   113: new 55	java/io/OutputStreamWriter
    //   116: dup
    //   117: aload 11
    //   119: invokevirtual 59	java/net/HttpURLConnection:getOutputStream	()Ljava/io/OutputStream;
    //   122: invokespecial 62	java/io/OutputStreamWriter:<init>	(Ljava/io/OutputStream;)V
    //   125: astore 8
    //   127: aload 8
    //   129: aload_2
    //   130: invokevirtual 66	java/lang/StringBuilder:toString	()Ljava/lang/String;
    //   133: invokevirtual 69	java/io/OutputStreamWriter:write	(Ljava/lang/String;)V
    //   136: aload 8
    //   138: invokevirtual 72	java/io/OutputStreamWriter:flush	()V
    //   141: new 74	java/io/InputStreamReader
    //   144: dup
    //   145: aload 11
    //   147: invokevirtual 78	java/net/HttpURLConnection:getInputStream	()Ljava/io/InputStream;
    //   150: invokespecial 81	java/io/InputStreamReader:<init>	(Ljava/io/InputStream;)V
    //   153: astore 12
    //   155: aload 12
    //   157: invokevirtual 84	java/io/InputStreamReader:read	()I
    //   160: istore 14
    //   162: iload 14
    //   164: bipush 48
    //   166: if_icmpne +29 -> 195
    //   169: iconst_1
    //   170: istore 15
    //   172: aload 8
    //   174: invokevirtual 87	java/io/OutputStreamWriter:close	()V
    //   177: aload 12
    //   179: invokevirtual 88	java/io/InputStreamReader:close	()V
    //   182: aload 11
    //   184: ifnull +8 -> 192
    //   187: aload 11
    //   189: invokevirtual 91	java/net/HttpURLConnection:disconnect	()V
    //   192: iload 15
    //   194: ireturn
    //   195: iconst_0
    //   196: istore 15
    //   198: goto -26 -> 172
    //   201: astore 7
    //   203: aconst_null
    //   204: astore 8
    //   206: aconst_null
    //   207: astore 9
    //   209: aconst_null
    //   210: astore 10
    //   212: aload 8
    //   214: ifnull +8 -> 222
    //   217: aload 8
    //   219: invokevirtual 87	java/io/OutputStreamWriter:close	()V
    //   222: aload 9
    //   224: ifnull +8 -> 232
    //   227: aload 9
    //   229: invokevirtual 88	java/io/InputStreamReader:close	()V
    //   232: aload 10
    //   234: ifnull +8 -> 242
    //   237: aload 10
    //   239: invokevirtual 91	java/net/HttpURLConnection:disconnect	()V
    //   242: aload 7
    //   244: athrow
    //   245: astore 7
    //   247: aload 11
    //   249: astore 10
    //   251: aconst_null
    //   252: astore 8
    //   254: aconst_null
    //   255: astore 9
    //   257: goto -45 -> 212
    //   260: astore 7
    //   262: aload 11
    //   264: astore 10
    //   266: aconst_null
    //   267: astore 9
    //   269: goto -57 -> 212
    //   272: astore 13
    //   274: aload 11
    //   276: astore 10
    //   278: aload 13
    //   280: astore 7
    //   282: aload 12
    //   284: astore 9
    //   286: goto -74 -> 212
    //
    // Exception table:
    //   from	to	target	type
    //   87	99	201	finally
    //   99	127	245	finally
    //   127	155	260	finally
    //   155	162	272	finally
  }
}

/* Location:           C:\Users\sandrocheng.21KUNPENG\Desktop\classes_dex2jar\
 * Qualified Name:     com.jxphone.b.a.a
 * JD-Core Version:    0.6.2
 */