package com.jxphone.a.a;

final class d extends Thread
{
  private final String b;
  private final h c;
  private final g d;

  private d(a parama, String paramString, byte paramByte)
  {
    this.b = paramString;
    this.c = null;
    this.d = null;
  }

  // ERROR //
  public final void run()
  {
    // Byte code:
    //   0: aconst_null
    //   1: astore_1
    //   2: new 33	java/net/URL
    //   5: dup
    //   6: aload_0
    //   7: getfield 19	com/jxphone/a/a/d:a	Lcom/jxphone/a/a/a;
    //   10: invokestatic 38	com/jxphone/a/a/a:a	(Lcom/jxphone/a/a/a;)Ljava/lang/String;
    //   13: aload_0
    //   14: getfield 24	com/jxphone/a/a/d:b	Ljava/lang/String;
    //   17: invokevirtual 44	java/lang/String:concat	(Ljava/lang/String;)Ljava/lang/String;
    //   20: invokespecial 47	java/net/URL:<init>	(Ljava/lang/String;)V
    //   23: invokevirtual 51	java/net/URL:openConnection	()Ljava/net/URLConnection;
    //   26: checkcast 53	java/net/HttpURLConnection
    //   29: astore 5
    //   31: aload 5
    //   33: invokevirtual 57	java/net/HttpURLConnection:getResponseCode	()I
    //   36: sipush 200
    //   39: if_icmpeq +43 -> 82
    //   42: aload_0
    //   43: invokevirtual 63	java/lang/Object:getClass	()Ljava/lang/Class;
    //   46: invokevirtual 69	java/lang/Class:getName	()Ljava/lang/String;
    //   49: ldc 71
    //   51: invokestatic 77	android/util/Log:w	(Ljava/lang/String;Ljava/lang/String;)I
    //   54: pop
    //   55: aload_0
    //   56: getfield 28	com/jxphone/a/a/d:d	Lcom/jxphone/a/a/g;
    //   59: ifnull +12 -> 71
    //   62: aload_0
    //   63: getfield 28	com/jxphone/a/a/d:d	Lcom/jxphone/a/a/g;
    //   66: invokeinterface 81 1 0
    //   71: aload 5
    //   73: ifnull +8 -> 81
    //   76: aload 5
    //   78: invokevirtual 84	java/net/HttpURLConnection:disconnect	()V
    //   81: return
    //   82: aload_0
    //   83: getfield 26	com/jxphone/a/a/d:c	Lcom/jxphone/a/a/h;
    //   86: ifnull -15 -> 71
    //   89: aload_0
    //   90: getfield 26	com/jxphone/a/a/d:c	Lcom/jxphone/a/a/h;
    //   93: invokeinterface 87 1 0
    //   98: goto -27 -> 71
    //   101: astore 7
    //   103: aload 5
    //   105: astore_1
    //   106: aload 7
    //   108: astore_2
    //   109: aload_0
    //   110: invokevirtual 63	java/lang/Object:getClass	()Ljava/lang/Class;
    //   113: invokevirtual 69	java/lang/Class:getName	()Ljava/lang/String;
    //   116: aload_2
    //   117: invokevirtual 90	java/io/IOException:toString	()Ljava/lang/String;
    //   120: invokestatic 93	android/util/Log:e	(Ljava/lang/String;Ljava/lang/String;)I
    //   123: pop
    //   124: aload_1
    //   125: ifnull -44 -> 81
    //   128: aload_1
    //   129: invokevirtual 84	java/net/HttpURLConnection:disconnect	()V
    //   132: goto -51 -> 81
    //   135: astore_3
    //   136: aload_1
    //   137: ifnull +7 -> 144
    //   140: aload_1
    //   141: invokevirtual 84	java/net/HttpURLConnection:disconnect	()V
    //   144: aload_3
    //   145: athrow
    //   146: astore 6
    //   148: aload 5
    //   150: astore_1
    //   151: aload 6
    //   153: astore_3
    //   154: goto -18 -> 136
    //   157: astore_2
    //   158: aconst_null
    //   159: astore_1
    //   160: goto -51 -> 109
    //
    // Exception table:
    //   from	to	target	type
    //   31	71	101	java/io/IOException
    //   82	98	101	java/io/IOException
    //   2	31	135	finally
    //   109	124	135	finally
    //   31	71	146	finally
    //   82	98	146	finally
    //   2	31	157	java/io/IOException
  }
}

/* Location:           C:\Users\sandrocheng.21KUNPENG\Desktop\classes_dex2jar\
 * Qualified Name:     com.jxphone.a.a.d
 * JD-Core Version:    0.6.2
 */