package com.avast.android.mobilesecurity.app.filter.core;

import android.provider.BaseColumns;

public class z
  implements BaseColumns
{
  public static final String b;
  public static final String c;
  public static final String d;
  public static final String e;
  public static final String f;
  public static final String g;
  public static final String h;
  public static final String i;
  public static final String j;

  // ERROR //
  static
  {
    // Byte code:
    //   0: ldc 22
    //   2: astore_0
    //   3: ldc 24
    //   5: astore_1
    //   6: ldc 26
    //   8: astore_2
    //   9: ldc 28
    //   11: astore_3
    //   12: ldc 30
    //   14: invokestatic 36	java/lang/Class:forName	(Ljava/lang/String;)Ljava/lang/Class;
    //   17: astore 18
    //   19: aload 18
    //   21: ldc 38
    //   23: invokevirtual 42	java/lang/Class:getField	(Ljava/lang/String;)Ljava/lang/reflect/Field;
    //   26: aconst_null
    //   27: invokevirtual 48	java/lang/reflect/Field:get	(Ljava/lang/Object;)Ljava/lang/Object;
    //   30: checkcast 50	java/lang/String
    //   33: astore 19
    //   35: aload 18
    //   37: ldc 52
    //   39: invokevirtual 42	java/lang/Class:getField	(Ljava/lang/String;)Ljava/lang/reflect/Field;
    //   42: aconst_null
    //   43: invokevirtual 48	java/lang/reflect/Field:get	(Ljava/lang/Object;)Ljava/lang/Object;
    //   46: checkcast 50	java/lang/String
    //   49: astore 6
    //   51: aload 18
    //   53: ldc 54
    //   55: invokevirtual 42	java/lang/Class:getField	(Ljava/lang/String;)Ljava/lang/reflect/Field;
    //   58: aconst_null
    //   59: invokevirtual 48	java/lang/reflect/Field:get	(Ljava/lang/Object;)Ljava/lang/Object;
    //   62: checkcast 50	java/lang/String
    //   65: astore 7
    //   67: aload 18
    //   69: ldc 56
    //   71: invokevirtual 42	java/lang/Class:getField	(Ljava/lang/String;)Ljava/lang/reflect/Field;
    //   74: aconst_null
    //   75: invokevirtual 48	java/lang/reflect/Field:get	(Ljava/lang/Object;)Ljava/lang/Object;
    //   78: checkcast 50	java/lang/String
    //   81: astore 8
    //   83: aload 18
    //   85: ldc 58
    //   87: invokevirtual 42	java/lang/Class:getField	(Ljava/lang/String;)Ljava/lang/reflect/Field;
    //   90: aconst_null
    //   91: invokevirtual 48	java/lang/reflect/Field:get	(Ljava/lang/Object;)Ljava/lang/Object;
    //   94: checkcast 50	java/lang/String
    //   97: astore 12
    //   99: aload 18
    //   101: ldc 60
    //   103: invokevirtual 42	java/lang/Class:getField	(Ljava/lang/String;)Ljava/lang/reflect/Field;
    //   106: aconst_null
    //   107: invokevirtual 48	java/lang/reflect/Field:get	(Ljava/lang/Object;)Ljava/lang/Object;
    //   110: checkcast 50	java/lang/String
    //   113: astore 13
    //   115: aload 18
    //   117: ldc 62
    //   119: invokevirtual 42	java/lang/Class:getField	(Ljava/lang/String;)Ljava/lang/reflect/Field;
    //   122: aconst_null
    //   123: invokevirtual 48	java/lang/reflect/Field:get	(Ljava/lang/Object;)Ljava/lang/Object;
    //   126: checkcast 50	java/lang/String
    //   129: astore 14
    //   131: aload 18
    //   133: ldc 64
    //   135: invokevirtual 42	java/lang/Class:getField	(Ljava/lang/String;)Ljava/lang/reflect/Field;
    //   138: aconst_null
    //   139: invokevirtual 48	java/lang/reflect/Field:get	(Ljava/lang/Object;)Ljava/lang/Object;
    //   142: checkcast 50	java/lang/String
    //   145: astore 15
    //   147: aload 18
    //   149: ldc 66
    //   151: invokevirtual 42	java/lang/Class:getField	(Ljava/lang/String;)Ljava/lang/reflect/Field;
    //   154: aconst_null
    //   155: invokevirtual 48	java/lang/reflect/Field:get	(Ljava/lang/Object;)Ljava/lang/Object;
    //   158: checkcast 50	java/lang/String
    //   161: astore 36
    //   163: aload 19
    //   165: putstatic 68	com/avast/android/mobilesecurity/app/filter/core/z:b	Ljava/lang/String;
    //   168: aload 6
    //   170: putstatic 70	com/avast/android/mobilesecurity/app/filter/core/z:c	Ljava/lang/String;
    //   173: aload 7
    //   175: putstatic 72	com/avast/android/mobilesecurity/app/filter/core/z:d	Ljava/lang/String;
    //   178: aload 8
    //   180: putstatic 74	com/avast/android/mobilesecurity/app/filter/core/z:e	Ljava/lang/String;
    //   183: aload 12
    //   185: putstatic 76	com/avast/android/mobilesecurity/app/filter/core/z:f	Ljava/lang/String;
    //   188: aload 13
    //   190: putstatic 78	com/avast/android/mobilesecurity/app/filter/core/z:g	Ljava/lang/String;
    //   193: aload 14
    //   195: putstatic 80	com/avast/android/mobilesecurity/app/filter/core/z:h	Ljava/lang/String;
    //   198: aload 15
    //   200: putstatic 82	com/avast/android/mobilesecurity/app/filter/core/z:i	Ljava/lang/String;
    //   203: aload 36
    //   205: putstatic 84	com/avast/android/mobilesecurity/app/filter/core/z:j	Ljava/lang/String;
    //   208: return
    //   209: astore 9
    //   211: aload_3
    //   212: astore 10
    //   214: ldc 86
    //   216: astore 11
    //   218: ldc 88
    //   220: astore 6
    //   222: ldc 90
    //   224: astore 7
    //   226: ldc 92
    //   228: astore 8
    //   230: aload_0
    //   231: astore 12
    //   233: aload_1
    //   234: astore 13
    //   236: aload_2
    //   237: astore 14
    //   239: aload 10
    //   241: astore 15
    //   243: ldc 94
    //   245: ldc 96
    //   247: aload 9
    //   249: invokestatic 101	com/avast/android/generic/util/m:c	(Ljava/lang/String;Ljava/lang/String;Ljava/lang/Throwable;)I
    //   252: pop
    //   253: aload 11
    //   255: putstatic 68	com/avast/android/mobilesecurity/app/filter/core/z:b	Ljava/lang/String;
    //   258: aload 6
    //   260: putstatic 70	com/avast/android/mobilesecurity/app/filter/core/z:c	Ljava/lang/String;
    //   263: aload 7
    //   265: putstatic 72	com/avast/android/mobilesecurity/app/filter/core/z:d	Ljava/lang/String;
    //   268: aload 8
    //   270: putstatic 74	com/avast/android/mobilesecurity/app/filter/core/z:e	Ljava/lang/String;
    //   273: aload 12
    //   275: putstatic 76	com/avast/android/mobilesecurity/app/filter/core/z:f	Ljava/lang/String;
    //   278: aload 13
    //   280: putstatic 78	com/avast/android/mobilesecurity/app/filter/core/z:g	Ljava/lang/String;
    //   283: aload 14
    //   285: putstatic 80	com/avast/android/mobilesecurity/app/filter/core/z:h	Ljava/lang/String;
    //   288: aload 15
    //   290: putstatic 82	com/avast/android/mobilesecurity/app/filter/core/z:i	Ljava/lang/String;
    //   293: ldc 103
    //   295: putstatic 84	com/avast/android/mobilesecurity/app/filter/core/z:j	Ljava/lang/String;
    //   298: goto -90 -> 208
    //   301: astore 4
    //   303: ldc 86
    //   305: astore 5
    //   307: ldc 88
    //   309: astore 6
    //   311: ldc 90
    //   313: astore 7
    //   315: ldc 92
    //   317: astore 8
    //   319: aload 5
    //   321: putstatic 68	com/avast/android/mobilesecurity/app/filter/core/z:b	Ljava/lang/String;
    //   324: aload 6
    //   326: putstatic 70	com/avast/android/mobilesecurity/app/filter/core/z:c	Ljava/lang/String;
    //   329: aload 7
    //   331: putstatic 72	com/avast/android/mobilesecurity/app/filter/core/z:d	Ljava/lang/String;
    //   334: aload 8
    //   336: putstatic 74	com/avast/android/mobilesecurity/app/filter/core/z:e	Ljava/lang/String;
    //   339: aload_0
    //   340: putstatic 76	com/avast/android/mobilesecurity/app/filter/core/z:f	Ljava/lang/String;
    //   343: aload_1
    //   344: putstatic 78	com/avast/android/mobilesecurity/app/filter/core/z:g	Ljava/lang/String;
    //   347: aload_2
    //   348: putstatic 80	com/avast/android/mobilesecurity/app/filter/core/z:h	Ljava/lang/String;
    //   351: aload_3
    //   352: putstatic 82	com/avast/android/mobilesecurity/app/filter/core/z:i	Ljava/lang/String;
    //   355: ldc 103
    //   357: putstatic 84	com/avast/android/mobilesecurity/app/filter/core/z:j	Ljava/lang/String;
    //   360: aload 4
    //   362: athrow
    //   363: astore 21
    //   365: ldc 88
    //   367: astore 6
    //   369: ldc 90
    //   371: astore 7
    //   373: ldc 92
    //   375: astore 8
    //   377: aload 19
    //   379: astore 5
    //   381: aload 21
    //   383: astore 4
    //   385: goto -66 -> 319
    //   388: astore 23
    //   390: ldc 90
    //   392: astore 7
    //   394: ldc 92
    //   396: astore 8
    //   398: aload 19
    //   400: astore 5
    //   402: aload 23
    //   404: astore 4
    //   406: goto -87 -> 319
    //   409: astore 25
    //   411: ldc 92
    //   413: astore 8
    //   415: aload 19
    //   417: astore 5
    //   419: aload 25
    //   421: astore 4
    //   423: goto -104 -> 319
    //   426: astore 27
    //   428: aload 19
    //   430: astore 5
    //   432: aload 27
    //   434: astore 4
    //   436: goto -117 -> 319
    //   439: astore 29
    //   441: aload 12
    //   443: astore_0
    //   444: aload 19
    //   446: astore 5
    //   448: aload 29
    //   450: astore 4
    //   452: goto -133 -> 319
    //   455: astore 31
    //   457: aload 13
    //   459: astore_1
    //   460: aload 12
    //   462: astore_0
    //   463: aload 19
    //   465: astore 5
    //   467: aload 31
    //   469: astore 4
    //   471: goto -152 -> 319
    //   474: astore 33
    //   476: aload 14
    //   478: astore_2
    //   479: aload 13
    //   481: astore_1
    //   482: aload 12
    //   484: astore_0
    //   485: aload 19
    //   487: astore 5
    //   489: aload 33
    //   491: astore 4
    //   493: goto -174 -> 319
    //   496: astore 35
    //   498: aload 15
    //   500: astore_3
    //   501: aload 14
    //   503: astore_2
    //   504: aload 13
    //   506: astore_1
    //   507: aload 12
    //   509: astore_0
    //   510: aload 19
    //   512: astore 5
    //   514: aload 35
    //   516: astore 4
    //   518: goto -199 -> 319
    //   521: astore 4
    //   523: aload 15
    //   525: astore 16
    //   527: aload 14
    //   529: astore_2
    //   530: aload 13
    //   532: astore_1
    //   533: aload 12
    //   535: astore_0
    //   536: aload 11
    //   538: astore 5
    //   540: aload 16
    //   542: astore_3
    //   543: goto -224 -> 319
    //   546: astore 20
    //   548: ldc 88
    //   550: astore 6
    //   552: ldc 90
    //   554: astore 7
    //   556: ldc 92
    //   558: astore 8
    //   560: aload_0
    //   561: astore 12
    //   563: aload_1
    //   564: astore 13
    //   566: aload_2
    //   567: astore 14
    //   569: aload_3
    //   570: astore 15
    //   572: aload 19
    //   574: astore 11
    //   576: aload 20
    //   578: astore 9
    //   580: goto -337 -> 243
    //   583: astore 22
    //   585: ldc 90
    //   587: astore 7
    //   589: ldc 92
    //   591: astore 8
    //   593: aload_0
    //   594: astore 12
    //   596: aload_1
    //   597: astore 13
    //   599: aload_2
    //   600: astore 14
    //   602: aload_3
    //   603: astore 15
    //   605: aload 19
    //   607: astore 11
    //   609: aload 22
    //   611: astore 9
    //   613: goto -370 -> 243
    //   616: astore 24
    //   618: ldc 92
    //   620: astore 8
    //   622: aload_0
    //   623: astore 12
    //   625: aload_1
    //   626: astore 13
    //   628: aload_2
    //   629: astore 14
    //   631: aload_3
    //   632: astore 15
    //   634: aload 19
    //   636: astore 11
    //   638: aload 24
    //   640: astore 9
    //   642: goto -399 -> 243
    //   645: astore 26
    //   647: aload_0
    //   648: astore 12
    //   650: aload_1
    //   651: astore 13
    //   653: aload_2
    //   654: astore 14
    //   656: aload_3
    //   657: astore 15
    //   659: aload 19
    //   661: astore 11
    //   663: aload 26
    //   665: astore 9
    //   667: goto -424 -> 243
    //   670: astore 28
    //   672: aload_1
    //   673: astore 13
    //   675: aload_2
    //   676: astore 14
    //   678: aload_3
    //   679: astore 15
    //   681: aload 19
    //   683: astore 11
    //   685: aload 28
    //   687: astore 9
    //   689: goto -446 -> 243
    //   692: astore 30
    //   694: aload_2
    //   695: astore 14
    //   697: aload_3
    //   698: astore 15
    //   700: aload 19
    //   702: astore 11
    //   704: aload 30
    //   706: astore 9
    //   708: goto -465 -> 243
    //   711: astore 32
    //   713: aload_3
    //   714: astore 15
    //   716: aload 19
    //   718: astore 11
    //   720: aload 32
    //   722: astore 9
    //   724: goto -481 -> 243
    //   727: astore 34
    //   729: aload 19
    //   731: astore 11
    //   733: aload 34
    //   735: astore 9
    //   737: goto -494 -> 243
    //
    // Exception table:
    //   from	to	target	type
    //   12	35	209	java/lang/Exception
    //   12	35	301	finally
    //   35	51	363	finally
    //   51	67	388	finally
    //   67	83	409	finally
    //   83	99	426	finally
    //   99	115	439	finally
    //   115	131	455	finally
    //   131	147	474	finally
    //   147	163	496	finally
    //   243	253	521	finally
    //   35	51	546	java/lang/Exception
    //   51	67	583	java/lang/Exception
    //   67	83	616	java/lang/Exception
    //   83	99	645	java/lang/Exception
    //   99	115	670	java/lang/Exception
    //   115	131	692	java/lang/Exception
    //   131	147	711	java/lang/Exception
    //   147	163	727	java/lang/Exception
  }
}

/* Location:           C:\Users\sandrocheng.21KUNPENG\Desktop\classes_dex2jar.jar
 * Qualified Name:     com.avast.android.mobilesecurity.app.filter.core.z
 * JD-Core Version:    0.6.2
 */