package a.a.a.a.a;

class b
  implements Runnable
{
  b(a parama, String paramString)
  {
  }

  // ERROR //
  public void run()
  {
    // Byte code:
    //   0: new 24	a/a/a/a/a/d
    //   3: dup
    //   4: aload_0
    //   5: getfield 14	a/a/a/a/a/b:b	La/a/a/a/a/a;
    //   8: invokestatic 29	a/a/a/a/a/a:a	(La/a/a/a/a/a;)Landroid/content/Context;
    //   11: invokespecial 32	a/a/a/a/a/d:<init>	(Landroid/content/Context;)V
    //   14: astore_1
    //   15: aload_1
    //   16: invokevirtual 35	a/a/a/a/a/d:a	()Landroid/b/a/a;
    //   19: astore 4
    //   21: aload_0
    //   22: getfield 14	a/a/a/a/a/b:b	La/a/a/a/a/a;
    //   25: invokestatic 38	a/a/a/a/a/a:b	(La/a/a/a/a/a;)Ljava/lang/String;
    //   28: ifnull +23 -> 51
    //   31: aload 4
    //   33: invokevirtual 44	android/b/a/a:getParams	()Lorg/apache/http/params/HttpParams;
    //   36: ldc 46
    //   38: aload_0
    //   39: getfield 14	a/a/a/a/a/b:b	La/a/a/a/a/a;
    //   42: invokestatic 38	a/a/a/a/a/a:b	(La/a/a/a/a/a;)Ljava/lang/String;
    //   45: invokeinterface 52 3 0
    //   50: pop
    //   51: new 54	org/apache/http/client/methods/HttpPost
    //   54: dup
    //   55: aload_0
    //   56: getfield 14	a/a/a/a/a/b:b	La/a/a/a/a/a;
    //   59: invokestatic 57	a/a/a/a/a/a:c	(La/a/a/a/a/a;)Ljava/lang/String;
    //   62: invokespecial 60	org/apache/http/client/methods/HttpPost:<init>	(Ljava/lang/String;)V
    //   65: astore 5
    //   67: aload 5
    //   69: new 62	org/apache/http/entity/StringEntity
    //   72: dup
    //   73: aload_0
    //   74: getfield 16	a/a/a/a/a/b:a	Ljava/lang/String;
    //   77: invokespecial 63	org/apache/http/entity/StringEntity:<init>	(Ljava/lang/String;)V
    //   80: invokevirtual 67	org/apache/http/client/methods/HttpPost:setEntity	(Lorg/apache/http/HttpEntity;)V
    //   83: aload 5
    //   85: ldc 69
    //   87: ldc 71
    //   89: invokevirtual 75	org/apache/http/client/methods/HttpPost:setHeader	(Ljava/lang/String;Ljava/lang/String;)V
    //   92: aload 5
    //   94: ldc 77
    //   96: ldc 71
    //   98: invokevirtual 75	org/apache/http/client/methods/HttpPost:setHeader	(Ljava/lang/String;Ljava/lang/String;)V
    //   101: ldc 79
    //   103: new 81	java/lang/StringBuilder
    //   106: dup
    //   107: invokespecial 82	java/lang/StringBuilder:<init>	()V
    //   110: ldc 84
    //   112: invokevirtual 88	java/lang/StringBuilder:append	(Ljava/lang/String;)Ljava/lang/StringBuilder;
    //   115: aload_0
    //   116: getfield 16	a/a/a/a/a/b:a	Ljava/lang/String;
    //   119: invokevirtual 88	java/lang/StringBuilder:append	(Ljava/lang/String;)Ljava/lang/StringBuilder;
    //   122: invokevirtual 92	java/lang/StringBuilder:toString	()Ljava/lang/String;
    //   125: invokestatic 96	com/avast/android/generic/util/t:a	(Ljava/lang/String;Ljava/lang/String;)V
    //   128: aload 4
    //   130: aload 5
    //   132: invokevirtual 100	android/b/a/a:execute	(Lorg/apache/http/client/methods/HttpUriRequest;)Lorg/apache/http/HttpResponse;
    //   135: invokeinterface 106 1 0
    //   140: invokeinterface 112 1 0
    //   145: istore 6
    //   147: ldc 79
    //   149: new 81	java/lang/StringBuilder
    //   152: dup
    //   153: invokespecial 82	java/lang/StringBuilder:<init>	()V
    //   156: ldc 114
    //   158: invokevirtual 88	java/lang/StringBuilder:append	(Ljava/lang/String;)Ljava/lang/StringBuilder;
    //   161: iload 6
    //   163: invokevirtual 117	java/lang/StringBuilder:append	(I)Ljava/lang/StringBuilder;
    //   166: invokevirtual 92	java/lang/StringBuilder:toString	()Ljava/lang/String;
    //   169: invokestatic 96	com/avast/android/generic/util/t:a	(Ljava/lang/String;Ljava/lang/String;)V
    //   172: aload_1
    //   173: ifnull +7 -> 180
    //   176: aload_1
    //   177: invokevirtual 119	a/a/a/a/a/d:b	()V
    //   180: return
    //   181: astore_2
    //   182: aconst_null
    //   183: astore_1
    //   184: ldc 79
    //   186: ldc 121
    //   188: aload_2
    //   189: invokestatic 124	com/avast/android/generic/util/t:a	(Ljava/lang/String;Ljava/lang/String;Ljava/lang/Throwable;)V
    //   192: aload_1
    //   193: ifnull -13 -> 180
    //   196: goto -20 -> 176
    //   199: astore_3
    //   200: aconst_null
    //   201: astore_1
    //   202: aload_1
    //   203: ifnull +7 -> 210
    //   206: aload_1
    //   207: invokevirtual 119	a/a/a/a/a/d:b	()V
    //   210: aload_3
    //   211: athrow
    //   212: astore_3
    //   213: goto -11 -> 202
    //   216: astore_2
    //   217: goto -33 -> 184
    //
    // Exception table:
    //   from	to	target	type
    //   0	15	181	java/lang/Throwable
    //   0	15	199	finally
    //   15	172	212	finally
    //   184	192	212	finally
    //   15	172	216	java/lang/Throwable
  }
}

/* Location:           C:\Users\sandrocheng.21KUNPENG\Desktop\classes_dex2jar.jar
 * Qualified Name:     a.a.a.a.a.b
 * JD-Core Version:    0.6.2
 */