package com.keniu.security.sync.d.a;

public final class a
{
  private static final String a = "http://app.cloud3.1tpan.com/3";
  private static final String b = "/list";
  private static final String c = "/getspace";
  private static final String d = "/info";
  private static final String e = "/openread";
  private static final String f = "/openwrite";
  private static final String g = "/closefile";
  private static final String h = "/delete";
  private static final String i = "/mkdir";
  private static final String j = "/openthumbs";
  private static final String k = "/";

  // ERROR //
  private static com.keniu.security.sync.d.d.a.bb a(String paramString)
  {
    // Byte code:
    //   0: invokestatic 49	com/keniu/security/sync/d/d/a/ay:l	()Lcom/keniu/security/sync/d/d/a/az;
    //   3: astore_1
    //   4: aload_1
    //   5: aload_0
    //   6: invokevirtual 54	com/keniu/security/sync/d/d/a/az:a	(Ljava/lang/String;)Lcom/keniu/security/sync/d/d/a/az;
    //   9: pop
    //   10: aconst_null
    //   11: astore_3
    //   12: new 56	com/keniu/security/sync/d/e/a
    //   15: dup
    //   16: ldc 58
    //   18: invokespecial 61	com/keniu/security/sync/d/e/a:<init>	(Ljava/lang/String;)V
    //   21: astore 4
    //   23: aload_1
    //   24: invokevirtual 64	com/keniu/security/sync/d/d/a/az:i	()Lcom/keniu/security/sync/d/d/a/ay;
    //   27: aload 4
    //   29: invokevirtual 67	com/keniu/security/sync/d/e/a:b	()Ljava/io/OutputStream;
    //   32: invokevirtual 70	com/keniu/security/sync/d/d/a/ay:a	(Ljava/io/OutputStream;)V
    //   35: aload 4
    //   37: invokevirtual 73	com/keniu/security/sync/d/e/a:c	()Ljava/io/InputStream;
    //   40: invokestatic 78	com/keniu/security/sync/d/d/a/bb:a	(Ljava/io/InputStream;)Lcom/keniu/security/sync/d/d/a/bb;
    //   43: astore 7
    //   45: aload 4
    //   47: invokestatic 81	com/keniu/security/sync/d/a/a:a	(Lcom/keniu/security/sync/d/e/a;)Lcom/keniu/security/sync/d/e/a;
    //   50: pop
    //   51: aload 7
    //   53: areturn
    //   54: astore 5
    //   56: aload_3
    //   57: invokestatic 81	com/keniu/security/sync/d/a/a:a	(Lcom/keniu/security/sync/d/e/a;)Lcom/keniu/security/sync/d/e/a;
    //   60: pop
    //   61: aload 5
    //   63: athrow
    //   64: astore 5
    //   66: aload 4
    //   68: astore_3
    //   69: goto -13 -> 56
    //
    // Exception table:
    //   from	to	target	type
    //   12	23	54	finally
    //   23	45	64	finally
  }

  // ERROR //
  private static com.keniu.security.sync.d.d.a.bn a(String paramString1, String paramString2, long paramLong)
  {
    // Byte code:
    //   0: invokestatic 88	com/keniu/security/sync/d/d/a/bk:r	()Lcom/keniu/security/sync/d/d/a/bl;
    //   3: astore 4
    //   5: aload 4
    //   7: aload_0
    //   8: invokevirtual 93	com/keniu/security/sync/d/d/a/bl:a	(Ljava/lang/String;)Lcom/keniu/security/sync/d/d/a/bl;
    //   11: pop
    //   12: aload 4
    //   14: iconst_0
    //   15: invokevirtual 96	com/keniu/security/sync/d/d/a/bl:a	(I)Lcom/keniu/security/sync/d/d/a/bl;
    //   18: pop
    //   19: aload_1
    //   20: ifnull +69 -> 89
    //   23: aload 4
    //   25: aload_1
    //   26: invokevirtual 98	com/keniu/security/sync/d/d/a/bl:b	(Ljava/lang/String;)Lcom/keniu/security/sync/d/d/a/bl;
    //   29: pop
    //   30: lload_2
    //   31: lconst_0
    //   32: lcmp
    //   33: ifle +10 -> 43
    //   36: aload 4
    //   38: lload_2
    //   39: invokevirtual 101	com/keniu/security/sync/d/d/a/bl:a	(J)Lcom/keniu/security/sync/d/d/a/bl;
    //   42: pop
    //   43: aconst_null
    //   44: astore 8
    //   46: new 56	com/keniu/security/sync/d/e/a
    //   49: dup
    //   50: ldc 103
    //   52: invokespecial 61	com/keniu/security/sync/d/e/a:<init>	(Ljava/lang/String;)V
    //   55: astore 9
    //   57: aload 4
    //   59: invokevirtual 106	com/keniu/security/sync/d/d/a/bl:i	()Lcom/keniu/security/sync/d/d/a/bk;
    //   62: aload 9
    //   64: invokevirtual 67	com/keniu/security/sync/d/e/a:b	()Ljava/io/OutputStream;
    //   67: invokevirtual 107	com/keniu/security/sync/d/d/a/bk:a	(Ljava/io/OutputStream;)V
    //   70: aload 9
    //   72: invokevirtual 73	com/keniu/security/sync/d/e/a:c	()Ljava/io/InputStream;
    //   75: invokestatic 112	com/keniu/security/sync/d/d/a/bn:a	(Ljava/io/InputStream;)Lcom/keniu/security/sync/d/d/a/bn;
    //   78: astore 12
    //   80: aload 9
    //   82: invokestatic 81	com/keniu/security/sync/d/a/a:a	(Lcom/keniu/security/sync/d/e/a;)Lcom/keniu/security/sync/d/e/a;
    //   85: pop
    //   86: aload 12
    //   88: areturn
    //   89: aload 4
    //   91: ldc 38
    //   93: invokevirtual 98	com/keniu/security/sync/d/d/a/bl:b	(Ljava/lang/String;)Lcom/keniu/security/sync/d/d/a/bl;
    //   96: pop
    //   97: goto -67 -> 30
    //   100: astore 10
    //   102: aload 8
    //   104: invokestatic 81	com/keniu/security/sync/d/a/a:a	(Lcom/keniu/security/sync/d/e/a;)Lcom/keniu/security/sync/d/e/a;
    //   107: pop
    //   108: aload 10
    //   110: athrow
    //   111: astore 10
    //   113: aload 9
    //   115: astore 8
    //   117: goto -15 -> 102
    //
    // Exception table:
    //   from	to	target	type
    //   46	57	100	finally
    //   57	80	111	finally
  }

  // ERROR //
  public static com.keniu.security.sync.d.d.a.cf a(String paramString1, String paramString2)
  {
    // Byte code:
    //   0: invokestatic 119	com/keniu/security/sync/d/d/a/cc:t	()Lcom/keniu/security/sync/d/d/a/cd;
    //   3: astore_2
    //   4: aload_2
    //   5: aload_0
    //   6: invokevirtual 124	com/keniu/security/sync/d/d/a/cd:a	(Ljava/lang/String;)Lcom/keniu/security/sync/d/d/a/cd;
    //   9: pop
    //   10: aload_2
    //   11: iconst_0
    //   12: invokevirtual 127	com/keniu/security/sync/d/d/a/cd:a	(I)Lcom/keniu/security/sync/d/d/a/cd;
    //   15: pop
    //   16: aload_2
    //   17: iconst_0
    //   18: invokevirtual 129	com/keniu/security/sync/d/d/a/cd:b	(I)Lcom/keniu/security/sync/d/d/a/cd;
    //   21: pop
    //   22: aload_1
    //   23: ifnull +70 -> 93
    //   26: aload_2
    //   27: aload_1
    //   28: invokevirtual 131	com/keniu/security/sync/d/d/a/cd:b	(Ljava/lang/String;)Lcom/keniu/security/sync/d/d/a/cd;
    //   31: pop
    //   32: ldc2_w 132
    //   35: lconst_0
    //   36: lcmp
    //   37: ifle +11 -> 48
    //   40: aload_2
    //   41: ldc2_w 132
    //   44: invokevirtual 136	com/keniu/security/sync/d/d/a/cd:a	(J)Lcom/keniu/security/sync/d/d/a/cd;
    //   47: pop
    //   48: aconst_null
    //   49: astore 7
    //   51: new 56	com/keniu/security/sync/d/e/a
    //   54: dup
    //   55: ldc 138
    //   57: invokespecial 61	com/keniu/security/sync/d/e/a:<init>	(Ljava/lang/String;)V
    //   60: astore 8
    //   62: aload_2
    //   63: invokevirtual 141	com/keniu/security/sync/d/d/a/cd:i	()Lcom/keniu/security/sync/d/d/a/cc;
    //   66: aload 8
    //   68: invokevirtual 67	com/keniu/security/sync/d/e/a:b	()Ljava/io/OutputStream;
    //   71: invokevirtual 142	com/keniu/security/sync/d/d/a/cc:a	(Ljava/io/OutputStream;)V
    //   74: aload 8
    //   76: invokevirtual 73	com/keniu/security/sync/d/e/a:c	()Ljava/io/InputStream;
    //   79: invokestatic 147	com/keniu/security/sync/d/d/a/cf:a	(Ljava/io/InputStream;)Lcom/keniu/security/sync/d/d/a/cf;
    //   82: astore 11
    //   84: aload 8
    //   86: invokestatic 81	com/keniu/security/sync/d/a/a:a	(Lcom/keniu/security/sync/d/e/a;)Lcom/keniu/security/sync/d/e/a;
    //   89: pop
    //   90: aload 11
    //   92: areturn
    //   93: aload_2
    //   94: ldc 38
    //   96: invokevirtual 131	com/keniu/security/sync/d/d/a/cd:b	(Ljava/lang/String;)Lcom/keniu/security/sync/d/d/a/cd;
    //   99: pop
    //   100: goto -68 -> 32
    //   103: astore 9
    //   105: aload 7
    //   107: invokestatic 81	com/keniu/security/sync/d/a/a:a	(Lcom/keniu/security/sync/d/e/a;)Lcom/keniu/security/sync/d/e/a;
    //   110: pop
    //   111: aload 9
    //   113: athrow
    //   114: astore 9
    //   116: aload 8
    //   118: astore 7
    //   120: goto -15 -> 105
    //
    // Exception table:
    //   from	to	target	type
    //   51	62	103	finally
    //   62	84	114	finally
  }

  // ERROR //
  private static com.keniu.security.sync.d.d.a.dr a(String paramString, String[] paramArrayOfString)
  {
    // Byte code:
    //   0: iconst_0
    //   1: istore_2
    //   2: invokestatic 153	com/keniu/security/sync/d/d/a/do:r	()Lcom/keniu/security/sync/d/d/a/dp;
    //   5: astore_3
    //   6: aload_3
    //   7: aload_0
    //   8: invokevirtual 158	com/keniu/security/sync/d/d/a/dp:a	(Ljava/lang/String;)Lcom/keniu/security/sync/d/d/a/dp;
    //   11: pop
    //   12: aload_3
    //   13: iconst_0
    //   14: invokevirtual 161	com/keniu/security/sync/d/d/a/dp:b	(I)Lcom/keniu/security/sync/d/d/a/dp;
    //   17: pop
    //   18: iload_2
    //   19: aload_1
    //   20: arraylength
    //   21: if_icmpge +18 -> 39
    //   24: aload_3
    //   25: iload_2
    //   26: aload_1
    //   27: iload_2
    //   28: aaload
    //   29: invokevirtual 164	com/keniu/security/sync/d/d/a/dp:a	(ILjava/lang/String;)Lcom/keniu/security/sync/d/d/a/dp;
    //   32: pop
    //   33: iinc 2 1
    //   36: goto -18 -> 18
    //   39: aconst_null
    //   40: astore 6
    //   42: new 56	com/keniu/security/sync/d/e/a
    //   45: dup
    //   46: ldc 166
    //   48: invokespecial 61	com/keniu/security/sync/d/e/a:<init>	(Ljava/lang/String;)V
    //   51: astore 7
    //   53: aload_3
    //   54: invokevirtual 169	com/keniu/security/sync/d/d/a/dp:i	()Lcom/keniu/security/sync/d/d/a/do;
    //   57: aload 7
    //   59: invokevirtual 67	com/keniu/security/sync/d/e/a:b	()Ljava/io/OutputStream;
    //   62: invokevirtual 170	com/keniu/security/sync/d/d/a/do:a	(Ljava/io/OutputStream;)V
    //   65: aload 7
    //   67: invokevirtual 73	com/keniu/security/sync/d/e/a:c	()Ljava/io/InputStream;
    //   70: invokestatic 175	com/keniu/security/sync/d/d/a/dr:a	(Ljava/io/InputStream;)Lcom/keniu/security/sync/d/d/a/dr;
    //   73: astore 10
    //   75: aload 7
    //   77: invokestatic 81	com/keniu/security/sync/d/a/a:a	(Lcom/keniu/security/sync/d/e/a;)Lcom/keniu/security/sync/d/e/a;
    //   80: pop
    //   81: aload 10
    //   83: areturn
    //   84: astore 8
    //   86: aload 6
    //   88: invokestatic 81	com/keniu/security/sync/d/a/a:a	(Lcom/keniu/security/sync/d/e/a;)Lcom/keniu/security/sync/d/e/a;
    //   91: pop
    //   92: aload 8
    //   94: athrow
    //   95: astore 8
    //   97: aload 7
    //   99: astore 6
    //   101: goto -15 -> 86
    //
    // Exception table:
    //   from	to	target	type
    //   42	53	84	finally
    //   53	75	95	finally
  }

  // ERROR //
  public static com.keniu.security.sync.d.d.a.dx a(String paramString1, String paramString2, String paramString3, long paramLong)
  {
    // Byte code:
    //   0: invokestatic 182	com/keniu/security/sync/d/d/a/du:J	()Lcom/keniu/security/sync/d/d/a/dv;
    //   3: astore 5
    //   5: aload 5
    //   7: aload_0
    //   8: invokevirtual 187	com/keniu/security/sync/d/d/a/dv:a	(Ljava/lang/String;)Lcom/keniu/security/sync/d/d/a/dv;
    //   11: pop
    //   12: aload 5
    //   14: aload_2
    //   15: invokevirtual 189	com/keniu/security/sync/d/d/a/dv:c	(Ljava/lang/String;)Lcom/keniu/security/sync/d/d/a/dv;
    //   18: pop
    //   19: aload 5
    //   21: lload_3
    //   22: invokevirtual 192	com/keniu/security/sync/d/d/a/dv:a	(J)Lcom/keniu/security/sync/d/d/a/dv;
    //   25: pop
    //   26: aload 5
    //   28: iconst_0
    //   29: invokevirtual 195	com/keniu/security/sync/d/d/a/dv:a	(I)Lcom/keniu/security/sync/d/d/a/dv;
    //   32: pop
    //   33: aload_1
    //   34: ifnull +56 -> 90
    //   37: aload 5
    //   39: aload_1
    //   40: invokevirtual 197	com/keniu/security/sync/d/d/a/dv:b	(Ljava/lang/String;)Lcom/keniu/security/sync/d/d/a/dv;
    //   43: pop
    //   44: aconst_null
    //   45: astore 11
    //   47: new 56	com/keniu/security/sync/d/e/a
    //   50: dup
    //   51: ldc 199
    //   53: invokespecial 61	com/keniu/security/sync/d/e/a:<init>	(Ljava/lang/String;)V
    //   56: astore 12
    //   58: aload 5
    //   60: invokevirtual 202	com/keniu/security/sync/d/d/a/dv:i	()Lcom/keniu/security/sync/d/d/a/du;
    //   63: aload 12
    //   65: invokevirtual 67	com/keniu/security/sync/d/e/a:b	()Ljava/io/OutputStream;
    //   68: invokevirtual 203	com/keniu/security/sync/d/d/a/du:a	(Ljava/io/OutputStream;)V
    //   71: aload 12
    //   73: invokevirtual 73	com/keniu/security/sync/d/e/a:c	()Ljava/io/InputStream;
    //   76: invokestatic 208	com/keniu/security/sync/d/d/a/dx:a	(Ljava/io/InputStream;)Lcom/keniu/security/sync/d/d/a/dx;
    //   79: astore 15
    //   81: aload 12
    //   83: invokestatic 81	com/keniu/security/sync/d/a/a:a	(Lcom/keniu/security/sync/d/e/a;)Lcom/keniu/security/sync/d/e/a;
    //   86: pop
    //   87: aload 15
    //   89: areturn
    //   90: aload 5
    //   92: ldc 38
    //   94: invokevirtual 197	com/keniu/security/sync/d/d/a/dv:b	(Ljava/lang/String;)Lcom/keniu/security/sync/d/d/a/dv;
    //   97: pop
    //   98: goto -54 -> 44
    //   101: astore 13
    //   103: aload 11
    //   105: invokestatic 81	com/keniu/security/sync/d/a/a:a	(Lcom/keniu/security/sync/d/e/a;)Lcom/keniu/security/sync/d/e/a;
    //   108: pop
    //   109: aload 13
    //   111: athrow
    //   112: astore 13
    //   114: aload 12
    //   116: astore 11
    //   118: goto -15 -> 103
    //
    // Exception table:
    //   from	to	target	type
    //   47	58	101	finally
    //   58	81	112	finally
  }

  // ERROR //
  public static com.keniu.security.sync.d.d.a.r a(com.keniu.security.sync.d.d.a.gn paramgn, String paramString1, String paramString2)
  {
    // Byte code:
    //   0: invokestatic 215	com/keniu/security/sync/d/d/a/o:w	()Lcom/keniu/security/sync/d/d/a/p;
    //   3: astore_3
    //   4: aload_3
    //   5: aload_1
    //   6: invokevirtual 220	com/keniu/security/sync/d/d/a/p:a	(Ljava/lang/String;)Lcom/keniu/security/sync/d/d/a/p;
    //   9: pop
    //   10: aload_3
    //   11: aload_2
    //   12: invokevirtual 222	com/keniu/security/sync/d/d/a/p:b	(Ljava/lang/String;)Lcom/keniu/security/sync/d/d/a/p;
    //   15: pop
    //   16: aload_3
    //   17: aload_0
    //   18: invokevirtual 225	com/keniu/security/sync/d/d/a/p:a	(Lcom/keniu/security/sync/d/d/a/gn;)Lcom/keniu/security/sync/d/d/a/p;
    //   21: pop
    //   22: aload_3
    //   23: iconst_1
    //   24: invokevirtual 228	com/keniu/security/sync/d/d/a/p:b	(I)Lcom/keniu/security/sync/d/d/a/p;
    //   27: pop
    //   28: aload_3
    //   29: iconst_0
    //   30: invokevirtual 230	com/keniu/security/sync/d/d/a/p:a	(I)Lcom/keniu/security/sync/d/d/a/p;
    //   33: pop
    //   34: aconst_null
    //   35: astore 9
    //   37: new 56	com/keniu/security/sync/d/e/a
    //   40: dup
    //   41: ldc 232
    //   43: invokespecial 61	com/keniu/security/sync/d/e/a:<init>	(Ljava/lang/String;)V
    //   46: astore 10
    //   48: aload_3
    //   49: invokevirtual 235	com/keniu/security/sync/d/d/a/p:i	()Lcom/keniu/security/sync/d/d/a/o;
    //   52: aload 10
    //   54: invokevirtual 67	com/keniu/security/sync/d/e/a:b	()Ljava/io/OutputStream;
    //   57: invokevirtual 236	com/keniu/security/sync/d/d/a/o:a	(Ljava/io/OutputStream;)V
    //   60: aload 10
    //   62: invokevirtual 73	com/keniu/security/sync/d/e/a:c	()Ljava/io/InputStream;
    //   65: invokestatic 241	com/keniu/security/sync/d/d/a/r:a	(Ljava/io/InputStream;)Lcom/keniu/security/sync/d/d/a/r;
    //   68: astore 13
    //   70: aload 10
    //   72: invokestatic 81	com/keniu/security/sync/d/a/a:a	(Lcom/keniu/security/sync/d/e/a;)Lcom/keniu/security/sync/d/e/a;
    //   75: pop
    //   76: aload 13
    //   78: areturn
    //   79: astore 11
    //   81: aload 9
    //   83: invokestatic 81	com/keniu/security/sync/d/a/a:a	(Lcom/keniu/security/sync/d/e/a;)Lcom/keniu/security/sync/d/e/a;
    //   86: pop
    //   87: aload 11
    //   89: athrow
    //   90: astore 11
    //   92: aload 10
    //   94: astore 9
    //   96: goto -15 -> 81
    //
    // Exception table:
    //   from	to	target	type
    //   37	48	79	finally
    //   48	70	90	finally
  }

  private static com.keniu.security.sync.d.e.a a(com.keniu.security.sync.d.e.a parama)
  {
    if (parama != null)
      parama.d();
    return null;
  }

  // ERROR //
  public static com.keniu.security.sync.d.d.a.ad b(String paramString1, String paramString2)
  {
    // Byte code:
    //   0: invokestatic 249	com/keniu/security/sync/d/d/a/aa:r	()Lcom/keniu/security/sync/d/d/a/ab;
    //   3: astore_2
    //   4: aload_2
    //   5: aload_1
    //   6: invokevirtual 254	com/keniu/security/sync/d/d/a/ab:b	(Ljava/lang/String;)Lcom/keniu/security/sync/d/d/a/ab;
    //   9: pop
    //   10: aload_2
    //   11: aload_0
    //   12: invokevirtual 256	com/keniu/security/sync/d/d/a/ab:a	(Ljava/lang/String;)Lcom/keniu/security/sync/d/d/a/ab;
    //   15: pop
    //   16: aload_2
    //   17: iconst_0
    //   18: invokevirtual 259	com/keniu/security/sync/d/d/a/ab:a	(I)Lcom/keniu/security/sync/d/d/a/ab;
    //   21: pop
    //   22: aload_2
    //   23: iconst_0
    //   24: invokevirtual 261	com/keniu/security/sync/d/d/a/ab:b	(I)Lcom/keniu/security/sync/d/d/a/ab;
    //   27: pop
    //   28: aconst_null
    //   29: astore 7
    //   31: new 56	com/keniu/security/sync/d/e/a
    //   34: dup
    //   35: ldc_w 263
    //   38: invokespecial 61	com/keniu/security/sync/d/e/a:<init>	(Ljava/lang/String;)V
    //   41: astore 8
    //   43: aload_2
    //   44: invokevirtual 266	com/keniu/security/sync/d/d/a/ab:i	()Lcom/keniu/security/sync/d/d/a/aa;
    //   47: aload 8
    //   49: invokevirtual 67	com/keniu/security/sync/d/e/a:b	()Ljava/io/OutputStream;
    //   52: invokevirtual 267	com/keniu/security/sync/d/d/a/aa:a	(Ljava/io/OutputStream;)V
    //   55: aload 8
    //   57: invokevirtual 73	com/keniu/security/sync/d/e/a:c	()Ljava/io/InputStream;
    //   60: invokestatic 272	com/keniu/security/sync/d/d/a/ad:a	(Ljava/io/InputStream;)Lcom/keniu/security/sync/d/d/a/ad;
    //   63: astore 11
    //   65: aload 8
    //   67: invokestatic 81	com/keniu/security/sync/d/a/a:a	(Lcom/keniu/security/sync/d/e/a;)Lcom/keniu/security/sync/d/e/a;
    //   70: pop
    //   71: aload 11
    //   73: areturn
    //   74: astore 9
    //   76: aload 7
    //   78: invokestatic 81	com/keniu/security/sync/d/a/a:a	(Lcom/keniu/security/sync/d/e/a;)Lcom/keniu/security/sync/d/e/a;
    //   81: pop
    //   82: aload 9
    //   84: athrow
    //   85: astore 9
    //   87: aload 8
    //   89: astore 7
    //   91: goto -15 -> 76
    //
    // Exception table:
    //   from	to	target	type
    //   31	43	74	finally
    //   43	65	85	finally
  }

  // ERROR //
  public static com.keniu.security.sync.d.d.a.cl b(String paramString1, String paramString2, String paramString3, long paramLong)
  {
    // Byte code:
    //   0: invokestatic 278	com/keniu/security/sync/d/d/a/ci:t	()Lcom/keniu/security/sync/d/d/a/cj;
    //   3: astore 5
    //   5: aload 5
    //   7: aload_0
    //   8: invokevirtual 283	com/keniu/security/sync/d/d/a/cj:a	(Ljava/lang/String;)Lcom/keniu/security/sync/d/d/a/cj;
    //   11: pop
    //   12: aload 5
    //   14: aload_1
    //   15: invokevirtual 285	com/keniu/security/sync/d/d/a/cj:b	(Ljava/lang/String;)Lcom/keniu/security/sync/d/d/a/cj;
    //   18: pop
    //   19: aload 5
    //   21: aload_2
    //   22: invokevirtual 287	com/keniu/security/sync/d/d/a/cj:c	(Ljava/lang/String;)Lcom/keniu/security/sync/d/d/a/cj;
    //   25: pop
    //   26: aload 5
    //   28: lload_3
    //   29: invokevirtual 290	com/keniu/security/sync/d/d/a/cj:a	(J)Lcom/keniu/security/sync/d/d/a/cj;
    //   32: pop
    //   33: aload 5
    //   35: iconst_0
    //   36: invokevirtual 293	com/keniu/security/sync/d/d/a/cj:a	(I)Lcom/keniu/security/sync/d/d/a/cj;
    //   39: pop
    //   40: aconst_null
    //   41: astore 11
    //   43: new 56	com/keniu/security/sync/d/e/a
    //   46: dup
    //   47: ldc_w 295
    //   50: invokespecial 61	com/keniu/security/sync/d/e/a:<init>	(Ljava/lang/String;)V
    //   53: astore 12
    //   55: aload 5
    //   57: invokevirtual 298	com/keniu/security/sync/d/d/a/cj:i	()Lcom/keniu/security/sync/d/d/a/ci;
    //   60: aload 12
    //   62: invokevirtual 67	com/keniu/security/sync/d/e/a:b	()Ljava/io/OutputStream;
    //   65: invokevirtual 299	com/keniu/security/sync/d/d/a/ci:a	(Ljava/io/OutputStream;)V
    //   68: aload 12
    //   70: invokevirtual 73	com/keniu/security/sync/d/e/a:c	()Ljava/io/InputStream;
    //   73: invokestatic 304	com/keniu/security/sync/d/d/a/cl:a	(Ljava/io/InputStream;)Lcom/keniu/security/sync/d/d/a/cl;
    //   76: astore 15
    //   78: aload 12
    //   80: invokestatic 81	com/keniu/security/sync/d/a/a:a	(Lcom/keniu/security/sync/d/e/a;)Lcom/keniu/security/sync/d/e/a;
    //   83: pop
    //   84: aload 15
    //   86: areturn
    //   87: astore 13
    //   89: aload 11
    //   91: invokestatic 81	com/keniu/security/sync/d/a/a:a	(Lcom/keniu/security/sync/d/e/a;)Lcom/keniu/security/sync/d/e/a;
    //   94: pop
    //   95: aload 13
    //   97: athrow
    //   98: astore 13
    //   100: aload 12
    //   102: astore 11
    //   104: goto -15 -> 89
    //
    // Exception table:
    //   from	to	target	type
    //   43	55	87	finally
    //   55	78	98	finally
  }

  // ERROR //
  public final com.keniu.security.sync.d.d.a.cx a(String paramString1, String paramString2, String paramString3, String paramString4)
  {
    // Byte code:
    //   0: invokestatic 310	com/keniu/security/sync/d/d/a/cu:t	()Lcom/keniu/security/sync/d/d/a/cv;
    //   3: astore 5
    //   5: aload 5
    //   7: aload_1
    //   8: invokevirtual 315	com/keniu/security/sync/d/d/a/cv:a	(Ljava/lang/String;)Lcom/keniu/security/sync/d/d/a/cv;
    //   11: pop
    //   12: aload 5
    //   14: aload_3
    //   15: invokevirtual 317	com/keniu/security/sync/d/d/a/cv:c	(Ljava/lang/String;)Lcom/keniu/security/sync/d/d/a/cv;
    //   18: pop
    //   19: aload 5
    //   21: aload 4
    //   23: invokevirtual 319	com/keniu/security/sync/d/d/a/cv:d	(Ljava/lang/String;)Lcom/keniu/security/sync/d/d/a/cv;
    //   26: pop
    //   27: aload 5
    //   29: iconst_0
    //   30: invokevirtual 322	com/keniu/security/sync/d/d/a/cv:a	(I)Lcom/keniu/security/sync/d/d/a/cv;
    //   33: pop
    //   34: aload_2
    //   35: ifnull +64 -> 99
    //   38: aload 5
    //   40: aload_2
    //   41: invokevirtual 324	com/keniu/security/sync/d/d/a/cv:b	(Ljava/lang/String;)Lcom/keniu/security/sync/d/d/a/cv;
    //   44: pop
    //   45: aconst_null
    //   46: astore 11
    //   48: aload_0
    //   49: ldc_w 326
    //   52: invokestatic 331	com/keniu/security/sync/i:a	(Ljava/lang/Object;Ljava/lang/String;)V
    //   55: new 56	com/keniu/security/sync/d/e/a
    //   58: dup
    //   59: ldc_w 333
    //   62: invokespecial 61	com/keniu/security/sync/d/e/a:<init>	(Ljava/lang/String;)V
    //   65: astore 14
    //   67: aload 5
    //   69: invokevirtual 336	com/keniu/security/sync/d/d/a/cv:i	()Lcom/keniu/security/sync/d/d/a/cu;
    //   72: aload 14
    //   74: invokevirtual 67	com/keniu/security/sync/d/e/a:b	()Ljava/io/OutputStream;
    //   77: invokevirtual 337	com/keniu/security/sync/d/d/a/cu:a	(Ljava/io/OutputStream;)V
    //   80: aload 14
    //   82: invokevirtual 73	com/keniu/security/sync/d/e/a:c	()Ljava/io/InputStream;
    //   85: invokestatic 342	com/keniu/security/sync/d/d/a/cx:a	(Ljava/io/InputStream;)Lcom/keniu/security/sync/d/d/a/cx;
    //   88: astore 15
    //   90: aload 14
    //   92: invokestatic 81	com/keniu/security/sync/d/a/a:a	(Lcom/keniu/security/sync/d/e/a;)Lcom/keniu/security/sync/d/e/a;
    //   95: pop
    //   96: aload 15
    //   98: areturn
    //   99: aload 5
    //   101: ldc 38
    //   103: invokevirtual 324	com/keniu/security/sync/d/d/a/cv:b	(Ljava/lang/String;)Lcom/keniu/security/sync/d/d/a/cv;
    //   106: pop
    //   107: goto -62 -> 45
    //   110: astore 12
    //   112: aload 11
    //   114: invokestatic 81	com/keniu/security/sync/d/a/a:a	(Lcom/keniu/security/sync/d/e/a;)Lcom/keniu/security/sync/d/e/a;
    //   117: pop
    //   118: aload 12
    //   120: athrow
    //   121: astore 12
    //   123: aload 14
    //   125: astore 11
    //   127: goto -15 -> 112
    //
    // Exception table:
    //   from	to	target	type
    //   48	67	110	finally
    //   67	90	121	finally
  }
}

/* Location:           C:\Users\sandrocheng.21KUNPENG\Desktop\classes_dex2jar\
 * Qualified Name:     com.keniu.security.sync.d.a.a
 * JD-Core Version:    0.6.2
 */