import java.util.HashMap;

final class ff<T extends fh> extends Thread
{
  private static final HashMap<String, byte[]> a = new HashMap();
  private static final short[] b = { 8, 64, 128 };
  private T c;
  private int d = 307200;
  private boolean e = true;
  private ev f = null;
  private fd<T> g;
  private String h;
  private byte[] i;
  private boolean j;
  private byte k = 0;

  public ff(T paramT, boolean paramBoolean, String paramString)
  {
    this.c = paramT;
    this.h = paramString;
    this.j = paramBoolean;
    synchronized (a)
    {
      byte[] arrayOfByte = (byte[])a.get(paramT.e);
      if (arrayOfByte == null)
      {
        arrayOfByte = new byte[0];
        a.put(paramT.e, arrayOfByte);
      }
      this.i = arrayOfByte;
      return;
    }
  }

  // ERROR //
  private void a(java.io.FileOutputStream paramFileOutputStream)
    throws eq
  {
    // Byte code:
    //   0: aconst_null
    //   1: astore_2
    //   2: lconst_0
    //   3: lstore_3
    //   4: getstatic 43	ff:b	[S
    //   7: iconst_1
    //   8: saload
    //   9: bipush 10
    //   11: ishl
    //   12: newarray byte
    //   14: astore 12
    //   16: aload_0
    //   17: getfield 52	ff:f	Lev;
    //   20: ifnonnull +42 -> 62
    //   23: aload_0
    //   24: getfield 56	ff:c	Lfh;
    //   27: getfield 87	fh:h	J
    //   30: lconst_0
    //   31: lcmp
    //   32: ifne +8 -> 40
    //   35: aload_0
    //   36: getfield 56	ff:c	Lfh;
    //   39: pop
    //   40: aload_0
    //   41: aload_0
    //   42: getfield 56	ff:c	Lfh;
    //   45: getfield 89	fh:b	Ljava/lang/String;
    //   48: invokestatic 94	ev:a	(Ljava/lang/String;)Lev;
    //   51: putfield 52	ff:f	Lev;
    //   54: aload_0
    //   55: getfield 52	ff:f	Lev;
    //   58: invokevirtual 97	ev:a	()I
    //   61: pop
    //   62: aload_0
    //   63: getfield 52	ff:f	Lev;
    //   66: invokevirtual 99	ev:c	()I
    //   69: sipush 200
    //   72: if_icmpeq +81 -> 153
    //   75: new 78	eq
    //   78: dup
    //   79: sipush -3000
    //   82: aload_0
    //   83: getfield 52	ff:f	Lev;
    //   86: invokevirtual 99	ev:c	()I
    //   89: iadd
    //   90: new 101	java/lang/StringBuilder
    //   93: dup
    //   94: ldc 103
    //   96: invokespecial 106	java/lang/StringBuilder:<init>	(Ljava/lang/String;)V
    //   99: aload_0
    //   100: getfield 52	ff:f	Lev;
    //   103: invokevirtual 99	ev:c	()I
    //   106: invokevirtual 110	java/lang/StringBuilder:append	(I)Ljava/lang/StringBuilder;
    //   109: invokevirtual 114	java/lang/StringBuilder:toString	()Ljava/lang/String;
    //   112: invokespecial 117	eq:<init>	(ILjava/lang/String;)V
    //   115: athrow
    //   116: astore 11
    //   118: aload 11
    //   120: athrow
    //   121: astore 7
    //   123: aload_2
    //   124: astore 6
    //   126: aload 6
    //   128: ifnull +8 -> 136
    //   131: aload 6
    //   133: invokevirtual 122	java/io/BufferedInputStream:close	()V
    //   136: lload_3
    //   137: lconst_0
    //   138: lcmp
    //   139: ifle +11 -> 150
    //   142: lload_3
    //   143: invokestatic 127	fj:a	()J
    //   146: ladd
    //   147: invokestatic 130	fj:a	(J)V
    //   150: aload 7
    //   152: athrow
    //   153: new 119	java/io/BufferedInputStream
    //   156: dup
    //   157: aload_0
    //   158: getfield 52	ff:f	Lev;
    //   161: invokevirtual 133	ev:b	()Ljava/io/InputStream;
    //   164: aload 12
    //   166: arraylength
    //   167: invokespecial 136	java/io/BufferedInputStream:<init>	(Ljava/io/InputStream;I)V
    //   170: astore 6
    //   172: invokestatic 141	java/lang/System:currentTimeMillis	()J
    //   175: lstore 13
    //   177: aload_0
    //   178: getfield 56	ff:c	Lfh;
    //   181: getfield 87	fh:h	J
    //   184: lstore 15
    //   186: invokestatic 146	bk:a	()LQQPIM/ConnectType;
    //   189: getstatic 152	QQPIM/ConnectType:CT_WIFI	LQQPIM/ConnectType;
    //   192: if_acmpeq +40 -> 232
    //   195: iconst_1
    //   196: istore 17
    //   198: goto +595 -> 793
    //   201: aload_0
    //   202: getfield 50	ff:e	Z
    //   205: istore 20
    //   207: iload 20
    //   209: ifne +29 -> 238
    //   212: aload 6
    //   214: invokevirtual 122	java/io/BufferedInputStream:close	()V
    //   217: lload_3
    //   218: lconst_0
    //   219: lcmp
    //   220: ifle +11 -> 231
    //   223: lload_3
    //   224: invokestatic 127	fj:a	()J
    //   227: ladd
    //   228: invokestatic 130	fj:a	(J)V
    //   231: return
    //   232: iconst_0
    //   233: istore 17
    //   235: goto +558 -> 793
    //   238: aload 6
    //   240: aload 18
    //   242: invokevirtual 156	java/io/BufferedInputStream:read	([B)I
    //   245: istore 21
    //   247: iload 21
    //   249: ifgt +50 -> 299
    //   252: aload_0
    //   253: getfield 56	ff:c	Lfh;
    //   256: getfield 87	fh:h	J
    //   259: aload_0
    //   260: getfield 56	ff:c	Lfh;
    //   263: getfield 158	fh:g	J
    //   266: lcmp
    //   267: ifle -55 -> 212
    //   270: aload_0
    //   271: getfield 56	ff:c	Lfh;
    //   274: getfield 158	fh:g	J
    //   277: lconst_0
    //   278: lcmp
    //   279: ifle -67 -> 212
    //   282: aload_0
    //   283: getfield 56	ff:c	Lfh;
    //   286: aload_0
    //   287: getfield 56	ff:c	Lfh;
    //   290: getfield 87	fh:h	J
    //   293: putfield 158	fh:g	J
    //   296: goto -84 -> 212
    //   299: aload_1
    //   300: aload 18
    //   302: iconst_0
    //   303: iload 21
    //   305: invokevirtual 164	java/io/FileOutputStream:write	([BII)V
    //   308: aload_0
    //   309: getfield 56	ff:c	Lfh;
    //   312: astore 22
    //   314: aload 22
    //   316: aload 22
    //   318: getfield 87	fh:h	J
    //   321: iload 21
    //   323: i2l
    //   324: ladd
    //   325: putfield 87	fh:h	J
    //   328: iload 19
    //   330: iload 21
    //   332: iadd
    //   333: istore 19
    //   335: iload 17
    //   337: ifeq +9 -> 346
    //   340: lload_3
    //   341: iload 21
    //   343: i2l
    //   344: ladd
    //   345: lstore_3
    //   346: aload_0
    //   347: getfield 56	ff:c	Lfh;
    //   350: getfield 158	fh:g	J
    //   353: aload_0
    //   354: getfield 56	ff:c	Lfh;
    //   357: getfield 87	fh:h	J
    //   360: lcmp
    //   361: ifne +51 -> 412
    //   364: aload_0
    //   365: getfield 56	ff:c	Lfh;
    //   368: fconst_1
    //   369: putfield 167	fh:i	F
    //   372: goto -160 -> 212
    //   375: astore 5
    //   377: new 78	eq
    //   380: dup
    //   381: bipush 197
    //   383: new 101	java/lang/StringBuilder
    //   386: dup
    //   387: ldc 169
    //   389: invokespecial 106	java/lang/StringBuilder:<init>	(Ljava/lang/String;)V
    //   392: aload 5
    //   394: invokevirtual 172	java/io/UnsupportedEncodingException:getMessage	()Ljava/lang/String;
    //   397: invokevirtual 175	java/lang/StringBuilder:append	(Ljava/lang/String;)Ljava/lang/StringBuilder;
    //   400: invokevirtual 114	java/lang/StringBuilder:toString	()Ljava/lang/String;
    //   403: invokespecial 117	eq:<init>	(ILjava/lang/String;)V
    //   406: athrow
    //   407: astore 7
    //   409: goto -283 -> 126
    //   412: aload_0
    //   413: getfield 56	ff:c	Lfh;
    //   416: getfield 158	fh:g	J
    //   419: lconst_0
    //   420: lcmp
    //   421: ifle +38 -> 459
    //   424: aload_0
    //   425: getfield 56	ff:c	Lfh;
    //   428: aload_0
    //   429: getfield 56	ff:c	Lfh;
    //   432: getfield 87	fh:h	J
    //   435: l2f
    //   436: aload_0
    //   437: getfield 56	ff:c	Lfh;
    //   440: getfield 158	fh:g	J
    //   443: l2f
    //   444: fdiv
    //   445: putfield 167	fh:i	F
    //   448: aload_0
    //   449: getfield 177	ff:g	Lfd;
    //   452: aload_0
    //   453: getfield 56	ff:c	Lfh;
    //   456: invokevirtual 182	fd:e	(Lfh;)V
    //   459: aload_0
    //   460: getfield 50	ff:e	Z
    //   463: ifeq -251 -> 212
    //   466: iload 19
    //   468: aload_0
    //   469: getfield 48	ff:d	I
    //   472: if_icmple -271 -> 201
    //   475: invokestatic 141	java/lang/System:currentTimeMillis	()J
    //   478: lload 13
    //   480: lsub
    //   481: lstore 23
    //   483: lload 23
    //   485: lconst_0
    //   486: lcmp
    //   487: ifgt +6 -> 493
    //   490: lconst_1
    //   491: lstore 23
    //   493: aload_0
    //   494: getfield 56	ff:c	Lfh;
    //   497: getfield 87	fh:h	J
    //   500: lload 15
    //   502: lsub
    //   503: lload 23
    //   505: ldiv
    //   506: l2i
    //   507: istore 25
    //   509: aload_0
    //   510: getfield 56	ff:c	Lfh;
    //   513: getfield 184	fh:j	I
    //   516: ifne +67 -> 583
    //   519: aload_0
    //   520: getfield 56	ff:c	Lfh;
    //   523: iload 25
    //   525: putfield 184	fh:j	I
    //   528: iload 25
    //   530: bipush 33
    //   532: if_icmpge +106 -> 638
    //   535: aload 18
    //   537: arraylength
    //   538: getstatic 43	ff:b	[S
    //   541: iconst_0
    //   542: saload
    //   543: bipush 10
    //   545: ishl
    //   546: if_icmpeq +15 -> 561
    //   549: getstatic 43	ff:b	[S
    //   552: iconst_0
    //   553: saload
    //   554: bipush 10
    //   556: ishl
    //   557: newarray byte
    //   559: astore 18
    //   561: lload_3
    //   562: lconst_0
    //   563: lcmp
    //   564: ifle +223 -> 787
    //   567: lload_3
    //   568: invokestatic 127	fj:a	()J
    //   571: ladd
    //   572: invokestatic 130	fj:a	(J)V
    //   575: lconst_0
    //   576: lstore_3
    //   577: iconst_0
    //   578: istore 19
    //   580: goto -379 -> 201
    //   583: aload_0
    //   584: getfield 56	ff:c	Lfh;
    //   587: iload 25
    //   589: aload_0
    //   590: getfield 56	ff:c	Lfh;
    //   593: getfield 184	fh:j	I
    //   596: iadd
    //   597: iconst_2
    //   598: idiv
    //   599: putfield 184	fh:j	I
    //   602: goto -74 -> 528
    //   605: astore 9
    //   607: new 78	eq
    //   610: dup
    //   611: sipush -7056
    //   614: new 101	java/lang/StringBuilder
    //   617: dup
    //   618: ldc 186
    //   620: invokespecial 106	java/lang/StringBuilder:<init>	(Ljava/lang/String;)V
    //   623: aload 9
    //   625: invokevirtual 187	java/io/IOException:getMessage	()Ljava/lang/String;
    //   628: invokevirtual 175	java/lang/StringBuilder:append	(Ljava/lang/String;)Ljava/lang/StringBuilder;
    //   631: invokevirtual 114	java/lang/StringBuilder:toString	()Ljava/lang/String;
    //   634: invokespecial 117	eq:<init>	(ILjava/lang/String;)V
    //   637: athrow
    //   638: iload 25
    //   640: bipush 65
    //   642: if_icmpge +32 -> 674
    //   645: aload 18
    //   647: arraylength
    //   648: getstatic 43	ff:b	[S
    //   651: iconst_1
    //   652: saload
    //   653: bipush 10
    //   655: ishl
    //   656: if_icmpeq -95 -> 561
    //   659: getstatic 43	ff:b	[S
    //   662: iconst_1
    //   663: saload
    //   664: bipush 10
    //   666: ishl
    //   667: newarray byte
    //   669: astore 18
    //   671: goto -110 -> 561
    //   674: aload 18
    //   676: arraylength
    //   677: getstatic 43	ff:b	[S
    //   680: iconst_2
    //   681: saload
    //   682: bipush 10
    //   684: ishl
    //   685: if_icmpeq -124 -> 561
    //   688: getstatic 43	ff:b	[S
    //   691: iconst_2
    //   692: saload
    //   693: bipush 10
    //   695: ishl
    //   696: newarray byte
    //   698: astore 18
    //   700: goto -139 -> 561
    //   703: astore 10
    //   705: aconst_null
    //   706: astore 6
    //   708: new 78	eq
    //   711: dup
    //   712: bipush 254
    //   714: new 101	java/lang/StringBuilder
    //   717: dup
    //   718: ldc 189
    //   720: invokespecial 106	java/lang/StringBuilder:<init>	(Ljava/lang/String;)V
    //   723: aload 10
    //   725: invokevirtual 190	java/lang/Exception:getMessage	()Ljava/lang/String;
    //   728: invokevirtual 175	java/lang/StringBuilder:append	(Ljava/lang/String;)Ljava/lang/StringBuilder;
    //   731: invokevirtual 114	java/lang/StringBuilder:toString	()Ljava/lang/String;
    //   734: invokespecial 117	eq:<init>	(ILjava/lang/String;)V
    //   737: athrow
    //   738: astore 8
    //   740: aload 8
    //   742: invokevirtual 193	java/lang/Exception:printStackTrace	()V
    //   745: goto -609 -> 136
    //   748: astore 26
    //   750: aload 26
    //   752: invokevirtual 193	java/lang/Exception:printStackTrace	()V
    //   755: goto -538 -> 217
    //   758: astore 7
    //   760: aconst_null
    //   761: astore 6
    //   763: goto -637 -> 126
    //   766: astore 10
    //   768: goto -60 -> 708
    //   771: astore 9
    //   773: aconst_null
    //   774: astore 6
    //   776: goto -169 -> 607
    //   779: astore 5
    //   781: aconst_null
    //   782: astore 6
    //   784: goto -407 -> 377
    //   787: iconst_0
    //   788: istore 19
    //   790: goto -589 -> 201
    //   793: aload 12
    //   795: astore 18
    //   797: iconst_0
    //   798: istore 19
    //   800: goto -599 -> 201
    //   803: astore 11
    //   805: aload 6
    //   807: astore_2
    //   808: goto -690 -> 118
    //
    // Exception table:
    //   from	to	target	type
    //   4	116	116	eq
    //   153	172	116	eq
    //   118	121	121	finally
    //   172	207	375	java/io/UnsupportedEncodingException
    //   238	372	375	java/io/UnsupportedEncodingException
    //   412	602	375	java/io/UnsupportedEncodingException
    //   645	700	375	java/io/UnsupportedEncodingException
    //   172	207	407	finally
    //   238	372	407	finally
    //   377	407	407	finally
    //   412	602	407	finally
    //   607	638	407	finally
    //   645	700	407	finally
    //   708	738	407	finally
    //   172	207	605	java/io/IOException
    //   238	372	605	java/io/IOException
    //   412	602	605	java/io/IOException
    //   645	700	605	java/io/IOException
    //   4	116	703	java/lang/Exception
    //   153	172	703	java/lang/Exception
    //   131	136	738	java/lang/Exception
    //   212	217	748	java/lang/Exception
    //   4	116	758	finally
    //   153	172	758	finally
    //   172	207	766	java/lang/Exception
    //   238	372	766	java/lang/Exception
    //   412	602	766	java/lang/Exception
    //   645	700	766	java/lang/Exception
    //   4	116	771	java/io/IOException
    //   153	172	771	java/io/IOException
    //   4	116	779	java/io/UnsupportedEncodingException
    //   153	172	779	java/io/UnsupportedEncodingException
    //   172	207	803	eq
    //   238	372	803	eq
    //   412	602	803	eq
    //   645	700	803	eq
  }

  // ERROR //
  private void b(java.io.FileOutputStream paramFileOutputStream)
    throws eq
  {
    // Byte code:
    //   0: aconst_null
    //   1: astore_2
    //   2: lconst_0
    //   3: lstore_3
    //   4: iconst_0
    //   5: istore 5
    //   7: aconst_null
    //   8: astore 6
    //   10: iconst_1
    //   11: istore 7
    //   13: getstatic 43	ff:b	[S
    //   16: iconst_1
    //   17: saload
    //   18: bipush 10
    //   20: ishl
    //   21: newarray byte
    //   23: astore 30
    //   25: iconst_1
    //   26: istore 31
    //   28: aload_0
    //   29: getfield 50	ff:e	Z
    //   32: istore 32
    //   34: aconst_null
    //   35: astore_2
    //   36: iload 32
    //   38: ifeq +19 -> 57
    //   41: aload_0
    //   42: getfield 56	ff:c	Lfh;
    //   45: getfield 167	fh:i	F
    //   48: fstore 34
    //   50: fload 34
    //   52: fconst_1
    //   53: fcmpl
    //   54: ifne +33 -> 87
    //   57: aload_0
    //   58: getfield 54	ff:k	B
    //   61: ifle +11 -> 72
    //   64: aload_1
    //   65: ifnull +7 -> 72
    //   68: aload_1
    //   69: invokevirtual 194	java/io/FileOutputStream:close	()V
    //   72: lload_3
    //   73: lconst_0
    //   74: lcmp
    //   75: ifle +11 -> 86
    //   78: lload_3
    //   79: invokestatic 127	fj:a	()J
    //   82: ladd
    //   83: invokestatic 130	fj:a	(J)V
    //   86: return
    //   87: new 196	java/lang/StringBuffer
    //   90: dup
    //   91: invokespecial 197	java/lang/StringBuffer:<init>	()V
    //   94: astore 35
    //   96: aload_0
    //   97: getfield 56	ff:c	Lfh;
    //   100: getfield 87	fh:h	J
    //   103: lstore 36
    //   105: lload 36
    //   107: lconst_1
    //   108: aload_0
    //   109: getfield 48	ff:d	I
    //   112: i2l
    //   113: lmul
    //   114: iload 7
    //   116: i2l
    //   117: lmul
    //   118: ladd
    //   119: lconst_1
    //   120: lsub
    //   121: lstore 38
    //   123: lload 38
    //   125: aload_0
    //   126: getfield 56	ff:c	Lfh;
    //   129: getfield 158	fh:g	J
    //   132: lcmp
    //   133: istore 40
    //   135: aconst_null
    //   136: astore_2
    //   137: iload 40
    //   139: iflt +14 -> 153
    //   142: aload_0
    //   143: getfield 56	ff:c	Lfh;
    //   146: getfield 158	fh:g	J
    //   149: lconst_1
    //   150: lsub
    //   151: lstore 38
    //   153: lload 36
    //   155: lload 38
    //   157: lcmp
    //   158: istore 41
    //   160: aconst_null
    //   161: astore_2
    //   162: iload 41
    //   164: ifge -107 -> 57
    //   167: aload 35
    //   169: ldc 199
    //   171: invokevirtual 202	java/lang/StringBuffer:append	(Ljava/lang/String;)Ljava/lang/StringBuffer;
    //   174: lload 36
    //   176: invokevirtual 205	java/lang/StringBuffer:append	(J)Ljava/lang/StringBuffer;
    //   179: bipush 45
    //   181: invokevirtual 208	java/lang/StringBuffer:append	(C)Ljava/lang/StringBuffer;
    //   184: lload 38
    //   186: invokevirtual 205	java/lang/StringBuffer:append	(J)Ljava/lang/StringBuffer;
    //   189: pop
    //   190: aload_0
    //   191: getfield 50	ff:e	Z
    //   194: istore 43
    //   196: aconst_null
    //   197: astore_2
    //   198: iload 43
    //   200: ifeq -143 -> 57
    //   203: iconst_0
    //   204: istore 5
    //   206: aload_0
    //   207: getfield 52	ff:f	Lev;
    //   210: astore 44
    //   212: aconst_null
    //   213: astore_2
    //   214: iconst_0
    //   215: istore 5
    //   217: aload 44
    //   219: ifnonnull +180 -> 399
    //   222: aload_0
    //   223: getfield 56	ff:c	Lfh;
    //   226: pop
    //   227: aload_0
    //   228: aload_0
    //   229: getfield 56	ff:c	Lfh;
    //   232: getfield 89	fh:b	Ljava/lang/String;
    //   235: invokestatic 94	ev:a	(Ljava/lang/String;)Lev;
    //   238: putfield 52	ff:f	Lev;
    //   241: aload_0
    //   242: getfield 52	ff:f	Lev;
    //   245: ldc 210
    //   247: aload 35
    //   249: invokevirtual 211	java/lang/StringBuffer:toString	()Ljava/lang/String;
    //   252: invokevirtual 214	ev:a	(Ljava/lang/String;Ljava/lang/String;)V
    //   255: aload_0
    //   256: getfield 52	ff:f	Lev;
    //   259: invokevirtual 97	ev:a	()I
    //   262: pop
    //   263: aload_0
    //   264: getfield 50	ff:e	Z
    //   267: istore 46
    //   269: aconst_null
    //   270: astore_2
    //   271: iconst_0
    //   272: istore 5
    //   274: iload 46
    //   276: ifeq -219 -> 57
    //   279: aload_0
    //   280: getfield 52	ff:f	Lev;
    //   283: invokevirtual 99	ev:c	()I
    //   286: istore 47
    //   288: aconst_null
    //   289: astore_2
    //   290: iconst_0
    //   291: istore 5
    //   293: iload 47
    //   295: sipush 206
    //   298: if_icmpeq +181 -> 479
    //   301: new 78	eq
    //   304: dup
    //   305: sipush -3000
    //   308: aload_0
    //   309: getfield 52	ff:f	Lev;
    //   312: invokevirtual 99	ev:c	()I
    //   315: iadd
    //   316: new 101	java/lang/StringBuilder
    //   319: dup
    //   320: ldc 216
    //   322: invokespecial 106	java/lang/StringBuilder:<init>	(Ljava/lang/String;)V
    //   325: aload_0
    //   326: getfield 52	ff:f	Lev;
    //   329: invokevirtual 99	ev:c	()I
    //   332: invokevirtual 110	java/lang/StringBuilder:append	(I)Ljava/lang/StringBuilder;
    //   335: invokevirtual 114	java/lang/StringBuilder:toString	()Ljava/lang/String;
    //   338: invokespecial 117	eq:<init>	(ILjava/lang/String;)V
    //   341: athrow
    //   342: astore 29
    //   344: aload 29
    //   346: athrow
    //   347: astore 14
    //   349: aload_2
    //   350: ifnull +7 -> 357
    //   353: aload_2
    //   354: invokevirtual 122	java/io/BufferedInputStream:close	()V
    //   357: aload_0
    //   358: getfield 54	ff:k	B
    //   361: ifle +11 -> 372
    //   364: aload_1
    //   365: ifnull +7 -> 372
    //   368: aload_1
    //   369: invokevirtual 194	java/io/FileOutputStream:close	()V
    //   372: aload 6
    //   374: ifnull +8 -> 382
    //   377: aload 6
    //   379: invokevirtual 219	java/nio/channels/FileChannel:close	()V
    //   382: lload_3
    //   383: lconst_0
    //   384: lcmp
    //   385: ifle +11 -> 396
    //   388: lload_3
    //   389: invokestatic 127	fj:a	()J
    //   392: ladd
    //   393: invokestatic 130	fj:a	(J)V
    //   396: aload 14
    //   398: athrow
    //   399: iload 31
    //   401: ifne -138 -> 263
    //   404: aload_0
    //   405: getfield 52	ff:f	Lev;
    //   408: invokevirtual 221	ev:d	()V
    //   411: aload_0
    //   412: aload_0
    //   413: getfield 52	ff:f	Lev;
    //   416: invokestatic 224	ev:a	(Lev;)Lev;
    //   419: putfield 52	ff:f	Lev;
    //   422: aload_0
    //   423: getfield 52	ff:f	Lev;
    //   426: ldc 210
    //   428: aload 35
    //   430: invokevirtual 211	java/lang/StringBuffer:toString	()Ljava/lang/String;
    //   433: invokevirtual 214	ev:a	(Ljava/lang/String;Ljava/lang/String;)V
    //   436: aload_0
    //   437: getfield 52	ff:f	Lev;
    //   440: invokevirtual 97	ev:a	()I
    //   443: pop
    //   444: goto -181 -> 263
    //   447: astore 28
    //   449: new 78	eq
    //   452: dup
    //   453: bipush 197
    //   455: new 101	java/lang/StringBuilder
    //   458: dup
    //   459: ldc 226
    //   461: invokespecial 106	java/lang/StringBuilder:<init>	(Ljava/lang/String;)V
    //   464: aload 28
    //   466: invokevirtual 172	java/io/UnsupportedEncodingException:getMessage	()Ljava/lang/String;
    //   469: invokevirtual 175	java/lang/StringBuilder:append	(Ljava/lang/String;)Ljava/lang/StringBuilder;
    //   472: invokevirtual 114	java/lang/StringBuilder:toString	()Ljava/lang/String;
    //   475: invokespecial 117	eq:<init>	(ILjava/lang/String;)V
    //   478: athrow
    //   479: iload 31
    //   481: ifeq +1194 -> 1675
    //   484: iconst_0
    //   485: istore 48
    //   487: invokestatic 146	bk:a	()LQQPIM/ConnectType;
    //   490: astore 49
    //   492: getstatic 152	QQPIM/ConnectType:CT_WIFI	LQQPIM/ConnectType;
    //   495: astore 50
    //   497: aconst_null
    //   498: astore_2
    //   499: iconst_0
    //   500: istore 5
    //   502: aload 49
    //   504: aload 50
    //   506: if_acmpeq +218 -> 724
    //   509: iconst_1
    //   510: istore 51
    //   512: aload_0
    //   513: getfield 50	ff:e	Z
    //   516: istore 52
    //   518: iload 52
    //   520: ifeq -463 -> 57
    //   523: iconst_1
    //   524: istore 53
    //   526: new 119	java/io/BufferedInputStream
    //   529: dup
    //   530: aload_0
    //   531: getfield 52	ff:f	Lev;
    //   534: invokevirtual 133	ev:b	()Ljava/io/InputStream;
    //   537: aload 30
    //   539: arraylength
    //   540: invokespecial 136	java/io/BufferedInputStream:<init>	(Ljava/io/InputStream;I)V
    //   543: astore 13
    //   545: invokestatic 141	java/lang/System:currentTimeMillis	()J
    //   548: lstore 54
    //   550: iload 53
    //   552: istore 56
    //   554: aload_0
    //   555: getfield 50	ff:e	Z
    //   558: istore 58
    //   560: iload 58
    //   562: ifne +168 -> 730
    //   565: iload 56
    //   567: istore 53
    //   569: aload 13
    //   571: invokevirtual 122	java/io/BufferedInputStream:close	()V
    //   574: aconst_null
    //   575: astore_2
    //   576: invokestatic 141	java/lang/System:currentTimeMillis	()J
    //   579: lload 54
    //   581: lsub
    //   582: lstore 64
    //   584: lload 64
    //   586: lconst_0
    //   587: lcmp
    //   588: istore 66
    //   590: aconst_null
    //   591: astore_2
    //   592: iload 66
    //   594: ifgt +6 -> 600
    //   597: lconst_1
    //   598: lstore 64
    //   600: aload_0
    //   601: getfield 56	ff:c	Lfh;
    //   604: getfield 87	fh:h	J
    //   607: lload 36
    //   609: lsub
    //   610: lload 64
    //   612: ldiv
    //   613: l2i
    //   614: istore 67
    //   616: aload_0
    //   617: getfield 56	ff:c	Lfh;
    //   620: getfield 184	fh:j	I
    //   623: istore 68
    //   625: aconst_null
    //   626: astore_2
    //   627: iload 68
    //   629: ifne +363 -> 992
    //   632: aload_0
    //   633: getfield 56	ff:c	Lfh;
    //   636: iload 67
    //   638: putfield 184	fh:j	I
    //   641: aconst_null
    //   642: astore_2
    //   643: iload 67
    //   645: bipush 33
    //   647: if_icmpge +544 -> 1191
    //   650: iconst_1
    //   651: istore 69
    //   653: aload 30
    //   655: arraylength
    //   656: istore 74
    //   658: getstatic 43	ff:b	[S
    //   661: iconst_0
    //   662: saload
    //   663: bipush 10
    //   665: ishl
    //   666: istore 75
    //   668: aconst_null
    //   669: astore_2
    //   670: iload 74
    //   672: iload 75
    //   674: if_icmpeq +994 -> 1668
    //   677: getstatic 43	ff:b	[S
    //   680: iconst_0
    //   681: saload
    //   682: bipush 10
    //   684: ishl
    //   685: newarray byte
    //   687: astore 30
    //   689: iload 69
    //   691: istore 7
    //   693: lload_3
    //   694: lconst_0
    //   695: lcmp
    //   696: ifle +961 -> 1657
    //   699: bipush 6
    //   701: istore 5
    //   703: lload_3
    //   704: invokestatic 127	fj:a	()J
    //   707: ladd
    //   708: invokestatic 130	fj:a	(J)V
    //   711: lconst_0
    //   712: lstore_3
    //   713: bipush 7
    //   715: istore 5
    //   717: iload 48
    //   719: istore 31
    //   721: goto -693 -> 28
    //   724: iconst_0
    //   725: istore 51
    //   727: goto -215 -> 512
    //   730: iconst_2
    //   731: istore 56
    //   733: aload 13
    //   735: aload 30
    //   737: invokevirtual 156	java/io/BufferedInputStream:read	([B)I
    //   740: istore 59
    //   742: iload 59
    //   744: ifgt +62 -> 806
    //   747: aload_0
    //   748: getfield 56	ff:c	Lfh;
    //   751: getfield 87	fh:h	J
    //   754: aload_0
    //   755: getfield 56	ff:c	Lfh;
    //   758: getfield 158	fh:g	J
    //   761: lcmp
    //   762: ifle -197 -> 565
    //   765: aload_0
    //   766: getfield 56	ff:c	Lfh;
    //   769: getfield 158	fh:g	J
    //   772: lconst_0
    //   773: lcmp
    //   774: ifle -209 -> 565
    //   777: aload_0
    //   778: getfield 56	ff:c	Lfh;
    //   781: aload_0
    //   782: getfield 56	ff:c	Lfh;
    //   785: getfield 87	fh:h	J
    //   788: putfield 158	fh:g	J
    //   791: aload_0
    //   792: getfield 56	ff:c	Lfh;
    //   795: fconst_1
    //   796: putfield 167	fh:i	F
    //   799: iload 56
    //   801: istore 53
    //   803: goto -234 -> 569
    //   806: aload_0
    //   807: getfield 50	ff:e	Z
    //   810: istore 60
    //   812: iload 60
    //   814: ifeq -249 -> 565
    //   817: iconst_3
    //   818: istore 56
    //   820: aload_1
    //   821: aload 30
    //   823: iconst_0
    //   824: iload 59
    //   826: invokevirtual 164	java/io/FileOutputStream:write	([BII)V
    //   829: aload_1
    //   830: invokevirtual 229	java/io/FileOutputStream:flush	()V
    //   833: aload_0
    //   834: getfield 56	ff:c	Lfh;
    //   837: astore 62
    //   839: aload 62
    //   841: aload 62
    //   843: getfield 87	fh:h	J
    //   846: iload 59
    //   848: i2l
    //   849: ladd
    //   850: putfield 87	fh:h	J
    //   853: iload 51
    //   855: ifeq +9 -> 864
    //   858: lload_3
    //   859: iload 59
    //   861: i2l
    //   862: ladd
    //   863: lstore_3
    //   864: aload_0
    //   865: getfield 56	ff:c	Lfh;
    //   868: getfield 158	fh:g	J
    //   871: aload_0
    //   872: getfield 56	ff:c	Lfh;
    //   875: getfield 87	fh:h	J
    //   878: lcmp
    //   879: ifne +51 -> 930
    //   882: aload_0
    //   883: getfield 56	ff:c	Lfh;
    //   886: fconst_1
    //   887: putfield 167	fh:i	F
    //   890: iload 56
    //   892: istore 53
    //   894: goto -325 -> 569
    //   897: astore 61
    //   899: new 78	eq
    //   902: dup
    //   903: sipush -7056
    //   906: new 101	java/lang/StringBuilder
    //   909: dup
    //   910: ldc 231
    //   912: invokespecial 106	java/lang/StringBuilder:<init>	(Ljava/lang/String;)V
    //   915: aload 61
    //   917: invokevirtual 187	java/io/IOException:getMessage	()Ljava/lang/String;
    //   920: invokevirtual 175	java/lang/StringBuilder:append	(Ljava/lang/String;)Ljava/lang/StringBuilder;
    //   923: invokevirtual 114	java/lang/StringBuilder:toString	()Ljava/lang/String;
    //   926: invokespecial 117	eq:<init>	(ILjava/lang/String;)V
    //   929: athrow
    //   930: aload_0
    //   931: getfield 56	ff:c	Lfh;
    //   934: aload_0
    //   935: getfield 56	ff:c	Lfh;
    //   938: getfield 87	fh:h	J
    //   941: l2f
    //   942: aload_0
    //   943: getfield 56	ff:c	Lfh;
    //   946: getfield 158	fh:g	J
    //   949: l2f
    //   950: fdiv
    //   951: putfield 167	fh:i	F
    //   954: iconst_4
    //   955: istore 56
    //   957: aload_0
    //   958: getfield 177	ff:g	Lfd;
    //   961: aload_0
    //   962: getfield 56	ff:c	Lfh;
    //   965: invokevirtual 182	fd:e	(Lfh;)V
    //   968: iconst_5
    //   969: istore 56
    //   971: goto -417 -> 554
    //   974: astore 63
    //   976: aload 63
    //   978: invokevirtual 193	java/lang/Exception:printStackTrace	()V
    //   981: goto -407 -> 574
    //   984: astore 28
    //   986: aload 13
    //   988: astore_2
    //   989: goto -540 -> 449
    //   992: aload_0
    //   993: getfield 56	ff:c	Lfh;
    //   996: iload 67
    //   998: aload_0
    //   999: getfield 56	ff:c	Lfh;
    //   1002: getfield 184	fh:j	I
    //   1005: iadd
    //   1006: iconst_2
    //   1007: idiv
    //   1008: putfield 184	fh:j	I
    //   1011: goto -370 -> 641
    //   1014: astore 8
    //   1016: aconst_null
    //   1017: astore 13
    //   1019: lload_3
    //   1020: lstore 10
    //   1022: iload 53
    //   1024: istore 12
    //   1026: aload_0
    //   1027: getfield 50	ff:e	Z
    //   1030: ifeq +330 -> 1360
    //   1033: aload_0
    //   1034: getfield 54	ff:k	B
    //   1037: istore 18
    //   1039: aload_0
    //   1040: iload 18
    //   1042: iconst_1
    //   1043: iadd
    //   1044: i2b
    //   1045: putfield 54	ff:k	B
    //   1048: iload 18
    //   1050: bipush 10
    //   1052: if_icmpge +308 -> 1360
    //   1055: aload_1
    //   1056: invokevirtual 229	java/io/FileOutputStream:flush	()V
    //   1059: aload_1
    //   1060: invokevirtual 194	java/io/FileOutputStream:close	()V
    //   1063: aload_0
    //   1064: getfield 52	ff:f	Lev;
    //   1067: invokevirtual 221	ev:d	()V
    //   1070: aload_0
    //   1071: aconst_null
    //   1072: putfield 52	ff:f	Lev;
    //   1075: aload_0
    //   1076: getfield 56	ff:c	Lfh;
    //   1079: new 233	java/io/File
    //   1082: dup
    //   1083: aload_0
    //   1084: getfield 58	ff:h	Ljava/lang/String;
    //   1087: invokespecial 234	java/io/File:<init>	(Ljava/lang/String;)V
    //   1090: invokevirtual 237	java/io/File:length	()J
    //   1093: putfield 87	fh:h	J
    //   1096: new 160	java/io/FileOutputStream
    //   1099: dup
    //   1100: aload_0
    //   1101: getfield 58	ff:h	Ljava/lang/String;
    //   1104: iconst_1
    //   1105: invokespecial 240	java/io/FileOutputStream:<init>	(Ljava/lang/String;Z)V
    //   1108: astore 21
    //   1110: aload 21
    //   1112: invokevirtual 244	java/io/FileOutputStream:getChannel	()Ljava/nio/channels/FileChannel;
    //   1115: astore 22
    //   1117: aload 22
    //   1119: astore 20
    //   1121: aload 20
    //   1123: aload_0
    //   1124: getfield 56	ff:c	Lfh;
    //   1127: getfield 87	fh:h	J
    //   1130: invokevirtual 248	java/nio/channels/FileChannel:position	(J)Ljava/nio/channels/FileChannel;
    //   1133: pop
    //   1134: aload_0
    //   1135: aload 21
    //   1137: invokespecial 250	ff:b	(Ljava/io/FileOutputStream;)V
    //   1140: aload 13
    //   1142: ifnull +8 -> 1150
    //   1145: aload 13
    //   1147: invokevirtual 122	java/io/BufferedInputStream:close	()V
    //   1150: aload_0
    //   1151: getfield 54	ff:k	B
    //   1154: ifle +8 -> 1162
    //   1157: aload 21
    //   1159: invokevirtual 194	java/io/FileOutputStream:close	()V
    //   1162: aload 20
    //   1164: ifnull +8 -> 1172
    //   1167: aload 20
    //   1169: invokevirtual 219	java/nio/channels/FileChannel:close	()V
    //   1172: lload 10
    //   1174: lconst_0
    //   1175: lcmp
    //   1176: ifle -1090 -> 86
    //   1179: lload 10
    //   1181: invokestatic 127	fj:a	()J
    //   1184: ladd
    //   1185: invokestatic 130	fj:a	(J)V
    //   1188: goto -1102 -> 86
    //   1191: iload 67
    //   1193: bipush 65
    //   1195: if_icmpge +51 -> 1246
    //   1198: iconst_2
    //   1199: istore 69
    //   1201: aload 30
    //   1203: arraylength
    //   1204: istore 72
    //   1206: getstatic 43	ff:b	[S
    //   1209: iconst_1
    //   1210: saload
    //   1211: bipush 10
    //   1213: ishl
    //   1214: istore 73
    //   1216: aconst_null
    //   1217: astore_2
    //   1218: iload 72
    //   1220: iload 73
    //   1222: if_icmpeq +446 -> 1668
    //   1225: getstatic 43	ff:b	[S
    //   1228: iconst_1
    //   1229: saload
    //   1230: bipush 10
    //   1232: ishl
    //   1233: newarray byte
    //   1235: astore 30
    //   1237: iload 69
    //   1239: istore 7
    //   1241: aconst_null
    //   1242: astore_2
    //   1243: goto -550 -> 693
    //   1246: iconst_3
    //   1247: istore 69
    //   1249: aload 30
    //   1251: arraylength
    //   1252: istore 70
    //   1254: getstatic 43	ff:b	[S
    //   1257: iconst_2
    //   1258: saload
    //   1259: bipush 10
    //   1261: ishl
    //   1262: istore 71
    //   1264: aconst_null
    //   1265: astore_2
    //   1266: iload 70
    //   1268: iload 71
    //   1270: if_icmpeq +398 -> 1668
    //   1273: getstatic 43	ff:b	[S
    //   1276: iconst_2
    //   1277: saload
    //   1278: bipush 10
    //   1280: ishl
    //   1281: newarray byte
    //   1283: astore 30
    //   1285: iload 69
    //   1287: istore 7
    //   1289: goto -596 -> 693
    //   1292: astore 19
    //   1294: aconst_null
    //   1295: astore 20
    //   1297: aload 19
    //   1299: invokevirtual 251	java/io/IOException:printStackTrace	()V
    //   1302: new 78	eq
    //   1305: dup
    //   1306: sipush -7056
    //   1309: new 101	java/lang/StringBuilder
    //   1312: dup
    //   1313: ldc 253
    //   1315: invokespecial 106	java/lang/StringBuilder:<init>	(Ljava/lang/String;)V
    //   1318: aload_0
    //   1319: getfield 54	ff:k	B
    //   1322: invokevirtual 110	java/lang/StringBuilder:append	(I)Ljava/lang/StringBuilder;
    //   1325: ldc 255
    //   1327: invokevirtual 175	java/lang/StringBuilder:append	(Ljava/lang/String;)Ljava/lang/StringBuilder;
    //   1330: aload 19
    //   1332: invokevirtual 187	java/io/IOException:getMessage	()Ljava/lang/String;
    //   1335: invokevirtual 175	java/lang/StringBuilder:append	(Ljava/lang/String;)Ljava/lang/StringBuilder;
    //   1338: invokevirtual 114	java/lang/StringBuilder:toString	()Ljava/lang/String;
    //   1341: invokespecial 117	eq:<init>	(ILjava/lang/String;)V
    //   1344: athrow
    //   1345: astore 14
    //   1347: aload 20
    //   1349: astore 6
    //   1351: lload 10
    //   1353: lstore_3
    //   1354: aload 13
    //   1356: astore_2
    //   1357: goto -1008 -> 349
    //   1360: new 78	eq
    //   1363: dup
    //   1364: sipush -7056
    //   1367: new 101	java/lang/StringBuilder
    //   1370: dup
    //   1371: ldc_w 257
    //   1374: invokespecial 106	java/lang/StringBuilder:<init>	(Ljava/lang/String;)V
    //   1377: aload 8
    //   1379: invokevirtual 187	java/io/IOException:getMessage	()Ljava/lang/String;
    //   1382: invokevirtual 175	java/lang/StringBuilder:append	(Ljava/lang/String;)Ljava/lang/StringBuilder;
    //   1385: ldc_w 259
    //   1388: invokevirtual 175	java/lang/StringBuilder:append	(Ljava/lang/String;)Ljava/lang/StringBuilder;
    //   1391: iload 12
    //   1393: invokevirtual 110	java/lang/StringBuilder:append	(I)Ljava/lang/StringBuilder;
    //   1396: invokevirtual 114	java/lang/StringBuilder:toString	()Ljava/lang/String;
    //   1399: invokespecial 117	eq:<init>	(ILjava/lang/String;)V
    //   1402: athrow
    //   1403: astore 14
    //   1405: lload 10
    //   1407: lstore_3
    //   1408: aload 13
    //   1410: astore_2
    //   1411: aconst_null
    //   1412: astore 6
    //   1414: goto -1065 -> 349
    //   1417: astore 26
    //   1419: aload 26
    //   1421: invokevirtual 193	java/lang/Exception:printStackTrace	()V
    //   1424: goto -274 -> 1150
    //   1427: astore 25
    //   1429: aload 25
    //   1431: invokevirtual 251	java/io/IOException:printStackTrace	()V
    //   1434: goto -272 -> 1162
    //   1437: astore 24
    //   1439: aload 24
    //   1441: invokevirtual 251	java/io/IOException:printStackTrace	()V
    //   1444: goto -272 -> 1172
    //   1447: astore 27
    //   1449: new 78	eq
    //   1452: dup
    //   1453: bipush 254
    //   1455: new 101	java/lang/StringBuilder
    //   1458: dup
    //   1459: ldc_w 261
    //   1462: invokespecial 106	java/lang/StringBuilder:<init>	(Ljava/lang/String;)V
    //   1465: aload 27
    //   1467: invokevirtual 267	java/lang/Object:getClass	()Ljava/lang/Class;
    //   1470: invokevirtual 272	java/lang/Class:getName	()Ljava/lang/String;
    //   1473: invokevirtual 175	java/lang/StringBuilder:append	(Ljava/lang/String;)Ljava/lang/StringBuilder;
    //   1476: ldc_w 274
    //   1479: invokevirtual 175	java/lang/StringBuilder:append	(Ljava/lang/String;)Ljava/lang/StringBuilder;
    //   1482: aload 27
    //   1484: invokevirtual 190	java/lang/Exception:getMessage	()Ljava/lang/String;
    //   1487: invokevirtual 175	java/lang/StringBuilder:append	(Ljava/lang/String;)Ljava/lang/StringBuilder;
    //   1490: invokevirtual 114	java/lang/StringBuilder:toString	()Ljava/lang/String;
    //   1493: invokespecial 117	eq:<init>	(ILjava/lang/String;)V
    //   1496: athrow
    //   1497: astore 17
    //   1499: aload 17
    //   1501: invokevirtual 193	java/lang/Exception:printStackTrace	()V
    //   1504: goto -1147 -> 357
    //   1507: astore 16
    //   1509: aload 16
    //   1511: invokevirtual 251	java/io/IOException:printStackTrace	()V
    //   1514: goto -1142 -> 372
    //   1517: astore 15
    //   1519: aload 15
    //   1521: invokevirtual 251	java/io/IOException:printStackTrace	()V
    //   1524: goto -1142 -> 382
    //   1527: astore 33
    //   1529: aload 33
    //   1531: invokevirtual 251	java/io/IOException:printStackTrace	()V
    //   1534: goto -1462 -> 72
    //   1537: astore 14
    //   1539: aload 13
    //   1541: astore_2
    //   1542: aconst_null
    //   1543: astore 6
    //   1545: goto -1196 -> 349
    //   1548: astore 14
    //   1550: aload 21
    //   1552: astore_1
    //   1553: lload 10
    //   1555: lstore_3
    //   1556: aload 13
    //   1558: astore_2
    //   1559: aconst_null
    //   1560: astore 6
    //   1562: goto -1213 -> 349
    //   1565: astore 14
    //   1567: aload 20
    //   1569: astore 6
    //   1571: aload 21
    //   1573: astore_1
    //   1574: lload 10
    //   1576: lstore_3
    //   1577: aload 13
    //   1579: astore_2
    //   1580: goto -1231 -> 349
    //   1583: astore 27
    //   1585: aload 13
    //   1587: astore_2
    //   1588: goto -139 -> 1449
    //   1591: astore 19
    //   1593: aload 21
    //   1595: astore_1
    //   1596: aconst_null
    //   1597: astore 20
    //   1599: goto -302 -> 1297
    //   1602: astore 19
    //   1604: aload 21
    //   1606: astore_1
    //   1607: goto -310 -> 1297
    //   1610: astore 8
    //   1612: iload 5
    //   1614: istore 9
    //   1616: lload_3
    //   1617: lstore 10
    //   1619: iload 9
    //   1621: istore 12
    //   1623: aconst_null
    //   1624: astore 13
    //   1626: goto -600 -> 1026
    //   1629: astore 8
    //   1631: lload_3
    //   1632: lstore 10
    //   1634: iload 53
    //   1636: istore 12
    //   1638: goto -612 -> 1026
    //   1641: astore 8
    //   1643: iload 56
    //   1645: istore 57
    //   1647: lload_3
    //   1648: lstore 10
    //   1650: iload 57
    //   1652: istore 12
    //   1654: goto -628 -> 1026
    //   1657: iload 53
    //   1659: istore 5
    //   1661: iload 48
    //   1663: istore 31
    //   1665: goto -1637 -> 28
    //   1668: iload 69
    //   1670: istore 7
    //   1672: goto -979 -> 693
    //   1675: iload 31
    //   1677: istore 48
    //   1679: goto -1192 -> 487
    //   1682: astore 29
    //   1684: aload 13
    //   1686: astore_2
    //   1687: goto -1343 -> 344
    //
    // Exception table:
    //   from	to	target	type
    //   13	50	342	eq
    //   87	342	342	eq
    //   404	444	342	eq
    //   487	518	342	eq
    //   526	545	342	eq
    //   576	689	342	eq
    //   703	711	342	eq
    //   992	1011	342	eq
    //   1201	1285	342	eq
    //   13	50	347	finally
    //   87	342	347	finally
    //   344	347	347	finally
    //   404	444	347	finally
    //   449	479	347	finally
    //   487	518	347	finally
    //   526	545	347	finally
    //   576	689	347	finally
    //   703	711	347	finally
    //   992	1011	347	finally
    //   1201	1285	347	finally
    //   1449	1497	347	finally
    //   13	50	447	java/io/UnsupportedEncodingException
    //   87	342	447	java/io/UnsupportedEncodingException
    //   404	444	447	java/io/UnsupportedEncodingException
    //   487	518	447	java/io/UnsupportedEncodingException
    //   526	545	447	java/io/UnsupportedEncodingException
    //   576	689	447	java/io/UnsupportedEncodingException
    //   703	711	447	java/io/UnsupportedEncodingException
    //   992	1011	447	java/io/UnsupportedEncodingException
    //   1201	1285	447	java/io/UnsupportedEncodingException
    //   820	853	897	java/io/IOException
    //   569	574	974	java/lang/Exception
    //   545	550	984	java/io/UnsupportedEncodingException
    //   554	560	984	java/io/UnsupportedEncodingException
    //   569	574	984	java/io/UnsupportedEncodingException
    //   733	812	984	java/io/UnsupportedEncodingException
    //   820	853	984	java/io/UnsupportedEncodingException
    //   864	968	984	java/io/UnsupportedEncodingException
    //   976	981	984	java/io/UnsupportedEncodingException
    //   526	545	1014	java/io/IOException
    //   576	689	1014	java/io/IOException
    //   992	1011	1014	java/io/IOException
    //   1201	1285	1014	java/io/IOException
    //   1055	1110	1292	java/io/IOException
    //   1297	1345	1345	finally
    //   1026	1048	1403	finally
    //   1055	1110	1403	finally
    //   1360	1403	1403	finally
    //   1145	1150	1417	java/lang/Exception
    //   1157	1162	1427	java/io/IOException
    //   1167	1172	1437	java/io/IOException
    //   13	50	1447	java/lang/Exception
    //   87	342	1447	java/lang/Exception
    //   404	444	1447	java/lang/Exception
    //   487	518	1447	java/lang/Exception
    //   526	545	1447	java/lang/Exception
    //   576	689	1447	java/lang/Exception
    //   703	711	1447	java/lang/Exception
    //   992	1011	1447	java/lang/Exception
    //   1201	1285	1447	java/lang/Exception
    //   353	357	1497	java/lang/Exception
    //   368	372	1507	java/io/IOException
    //   377	382	1517	java/io/IOException
    //   68	72	1527	java/io/IOException
    //   545	550	1537	finally
    //   554	560	1537	finally
    //   569	574	1537	finally
    //   733	812	1537	finally
    //   820	853	1537	finally
    //   864	968	1537	finally
    //   976	981	1537	finally
    //   1110	1117	1548	finally
    //   1121	1140	1565	finally
    //   545	550	1583	java/lang/Exception
    //   554	560	1583	java/lang/Exception
    //   733	812	1583	java/lang/Exception
    //   820	853	1583	java/lang/Exception
    //   864	968	1583	java/lang/Exception
    //   976	981	1583	java/lang/Exception
    //   1110	1117	1591	java/io/IOException
    //   1121	1140	1602	java/io/IOException
    //   13	50	1610	java/io/IOException
    //   87	342	1610	java/io/IOException
    //   404	444	1610	java/io/IOException
    //   487	518	1610	java/io/IOException
    //   703	711	1610	java/io/IOException
    //   545	550	1629	java/io/IOException
    //   569	574	1629	java/io/IOException
    //   976	981	1629	java/io/IOException
    //   554	560	1641	java/io/IOException
    //   733	812	1641	java/io/IOException
    //   864	968	1641	java/io/IOException
    //   545	550	1682	eq
    //   554	560	1682	eq
    //   569	574	1682	eq
    //   733	812	1682	eq
    //   820	853	1682	eq
    //   864	968	1682	eq
    //   976	981	1682	eq
  }

  final void a()
  {
    this.e = false;
    if (this.f != null);
    try
    {
      this.f.d();
      this.f = null;
      return;
    }
    catch (Exception localException)
    {
      while (true)
        localException.printStackTrace();
    }
  }

  final void a(fd<T> paramfd)
  {
    this.g = paramfd;
  }

  // ERROR //
  public final void run()
  {
    // Byte code:
    //   0: aconst_null
    //   1: astore_1
    //   2: aload_0
    //   3: getfield 75	ff:i	[B
    //   6: astore_2
    //   7: aload_2
    //   8: monitorenter
    //   9: aload_0
    //   10: getfield 56	ff:c	Lfh;
    //   13: pop
    //   14: invokestatic 146	bk:a	()LQQPIM/ConnectType;
    //   17: pop
    //   18: aload_0
    //   19: getfield 56	ff:c	Lfh;
    //   22: pop
    //   23: invokestatic 284	com/tencent/tmsecure/common/TMSApplication:getApplicaionContext	()Landroid/content/Context;
    //   26: ldc_w 286
    //   29: invokevirtual 292	android/content/Context:getSystemService	(Ljava/lang/String;)Ljava/lang/Object;
    //   32: checkcast 294	android/net/ConnectivityManager
    //   35: invokevirtual 298	android/net/ConnectivityManager:getActiveNetworkInfo	()Landroid/net/NetworkInfo;
    //   38: astore 7
    //   40: aload 7
    //   42: ifnull +16 -> 58
    //   45: aload 7
    //   47: invokevirtual 303	android/net/NetworkInfo:getType	()I
    //   50: iconst_1
    //   51: if_icmpne +296 -> 347
    //   54: invokestatic 305	bk:b	()Ljava/lang/String;
    //   57: pop
    //   58: aload_0
    //   59: getfield 56	ff:c	Lfh;
    //   62: getfield 87	fh:h	J
    //   65: aload_0
    //   66: getfield 56	ff:c	Lfh;
    //   69: getfield 158	fh:g	J
    //   72: lcmp
    //   73: ifne +324 -> 397
    //   76: aload_0
    //   77: getfield 56	ff:c	Lfh;
    //   80: getfield 87	fh:h	J
    //   83: lconst_0
    //   84: lcmp
    //   85: ifle +312 -> 397
    //   88: aload_0
    //   89: getfield 56	ff:c	Lfh;
    //   92: iconst_3
    //   93: putfield 306	fh:d	I
    //   96: aload_0
    //   97: getfield 56	ff:c	Lfh;
    //   100: pop
    //   101: aload_0
    //   102: getfield 56	ff:c	Lfh;
    //   105: pop
    //   106: aload_0
    //   107: getfield 56	ff:c	Lfh;
    //   110: pop
    //   111: aload_0
    //   112: getfield 56	ff:c	Lfh;
    //   115: fconst_1
    //   116: putfield 167	fh:i	F
    //   119: aload_0
    //   120: getfield 177	ff:g	Lfd;
    //   123: aload_0
    //   124: getfield 56	ff:c	Lfh;
    //   127: invokevirtual 308	fd:d	(Lfh;)V
    //   130: aload_0
    //   131: getfield 56	ff:c	Lfh;
    //   134: getfield 87	fh:h	J
    //   137: aload_0
    //   138: getfield 56	ff:c	Lfh;
    //   141: getfield 158	fh:g	J
    //   144: lcmp
    //   145: ifne +15 -> 160
    //   148: aload_0
    //   149: getfield 56	ff:c	Lfh;
    //   152: getfield 87	fh:h	J
    //   155: lconst_0
    //   156: lcmp
    //   157: ifgt +55 -> 212
    //   160: aload_0
    //   161: getfield 56	ff:c	Lfh;
    //   164: getfield 306	fh:d	I
    //   167: iconst_2
    //   168: if_icmpeq +193 -> 361
    //   171: aload_0
    //   172: getfield 50	ff:e	Z
    //   175: ifeq +186 -> 361
    //   178: aload_0
    //   179: getfield 56	ff:c	Lfh;
    //   182: getfield 310	fh:c	Z
    //   185: ifne +176 -> 361
    //   188: aload_0
    //   189: getfield 56	ff:c	Lfh;
    //   192: getfield 158	fh:g	J
    //   195: lconst_0
    //   196: lcmp
    //   197: ifgt +164 -> 361
    //   200: aload_0
    //   201: getfield 56	ff:c	Lfh;
    //   204: getfield 87	fh:h	J
    //   207: lconst_0
    //   208: lcmp
    //   209: ifle +152 -> 361
    //   212: aload_0
    //   213: getfield 56	ff:c	Lfh;
    //   216: getfield 306	fh:d	I
    //   219: iconst_2
    //   220: if_icmpeq +13 -> 233
    //   223: aload_0
    //   224: getfield 56	ff:c	Lfh;
    //   227: pop
    //   228: aload_0
    //   229: getfield 56	ff:c	Lfh;
    //   232: pop
    //   233: aload_0
    //   234: getfield 56	ff:c	Lfh;
    //   237: pop
    //   238: aload_0
    //   239: getfield 56	ff:c	Lfh;
    //   242: iconst_3
    //   243: putfield 306	fh:d	I
    //   246: aload_0
    //   247: getfield 56	ff:c	Lfh;
    //   250: pop
    //   251: aload_0
    //   252: getfield 52	ff:f	Lev;
    //   255: ifnull +129 -> 384
    //   258: aload_0
    //   259: getfield 56	ff:c	Lfh;
    //   262: aload_0
    //   263: getfield 52	ff:f	Lev;
    //   266: invokevirtual 312	ev:h	()Ljava/lang/String;
    //   269: putfield 315	fh:l	Ljava/lang/String;
    //   272: ldc_w 317
    //   275: aload_0
    //   276: getfield 56	ff:c	Lfh;
    //   279: getfield 315	fh:l	Ljava/lang/String;
    //   282: invokevirtual 323	java/lang/String:equals	(Ljava/lang/Object;)Z
    //   285: ifeq +27 -> 312
    //   288: aload_0
    //   289: getfield 56	ff:c	Lfh;
    //   292: getfield 306	fh:d	I
    //   295: iconst_2
    //   296: if_icmpne +16 -> 312
    //   299: aload_0
    //   300: getfield 56	ff:c	Lfh;
    //   303: pop
    //   304: aload_0
    //   305: getfield 52	ff:f	Lev;
    //   308: invokevirtual 325	ev:g	()Ljava/lang/String;
    //   311: pop
    //   312: aload_0
    //   313: getfield 177	ff:g	Lfd;
    //   316: aload_0
    //   317: getfield 56	ff:c	Lfh;
    //   320: invokevirtual 308	fd:d	(Lfh;)V
    //   323: aload_0
    //   324: getfield 52	ff:f	Lev;
    //   327: ifnull +15 -> 342
    //   330: aload_0
    //   331: getfield 52	ff:f	Lev;
    //   334: invokevirtual 221	ev:d	()V
    //   337: aload_0
    //   338: aconst_null
    //   339: putfield 52	ff:f	Lev;
    //   342: aload_2
    //   343: monitorexit
    //   344: goto +2003 -> 2347
    //   347: aload 7
    //   349: invokevirtual 328	android/net/NetworkInfo:getExtraInfo	()Ljava/lang/String;
    //   352: pop
    //   353: goto -295 -> 58
    //   356: astore_3
    //   357: aload_2
    //   358: monitorexit
    //   359: aload_3
    //   360: athrow
    //   361: aload_0
    //   362: getfield 56	ff:c	Lfh;
    //   365: getfield 306	fh:d	I
    //   368: iconst_2
    //   369: if_icmpne -123 -> 246
    //   372: aload_0
    //   373: getfield 56	ff:c	Lfh;
    //   376: pop
    //   377: invokestatic 329	bk:c	()I
    //   380: pop
    //   381: goto -135 -> 246
    //   384: aload_0
    //   385: getfield 56	ff:c	Lfh;
    //   388: ldc_w 331
    //   391: putfield 315	fh:l	Ljava/lang/String;
    //   394: goto -82 -> 312
    //   397: aload_0
    //   398: getfield 60	ff:j	Z
    //   401: istore 63
    //   403: iload 63
    //   405: ifne +143 -> 548
    //   408: aload_0
    //   409: getfield 56	ff:c	Lfh;
    //   412: pop
    //   413: aload_0
    //   414: aload_0
    //   415: getfield 56	ff:c	Lfh;
    //   418: getfield 89	fh:b	Ljava/lang/String;
    //   421: invokestatic 94	ev:a	(Ljava/lang/String;)Lev;
    //   424: putfield 52	ff:f	Lev;
    //   427: new 101	java/lang/StringBuilder
    //   430: dup
    //   431: ldc_w 333
    //   434: invokespecial 106	java/lang/StringBuilder:<init>	(Ljava/lang/String;)V
    //   437: bipush 45
    //   439: invokevirtual 336	java/lang/StringBuilder:append	(C)Ljava/lang/StringBuilder;
    //   442: iconst_m1
    //   443: aload_0
    //   444: getfield 48	ff:d	I
    //   447: iadd
    //   448: invokevirtual 110	java/lang/StringBuilder:append	(I)Ljava/lang/StringBuilder;
    //   451: invokevirtual 114	java/lang/StringBuilder:toString	()Ljava/lang/String;
    //   454: astore 78
    //   456: aload_0
    //   457: getfield 52	ff:f	Lev;
    //   460: ldc 210
    //   462: aload 78
    //   464: invokevirtual 214	ev:a	(Ljava/lang/String;Ljava/lang/String;)V
    //   467: aload_0
    //   468: getfield 52	ff:f	Lev;
    //   471: invokevirtual 97	ev:a	()I
    //   474: sipush 206
    //   477: if_icmpeq +32 -> 509
    //   480: aload_0
    //   481: getfield 52	ff:f	Lev;
    //   484: invokevirtual 221	ev:d	()V
    //   487: aload_0
    //   488: aload_0
    //   489: getfield 56	ff:c	Lfh;
    //   492: getfield 89	fh:b	Ljava/lang/String;
    //   495: invokestatic 94	ev:a	(Ljava/lang/String;)Lev;
    //   498: putfield 52	ff:f	Lev;
    //   501: aload_0
    //   502: getfield 52	ff:f	Lev;
    //   505: invokevirtual 97	ev:a	()I
    //   508: pop
    //   509: aload_0
    //   510: getfield 52	ff:f	Lev;
    //   513: invokevirtual 99	ev:c	()I
    //   516: istore 79
    //   518: iload 79
    //   520: sipush 206
    //   523: if_icmpne +313 -> 836
    //   526: aload_0
    //   527: getfield 56	ff:c	Lfh;
    //   530: iconst_1
    //   531: putfield 310	fh:c	Z
    //   534: aload_0
    //   535: getfield 56	ff:c	Lfh;
    //   538: aload_0
    //   539: getfield 52	ff:f	Lev;
    //   542: invokevirtual 338	ev:e	()J
    //   545: putfield 158	fh:g	J
    //   548: new 160	java/io/FileOutputStream
    //   551: dup
    //   552: aload_0
    //   553: getfield 58	ff:h	Ljava/lang/String;
    //   556: iconst_1
    //   557: invokespecial 240	java/io/FileOutputStream:<init>	(Ljava/lang/String;Z)V
    //   560: astore 9
    //   562: aload 9
    //   564: invokevirtual 244	java/io/FileOutputStream:getChannel	()Ljava/nio/channels/FileChannel;
    //   567: astore_1
    //   568: aload_1
    //   569: aload_0
    //   570: getfield 56	ff:c	Lfh;
    //   573: getfield 87	fh:h	J
    //   576: invokevirtual 248	java/nio/channels/FileChannel:position	(J)Ljava/nio/channels/FileChannel;
    //   579: pop
    //   580: aload_0
    //   581: getfield 56	ff:c	Lfh;
    //   584: getfield 310	fh:c	Z
    //   587: ifne +901 -> 1488
    //   590: aload_0
    //   591: aload 9
    //   593: invokespecial 340	ff:a	(Ljava/io/FileOutputStream;)V
    //   596: aload 9
    //   598: invokevirtual 229	java/io/FileOutputStream:flush	()V
    //   601: aload_0
    //   602: getfield 56	ff:c	Lfh;
    //   605: getfield 87	fh:h	J
    //   608: aload_0
    //   609: getfield 56	ff:c	Lfh;
    //   612: getfield 158	fh:g	J
    //   615: lcmp
    //   616: ifne +15 -> 631
    //   619: aload_0
    //   620: getfield 56	ff:c	Lfh;
    //   623: getfield 87	fh:h	J
    //   626: lconst_0
    //   627: lcmp
    //   628: ifgt +55 -> 683
    //   631: aload_0
    //   632: getfield 56	ff:c	Lfh;
    //   635: getfield 306	fh:d	I
    //   638: iconst_2
    //   639: if_icmpeq +1637 -> 2276
    //   642: aload_0
    //   643: getfield 50	ff:e	Z
    //   646: ifeq +1630 -> 2276
    //   649: aload_0
    //   650: getfield 56	ff:c	Lfh;
    //   653: getfield 310	fh:c	Z
    //   656: ifne +1620 -> 2276
    //   659: aload_0
    //   660: getfield 56	ff:c	Lfh;
    //   663: getfield 158	fh:g	J
    //   666: lconst_0
    //   667: lcmp
    //   668: ifgt +1608 -> 2276
    //   671: aload_0
    //   672: getfield 56	ff:c	Lfh;
    //   675: getfield 87	fh:h	J
    //   678: lconst_0
    //   679: lcmp
    //   680: ifle +1596 -> 2276
    //   683: aload_0
    //   684: getfield 56	ff:c	Lfh;
    //   687: getfield 306	fh:d	I
    //   690: iconst_2
    //   691: if_icmpeq +13 -> 704
    //   694: aload_0
    //   695: getfield 56	ff:c	Lfh;
    //   698: pop
    //   699: aload_0
    //   700: getfield 56	ff:c	Lfh;
    //   703: pop
    //   704: aload_0
    //   705: getfield 56	ff:c	Lfh;
    //   708: pop
    //   709: aload_0
    //   710: getfield 56	ff:c	Lfh;
    //   713: iconst_3
    //   714: putfield 306	fh:d	I
    //   717: aload_0
    //   718: getfield 56	ff:c	Lfh;
    //   721: pop
    //   722: aload_0
    //   723: getfield 52	ff:f	Lev;
    //   726: ifnull +1573 -> 2299
    //   729: aload_0
    //   730: getfield 56	ff:c	Lfh;
    //   733: aload_0
    //   734: getfield 52	ff:f	Lev;
    //   737: invokevirtual 312	ev:h	()Ljava/lang/String;
    //   740: putfield 315	fh:l	Ljava/lang/String;
    //   743: ldc_w 317
    //   746: aload_0
    //   747: getfield 56	ff:c	Lfh;
    //   750: getfield 315	fh:l	Ljava/lang/String;
    //   753: invokevirtual 323	java/lang/String:equals	(Ljava/lang/Object;)Z
    //   756: ifeq +27 -> 783
    //   759: aload_0
    //   760: getfield 56	ff:c	Lfh;
    //   763: getfield 306	fh:d	I
    //   766: iconst_2
    //   767: if_icmpne +16 -> 783
    //   770: aload_0
    //   771: getfield 56	ff:c	Lfh;
    //   774: pop
    //   775: aload_0
    //   776: getfield 52	ff:f	Lev;
    //   779: invokevirtual 325	ev:g	()Ljava/lang/String;
    //   782: pop
    //   783: aload_0
    //   784: getfield 177	ff:g	Lfd;
    //   787: aload_0
    //   788: getfield 56	ff:c	Lfh;
    //   791: invokevirtual 308	fd:d	(Lfh;)V
    //   794: aload_1
    //   795: ifnull +7 -> 802
    //   798: aload_1
    //   799: invokevirtual 219	java/nio/channels/FileChannel:close	()V
    //   802: aload 9
    //   804: invokevirtual 229	java/io/FileOutputStream:flush	()V
    //   807: aload 9
    //   809: invokevirtual 194	java/io/FileOutputStream:close	()V
    //   812: aload_0
    //   813: getfield 52	ff:f	Lev;
    //   816: ifnull +15 -> 831
    //   819: aload_0
    //   820: getfield 52	ff:f	Lev;
    //   823: invokevirtual 221	ev:d	()V
    //   826: aload_0
    //   827: aconst_null
    //   828: putfield 52	ff:f	Lev;
    //   831: aload_2
    //   832: monitorexit
    //   833: goto +1514 -> 2347
    //   836: iload 79
    //   838: sipush 200
    //   841: if_icmpne -293 -> 548
    //   844: aload_0
    //   845: getfield 56	ff:c	Lfh;
    //   848: iconst_0
    //   849: putfield 310	fh:c	Z
    //   852: aload_0
    //   853: getfield 56	ff:c	Lfh;
    //   856: aload_0
    //   857: getfield 52	ff:f	Lev;
    //   860: invokevirtual 342	ev:f	()J
    //   863: putfield 158	fh:g	J
    //   866: goto -318 -> 548
    //   869: astore 76
    //   871: aload 76
    //   873: athrow
    //   874: astore 48
    //   876: aconst_null
    //   877: astore 9
    //   879: aload 48
    //   881: invokevirtual 343	eq:printStackTrace	()V
    //   884: aload_0
    //   885: getfield 50	ff:e	Z
    //   888: ifeq +33 -> 921
    //   891: aload_0
    //   892: getfield 56	ff:c	Lfh;
    //   895: iconst_2
    //   896: putfield 306	fh:d	I
    //   899: aload_0
    //   900: getfield 56	ff:c	Lfh;
    //   903: pop
    //   904: aload 48
    //   906: invokevirtual 344	eq:a	()I
    //   909: pop
    //   910: aload_0
    //   911: getfield 56	ff:c	Lfh;
    //   914: pop
    //   915: aload 48
    //   917: invokevirtual 345	eq:b	()Ljava/lang/String;
    //   920: pop
    //   921: aload_0
    //   922: getfield 56	ff:c	Lfh;
    //   925: getfield 87	fh:h	J
    //   928: aload_0
    //   929: getfield 56	ff:c	Lfh;
    //   932: getfield 158	fh:g	J
    //   935: lcmp
    //   936: ifne +15 -> 951
    //   939: aload_0
    //   940: getfield 56	ff:c	Lfh;
    //   943: getfield 87	fh:h	J
    //   946: lconst_0
    //   947: lcmp
    //   948: ifgt +55 -> 1003
    //   951: aload_0
    //   952: getfield 56	ff:c	Lfh;
    //   955: getfield 306	fh:d	I
    //   958: iconst_2
    //   959: if_icmpeq +543 -> 1502
    //   962: aload_0
    //   963: getfield 50	ff:e	Z
    //   966: ifeq +536 -> 1502
    //   969: aload_0
    //   970: getfield 56	ff:c	Lfh;
    //   973: getfield 310	fh:c	Z
    //   976: ifne +526 -> 1502
    //   979: aload_0
    //   980: getfield 56	ff:c	Lfh;
    //   983: getfield 158	fh:g	J
    //   986: lconst_0
    //   987: lcmp
    //   988: ifgt +514 -> 1502
    //   991: aload_0
    //   992: getfield 56	ff:c	Lfh;
    //   995: getfield 87	fh:h	J
    //   998: lconst_0
    //   999: lcmp
    //   1000: ifle +502 -> 1502
    //   1003: aload_0
    //   1004: getfield 56	ff:c	Lfh;
    //   1007: getfield 306	fh:d	I
    //   1010: iconst_2
    //   1011: if_icmpeq +13 -> 1024
    //   1014: aload_0
    //   1015: getfield 56	ff:c	Lfh;
    //   1018: pop
    //   1019: aload_0
    //   1020: getfield 56	ff:c	Lfh;
    //   1023: pop
    //   1024: aload_0
    //   1025: getfield 56	ff:c	Lfh;
    //   1028: pop
    //   1029: aload_0
    //   1030: getfield 56	ff:c	Lfh;
    //   1033: iconst_3
    //   1034: putfield 306	fh:d	I
    //   1037: aload_0
    //   1038: getfield 56	ff:c	Lfh;
    //   1041: pop
    //   1042: aload_0
    //   1043: getfield 52	ff:f	Lev;
    //   1046: ifnull +479 -> 1525
    //   1049: aload_0
    //   1050: getfield 56	ff:c	Lfh;
    //   1053: aload_0
    //   1054: getfield 52	ff:f	Lev;
    //   1057: invokevirtual 312	ev:h	()Ljava/lang/String;
    //   1060: putfield 315	fh:l	Ljava/lang/String;
    //   1063: ldc_w 317
    //   1066: aload_0
    //   1067: getfield 56	ff:c	Lfh;
    //   1070: getfield 315	fh:l	Ljava/lang/String;
    //   1073: invokevirtual 323	java/lang/String:equals	(Ljava/lang/Object;)Z
    //   1076: ifeq +27 -> 1103
    //   1079: aload_0
    //   1080: getfield 56	ff:c	Lfh;
    //   1083: getfield 306	fh:d	I
    //   1086: iconst_2
    //   1087: if_icmpne +16 -> 1103
    //   1090: aload_0
    //   1091: getfield 56	ff:c	Lfh;
    //   1094: pop
    //   1095: aload_0
    //   1096: getfield 52	ff:f	Lev;
    //   1099: invokevirtual 325	ev:g	()Ljava/lang/String;
    //   1102: pop
    //   1103: aload_0
    //   1104: getfield 177	ff:g	Lfd;
    //   1107: aload_0
    //   1108: getfield 56	ff:c	Lfh;
    //   1111: invokevirtual 308	fd:d	(Lfh;)V
    //   1114: aload_1
    //   1115: ifnull +7 -> 1122
    //   1118: aload_1
    //   1119: invokevirtual 219	java/nio/channels/FileChannel:close	()V
    //   1122: aload 9
    //   1124: ifnull +13 -> 1137
    //   1127: aload 9
    //   1129: invokevirtual 229	java/io/FileOutputStream:flush	()V
    //   1132: aload 9
    //   1134: invokevirtual 194	java/io/FileOutputStream:close	()V
    //   1137: aload_0
    //   1138: getfield 52	ff:f	Lev;
    //   1141: ifnull -310 -> 831
    //   1144: aload_0
    //   1145: getfield 52	ff:f	Lev;
    //   1148: invokevirtual 221	ev:d	()V
    //   1151: aload_0
    //   1152: aconst_null
    //   1153: putfield 52	ff:f	Lev;
    //   1156: goto -325 -> 831
    //   1159: astore 75
    //   1161: new 78	eq
    //   1164: dup
    //   1165: bipush 254
    //   1167: new 101	java/lang/StringBuilder
    //   1170: dup
    //   1171: ldc_w 347
    //   1174: invokespecial 106	java/lang/StringBuilder:<init>	(Ljava/lang/String;)V
    //   1177: aload 75
    //   1179: invokevirtual 267	java/lang/Object:getClass	()Ljava/lang/Class;
    //   1182: invokevirtual 272	java/lang/Class:getName	()Ljava/lang/String;
    //   1185: invokevirtual 175	java/lang/StringBuilder:append	(Ljava/lang/String;)Ljava/lang/StringBuilder;
    //   1188: ldc_w 349
    //   1191: invokevirtual 175	java/lang/StringBuilder:append	(Ljava/lang/String;)Ljava/lang/StringBuilder;
    //   1194: aload 75
    //   1196: invokevirtual 190	java/lang/Exception:getMessage	()Ljava/lang/String;
    //   1199: invokevirtual 175	java/lang/StringBuilder:append	(Ljava/lang/String;)Ljava/lang/StringBuilder;
    //   1202: invokevirtual 114	java/lang/StringBuilder:toString	()Ljava/lang/String;
    //   1205: invokespecial 117	eq:<init>	(ILjava/lang/String;)V
    //   1208: athrow
    //   1209: astore 34
    //   1211: aconst_null
    //   1212: astore 9
    //   1214: aload 34
    //   1216: invokevirtual 350	java/io/FileNotFoundException:printStackTrace	()V
    //   1219: aload_0
    //   1220: getfield 50	ff:e	Z
    //   1223: ifeq +27 -> 1250
    //   1226: aload_0
    //   1227: getfield 56	ff:c	Lfh;
    //   1230: iconst_2
    //   1231: putfield 306	fh:d	I
    //   1234: aload_0
    //   1235: getfield 56	ff:c	Lfh;
    //   1238: pop
    //   1239: aload_0
    //   1240: getfield 56	ff:c	Lfh;
    //   1243: pop
    //   1244: aload 34
    //   1246: invokevirtual 351	java/io/FileNotFoundException:getMessage	()Ljava/lang/String;
    //   1249: pop
    //   1250: aload_0
    //   1251: getfield 56	ff:c	Lfh;
    //   1254: getfield 87	fh:h	J
    //   1257: aload_0
    //   1258: getfield 56	ff:c	Lfh;
    //   1261: getfield 158	fh:g	J
    //   1264: lcmp
    //   1265: ifne +15 -> 1280
    //   1268: aload_0
    //   1269: getfield 56	ff:c	Lfh;
    //   1272: getfield 87	fh:h	J
    //   1275: lconst_0
    //   1276: lcmp
    //   1277: ifgt +55 -> 1332
    //   1280: aload_0
    //   1281: getfield 56	ff:c	Lfh;
    //   1284: getfield 306	fh:d	I
    //   1287: iconst_2
    //   1288: if_icmpeq +270 -> 1558
    //   1291: aload_0
    //   1292: getfield 50	ff:e	Z
    //   1295: ifeq +263 -> 1558
    //   1298: aload_0
    //   1299: getfield 56	ff:c	Lfh;
    //   1302: getfield 310	fh:c	Z
    //   1305: ifne +253 -> 1558
    //   1308: aload_0
    //   1309: getfield 56	ff:c	Lfh;
    //   1312: getfield 158	fh:g	J
    //   1315: lconst_0
    //   1316: lcmp
    //   1317: ifgt +241 -> 1558
    //   1320: aload_0
    //   1321: getfield 56	ff:c	Lfh;
    //   1324: getfield 87	fh:h	J
    //   1327: lconst_0
    //   1328: lcmp
    //   1329: ifle +229 -> 1558
    //   1332: aload_0
    //   1333: getfield 56	ff:c	Lfh;
    //   1336: getfield 306	fh:d	I
    //   1339: iconst_2
    //   1340: if_icmpeq +13 -> 1353
    //   1343: aload_0
    //   1344: getfield 56	ff:c	Lfh;
    //   1347: pop
    //   1348: aload_0
    //   1349: getfield 56	ff:c	Lfh;
    //   1352: pop
    //   1353: aload_0
    //   1354: getfield 56	ff:c	Lfh;
    //   1357: pop
    //   1358: aload_0
    //   1359: getfield 56	ff:c	Lfh;
    //   1362: iconst_3
    //   1363: putfield 306	fh:d	I
    //   1366: aload_0
    //   1367: getfield 56	ff:c	Lfh;
    //   1370: pop
    //   1371: aload_0
    //   1372: getfield 52	ff:f	Lev;
    //   1375: ifnull +206 -> 1581
    //   1378: aload_0
    //   1379: getfield 56	ff:c	Lfh;
    //   1382: aload_0
    //   1383: getfield 52	ff:f	Lev;
    //   1386: invokevirtual 312	ev:h	()Ljava/lang/String;
    //   1389: putfield 315	fh:l	Ljava/lang/String;
    //   1392: ldc_w 317
    //   1395: aload_0
    //   1396: getfield 56	ff:c	Lfh;
    //   1399: getfield 315	fh:l	Ljava/lang/String;
    //   1402: invokevirtual 323	java/lang/String:equals	(Ljava/lang/Object;)Z
    //   1405: ifeq +27 -> 1432
    //   1408: aload_0
    //   1409: getfield 56	ff:c	Lfh;
    //   1412: getfield 306	fh:d	I
    //   1415: iconst_2
    //   1416: if_icmpne +16 -> 1432
    //   1419: aload_0
    //   1420: getfield 56	ff:c	Lfh;
    //   1423: pop
    //   1424: aload_0
    //   1425: getfield 52	ff:f	Lev;
    //   1428: invokevirtual 325	ev:g	()Ljava/lang/String;
    //   1431: pop
    //   1432: aload_0
    //   1433: getfield 177	ff:g	Lfd;
    //   1436: aload_0
    //   1437: getfield 56	ff:c	Lfh;
    //   1440: invokevirtual 308	fd:d	(Lfh;)V
    //   1443: aload_1
    //   1444: ifnull +7 -> 1451
    //   1447: aload_1
    //   1448: invokevirtual 219	java/nio/channels/FileChannel:close	()V
    //   1451: aload 9
    //   1453: ifnull +13 -> 1466
    //   1456: aload 9
    //   1458: invokevirtual 229	java/io/FileOutputStream:flush	()V
    //   1461: aload 9
    //   1463: invokevirtual 194	java/io/FileOutputStream:close	()V
    //   1466: aload_0
    //   1467: getfield 52	ff:f	Lev;
    //   1470: ifnull -639 -> 831
    //   1473: aload_0
    //   1474: getfield 52	ff:f	Lev;
    //   1477: invokevirtual 221	ev:d	()V
    //   1480: aload_0
    //   1481: aconst_null
    //   1482: putfield 52	ff:f	Lev;
    //   1485: goto -654 -> 831
    //   1488: aload_0
    //   1489: aload 9
    //   1491: invokespecial 250	ff:b	(Ljava/io/FileOutputStream;)V
    //   1494: goto -898 -> 596
    //   1497: astore 48
    //   1499: goto -620 -> 879
    //   1502: aload_0
    //   1503: getfield 56	ff:c	Lfh;
    //   1506: getfield 306	fh:d	I
    //   1509: iconst_2
    //   1510: if_icmpne -473 -> 1037
    //   1513: aload_0
    //   1514: getfield 56	ff:c	Lfh;
    //   1517: pop
    //   1518: invokestatic 329	bk:c	()I
    //   1521: pop
    //   1522: goto -485 -> 1037
    //   1525: aload_0
    //   1526: getfield 56	ff:c	Lfh;
    //   1529: ldc_w 331
    //   1532: putfield 315	fh:l	Ljava/lang/String;
    //   1535: goto -432 -> 1103
    //   1538: astore 53
    //   1540: aload 53
    //   1542: invokevirtual 251	java/io/IOException:printStackTrace	()V
    //   1545: goto -423 -> 1122
    //   1548: astore 52
    //   1550: aload 52
    //   1552: invokevirtual 251	java/io/IOException:printStackTrace	()V
    //   1555: goto -418 -> 1137
    //   1558: aload_0
    //   1559: getfield 56	ff:c	Lfh;
    //   1562: getfield 306	fh:d	I
    //   1565: iconst_2
    //   1566: if_icmpne -200 -> 1366
    //   1569: aload_0
    //   1570: getfield 56	ff:c	Lfh;
    //   1573: pop
    //   1574: invokestatic 329	bk:c	()I
    //   1577: pop
    //   1578: goto -212 -> 1366
    //   1581: aload_0
    //   1582: getfield 56	ff:c	Lfh;
    //   1585: ldc_w 331
    //   1588: putfield 315	fh:l	Ljava/lang/String;
    //   1591: goto -159 -> 1432
    //   1594: astore 39
    //   1596: aload 39
    //   1598: invokevirtual 251	java/io/IOException:printStackTrace	()V
    //   1601: goto -150 -> 1451
    //   1604: astore 38
    //   1606: aload 38
    //   1608: invokevirtual 251	java/io/IOException:printStackTrace	()V
    //   1611: goto -145 -> 1466
    //   1614: astore 20
    //   1616: aconst_null
    //   1617: astore 9
    //   1619: aload 20
    //   1621: invokevirtual 193	java/lang/Exception:printStackTrace	()V
    //   1624: aload_0
    //   1625: getfield 50	ff:e	Z
    //   1628: ifeq +60 -> 1688
    //   1631: aload_0
    //   1632: getfield 56	ff:c	Lfh;
    //   1635: iconst_2
    //   1636: putfield 306	fh:d	I
    //   1639: aload_0
    //   1640: getfield 56	ff:c	Lfh;
    //   1643: pop
    //   1644: aload_0
    //   1645: getfield 56	ff:c	Lfh;
    //   1648: pop
    //   1649: new 101	java/lang/StringBuilder
    //   1652: dup
    //   1653: ldc_w 353
    //   1656: invokespecial 106	java/lang/StringBuilder:<init>	(Ljava/lang/String;)V
    //   1659: aload 20
    //   1661: invokevirtual 267	java/lang/Object:getClass	()Ljava/lang/Class;
    //   1664: invokevirtual 272	java/lang/Class:getName	()Ljava/lang/String;
    //   1667: invokevirtual 175	java/lang/StringBuilder:append	(Ljava/lang/String;)Ljava/lang/StringBuilder;
    //   1670: ldc_w 274
    //   1673: invokevirtual 175	java/lang/StringBuilder:append	(Ljava/lang/String;)Ljava/lang/StringBuilder;
    //   1676: aload 20
    //   1678: invokevirtual 190	java/lang/Exception:getMessage	()Ljava/lang/String;
    //   1681: invokevirtual 175	java/lang/StringBuilder:append	(Ljava/lang/String;)Ljava/lang/StringBuilder;
    //   1684: invokevirtual 114	java/lang/StringBuilder:toString	()Ljava/lang/String;
    //   1687: pop
    //   1688: aload_0
    //   1689: getfield 56	ff:c	Lfh;
    //   1692: getfield 87	fh:h	J
    //   1695: aload_0
    //   1696: getfield 56	ff:c	Lfh;
    //   1699: getfield 158	fh:g	J
    //   1702: lcmp
    //   1703: ifne +15 -> 1718
    //   1706: aload_0
    //   1707: getfield 56	ff:c	Lfh;
    //   1710: getfield 87	fh:h	J
    //   1713: lconst_0
    //   1714: lcmp
    //   1715: ifgt +55 -> 1770
    //   1718: aload_0
    //   1719: getfield 56	ff:c	Lfh;
    //   1722: getfield 306	fh:d	I
    //   1725: iconst_2
    //   1726: if_icmpeq +200 -> 1926
    //   1729: aload_0
    //   1730: getfield 50	ff:e	Z
    //   1733: ifeq +193 -> 1926
    //   1736: aload_0
    //   1737: getfield 56	ff:c	Lfh;
    //   1740: getfield 310	fh:c	Z
    //   1743: ifne +183 -> 1926
    //   1746: aload_0
    //   1747: getfield 56	ff:c	Lfh;
    //   1750: getfield 158	fh:g	J
    //   1753: lconst_0
    //   1754: lcmp
    //   1755: ifgt +171 -> 1926
    //   1758: aload_0
    //   1759: getfield 56	ff:c	Lfh;
    //   1762: getfield 87	fh:h	J
    //   1765: lconst_0
    //   1766: lcmp
    //   1767: ifle +159 -> 1926
    //   1770: aload_0
    //   1771: getfield 56	ff:c	Lfh;
    //   1774: getfield 306	fh:d	I
    //   1777: iconst_2
    //   1778: if_icmpeq +13 -> 1791
    //   1781: aload_0
    //   1782: getfield 56	ff:c	Lfh;
    //   1785: pop
    //   1786: aload_0
    //   1787: getfield 56	ff:c	Lfh;
    //   1790: pop
    //   1791: aload_0
    //   1792: getfield 56	ff:c	Lfh;
    //   1795: pop
    //   1796: aload_0
    //   1797: getfield 56	ff:c	Lfh;
    //   1800: iconst_3
    //   1801: putfield 306	fh:d	I
    //   1804: aload_0
    //   1805: getfield 56	ff:c	Lfh;
    //   1808: pop
    //   1809: aload_0
    //   1810: getfield 52	ff:f	Lev;
    //   1813: ifnull +136 -> 1949
    //   1816: aload_0
    //   1817: getfield 56	ff:c	Lfh;
    //   1820: aload_0
    //   1821: getfield 52	ff:f	Lev;
    //   1824: invokevirtual 312	ev:h	()Ljava/lang/String;
    //   1827: putfield 315	fh:l	Ljava/lang/String;
    //   1830: ldc_w 317
    //   1833: aload_0
    //   1834: getfield 56	ff:c	Lfh;
    //   1837: getfield 315	fh:l	Ljava/lang/String;
    //   1840: invokevirtual 323	java/lang/String:equals	(Ljava/lang/Object;)Z
    //   1843: ifeq +27 -> 1870
    //   1846: aload_0
    //   1847: getfield 56	ff:c	Lfh;
    //   1850: getfield 306	fh:d	I
    //   1853: iconst_2
    //   1854: if_icmpne +16 -> 1870
    //   1857: aload_0
    //   1858: getfield 56	ff:c	Lfh;
    //   1861: pop
    //   1862: aload_0
    //   1863: getfield 52	ff:f	Lev;
    //   1866: invokevirtual 325	ev:g	()Ljava/lang/String;
    //   1869: pop
    //   1870: aload_0
    //   1871: getfield 177	ff:g	Lfd;
    //   1874: aload_0
    //   1875: getfield 56	ff:c	Lfh;
    //   1878: invokevirtual 308	fd:d	(Lfh;)V
    //   1881: aload_1
    //   1882: ifnull +7 -> 1889
    //   1885: aload_1
    //   1886: invokevirtual 219	java/nio/channels/FileChannel:close	()V
    //   1889: aload 9
    //   1891: ifnull +13 -> 1904
    //   1894: aload 9
    //   1896: invokevirtual 229	java/io/FileOutputStream:flush	()V
    //   1899: aload 9
    //   1901: invokevirtual 194	java/io/FileOutputStream:close	()V
    //   1904: aload_0
    //   1905: getfield 52	ff:f	Lev;
    //   1908: ifnull -1077 -> 831
    //   1911: aload_0
    //   1912: getfield 52	ff:f	Lev;
    //   1915: invokevirtual 221	ev:d	()V
    //   1918: aload_0
    //   1919: aconst_null
    //   1920: putfield 52	ff:f	Lev;
    //   1923: goto -1092 -> 831
    //   1926: aload_0
    //   1927: getfield 56	ff:c	Lfh;
    //   1930: getfield 306	fh:d	I
    //   1933: iconst_2
    //   1934: if_icmpne -130 -> 1804
    //   1937: aload_0
    //   1938: getfield 56	ff:c	Lfh;
    //   1941: pop
    //   1942: invokestatic 329	bk:c	()I
    //   1945: pop
    //   1946: goto -142 -> 1804
    //   1949: aload_0
    //   1950: getfield 56	ff:c	Lfh;
    //   1953: ldc_w 331
    //   1956: putfield 315	fh:l	Ljava/lang/String;
    //   1959: goto -89 -> 1870
    //   1962: astore 25
    //   1964: aload 25
    //   1966: invokevirtual 251	java/io/IOException:printStackTrace	()V
    //   1969: goto -80 -> 1889
    //   1972: astore 24
    //   1974: aload 24
    //   1976: invokevirtual 251	java/io/IOException:printStackTrace	()V
    //   1979: goto -75 -> 1904
    //   1982: aload_0
    //   1983: getfield 56	ff:c	Lfh;
    //   1986: getfield 87	fh:h	J
    //   1989: aload_0
    //   1990: getfield 56	ff:c	Lfh;
    //   1993: getfield 158	fh:g	J
    //   1996: lcmp
    //   1997: ifne +15 -> 2012
    //   2000: aload_0
    //   2001: getfield 56	ff:c	Lfh;
    //   2004: getfield 87	fh:h	J
    //   2007: lconst_0
    //   2008: lcmp
    //   2009: ifgt +55 -> 2064
    //   2012: aload_0
    //   2013: getfield 56	ff:c	Lfh;
    //   2016: getfield 306	fh:d	I
    //   2019: iconst_2
    //   2020: if_icmpeq +200 -> 2220
    //   2023: aload_0
    //   2024: getfield 50	ff:e	Z
    //   2027: ifeq +193 -> 2220
    //   2030: aload_0
    //   2031: getfield 56	ff:c	Lfh;
    //   2034: getfield 310	fh:c	Z
    //   2037: ifne +183 -> 2220
    //   2040: aload_0
    //   2041: getfield 56	ff:c	Lfh;
    //   2044: getfield 158	fh:g	J
    //   2047: lconst_0
    //   2048: lcmp
    //   2049: ifgt +171 -> 2220
    //   2052: aload_0
    //   2053: getfield 56	ff:c	Lfh;
    //   2056: getfield 87	fh:h	J
    //   2059: lconst_0
    //   2060: lcmp
    //   2061: ifle +159 -> 2220
    //   2064: aload_0
    //   2065: getfield 56	ff:c	Lfh;
    //   2068: getfield 306	fh:d	I
    //   2071: iconst_2
    //   2072: if_icmpeq +13 -> 2085
    //   2075: aload_0
    //   2076: getfield 56	ff:c	Lfh;
    //   2079: pop
    //   2080: aload_0
    //   2081: getfield 56	ff:c	Lfh;
    //   2084: pop
    //   2085: aload_0
    //   2086: getfield 56	ff:c	Lfh;
    //   2089: pop
    //   2090: aload_0
    //   2091: getfield 56	ff:c	Lfh;
    //   2094: iconst_3
    //   2095: putfield 306	fh:d	I
    //   2098: aload_0
    //   2099: getfield 56	ff:c	Lfh;
    //   2102: pop
    //   2103: aload_0
    //   2104: getfield 52	ff:f	Lev;
    //   2107: ifnull +136 -> 2243
    //   2110: aload_0
    //   2111: getfield 56	ff:c	Lfh;
    //   2114: aload_0
    //   2115: getfield 52	ff:f	Lev;
    //   2118: invokevirtual 312	ev:h	()Ljava/lang/String;
    //   2121: putfield 315	fh:l	Ljava/lang/String;
    //   2124: ldc_w 317
    //   2127: aload_0
    //   2128: getfield 56	ff:c	Lfh;
    //   2131: getfield 315	fh:l	Ljava/lang/String;
    //   2134: invokevirtual 323	java/lang/String:equals	(Ljava/lang/Object;)Z
    //   2137: ifeq +27 -> 2164
    //   2140: aload_0
    //   2141: getfield 56	ff:c	Lfh;
    //   2144: getfield 306	fh:d	I
    //   2147: iconst_2
    //   2148: if_icmpne +16 -> 2164
    //   2151: aload_0
    //   2152: getfield 56	ff:c	Lfh;
    //   2155: pop
    //   2156: aload_0
    //   2157: getfield 52	ff:f	Lev;
    //   2160: invokevirtual 325	ev:g	()Ljava/lang/String;
    //   2163: pop
    //   2164: aload_0
    //   2165: getfield 177	ff:g	Lfd;
    //   2168: aload_0
    //   2169: getfield 56	ff:c	Lfh;
    //   2172: invokevirtual 308	fd:d	(Lfh;)V
    //   2175: aload_1
    //   2176: ifnull +7 -> 2183
    //   2179: aload_1
    //   2180: invokevirtual 219	java/nio/channels/FileChannel:close	()V
    //   2183: aload 9
    //   2185: ifnull +13 -> 2198
    //   2188: aload 9
    //   2190: invokevirtual 229	java/io/FileOutputStream:flush	()V
    //   2193: aload 9
    //   2195: invokevirtual 194	java/io/FileOutputStream:close	()V
    //   2198: aload_0
    //   2199: getfield 52	ff:f	Lev;
    //   2202: ifnull +15 -> 2217
    //   2205: aload_0
    //   2206: getfield 52	ff:f	Lev;
    //   2209: invokevirtual 221	ev:d	()V
    //   2212: aload_0
    //   2213: aconst_null
    //   2214: putfield 52	ff:f	Lev;
    //   2217: aload 8
    //   2219: athrow
    //   2220: aload_0
    //   2221: getfield 56	ff:c	Lfh;
    //   2224: getfield 306	fh:d	I
    //   2227: iconst_2
    //   2228: if_icmpne -130 -> 2098
    //   2231: aload_0
    //   2232: getfield 56	ff:c	Lfh;
    //   2235: pop
    //   2236: invokestatic 329	bk:c	()I
    //   2239: pop
    //   2240: goto -142 -> 2098
    //   2243: aload_0
    //   2244: getfield 56	ff:c	Lfh;
    //   2247: ldc_w 331
    //   2250: putfield 315	fh:l	Ljava/lang/String;
    //   2253: goto -89 -> 2164
    //   2256: astore 14
    //   2258: aload 14
    //   2260: invokevirtual 251	java/io/IOException:printStackTrace	()V
    //   2263: goto -80 -> 2183
    //   2266: astore 13
    //   2268: aload 13
    //   2270: invokevirtual 251	java/io/IOException:printStackTrace	()V
    //   2273: goto -75 -> 2198
    //   2276: aload_0
    //   2277: getfield 56	ff:c	Lfh;
    //   2280: getfield 306	fh:d	I
    //   2283: iconst_2
    //   2284: if_icmpne -1567 -> 717
    //   2287: aload_0
    //   2288: getfield 56	ff:c	Lfh;
    //   2291: pop
    //   2292: invokestatic 329	bk:c	()I
    //   2295: pop
    //   2296: goto -1579 -> 717
    //   2299: aload_0
    //   2300: getfield 56	ff:c	Lfh;
    //   2303: ldc_w 331
    //   2306: putfield 315	fh:l	Ljava/lang/String;
    //   2309: goto -1526 -> 783
    //   2312: astore 69
    //   2314: aload 69
    //   2316: invokevirtual 251	java/io/IOException:printStackTrace	()V
    //   2319: goto -1517 -> 802
    //   2322: astore 68
    //   2324: aload 68
    //   2326: invokevirtual 251	java/io/IOException:printStackTrace	()V
    //   2329: goto -1517 -> 812
    //   2332: astore 8
    //   2334: goto -352 -> 1982
    //   2337: astore 20
    //   2339: goto -720 -> 1619
    //   2342: astore 34
    //   2344: goto -1130 -> 1214
    //   2347: return
    //   2348: astore 8
    //   2350: aconst_null
    //   2351: astore_1
    //   2352: aconst_null
    //   2353: astore 9
    //   2355: goto -373 -> 1982
    //
    // Exception table:
    //   from	to	target	type
    //   9	58	356	finally
    //   130	353	356	finally
    //   361	394	356	finally
    //   601	794	356	finally
    //   798	802	356	finally
    //   802	812	356	finally
    //   812	833	356	finally
    //   921	1114	356	finally
    //   1118	1122	356	finally
    //   1127	1137	356	finally
    //   1137	1156	356	finally
    //   1250	1443	356	finally
    //   1447	1451	356	finally
    //   1456	1466	356	finally
    //   1466	1485	356	finally
    //   1502	1611	356	finally
    //   1688	1881	356	finally
    //   1885	1889	356	finally
    //   1894	1904	356	finally
    //   1904	2175	356	finally
    //   2179	2183	356	finally
    //   2188	2198	356	finally
    //   2198	2329	356	finally
    //   408	548	869	eq
    //   844	866	869	eq
    //   58	130	874	eq
    //   397	403	874	eq
    //   548	562	874	eq
    //   871	874	874	eq
    //   1161	1209	874	eq
    //   408	548	1159	java/lang/Exception
    //   844	866	1159	java/lang/Exception
    //   58	130	1209	java/io/FileNotFoundException
    //   397	403	1209	java/io/FileNotFoundException
    //   408	548	1209	java/io/FileNotFoundException
    //   548	562	1209	java/io/FileNotFoundException
    //   844	866	1209	java/io/FileNotFoundException
    //   871	874	1209	java/io/FileNotFoundException
    //   1161	1209	1209	java/io/FileNotFoundException
    //   562	601	1497	eq
    //   1488	1494	1497	eq
    //   1118	1122	1538	java/io/IOException
    //   1127	1137	1548	java/io/IOException
    //   1447	1451	1594	java/io/IOException
    //   1456	1466	1604	java/io/IOException
    //   58	130	1614	java/lang/Exception
    //   397	403	1614	java/lang/Exception
    //   548	562	1614	java/lang/Exception
    //   871	874	1614	java/lang/Exception
    //   1161	1209	1614	java/lang/Exception
    //   1885	1889	1962	java/io/IOException
    //   1894	1904	1972	java/io/IOException
    //   2179	2183	2256	java/io/IOException
    //   2188	2198	2266	java/io/IOException
    //   798	802	2312	java/io/IOException
    //   802	812	2322	java/io/IOException
    //   562	601	2332	finally
    //   879	921	2332	finally
    //   1214	1250	2332	finally
    //   1488	1494	2332	finally
    //   1619	1688	2332	finally
    //   562	601	2337	java/lang/Exception
    //   1488	1494	2337	java/lang/Exception
    //   562	601	2342	java/io/FileNotFoundException
    //   1488	1494	2342	java/io/FileNotFoundException
    //   58	130	2348	finally
    //   397	403	2348	finally
    //   408	548	2348	finally
    //   548	562	2348	finally
    //   844	866	2348	finally
    //   871	874	2348	finally
    //   1161	1209	2348	finally
  }
}

/* Location:           C:\Users\sandrocheng.21KUNPENG\Desktop\classes_dex2jar\
 * Qualified Name:     ff
 * JD-Core Version:    0.6.2
 */