package com.avast.android.generic.app.about;

public class r
{
  // ERROR //
  public static byte[] a()
  {
    // Byte code:
    //   0: new 12	java/text/SimpleDateFormat
    //   3: dup
    //   4: ldc 14
    //   6: invokespecial 18	java/text/SimpleDateFormat:<init>	(Ljava/lang/String;)V
    //   9: astore_0
    //   10: invokestatic 24	java/util/Calendar:getInstance	()Ljava/util/Calendar;
    //   13: astore_1
    //   14: aload_1
    //   15: invokevirtual 28	java/util/Calendar:getTime	()Ljava/util/Date;
    //   18: astore_2
    //   19: aload_1
    //   20: bipush 12
    //   22: bipush 226
    //   24: invokevirtual 32	java/util/Calendar:add	(II)V
    //   27: aload_1
    //   28: invokevirtual 28	java/util/Calendar:getTime	()Ljava/util/Date;
    //   31: astore_3
    //   32: new 34	java/io/ByteArrayOutputStream
    //   35: dup
    //   36: invokespecial 37	java/io/ByteArrayOutputStream:<init>	()V
    //   39: astore 4
    //   41: new 39	java/util/zip/ZipOutputStream
    //   44: dup
    //   45: aload 4
    //   47: invokespecial 42	java/util/zip/ZipOutputStream:<init>	(Ljava/io/OutputStream;)V
    //   50: astore 5
    //   52: aload 5
    //   54: bipush 8
    //   56: invokevirtual 46	java/util/zip/ZipOutputStream:setMethod	(I)V
    //   59: aload 5
    //   61: new 48	java/util/zip/ZipEntry
    //   64: dup
    //   65: ldc 50
    //   67: invokespecial 51	java/util/zip/ZipEntry:<init>	(Ljava/lang/String;)V
    //   70: invokevirtual 55	java/util/zip/ZipOutputStream:putNextEntry	(Ljava/util/zip/ZipEntry;)V
    //   73: new 57	java/io/BufferedReader
    //   76: dup
    //   77: new 59	java/io/InputStreamReader
    //   80: dup
    //   81: invokestatic 65	java/lang/Runtime:getRuntime	()Ljava/lang/Runtime;
    //   84: ldc 67
    //   86: invokevirtual 71	java/lang/Runtime:exec	(Ljava/lang/String;)Ljava/lang/Process;
    //   89: invokevirtual 77	java/lang/Process:getInputStream	()Ljava/io/InputStream;
    //   92: invokespecial 80	java/io/InputStreamReader:<init>	(Ljava/io/InputStream;)V
    //   95: invokespecial 83	java/io/BufferedReader:<init>	(Ljava/io/Reader;)V
    //   98: astore 7
    //   100: aload 7
    //   102: invokevirtual 87	java/io/BufferedReader:readLine	()Ljava/lang/String;
    //   105: astore 18
    //   107: aload 18
    //   109: ifnull +58 -> 167
    //   112: aload 18
    //   114: invokevirtual 93	java/lang/String:length	()I
    //   117: bipush 18
    //   119: if_icmplt -19 -> 100
    //   122: aload_0
    //   123: aload 18
    //   125: iconst_0
    //   126: bipush 18
    //   128: invokevirtual 97	java/lang/String:substring	(II)Ljava/lang/String;
    //   131: invokevirtual 101	java/text/SimpleDateFormat:parse	(Ljava/lang/String;)Ljava/util/Date;
    //   134: astore 23
    //   136: aload 23
    //   138: aload_3
    //   139: invokevirtual 106	java/util/Date:getYear	()I
    //   142: invokevirtual 109	java/util/Date:setYear	(I)V
    //   145: aload 23
    //   147: aload_3
    //   148: invokevirtual 113	java/util/Date:before	(Ljava/util/Date;)Z
    //   151: ifne -51 -> 100
    //   154: aload 23
    //   156: aload_2
    //   157: invokevirtual 116	java/util/Date:after	(Ljava/util/Date;)Z
    //   160: istore 24
    //   162: iload 24
    //   164: ifeq +66 -> 230
    //   167: aload 5
    //   169: invokevirtual 119	java/util/zip/ZipOutputStream:flush	()V
    //   172: aload 5
    //   174: ifnull +18 -> 192
    //   177: aload 5
    //   179: invokevirtual 119	java/util/zip/ZipOutputStream:flush	()V
    //   182: aload 5
    //   184: invokevirtual 122	java/util/zip/ZipOutputStream:closeEntry	()V
    //   187: aload 5
    //   189: invokevirtual 125	java/util/zip/ZipOutputStream:close	()V
    //   192: aconst_null
    //   193: astore 13
    //   195: aload 4
    //   197: ifnull +20 -> 217
    //   200: aload 4
    //   202: invokevirtual 126	java/io/ByteArrayOutputStream:flush	()V
    //   205: aload 4
    //   207: invokevirtual 129	java/io/ByteArrayOutputStream:toByteArray	()[B
    //   210: astore 13
    //   212: aload 4
    //   214: invokevirtual 130	java/io/ByteArrayOutputStream:close	()V
    //   217: aload 7
    //   219: ifnull +8 -> 227
    //   222: aload 7
    //   224: invokevirtual 131	java/io/BufferedReader:close	()V
    //   227: aload 13
    //   229: areturn
    //   230: aload 5
    //   232: new 133	java/lang/StringBuilder
    //   235: dup
    //   236: invokespecial 134	java/lang/StringBuilder:<init>	()V
    //   239: aload 18
    //   241: invokevirtual 138	java/lang/StringBuilder:append	(Ljava/lang/String;)Ljava/lang/StringBuilder;
    //   244: ldc 140
    //   246: invokevirtual 138	java/lang/StringBuilder:append	(Ljava/lang/String;)Ljava/lang/StringBuilder;
    //   249: invokevirtual 143	java/lang/StringBuilder:toString	()Ljava/lang/String;
    //   252: invokevirtual 146	java/lang/String:getBytes	()[B
    //   255: invokevirtual 150	java/util/zip/ZipOutputStream:write	([B)V
    //   258: goto -158 -> 100
    //   261: astore 6
    //   263: aload 6
    //   265: invokevirtual 153	java/io/IOException:printStackTrace	()V
    //   268: aload 5
    //   270: ifnull +18 -> 288
    //   273: aload 5
    //   275: invokevirtual 119	java/util/zip/ZipOutputStream:flush	()V
    //   278: aload 5
    //   280: invokevirtual 122	java/util/zip/ZipOutputStream:closeEntry	()V
    //   283: aload 5
    //   285: invokevirtual 125	java/util/zip/ZipOutputStream:close	()V
    //   288: aconst_null
    //   289: astore 13
    //   291: aload 4
    //   293: ifnull +20 -> 313
    //   296: aload 4
    //   298: invokevirtual 126	java/io/ByteArrayOutputStream:flush	()V
    //   301: aload 4
    //   303: invokevirtual 129	java/io/ByteArrayOutputStream:toByteArray	()[B
    //   306: astore 13
    //   308: aload 4
    //   310: invokevirtual 130	java/io/ByteArrayOutputStream:close	()V
    //   313: aload 7
    //   315: ifnull -88 -> 227
    //   318: aload 7
    //   320: invokevirtual 131	java/io/BufferedReader:close	()V
    //   323: goto -96 -> 227
    //   326: astore 14
    //   328: goto -101 -> 227
    //   331: astore 26
    //   333: aconst_null
    //   334: astore 5
    //   336: aconst_null
    //   337: astore 4
    //   339: aconst_null
    //   340: astore 7
    //   342: aload 26
    //   344: astore 8
    //   346: aload 5
    //   348: ifnull +18 -> 366
    //   351: aload 5
    //   353: invokevirtual 119	java/util/zip/ZipOutputStream:flush	()V
    //   356: aload 5
    //   358: invokevirtual 122	java/util/zip/ZipOutputStream:closeEntry	()V
    //   361: aload 5
    //   363: invokevirtual 125	java/util/zip/ZipOutputStream:close	()V
    //   366: aload 4
    //   368: ifnull +19 -> 387
    //   371: aload 4
    //   373: invokevirtual 126	java/io/ByteArrayOutputStream:flush	()V
    //   376: aload 4
    //   378: invokevirtual 129	java/io/ByteArrayOutputStream:toByteArray	()[B
    //   381: pop
    //   382: aload 4
    //   384: invokevirtual 130	java/io/ByteArrayOutputStream:close	()V
    //   387: aload 7
    //   389: ifnull +8 -> 397
    //   392: aload 7
    //   394: invokevirtual 131	java/io/BufferedReader:close	()V
    //   397: aload 8
    //   399: athrow
    //   400: astore 19
    //   402: goto -175 -> 227
    //   405: astore 9
    //   407: goto -10 -> 397
    //   410: astore 10
    //   412: goto -25 -> 387
    //   415: astore 12
    //   417: goto -51 -> 366
    //   420: astore 25
    //   422: aload 25
    //   424: astore 8
    //   426: aconst_null
    //   427: astore 5
    //   429: aconst_null
    //   430: astore 7
    //   432: goto -86 -> 346
    //   435: astore 17
    //   437: aload 17
    //   439: astore 8
    //   441: aconst_null
    //   442: astore 7
    //   444: goto -98 -> 346
    //   447: astore 8
    //   449: goto -103 -> 346
    //   452: astore 15
    //   454: goto -141 -> 313
    //   457: astore 16
    //   459: goto -171 -> 288
    //   462: astore 6
    //   464: aconst_null
    //   465: astore 5
    //   467: aconst_null
    //   468: astore 4
    //   470: aconst_null
    //   471: astore 7
    //   473: goto -210 -> 263
    //   476: astore 6
    //   478: aconst_null
    //   479: astore 5
    //   481: aconst_null
    //   482: astore 7
    //   484: goto -221 -> 263
    //   487: astore 6
    //   489: aconst_null
    //   490: astore 7
    //   492: goto -229 -> 263
    //   495: astore 20
    //   497: goto -280 -> 217
    //   500: astore 21
    //   502: goto -310 -> 192
    //   505: astore 22
    //   507: goto -407 -> 100
    //
    // Exception table:
    //   from	to	target	type
    //   100	107	261	java/io/IOException
    //   112	162	261	java/io/IOException
    //   167	172	261	java/io/IOException
    //   230	258	261	java/io/IOException
    //   318	323	326	java/io/IOException
    //   32	41	331	finally
    //   222	227	400	java/io/IOException
    //   392	397	405	java/io/IOException
    //   371	387	410	java/io/IOException
    //   351	366	415	java/io/IOException
    //   41	52	420	finally
    //   52	100	435	finally
    //   100	107	447	finally
    //   112	162	447	finally
    //   167	172	447	finally
    //   230	258	447	finally
    //   263	268	447	finally
    //   296	313	452	java/io/IOException
    //   273	288	457	java/io/IOException
    //   32	41	462	java/io/IOException
    //   41	52	476	java/io/IOException
    //   52	100	487	java/io/IOException
    //   200	217	495	java/io/IOException
    //   177	192	500	java/io/IOException
    //   112	162	505	java/text/ParseException
  }

  // ERROR //
  public static byte[] b()
  {
    // Byte code:
    //   0: new 34	java/io/ByteArrayOutputStream
    //   3: dup
    //   4: invokespecial 37	java/io/ByteArrayOutputStream:<init>	()V
    //   7: astore_0
    //   8: new 39	java/util/zip/ZipOutputStream
    //   11: dup
    //   12: aload_0
    //   13: invokespecial 42	java/util/zip/ZipOutputStream:<init>	(Ljava/io/OutputStream;)V
    //   16: astore_1
    //   17: aload_1
    //   18: bipush 8
    //   20: invokevirtual 46	java/util/zip/ZipOutputStream:setMethod	(I)V
    //   23: aload_1
    //   24: new 48	java/util/zip/ZipEntry
    //   27: dup
    //   28: ldc 156
    //   30: invokespecial 51	java/util/zip/ZipEntry:<init>	(Ljava/lang/String;)V
    //   33: invokevirtual 55	java/util/zip/ZipOutputStream:putNextEntry	(Ljava/util/zip/ZipEntry;)V
    //   36: new 57	java/io/BufferedReader
    //   39: dup
    //   40: new 59	java/io/InputStreamReader
    //   43: dup
    //   44: invokestatic 65	java/lang/Runtime:getRuntime	()Ljava/lang/Runtime;
    //   47: ldc 158
    //   49: invokevirtual 71	java/lang/Runtime:exec	(Ljava/lang/String;)Ljava/lang/Process;
    //   52: invokevirtual 77	java/lang/Process:getInputStream	()Ljava/io/InputStream;
    //   55: invokespecial 80	java/io/InputStreamReader:<init>	(Ljava/io/InputStream;)V
    //   58: invokespecial 83	java/io/BufferedReader:<init>	(Ljava/io/Reader;)V
    //   61: astore_3
    //   62: aload_3
    //   63: invokevirtual 87	java/io/BufferedReader:readLine	()Ljava/lang/String;
    //   66: astore 29
    //   68: aload 29
    //   70: ifnull +249 -> 319
    //   73: aload_1
    //   74: new 133	java/lang/StringBuilder
    //   77: dup
    //   78: invokespecial 134	java/lang/StringBuilder:<init>	()V
    //   81: aload 29
    //   83: invokevirtual 138	java/lang/StringBuilder:append	(Ljava/lang/String;)Ljava/lang/StringBuilder;
    //   86: ldc 140
    //   88: invokevirtual 138	java/lang/StringBuilder:append	(Ljava/lang/String;)Ljava/lang/StringBuilder;
    //   91: invokevirtual 143	java/lang/StringBuilder:toString	()Ljava/lang/String;
    //   94: invokevirtual 146	java/lang/String:getBytes	()[B
    //   97: invokevirtual 150	java/util/zip/ZipOutputStream:write	([B)V
    //   100: goto -38 -> 62
    //   103: astore_2
    //   104: aload_2
    //   105: invokevirtual 153	java/io/IOException:printStackTrace	()V
    //   108: aload_1
    //   109: ifnull +11 -> 120
    //   112: aload_1
    //   113: invokevirtual 119	java/util/zip/ZipOutputStream:flush	()V
    //   116: aload_1
    //   117: invokevirtual 122	java/util/zip/ZipOutputStream:closeEntry	()V
    //   120: aload_3
    //   121: ifnull +7 -> 128
    //   124: aload_3
    //   125: invokevirtual 131	java/io/BufferedReader:close	()V
    //   128: aload_0
    //   129: astore 7
    //   131: aload_3
    //   132: astore 8
    //   134: aload_1
    //   135: astore 9
    //   137: aload 9
    //   139: new 48	java/util/zip/ZipEntry
    //   142: dup
    //   143: ldc 160
    //   145: invokespecial 51	java/util/zip/ZipEntry:<init>	(Ljava/lang/String;)V
    //   148: invokevirtual 55	java/util/zip/ZipOutputStream:putNextEntry	(Ljava/util/zip/ZipEntry;)V
    //   151: new 162	java/io/File
    //   154: dup
    //   155: ldc 164
    //   157: invokespecial 165	java/io/File:<init>	(Ljava/lang/String;)V
    //   160: astore 21
    //   162: aload 21
    //   164: invokevirtual 169	java/io/File:exists	()Z
    //   167: ifeq +258 -> 425
    //   170: aload 21
    //   172: invokevirtual 172	java/io/File:isFile	()Z
    //   175: ifeq +250 -> 425
    //   178: aload 21
    //   180: invokevirtual 175	java/io/File:canRead	()Z
    //   183: ifeq +242 -> 425
    //   186: new 57	java/io/BufferedReader
    //   189: dup
    //   190: new 59	java/io/InputStreamReader
    //   193: dup
    //   194: new 177	java/io/FileInputStream
    //   197: dup
    //   198: aload 21
    //   200: invokespecial 180	java/io/FileInputStream:<init>	(Ljava/io/File;)V
    //   203: invokespecial 80	java/io/InputStreamReader:<init>	(Ljava/io/InputStream;)V
    //   206: invokespecial 83	java/io/BufferedReader:<init>	(Ljava/io/Reader;)V
    //   209: astore 11
    //   211: aload 11
    //   213: invokevirtual 87	java/io/BufferedReader:readLine	()Ljava/lang/String;
    //   216: astore 25
    //   218: aload 25
    //   220: ifnull +196 -> 416
    //   223: aload 9
    //   225: new 133	java/lang/StringBuilder
    //   228: dup
    //   229: invokespecial 134	java/lang/StringBuilder:<init>	()V
    //   232: aload 25
    //   234: invokevirtual 138	java/lang/StringBuilder:append	(Ljava/lang/String;)Ljava/lang/StringBuilder;
    //   237: ldc 140
    //   239: invokevirtual 138	java/lang/StringBuilder:append	(Ljava/lang/String;)Ljava/lang/StringBuilder;
    //   242: invokevirtual 143	java/lang/StringBuilder:toString	()Ljava/lang/String;
    //   245: invokevirtual 146	java/lang/String:getBytes	()[B
    //   248: invokevirtual 150	java/util/zip/ZipOutputStream:write	([B)V
    //   251: goto -40 -> 211
    //   254: astore 10
    //   256: aload 10
    //   258: invokevirtual 153	java/io/IOException:printStackTrace	()V
    //   261: aload 9
    //   263: ifnull +18 -> 281
    //   266: aload 9
    //   268: invokevirtual 119	java/util/zip/ZipOutputStream:flush	()V
    //   271: aload 9
    //   273: invokevirtual 122	java/util/zip/ZipOutputStream:closeEntry	()V
    //   276: aload 9
    //   278: invokevirtual 125	java/util/zip/ZipOutputStream:close	()V
    //   281: aconst_null
    //   282: astore 17
    //   284: aload 7
    //   286: ifnull +20 -> 306
    //   289: aload 7
    //   291: invokevirtual 126	java/io/ByteArrayOutputStream:flush	()V
    //   294: aload 7
    //   296: invokevirtual 129	java/io/ByteArrayOutputStream:toByteArray	()[B
    //   299: astore 17
    //   301: aload 7
    //   303: invokevirtual 130	java/io/ByteArrayOutputStream:close	()V
    //   306: aload 11
    //   308: ifnull +8 -> 316
    //   311: aload 11
    //   313: invokevirtual 131	java/io/BufferedReader:close	()V
    //   316: aload 17
    //   318: areturn
    //   319: aload_1
    //   320: invokevirtual 119	java/util/zip/ZipOutputStream:flush	()V
    //   323: aload_1
    //   324: ifnull +11 -> 335
    //   327: aload_1
    //   328: invokevirtual 119	java/util/zip/ZipOutputStream:flush	()V
    //   331: aload_1
    //   332: invokevirtual 122	java/util/zip/ZipOutputStream:closeEntry	()V
    //   335: aload_3
    //   336: ifnull +7 -> 343
    //   339: aload_3
    //   340: invokevirtual 131	java/io/BufferedReader:close	()V
    //   343: aload_0
    //   344: astore 7
    //   346: aload_3
    //   347: astore 8
    //   349: aload_1
    //   350: astore 9
    //   352: goto -215 -> 137
    //   355: astore 30
    //   357: aload_0
    //   358: astore 7
    //   360: aload_3
    //   361: astore 8
    //   363: aload_1
    //   364: astore 9
    //   366: goto -229 -> 137
    //   369: astore 26
    //   371: aload_0
    //   372: astore 7
    //   374: aload_3
    //   375: astore 8
    //   377: aload_1
    //   378: astore 9
    //   380: goto -243 -> 137
    //   383: astore 32
    //   385: aconst_null
    //   386: astore_1
    //   387: aconst_null
    //   388: astore_3
    //   389: aload 32
    //   391: astore 4
    //   393: aload_1
    //   394: ifnull +11 -> 405
    //   397: aload_1
    //   398: invokevirtual 119	java/util/zip/ZipOutputStream:flush	()V
    //   401: aload_1
    //   402: invokevirtual 122	java/util/zip/ZipOutputStream:closeEntry	()V
    //   405: aload_3
    //   406: ifnull +7 -> 413
    //   409: aload_3
    //   410: invokevirtual 131	java/io/BufferedReader:close	()V
    //   413: aload 4
    //   415: athrow
    //   416: aload 9
    //   418: invokevirtual 119	java/util/zip/ZipOutputStream:flush	()V
    //   421: aload 11
    //   423: astore 8
    //   425: aload 9
    //   427: ifnull +18 -> 445
    //   430: aload 9
    //   432: invokevirtual 119	java/util/zip/ZipOutputStream:flush	()V
    //   435: aload 9
    //   437: invokevirtual 122	java/util/zip/ZipOutputStream:closeEntry	()V
    //   440: aload 9
    //   442: invokevirtual 125	java/util/zip/ZipOutputStream:close	()V
    //   445: aconst_null
    //   446: astore 17
    //   448: aload 7
    //   450: ifnull +20 -> 470
    //   453: aload 7
    //   455: invokevirtual 126	java/io/ByteArrayOutputStream:flush	()V
    //   458: aload 7
    //   460: invokevirtual 129	java/io/ByteArrayOutputStream:toByteArray	()[B
    //   463: astore 17
    //   465: aload 7
    //   467: invokevirtual 130	java/io/ByteArrayOutputStream:close	()V
    //   470: aload 8
    //   472: ifnull -156 -> 316
    //   475: aload 8
    //   477: invokevirtual 131	java/io/BufferedReader:close	()V
    //   480: goto -164 -> 316
    //   483: astore 22
    //   485: goto -169 -> 316
    //   488: astore 12
    //   490: aload 9
    //   492: ifnull +18 -> 510
    //   495: aload 9
    //   497: invokevirtual 119	java/util/zip/ZipOutputStream:flush	()V
    //   500: aload 9
    //   502: invokevirtual 122	java/util/zip/ZipOutputStream:closeEntry	()V
    //   505: aload 9
    //   507: invokevirtual 125	java/util/zip/ZipOutputStream:close	()V
    //   510: aload 7
    //   512: ifnull +19 -> 531
    //   515: aload 7
    //   517: invokevirtual 126	java/io/ByteArrayOutputStream:flush	()V
    //   520: aload 7
    //   522: invokevirtual 129	java/io/ByteArrayOutputStream:toByteArray	()[B
    //   525: pop
    //   526: aload 7
    //   528: invokevirtual 130	java/io/ByteArrayOutputStream:close	()V
    //   531: aload 8
    //   533: ifnull +8 -> 541
    //   536: aload 8
    //   538: invokevirtual 131	java/io/BufferedReader:close	()V
    //   541: aload 12
    //   543: athrow
    //   544: astore 5
    //   546: goto -133 -> 413
    //   549: astore 18
    //   551: goto -235 -> 316
    //   554: astore 13
    //   556: goto -15 -> 541
    //   559: astore 14
    //   561: goto -30 -> 531
    //   564: astore 16
    //   566: goto -56 -> 510
    //   569: astore 12
    //   571: aload 11
    //   573: astore 8
    //   575: goto -85 -> 490
    //   578: astore 12
    //   580: aload 11
    //   582: astore 8
    //   584: goto -94 -> 490
    //   587: astore 19
    //   589: goto -283 -> 306
    //   592: astore 20
    //   594: goto -313 -> 281
    //   597: astore 10
    //   599: aload 8
    //   601: astore 11
    //   603: goto -347 -> 256
    //   606: astore 23
    //   608: goto -138 -> 470
    //   611: astore 24
    //   613: goto -168 -> 445
    //   616: astore 6
    //   618: goto -213 -> 405
    //   621: astore 28
    //   623: aload 28
    //   625: astore 4
    //   627: aconst_null
    //   628: astore_3
    //   629: goto -236 -> 393
    //   632: astore 4
    //   634: goto -241 -> 393
    //   637: astore 27
    //   639: goto -519 -> 120
    //   642: astore_2
    //   643: aconst_null
    //   644: astore_1
    //   645: aconst_null
    //   646: astore_0
    //   647: aconst_null
    //   648: astore_3
    //   649: goto -545 -> 104
    //   652: astore_2
    //   653: aconst_null
    //   654: astore_1
    //   655: aconst_null
    //   656: astore_3
    //   657: goto -553 -> 104
    //   660: astore_2
    //   661: aconst_null
    //   662: astore_3
    //   663: goto -559 -> 104
    //   666: astore 31
    //   668: goto -333 -> 335
    //
    // Exception table:
    //   from	to	target	type
    //   62	100	103	java/io/IOException
    //   319	323	103	java/io/IOException
    //   211	251	254	java/io/IOException
    //   416	421	254	java/io/IOException
    //   339	343	355	java/io/IOException
    //   124	128	369	java/io/IOException
    //   0	8	383	finally
    //   8	17	383	finally
    //   475	480	483	java/io/IOException
    //   137	211	488	finally
    //   409	413	544	java/io/IOException
    //   311	316	549	java/io/IOException
    //   536	541	554	java/io/IOException
    //   515	531	559	java/io/IOException
    //   495	510	564	java/io/IOException
    //   211	251	569	finally
    //   416	421	569	finally
    //   256	261	578	finally
    //   289	306	587	java/io/IOException
    //   266	281	592	java/io/IOException
    //   137	211	597	java/io/IOException
    //   453	470	606	java/io/IOException
    //   430	445	611	java/io/IOException
    //   397	405	616	java/io/IOException
    //   17	62	621	finally
    //   62	100	632	finally
    //   104	108	632	finally
    //   319	323	632	finally
    //   112	120	637	java/io/IOException
    //   0	8	642	java/io/IOException
    //   8	17	652	java/io/IOException
    //   17	62	660	java/io/IOException
    //   327	335	666	java/io/IOException
  }
}

/* Location:           C:\Users\sandrocheng.21KUNPENG\Desktop\classes_dex2jar.jar
 * Qualified Name:     com.avast.android.generic.app.about.r
 * JD-Core Version:    0.6.2
 */