package com.tencent.feedback.upload;

import android.content.Context;
import com.tencent.feedback.common.ELog;

public abstract class c
{
  private static c a = null;

  public static c a(Context paramContext)
  {
    try
    {
      if (a == null)
        a = new a(paramContext.getApplicationContext());
      c localc = a;
      return localc;
    }
    finally
    {
      localObject = finally;
      throw localObject;
    }
  }

  public abstract byte[] a(String paramString1, byte[] paramArrayOfByte, String paramString2, b paramb);

  public static final class a extends c
  {
    public a(Context paramContext)
    {
      paramContext.getApplicationContext();
      paramContext.getSystemService("connectivity");
    }

    // ERROR //
    public final byte[] a(String paramString1, byte[] paramArrayOfByte, String paramString2, c.b paramb)
    {
      // Byte code:
      //   0: new 27	java/lang/StringBuilder
      //   3: dup
      //   4: invokespecial 28	java/lang/StringBuilder:<init>	()V
      //   7: ldc 30
      //   9: invokevirtual 34	java/lang/StringBuilder:append	(Ljava/lang/String;)Ljava/lang/StringBuilder;
      //   12: aload_1
      //   13: invokevirtual 34	java/lang/StringBuilder:append	(Ljava/lang/String;)Ljava/lang/StringBuilder;
      //   16: invokevirtual 38	java/lang/StringBuilder:toString	()Ljava/lang/String;
      //   19: invokestatic 44	com/tencent/feedback/common/ELog:debug	(Ljava/lang/String;)V
      //   22: aload_2
      //   23: ifnonnull +547 -> 570
      //   26: lconst_0
      //   27: lstore 5
      //   29: aconst_null
      //   30: astore 7
      //   32: aconst_null
      //   33: astore 8
      //   35: new 27	java/lang/StringBuilder
      //   38: dup
      //   39: invokespecial 28	java/lang/StringBuilder:<init>	()V
      //   42: ldc 46
      //   44: invokevirtual 34	java/lang/StringBuilder:append	(Ljava/lang/String;)Ljava/lang/StringBuilder;
      //   47: lload 5
      //   49: invokevirtual 49	java/lang/StringBuilder:append	(J)Ljava/lang/StringBuilder;
      //   52: invokevirtual 38	java/lang/StringBuilder:toString	()Ljava/lang/String;
      //   55: invokestatic 44	com/tencent/feedback/common/ELog:debug	(Ljava/lang/String;)V
      //   58: aconst_null
      //   59: astore 7
      //   61: aload_2
      //   62: ifnull +516 -> 578
      //   65: new 51	org/apache/http/entity/ByteArrayEntity
      //   68: dup
      //   69: aload_2
      //   70: invokespecial 54	org/apache/http/entity/ByteArrayEntity:<init>	([B)V
      //   73: astore 22
      //   75: new 56	org/apache/http/params/BasicHttpParams
      //   78: dup
      //   79: invokespecial 57	org/apache/http/params/BasicHttpParams:<init>	()V
      //   82: astore 23
      //   84: aload 23
      //   86: sipush 30000
      //   89: invokestatic 63	org/apache/http/params/HttpConnectionParams:setConnectionTimeout	(Lorg/apache/http/params/HttpParams;I)V
      //   92: aload 23
      //   94: sipush 10000
      //   97: invokestatic 66	org/apache/http/params/HttpConnectionParams:setSoTimeout	(Lorg/apache/http/params/HttpParams;I)V
      //   100: aload 23
      //   102: sipush 2000
      //   105: invokestatic 69	org/apache/http/params/HttpConnectionParams:setSocketBufferSize	(Lorg/apache/http/params/HttpParams;I)V
      //   108: aload 23
      //   110: ldc 71
      //   112: iconst_0
      //   113: invokevirtual 75	org/apache/http/params/BasicHttpParams:setBooleanParameter	(Ljava/lang/String;Z)Lorg/apache/http/params/HttpParams;
      //   116: pop
      //   117: new 77	org/apache/http/impl/client/DefaultHttpClient
      //   120: dup
      //   121: aload 23
      //   123: invokespecial 80	org/apache/http/impl/client/DefaultHttpClient:<init>	(Lorg/apache/http/params/HttpParams;)V
      //   126: astore 25
      //   128: aload 25
      //   130: new 82	com/tencent/feedback/upload/d
      //   133: dup
      //   134: aload_0
      //   135: invokespecial 85	com/tencent/feedback/upload/d:<init>	(Lcom/tencent/feedback/upload/c$a;)V
      //   138: invokevirtual 89	org/apache/http/impl/client/DefaultHttpClient:setHttpRequestRetryHandler	(Lorg/apache/http/client/HttpRequestRetryHandler;)V
      //   141: aconst_null
      //   142: astore 7
      //   144: aload_3
      //   145: ifnull +74 -> 219
      //   148: aload_3
      //   149: invokevirtual 94	java/lang/String:toLowerCase	()Ljava/lang/String;
      //   152: ldc 96
      //   154: invokevirtual 100	java/lang/String:contains	(Ljava/lang/CharSequence;)Z
      //   157: istore 59
      //   159: aconst_null
      //   160: astore 7
      //   162: iload 59
      //   164: ifeq +55 -> 219
      //   167: new 27	java/lang/StringBuilder
      //   170: dup
      //   171: invokespecial 28	java/lang/StringBuilder:<init>	()V
      //   174: ldc 102
      //   176: invokevirtual 34	java/lang/StringBuilder:append	(Ljava/lang/String;)Ljava/lang/StringBuilder;
      //   179: aload_3
      //   180: invokevirtual 34	java/lang/StringBuilder:append	(Ljava/lang/String;)Ljava/lang/StringBuilder;
      //   183: invokevirtual 38	java/lang/StringBuilder:toString	()Ljava/lang/String;
      //   186: invokestatic 105	com/tencent/feedback/common/ELog:info	(Ljava/lang/String;)V
      //   189: new 107	org/apache/http/HttpHost
      //   192: dup
      //   193: invokestatic 112	android/net/Proxy:getDefaultHost	()Ljava/lang/String;
      //   196: invokestatic 116	android/net/Proxy:getDefaultPort	()I
      //   199: invokespecial 119	org/apache/http/HttpHost:<init>	(Ljava/lang/String;I)V
      //   202: astore 60
      //   204: aload 25
      //   206: invokevirtual 123	org/apache/http/impl/client/DefaultHttpClient:getParams	()Lorg/apache/http/params/HttpParams;
      //   209: ldc 125
      //   211: aload 60
      //   213: invokeinterface 131 3 0
      //   218: pop
      //   219: new 133	org/apache/http/client/methods/HttpPost
      //   222: dup
      //   223: aload_1
      //   224: invokespecial 135	org/apache/http/client/methods/HttpPost:<init>	(Ljava/lang/String;)V
      //   227: astore 26
      //   229: aload 26
      //   231: aload 22
      //   233: invokevirtual 139	org/apache/http/client/methods/HttpPost:setEntity	(Lorg/apache/http/HttpEntity;)V
      //   236: aconst_null
      //   237: astore 28
      //   239: iconst_0
      //   240: istore 29
      //   242: iconst_0
      //   243: istore 30
      //   245: iconst_0
      //   246: istore 31
      //   248: aload 26
      //   250: astore 7
      //   252: aconst_null
      //   253: astore 32
      //   255: iload 30
      //   257: iconst_2
      //   258: if_icmpge +1056 -> 1314
      //   261: iload 31
      //   263: iconst_2
      //   264: if_icmpge +1050 -> 1314
      //   267: new 27	java/lang/StringBuilder
      //   270: dup
      //   271: invokespecial 28	java/lang/StringBuilder:<init>	()V
      //   274: ldc 141
      //   276: invokevirtual 34	java/lang/StringBuilder:append	(Ljava/lang/String;)Ljava/lang/StringBuilder;
      //   279: iload 30
      //   281: invokevirtual 144	java/lang/StringBuilder:append	(I)Ljava/lang/StringBuilder;
      //   284: invokevirtual 38	java/lang/StringBuilder:toString	()Ljava/lang/String;
      //   287: invokestatic 44	com/tencent/feedback/common/ELog:debug	(Ljava/lang/String;)V
      //   290: iload 30
      //   292: iconst_1
      //   293: iadd
      //   294: istore 46
      //   296: aload 4
      //   298: ifnull +19 -> 317
      //   301: aload 4
      //   303: aload 7
      //   305: invokevirtual 148	org/apache/http/client/methods/HttpPost:getURI	()Ljava/net/URI;
      //   308: invokevirtual 151	java/net/URI:toString	()Ljava/lang/String;
      //   311: lload 5
      //   313: aload_3
      //   314: invokevirtual 156	com/tencent/feedback/upload/c$b:a	(Ljava/lang/String;JLjava/lang/String;)V
      //   317: new 158	org/apache/http/protocol/BasicHttpContext
      //   320: dup
      //   321: invokespecial 159	org/apache/http/protocol/BasicHttpContext:<init>	()V
      //   324: astore 47
      //   326: aload 25
      //   328: aload 7
      //   330: aload 47
      //   332: invokevirtual 163	org/apache/http/impl/client/DefaultHttpClient:execute	(Lorg/apache/http/client/methods/HttpUriRequest;Lorg/apache/http/protocol/HttpContext;)Lorg/apache/http/HttpResponse;
      //   335: astore 49
      //   337: aload 47
      //   339: ldc 165
      //   341: invokeinterface 170 2 0
      //   346: checkcast 172	org/apache/http/HttpRequest
      //   349: astore 50
      //   351: new 27	java/lang/StringBuilder
      //   354: dup
      //   355: invokespecial 28	java/lang/StringBuilder:<init>	()V
      //   358: ldc 174
      //   360: invokevirtual 34	java/lang/StringBuilder:append	(Ljava/lang/String;)Ljava/lang/StringBuilder;
      //   363: aload 50
      //   365: invokeinterface 178 1 0
      //   370: invokevirtual 181	java/lang/Object:toString	()Ljava/lang/String;
      //   373: invokevirtual 34	java/lang/StringBuilder:append	(Ljava/lang/String;)Ljava/lang/StringBuilder;
      //   376: invokevirtual 38	java/lang/StringBuilder:toString	()Ljava/lang/String;
      //   379: invokestatic 44	com/tencent/feedback/common/ELog:debug	(Ljava/lang/String;)V
      //   382: aload 49
      //   384: invokeinterface 187 1 0
      //   389: invokeinterface 192 1 0
      //   394: istore 51
      //   396: aload 49
      //   398: invokeinterface 196 1 0
      //   403: astore 28
      //   405: aload 28
      //   407: ifnull +213 -> 620
      //   410: aload 28
      //   412: invokeinterface 202 1 0
      //   417: lconst_0
      //   418: lcmp
      //   419: ifle +201 -> 620
      //   422: aload 4
      //   424: aload 28
      //   426: invokeinterface 202 1 0
      //   431: invokevirtual 205	com/tencent/feedback/upload/c$b:a	(J)V
      //   434: goto +891 -> 1325
      //   437: iload 52
      //   439: ifeq +370 -> 809
      //   442: iinc 31 1
      //   445: aload 49
      //   447: ldc 207
      //   449: invokeinterface 211 2 0
      //   454: astore 55
      //   456: aload 55
      //   458: ifnonnull +267 -> 725
      //   461: new 27	java/lang/StringBuilder
      //   464: dup
      //   465: invokespecial 28	java/lang/StringBuilder:<init>	()V
      //   468: ldc 213
      //   470: invokevirtual 34	java/lang/StringBuilder:append	(Ljava/lang/String;)Ljava/lang/StringBuilder;
      //   473: iload 51
      //   475: invokevirtual 144	java/lang/StringBuilder:append	(I)Ljava/lang/StringBuilder;
      //   478: ldc 215
      //   480: invokevirtual 34	java/lang/StringBuilder:append	(Ljava/lang/String;)Ljava/lang/StringBuilder;
      //   483: invokevirtual 38	java/lang/StringBuilder:toString	()Ljava/lang/String;
      //   486: invokestatic 218	com/tencent/feedback/common/ELog:error	(Ljava/lang/String;)V
      //   489: aload 49
      //   491: astore 33
      //   493: iload 51
      //   495: istore 34
      //   497: iload 34
      //   499: sipush 200
      //   502: if_icmpeq +399 -> 901
      //   505: aload 33
      //   507: invokeinterface 187 1 0
      //   512: astore 43
      //   514: new 27	java/lang/StringBuilder
      //   517: dup
      //   518: invokespecial 28	java/lang/StringBuilder:<init>	()V
      //   521: ldc 220
      //   523: invokevirtual 34	java/lang/StringBuilder:append	(Ljava/lang/String;)Ljava/lang/StringBuilder;
      //   526: iload 34
      //   528: invokevirtual 144	java/lang/StringBuilder:append	(I)Ljava/lang/StringBuilder;
      //   531: ldc 222
      //   533: invokevirtual 34	java/lang/StringBuilder:append	(Ljava/lang/String;)Ljava/lang/StringBuilder;
      //   536: aload 43
      //   538: invokevirtual 225	java/lang/StringBuilder:append	(Ljava/lang/Object;)Ljava/lang/StringBuilder;
      //   541: invokevirtual 38	java/lang/StringBuilder:toString	()Ljava/lang/String;
      //   544: ifnull +331 -> 875
      //   547: aload 43
      //   549: invokevirtual 181	java/lang/Object:toString	()Ljava/lang/String;
      //   552: astore 44
      //   554: aload 44
      //   556: invokestatic 218	com/tencent/feedback/common/ELog:error	(Ljava/lang/String;)V
      //   559: aload 7
      //   561: invokevirtual 228	org/apache/http/client/methods/HttpPost:abort	()V
      //   564: aconst_null
      //   565: astore 11
      //   567: aload 11
      //   569: areturn
      //   570: aload_2
      //   571: arraylength
      //   572: i2l
      //   573: lstore 5
      //   575: goto -546 -> 29
      //   578: new 51	org/apache/http/entity/ByteArrayEntity
      //   581: dup
      //   582: ldc 230
      //   584: invokevirtual 234	java/lang/String:getBytes	()[B
      //   587: invokespecial 54	org/apache/http/entity/ByteArrayEntity:<init>	([B)V
      //   590: astore 21
      //   592: aload 21
      //   594: astore 22
      //   596: goto -521 -> 75
      //   599: astore 48
      //   601: aload 48
      //   603: invokevirtual 237	java/lang/Throwable:printStackTrace	()V
      //   606: aload 4
      //   608: ifnull +755 -> 1363
      //   611: aload 4
      //   613: lconst_0
      //   614: invokevirtual 205	com/tencent/feedback/upload/c$b:a	(J)V
      //   617: goto +746 -> 1363
      //   620: aload 4
      //   622: ldc2_w 238
      //   625: invokevirtual 205	com/tencent/feedback/upload/c$b:a	(J)V
      //   628: goto +697 -> 1325
      //   631: astore 41
      //   633: aload 41
      //   635: astore 10
      //   637: aconst_null
      //   638: astore 12
      //   640: aconst_null
      //   641: astore 11
      //   643: aload 7
      //   645: astore 13
      //   647: aload 10
      //   649: invokevirtual 237	java/lang/Throwable:printStackTrace	()V
      //   652: aload 10
      //   654: invokevirtual 242	java/lang/Throwable:getMessage	()Ljava/lang/String;
      //   657: invokestatic 218	com/tencent/feedback/common/ELog:error	(Ljava/lang/String;)V
      //   660: aload 12
      //   662: ifnull +8 -> 670
      //   665: aload 12
      //   667: invokevirtual 247	java/io/DataInputStream:close	()V
      //   670: aload 13
      //   672: ifnull +8 -> 680
      //   675: aload 13
      //   677: invokevirtual 228	org/apache/http/client/methods/HttpPost:abort	()V
      //   680: ldc 249
      //   682: invokestatic 44	com/tencent/feedback/common/ELog:debug	(Ljava/lang/String;)V
      //   685: aload 11
      //   687: ifnonnull +476 -> 1163
      //   690: lconst_0
      //   691: lstore 17
      //   693: new 27	java/lang/StringBuilder
      //   696: dup
      //   697: invokespecial 28	java/lang/StringBuilder:<init>	()V
      //   700: ldc 251
      //   702: invokevirtual 34	java/lang/StringBuilder:append	(Ljava/lang/String;)Ljava/lang/StringBuilder;
      //   705: lload 17
      //   707: invokevirtual 49	java/lang/StringBuilder:append	(J)Ljava/lang/StringBuilder;
      //   710: invokevirtual 38	java/lang/StringBuilder:toString	()Ljava/lang/String;
      //   713: invokestatic 44	com/tencent/feedback/common/ELog:debug	(Ljava/lang/String;)V
      //   716: goto -149 -> 567
      //   719: iconst_0
      //   720: istore 52
      //   722: goto -285 -> 437
      //   725: aload 55
      //   727: invokeinterface 256 1 0
      //   732: astore 56
      //   734: new 27	java/lang/StringBuilder
      //   737: dup
      //   738: invokespecial 28	java/lang/StringBuilder:<init>	()V
      //   741: ldc 213
      //   743: invokevirtual 34	java/lang/StringBuilder:append	(Ljava/lang/String;)Ljava/lang/StringBuilder;
      //   746: iload 51
      //   748: invokevirtual 144	java/lang/StringBuilder:append	(I)Ljava/lang/StringBuilder;
      //   751: ldc_w 258
      //   754: invokevirtual 34	java/lang/StringBuilder:append	(Ljava/lang/String;)Ljava/lang/StringBuilder;
      //   757: aload 56
      //   759: invokevirtual 34	java/lang/StringBuilder:append	(Ljava/lang/String;)Ljava/lang/StringBuilder;
      //   762: invokevirtual 38	java/lang/StringBuilder:toString	()Ljava/lang/String;
      //   765: invokestatic 44	com/tencent/feedback/common/ELog:debug	(Ljava/lang/String;)V
      //   768: aload 7
      //   770: invokevirtual 228	org/apache/http/client/methods/HttpPost:abort	()V
      //   773: new 133	org/apache/http/client/methods/HttpPost
      //   776: dup
      //   777: aload 56
      //   779: invokespecial 135	org/apache/http/client/methods/HttpPost:<init>	(Ljava/lang/String;)V
      //   782: astore 57
      //   784: aload 57
      //   786: aload 22
      //   788: invokevirtual 139	org/apache/http/client/methods/HttpPost:setEntity	(Lorg/apache/http/HttpEntity;)V
      //   791: aload 57
      //   793: astore 7
      //   795: aload 49
      //   797: astore 32
      //   799: iload 51
      //   801: istore 29
      //   803: iconst_0
      //   804: istore 30
      //   806: goto -551 -> 255
      //   809: iload 51
      //   811: sipush 200
      //   814: if_icmpne +20 -> 834
      //   817: ldc_w 260
      //   820: invokestatic 105	com/tencent/feedback/common/ELog:info	(Ljava/lang/String;)V
      //   823: aload 49
      //   825: astore 33
      //   827: iload 51
      //   829: istore 34
      //   831: goto -334 -> 497
      //   834: aload 7
      //   836: invokevirtual 228	org/apache/http/client/methods/HttpPost:abort	()V
      //   839: new 133	org/apache/http/client/methods/HttpPost
      //   842: dup
      //   843: aload_1
      //   844: invokespecial 135	org/apache/http/client/methods/HttpPost:<init>	(Ljava/lang/String;)V
      //   847: astore 53
      //   849: aload 53
      //   851: aload 22
      //   853: invokevirtual 139	org/apache/http/client/methods/HttpPost:setEntity	(Lorg/apache/http/HttpEntity;)V
      //   856: aload 53
      //   858: astore 7
      //   860: aload 49
      //   862: astore 32
      //   864: iload 51
      //   866: istore 29
      //   868: iload 46
      //   870: istore 30
      //   872: goto -617 -> 255
      //   875: ldc_w 262
      //   878: astore 44
      //   880: goto -326 -> 554
      //   883: astore 45
      //   885: aload 45
      //   887: invokevirtual 237	java/lang/Throwable:printStackTrace	()V
      //   890: aload 45
      //   892: invokevirtual 242	java/lang/Throwable:getMessage	()Ljava/lang/String;
      //   895: invokestatic 218	com/tencent/feedback/common/ELog:error	(Ljava/lang/String;)V
      //   898: goto -334 -> 564
      //   901: aload 28
      //   903: ifnonnull +38 -> 941
      //   906: ldc_w 264
      //   909: invokestatic 218	com/tencent/feedback/common/ELog:error	(Ljava/lang/String;)V
      //   912: aload 7
      //   914: invokevirtual 228	org/apache/http/client/methods/HttpPost:abort	()V
      //   917: aconst_null
      //   918: astore 11
      //   920: goto -353 -> 567
      //   923: astore 42
      //   925: aload 42
      //   927: invokevirtual 237	java/lang/Throwable:printStackTrace	()V
      //   930: aload 42
      //   932: invokevirtual 242	java/lang/Throwable:getMessage	()Ljava/lang/String;
      //   935: invokestatic 218	com/tencent/feedback/common/ELog:error	(Ljava/lang/String;)V
      //   938: goto -21 -> 917
      //   941: ldc_w 266
      //   944: invokestatic 105	com/tencent/feedback/common/ELog:info	(Ljava/lang/String;)V
      //   947: new 244	java/io/DataInputStream
      //   950: dup
      //   951: aload 28
      //   953: invokeinterface 270 1 0
      //   958: invokespecial 273	java/io/DataInputStream:<init>	(Ljava/io/InputStream;)V
      //   961: astore 12
      //   963: new 275	java/io/ByteArrayOutputStream
      //   966: dup
      //   967: invokespecial 276	java/io/ByteArrayOutputStream:<init>	()V
      //   970: astore 35
      //   972: aload 12
      //   974: invokevirtual 279	java/io/DataInputStream:read	()I
      //   977: istore 37
      //   979: iload 37
      //   981: iconst_m1
      //   982: if_icmpeq +13 -> 995
      //   985: aload 35
      //   987: iload 37
      //   989: invokevirtual 283	java/io/ByteArrayOutputStream:write	(I)V
      //   992: goto -20 -> 972
      //   995: aload 35
      //   997: invokevirtual 286	java/io/ByteArrayOutputStream:flush	()V
      //   1000: aload 35
      //   1002: invokevirtual 289	java/io/ByteArrayOutputStream:toByteArray	()[B
      //   1005: astore 38
      //   1007: aload 38
      //   1009: astore 11
      //   1011: ldc_w 291
      //   1014: invokestatic 105	com/tencent/feedback/common/ELog:info	(Ljava/lang/String;)V
      //   1017: aload 12
      //   1019: invokevirtual 247	java/io/DataInputStream:close	()V
      //   1022: aload 7
      //   1024: invokevirtual 228	org/apache/http/client/methods/HttpPost:abort	()V
      //   1027: goto -347 -> 680
      //   1030: astore 40
      //   1032: aload 40
      //   1034: invokevirtual 237	java/lang/Throwable:printStackTrace	()V
      //   1037: aload 40
      //   1039: invokevirtual 242	java/lang/Throwable:getMessage	()Ljava/lang/String;
      //   1042: invokestatic 218	com/tencent/feedback/common/ELog:error	(Ljava/lang/String;)V
      //   1045: goto -365 -> 680
      //   1048: astore 39
      //   1050: aload 39
      //   1052: invokevirtual 237	java/lang/Throwable:printStackTrace	()V
      //   1055: aload 39
      //   1057: invokevirtual 242	java/lang/Throwable:getMessage	()Ljava/lang/String;
      //   1060: invokestatic 218	com/tencent/feedback/common/ELog:error	(Ljava/lang/String;)V
      //   1063: goto -41 -> 1022
      //   1066: astore 20
      //   1068: aload 20
      //   1070: invokevirtual 237	java/lang/Throwable:printStackTrace	()V
      //   1073: aload 20
      //   1075: invokevirtual 242	java/lang/Throwable:getMessage	()Ljava/lang/String;
      //   1078: invokestatic 218	com/tencent/feedback/common/ELog:error	(Ljava/lang/String;)V
      //   1081: goto -411 -> 670
      //   1084: astore 19
      //   1086: aload 19
      //   1088: invokevirtual 237	java/lang/Throwable:printStackTrace	()V
      //   1091: aload 19
      //   1093: invokevirtual 242	java/lang/Throwable:getMessage	()Ljava/lang/String;
      //   1096: invokestatic 218	com/tencent/feedback/common/ELog:error	(Ljava/lang/String;)V
      //   1099: goto -419 -> 680
      //   1102: astore 14
      //   1104: aload 8
      //   1106: ifnull +8 -> 1114
      //   1109: aload 8
      //   1111: invokevirtual 247	java/io/DataInputStream:close	()V
      //   1114: aload 7
      //   1116: ifnull +8 -> 1124
      //   1119: aload 7
      //   1121: invokevirtual 228	org/apache/http/client/methods/HttpPost:abort	()V
      //   1124: aload 14
      //   1126: athrow
      //   1127: astore 16
      //   1129: aload 16
      //   1131: invokevirtual 237	java/lang/Throwable:printStackTrace	()V
      //   1134: aload 16
      //   1136: invokevirtual 242	java/lang/Throwable:getMessage	()Ljava/lang/String;
      //   1139: invokestatic 218	com/tencent/feedback/common/ELog:error	(Ljava/lang/String;)V
      //   1142: goto -28 -> 1114
      //   1145: astore 15
      //   1147: aload 15
      //   1149: invokevirtual 237	java/lang/Throwable:printStackTrace	()V
      //   1152: aload 15
      //   1154: invokevirtual 242	java/lang/Throwable:getMessage	()Ljava/lang/String;
      //   1157: invokestatic 218	com/tencent/feedback/common/ELog:error	(Ljava/lang/String;)V
      //   1160: goto -36 -> 1124
      //   1163: aload 11
      //   1165: arraylength
      //   1166: i2l
      //   1167: lstore 17
      //   1169: goto -476 -> 693
      //   1172: astore 14
      //   1174: aload 26
      //   1176: astore 7
      //   1178: aconst_null
      //   1179: astore 8
      //   1181: goto -77 -> 1104
      //   1184: astore 14
      //   1186: aload 57
      //   1188: astore 7
      //   1190: aconst_null
      //   1191: astore 8
      //   1193: goto -89 -> 1104
      //   1196: astore 14
      //   1198: aload 53
      //   1200: astore 7
      //   1202: aconst_null
      //   1203: astore 8
      //   1205: goto -101 -> 1104
      //   1208: astore 14
      //   1210: aload 12
      //   1212: astore 8
      //   1214: goto -110 -> 1104
      //   1217: astore 14
      //   1219: aload 13
      //   1221: astore 7
      //   1223: aload 12
      //   1225: astore 8
      //   1227: goto -123 -> 1104
      //   1230: astore 9
      //   1232: aload 9
      //   1234: astore 10
      //   1236: aconst_null
      //   1237: astore 11
      //   1239: aconst_null
      //   1240: astore 12
      //   1242: aconst_null
      //   1243: astore 13
      //   1245: goto -598 -> 647
      //   1248: astore 27
      //   1250: aload 27
      //   1252: astore 10
      //   1254: aload 26
      //   1256: astore 13
      //   1258: aconst_null
      //   1259: astore 11
      //   1261: aconst_null
      //   1262: astore 12
      //   1264: goto -617 -> 647
      //   1267: astore 58
      //   1269: aload 58
      //   1271: astore 10
      //   1273: aload 57
      //   1275: astore 13
      //   1277: aconst_null
      //   1278: astore 11
      //   1280: aconst_null
      //   1281: astore 12
      //   1283: goto -636 -> 647
      //   1286: astore 54
      //   1288: aload 54
      //   1290: astore 10
      //   1292: aload 53
      //   1294: astore 13
      //   1296: aconst_null
      //   1297: astore 11
      //   1299: aconst_null
      //   1300: astore 12
      //   1302: goto -655 -> 647
      //   1305: astore 10
      //   1307: aload 7
      //   1309: astore 13
      //   1311: goto -664 -> 647
      //   1314: aload 32
      //   1316: astore 33
      //   1318: iload 29
      //   1320: istore 34
      //   1322: goto -825 -> 497
      //   1325: iload 51
      //   1327: sipush 301
      //   1330: if_icmpeq +27 -> 1357
      //   1333: iload 51
      //   1335: sipush 302
      //   1338: if_icmpeq +19 -> 1357
      //   1341: iload 51
      //   1343: sipush 303
      //   1346: if_icmpeq +11 -> 1357
      //   1349: iload 51
      //   1351: sipush 307
      //   1354: if_icmpne -635 -> 719
      //   1357: iconst_1
      //   1358: istore 52
      //   1360: goto -923 -> 437
      //   1363: iload 46
      //   1365: istore 30
      //   1367: goto -1112 -> 255
      //   1370: astore 36
      //   1372: aload 36
      //   1374: astore 10
      //   1376: aload 7
      //   1378: astore 13
      //   1380: aconst_null
      //   1381: astore 11
      //   1383: goto -736 -> 647
      //
      // Exception table:
      //   from	to	target	type
      //   326	337	599	java/lang/Throwable
      //   267	326	631	java/lang/Throwable
      //   337	559	631	java/lang/Throwable
      //   601	628	631	java/lang/Throwable
      //   725	784	631	java/lang/Throwable
      //   817	849	631	java/lang/Throwable
      //   906	912	631	java/lang/Throwable
      //   941	963	631	java/lang/Throwable
      //   559	564	883	java/lang/Throwable
      //   912	917	923	java/lang/Throwable
      //   1022	1027	1030	java/lang/Throwable
      //   1017	1022	1048	java/lang/Throwable
      //   665	670	1066	java/lang/Throwable
      //   675	680	1084	java/lang/Throwable
      //   35	229	1102	finally
      //   267	326	1102	finally
      //   326	337	1102	finally
      //   337	559	1102	finally
      //   578	592	1102	finally
      //   601	628	1102	finally
      //   725	784	1102	finally
      //   817	849	1102	finally
      //   906	912	1102	finally
      //   941	963	1102	finally
      //   1109	1114	1127	java/lang/Throwable
      //   1119	1124	1145	java/lang/Throwable
      //   229	236	1172	finally
      //   784	791	1184	finally
      //   849	856	1196	finally
      //   963	1007	1208	finally
      //   1011	1017	1208	finally
      //   647	660	1217	finally
      //   35	229	1230	java/lang/Throwable
      //   578	592	1230	java/lang/Throwable
      //   229	236	1248	java/lang/Throwable
      //   784	791	1267	java/lang/Throwable
      //   849	856	1286	java/lang/Throwable
      //   1011	1017	1305	java/lang/Throwable
      //   963	1007	1370	java/lang/Throwable
    }
  }

  public static class b
  {
    public int a = 0;
    public long b = 0L;
    public long c = 0L;

    protected b(e parame)
    {
    }

    public void a(long paramLong)
    {
      ELog.debug("onResponse:" + paramLong);
      this.c = (paramLong + this.c);
    }

    public void a(String paramString1, long paramLong, String paramString2)
    {
      ELog.debug("onRequest:" + paramString1 + " requestSize:" + paramLong + " apn" + paramString2);
      this.a = (1 + this.a);
      this.b = (paramLong + this.b);
    }
  }
}

/* Location:           C:\Users\sandrocheng.21KUNPENG\Desktop\classes_dex2jar.jar
 * Qualified Name:     com.tencent.feedback.upload.c
 * JD-Core Version:    0.6.2
 */