package com.tencent.feedback.upload;

import android.content.Context;
import com.qq.taf.jce.JceInputStream;
import com.tencent.feedback.common.ELog;
import common.MixPackage;
import java.util.Iterator;
import java.util.Map;
import java.util.Set;

public class e
  implements UploadHandler
{
  private static e b = null;
  private Context a = null;
  private c c = null;
  private a d = null;
  private b e = null;
  private b f;

  private e(Context paramContext)
  {
    this.a = paramContext;
    this.c = c.a(paramContext.getApplicationContext());
    this.f = new b(paramContext.getApplicationContext());
  }

  private a a()
  {
    try
    {
      a locala = this.d;
      return locala;
    }
    finally
    {
      localObject = finally;
      throw localObject;
    }
  }

  public static e a(Context paramContext)
  {
    try
    {
      if (b == null)
        b = new e(paramContext.getApplicationContext());
      e locale = b;
      return locale;
    }
    finally
    {
      localObject = finally;
      throw localObject;
    }
  }

  private void a(int paramInt, byte[] paramArrayOfByte, Object paramObject)
  {
    ELog.debug("dispatch2OnRecevied start");
    if ((paramArrayOfByte == null) || (paramInt == 0))
    {
      ELog.debug("process responseDatas == null or CMD_RESPONSE_NO_DATA");
      return;
    }
    if (paramInt == 10)
    {
      ELog.debug("process CMD_RESPONSE_ALL_STRATEGY");
      MixPackage localMixPackage = new MixPackage();
      localMixPackage.readFrom(new JceInputStream(paramArrayOfByte));
      Map localMap = localMixPackage.a();
      if ((localMap != null) && (localMap.size() > 0))
      {
        Iterator localIterator = localMap.keySet().iterator();
        while (localIterator.hasNext())
        {
          Integer localInteger = (Integer)localIterator.next();
          a(localInteger.intValue(), (byte[])localMap.get(localInteger), paramObject);
        }
      }
    }
    else
    {
      if (paramInt != 9)
        break label175;
      ELog.debug("process CMD_RESPONSE_SPEEDMONITOR_STRATEGY");
      b localb3 = b();
      if (localb3 != null)
        localb3.a(9, paramArrayOfByte);
    }
    while (true)
    {
      ELog.debug("dispatch2OnRecevied end");
      break;
      label175: ELog.debug("process common received");
      b localb1 = d();
      if (localb1 != null)
        localb1.a(paramInt, paramArrayOfByte);
      b localb2 = c();
      if (localb2 != null)
        localb2.a(paramInt, paramArrayOfByte);
    }
  }

  private b b()
  {
    try
    {
      b localb = this.e;
      return localb;
    }
    finally
    {
      localObject = finally;
      throw localObject;
    }
  }

  private b c()
  {
    return null;
  }

  private b d()
  {
    try
    {
      b localb = this.f;
      return localb;
    }
    finally
    {
      localObject = finally;
      throw localObject;
    }
  }

  public final void a(a parama)
  {
    try
    {
      this.d = parama;
      return;
    }
    finally
    {
      localObject = finally;
      throw localObject;
    }
  }

  public final void a(b paramb)
  {
    try
    {
      this.e = paramb;
      return;
    }
    finally
    {
      localObject = finally;
      throw localObject;
    }
  }

  // ERROR //
  public void doUpload(AbstractUploadDatas paramAbstractUploadDatas, OnUploadFinshed paramOnUploadFinshed, Object paramObject)
  {
    // Byte code:
    //   0: ldc 146
    //   2: invokestatic 62	com/tencent/feedback/common/ELog:debug	(Ljava/lang/String;)V
    //   5: aconst_null
    //   6: astore 4
    //   8: aload_1
    //   9: ifnonnull +51 -> 60
    //   12: ldc 148
    //   14: invokestatic 151	com/tencent/feedback/common/ELog:error	(Ljava/lang/String;)V
    //   17: getstatic 157	com/tencent/feedback/upload/OnUploadFinshed$UploadResult:UploadError	Lcom/tencent/feedback/upload/OnUploadFinshed$UploadResult;
    //   20: astore 45
    //   22: aload_2
    //   23: ifnull +22 -> 45
    //   26: aload_1
    //   27: ifnonnull +24 -> 51
    //   30: aconst_null
    //   31: astore 46
    //   33: aload_2
    //   34: aload 46
    //   36: aload 45
    //   38: ldc 159
    //   40: invokeinterface 165 4 0
    //   45: ldc 167
    //   47: invokestatic 62	com/tencent/feedback/common/ELog:debug	(Ljava/lang/String;)V
    //   50: return
    //   51: aload_1
    //   52: invokevirtual 173	com/tencent/feedback/upload/AbstractUploadDatas:getmUploadDataType	()Lcom/tencent/feedback/upload/AbstractUploadDatas$UploadDataType;
    //   55: astore 46
    //   57: goto -24 -> 33
    //   60: aload_1
    //   61: iconst_1
    //   62: invokevirtual 177	com/tencent/feedback/upload/AbstractUploadDatas:getUploadRequestPackage	(Z)Lcommon/RequestPackage;
    //   65: astore 13
    //   67: aload 13
    //   69: ifnonnull +53 -> 122
    //   72: ldc 179
    //   74: invokestatic 182	com/tencent/feedback/common/ELog:warn	(Ljava/lang/String;)V
    //   77: getstatic 185	com/tencent/feedback/upload/OnUploadFinshed$UploadResult:UploadFail	Lcom/tencent/feedback/upload/OnUploadFinshed$UploadResult;
    //   80: astore 43
    //   82: aload_2
    //   83: ifnull +22 -> 105
    //   86: aload_1
    //   87: ifnonnull +26 -> 113
    //   90: aconst_null
    //   91: astore 44
    //   93: aload_2
    //   94: aload 44
    //   96: aload 43
    //   98: ldc 187
    //   100: invokeinterface 165 4 0
    //   105: ldc 167
    //   107: invokestatic 62	com/tencent/feedback/common/ELog:debug	(Ljava/lang/String;)V
    //   110: goto -60 -> 50
    //   113: aload_1
    //   114: invokevirtual 173	com/tencent/feedback/upload/AbstractUploadDatas:getmUploadDataType	()Lcom/tencent/feedback/upload/AbstractUploadDatas$UploadDataType;
    //   117: astore 44
    //   119: goto -26 -> 93
    //   122: new 189	java/lang/StringBuilder
    //   125: dup
    //   126: invokespecial 190	java/lang/StringBuilder:<init>	()V
    //   129: ldc 192
    //   131: invokevirtual 196	java/lang/StringBuilder:append	(Ljava/lang/String;)Ljava/lang/StringBuilder;
    //   134: aload 13
    //   136: invokevirtual 202	common/RequestPackage:toString	()Ljava/lang/String;
    //   139: invokevirtual 196	java/lang/StringBuilder:append	(Ljava/lang/String;)Ljava/lang/StringBuilder;
    //   142: invokevirtual 203	java/lang/StringBuilder:toString	()Ljava/lang/String;
    //   145: invokestatic 62	com/tencent/feedback/common/ELog:debug	(Ljava/lang/String;)V
    //   148: new 205	com/qq/jce/wup/UniPacket
    //   151: dup
    //   152: invokespecial 206	com/qq/jce/wup/UniPacket:<init>	()V
    //   155: astore 14
    //   157: aload 14
    //   159: iconst_1
    //   160: invokevirtual 210	com/qq/jce/wup/UniPacket:setRequestId	(I)V
    //   163: aload 14
    //   165: ldc 212
    //   167: invokevirtual 215	com/qq/jce/wup/UniPacket:setServantName	(Ljava/lang/String;)V
    //   170: aload 14
    //   172: ldc 212
    //   174: invokevirtual 218	com/qq/jce/wup/UniPacket:setFuncName	(Ljava/lang/String;)V
    //   177: aload 14
    //   179: ldc 220
    //   181: aload 13
    //   183: invokevirtual 224	com/qq/jce/wup/UniPacket:put	(Ljava/lang/String;Ljava/lang/Object;)V
    //   186: aload 14
    //   188: invokevirtual 228	com/qq/jce/wup/UniPacket:encode	()[B
    //   191: astore 15
    //   193: new 189	java/lang/StringBuilder
    //   196: dup
    //   197: invokespecial 190	java/lang/StringBuilder:<init>	()V
    //   200: ldc 230
    //   202: invokevirtual 196	java/lang/StringBuilder:append	(Ljava/lang/String;)Ljava/lang/StringBuilder;
    //   205: aload_1
    //   206: invokevirtual 173	com/tencent/feedback/upload/AbstractUploadDatas:getmUploadDataType	()Lcom/tencent/feedback/upload/AbstractUploadDatas$UploadDataType;
    //   209: invokevirtual 233	java/lang/StringBuilder:append	(Ljava/lang/Object;)Ljava/lang/StringBuilder;
    //   212: invokevirtual 203	java/lang/StringBuilder:toString	()Ljava/lang/String;
    //   215: astore 16
    //   217: aload 16
    //   219: ldc 235
    //   221: invokevirtual 241	java/lang/String:startsWith	(Ljava/lang/String;)Z
    //   224: ifeq +114 -> 338
    //   227: aload_0
    //   228: getfield 27	com/tencent/feedback/upload/e:a	Landroid/content/Context;
    //   231: invokestatic 246	com/tencent/feedback/common/strategy/a:a	(Landroid/content/Context;)Lcom/tencent/feedback/common/strategy/a;
    //   234: aload_0
    //   235: getfield 27	com/tencent/feedback/upload/e:a	Landroid/content/Context;
    //   238: invokevirtual 249	com/tencent/feedback/common/strategy/a:c	(Landroid/content/Context;)Lcom/tencent/feedback/common/strategy/UploadStrategyBean;
    //   241: invokevirtual 254	com/tencent/feedback/common/strategy/UploadStrategyBean:getGrayUploadServer	()Ljava/lang/String;
    //   244: astore 17
    //   246: aload 17
    //   248: ifnonnull +136 -> 384
    //   251: new 189	java/lang/StringBuilder
    //   254: dup
    //   255: invokespecial 190	java/lang/StringBuilder:<init>	()V
    //   258: ldc_w 256
    //   261: invokevirtual 196	java/lang/StringBuilder:append	(Ljava/lang/String;)Ljava/lang/StringBuilder;
    //   264: aload_1
    //   265: invokevirtual 173	com/tencent/feedback/upload/AbstractUploadDatas:getmUploadDataType	()Lcom/tencent/feedback/upload/AbstractUploadDatas$UploadDataType;
    //   268: invokevirtual 233	java/lang/StringBuilder:append	(Ljava/lang/Object;)Ljava/lang/StringBuilder;
    //   271: invokevirtual 203	java/lang/StringBuilder:toString	()Ljava/lang/String;
    //   274: invokestatic 151	com/tencent/feedback/common/ELog:error	(Ljava/lang/String;)V
    //   277: getstatic 157	com/tencent/feedback/upload/OnUploadFinshed$UploadResult:UploadError	Lcom/tencent/feedback/upload/OnUploadFinshed$UploadResult;
    //   280: astore 6
    //   282: new 189	java/lang/StringBuilder
    //   285: dup
    //   286: invokespecial 190	java/lang/StringBuilder:<init>	()V
    //   289: ldc_w 256
    //   292: invokevirtual 196	java/lang/StringBuilder:append	(Ljava/lang/String;)Ljava/lang/StringBuilder;
    //   295: aload_1
    //   296: invokevirtual 173	com/tencent/feedback/upload/AbstractUploadDatas:getmUploadDataType	()Lcom/tencent/feedback/upload/AbstractUploadDatas$UploadDataType;
    //   299: invokevirtual 233	java/lang/StringBuilder:append	(Ljava/lang/Object;)Ljava/lang/StringBuilder;
    //   302: invokevirtual 203	java/lang/StringBuilder:toString	()Ljava/lang/String;
    //   305: astore 40
    //   307: aload_2
    //   308: ifnull +22 -> 330
    //   311: aload_1
    //   312: ifnonnull +63 -> 375
    //   315: aconst_null
    //   316: astore 41
    //   318: aload_2
    //   319: aload 41
    //   321: aload 6
    //   323: aload 40
    //   325: invokeinterface 165 4 0
    //   330: ldc 167
    //   332: invokestatic 62	com/tencent/feedback/common/ELog:debug	(Ljava/lang/String;)V
    //   335: goto -285 -> 50
    //   338: aload 16
    //   340: ldc_w 258
    //   343: invokevirtual 241	java/lang/String:startsWith	(Ljava/lang/String;)Z
    //   346: ifeq +710 -> 1056
    //   349: aload_0
    //   350: getfield 27	com/tencent/feedback/upload/e:a	Landroid/content/Context;
    //   353: invokestatic 246	com/tencent/feedback/common/strategy/a:a	(Landroid/content/Context;)Lcom/tencent/feedback/common/strategy/a;
    //   356: aload_0
    //   357: getfield 27	com/tencent/feedback/upload/e:a	Landroid/content/Context;
    //   360: invokevirtual 249	com/tencent/feedback/common/strategy/a:c	(Landroid/content/Context;)Lcom/tencent/feedback/common/strategy/UploadStrategyBean;
    //   363: invokevirtual 261	com/tencent/feedback/common/strategy/UploadStrategyBean:getUploadServer	()Ljava/lang/String;
    //   366: astore 42
    //   368: aload 42
    //   370: astore 17
    //   372: goto -126 -> 246
    //   375: aload_1
    //   376: invokevirtual 173	com/tencent/feedback/upload/AbstractUploadDatas:getmUploadDataType	()Lcom/tencent/feedback/upload/AbstractUploadDatas$UploadDataType;
    //   379: astore 41
    //   381: goto -63 -> 318
    //   384: aload_0
    //   385: getfield 27	com/tencent/feedback/upload/e:a	Landroid/content/Context;
    //   388: invokestatic 266	com/tencent/feedback/common/d:b	(Landroid/content/Context;)Ljava/lang/String;
    //   391: astore 18
    //   393: aload 18
    //   395: ifnull +13 -> 408
    //   398: aload 18
    //   400: ldc 230
    //   402: invokevirtual 270	java/lang/String:equals	(Ljava/lang/Object;)Z
    //   405: ifeq +18 -> 423
    //   408: ldc2_w 271
    //   411: invokestatic 278	java/lang/Thread:sleep	(J)V
    //   414: aload_0
    //   415: getfield 27	com/tencent/feedback/upload/e:a	Landroid/content/Context;
    //   418: invokestatic 266	com/tencent/feedback/common/d:b	(Landroid/content/Context;)Ljava/lang/String;
    //   421: astore 18
    //   423: aconst_null
    //   424: astore 19
    //   426: aload 18
    //   428: ifnull +95 -> 523
    //   431: aload 18
    //   433: ldc 230
    //   435: invokevirtual 270	java/lang/String:equals	(Ljava/lang/Object;)Z
    //   438: istore 32
    //   440: aconst_null
    //   441: astore 19
    //   443: iload 32
    //   445: ifne +78 -> 523
    //   448: new 280	com/tencent/feedback/upload/c$b
    //   451: dup
    //   452: aload_0
    //   453: invokespecial 283	com/tencent/feedback/upload/c$b:<init>	(Lcom/tencent/feedback/upload/e;)V
    //   456: astore 33
    //   458: invokestatic 289	java/lang/System:currentTimeMillis	()J
    //   461: lstore 34
    //   463: aload_0
    //   464: getfield 29	com/tencent/feedback/upload/e:c	Lcom/tencent/feedback/upload/c;
    //   467: aload 17
    //   469: aload 15
    //   471: aload 18
    //   473: aload 33
    //   475: invokevirtual 292	com/tencent/feedback/upload/c:a	(Ljava/lang/String;[BLjava/lang/String;Lcom/tencent/feedback/upload/c$b;)[B
    //   478: astore 36
    //   480: invokestatic 289	java/lang/System:currentTimeMillis	()J
    //   483: lload 34
    //   485: lsub
    //   486: lstore 37
    //   488: aload_0
    //   489: invokespecial 294	com/tencent/feedback/upload/e:a	()Lcom/tencent/feedback/upload/e$a;
    //   492: astore 39
    //   494: aload 39
    //   496: ifnull +566 -> 1062
    //   499: aload 39
    //   501: aload 18
    //   503: lload 37
    //   505: aload 33
    //   507: getfield 297	com/tencent/feedback/upload/c$b:b	J
    //   510: aload 33
    //   512: getfield 299	com/tencent/feedback/upload/c$b:c	J
    //   515: invokeinterface 304 8 0
    //   520: goto +542 -> 1062
    //   523: aload 19
    //   525: ifnonnull +55 -> 580
    //   528: ldc_w 306
    //   531: invokestatic 151	com/tencent/feedback/common/ELog:error	(Ljava/lang/String;)V
    //   534: getstatic 157	com/tencent/feedback/upload/OnUploadFinshed$UploadResult:UploadError	Lcom/tencent/feedback/upload/OnUploadFinshed$UploadResult;
    //   537: astore 30
    //   539: aload_2
    //   540: ifnull +23 -> 563
    //   543: aload_1
    //   544: ifnonnull +27 -> 571
    //   547: aconst_null
    //   548: astore 31
    //   550: aload_2
    //   551: aload 31
    //   553: aload 30
    //   555: ldc_w 308
    //   558: invokeinterface 165 4 0
    //   563: ldc 167
    //   565: invokestatic 62	com/tencent/feedback/common/ELog:debug	(Ljava/lang/String;)V
    //   568: goto -518 -> 50
    //   571: aload_1
    //   572: invokevirtual 173	com/tencent/feedback/upload/AbstractUploadDatas:getmUploadDataType	()Lcom/tencent/feedback/upload/AbstractUploadDatas$UploadDataType;
    //   575: astore 31
    //   577: goto -27 -> 550
    //   580: new 205	com/qq/jce/wup/UniPacket
    //   583: dup
    //   584: invokespecial 206	com/qq/jce/wup/UniPacket:<init>	()V
    //   587: astore 20
    //   589: aload 20
    //   591: aload 19
    //   593: invokevirtual 311	com/qq/jce/wup/UniPacket:decode	([B)V
    //   596: aload 20
    //   598: ldc 220
    //   600: invokevirtual 314	com/qq/jce/wup/UniPacket:get	(Ljava/lang/String;)Ljava/lang/Object;
    //   603: checkcast 316	common/ResponsePackage
    //   606: astore 21
    //   608: aload 21
    //   610: getfield 319	common/ResponsePackage:a	B
    //   613: ifne +284 -> 897
    //   616: getstatic 322	com/tencent/feedback/upload/OnUploadFinshed$UploadResult:UploadOk	Lcom/tencent/feedback/upload/OnUploadFinshed$UploadResult;
    //   619: astore 6
    //   621: aload 6
    //   623: getstatic 322	com/tencent/feedback/upload/OnUploadFinshed$UploadResult:UploadOk	Lcom/tencent/feedback/upload/OnUploadFinshed$UploadResult;
    //   626: if_acmpne +240 -> 866
    //   629: ldc_w 324
    //   632: invokestatic 62	com/tencent/feedback/common/ELog:debug	(Ljava/lang/String;)V
    //   635: aload 21
    //   637: ifnull +229 -> 866
    //   640: new 189	java/lang/StringBuilder
    //   643: dup
    //   644: invokespecial 190	java/lang/StringBuilder:<init>	()V
    //   647: ldc_w 326
    //   650: invokevirtual 196	java/lang/StringBuilder:append	(Ljava/lang/String;)Ljava/lang/StringBuilder;
    //   653: aload 21
    //   655: invokevirtual 327	common/ResponsePackage:toString	()Ljava/lang/String;
    //   658: invokevirtual 196	java/lang/StringBuilder:append	(Ljava/lang/String;)Ljava/lang/StringBuilder;
    //   661: invokevirtual 203	java/lang/StringBuilder:toString	()Ljava/lang/String;
    //   664: invokestatic 62	com/tencent/feedback/common/ELog:debug	(Ljava/lang/String;)V
    //   667: aload 21
    //   669: invokevirtual 330	common/ResponsePackage:a	()B
    //   672: ifne +233 -> 905
    //   675: iconst_1
    //   676: istore 23
    //   678: aload_1
    //   679: iload 23
    //   681: invokevirtual 334	com/tencent/feedback/upload/AbstractUploadDatas:done	(Z)V
    //   684: ldc_w 336
    //   687: invokestatic 62	com/tencent/feedback/common/ELog:debug	(Ljava/lang/String;)V
    //   690: invokestatic 342	com/tencent/feedback/common/CommonInfo:getCommonInfo	()Lcom/tencent/feedback/common/CommonInfo;
    //   693: astore 24
    //   695: aload 24
    //   697: ifnull +110 -> 807
    //   700: aload 24
    //   702: aload 21
    //   704: invokevirtual 344	common/ResponsePackage:d	()Ljava/lang/String;
    //   707: invokevirtual 347	com/tencent/feedback/common/CommonInfo:setGateIP	(Ljava/lang/String;)V
    //   710: aload 21
    //   712: invokevirtual 350	common/ResponsePackage:g	()J
    //   715: ldc2_w 351
    //   718: lcmp
    //   719: iflt +34 -> 753
    //   722: ldc_w 354
    //   725: invokestatic 357	com/tencent/feedback/common/ELog:info	(Ljava/lang/String;)V
    //   728: new 359	java/util/Date
    //   731: dup
    //   732: invokespecial 360	java/util/Date:<init>	()V
    //   735: astore 29
    //   737: aload 24
    //   739: aload 21
    //   741: invokevirtual 350	common/ResponsePackage:g	()J
    //   744: aload 29
    //   746: invokevirtual 363	java/util/Date:getTime	()J
    //   749: lsub
    //   750: invokevirtual 366	com/tencent/feedback/common/CommonInfo:setServerTimeGap	(J)V
    //   753: new 189	java/lang/StringBuilder
    //   756: dup
    //   757: invokespecial 190	java/lang/StringBuilder:<init>	()V
    //   760: ldc_w 368
    //   763: invokevirtual 196	java/lang/StringBuilder:append	(Ljava/lang/String;)Ljava/lang/StringBuilder;
    //   766: aload 24
    //   768: invokevirtual 371	com/tencent/feedback/common/CommonInfo:getGateIP	()Ljava/lang/String;
    //   771: invokevirtual 196	java/lang/StringBuilder:append	(Ljava/lang/String;)Ljava/lang/StringBuilder;
    //   774: invokevirtual 203	java/lang/StringBuilder:toString	()Ljava/lang/String;
    //   777: invokestatic 62	com/tencent/feedback/common/ELog:debug	(Ljava/lang/String;)V
    //   780: new 189	java/lang/StringBuilder
    //   783: dup
    //   784: invokespecial 190	java/lang/StringBuilder:<init>	()V
    //   787: ldc_w 373
    //   790: invokevirtual 196	java/lang/StringBuilder:append	(Ljava/lang/String;)Ljava/lang/StringBuilder;
    //   793: aload 24
    //   795: invokevirtual 376	com/tencent/feedback/common/CommonInfo:getServerTimeGap	()J
    //   798: invokevirtual 379	java/lang/StringBuilder:append	(J)Ljava/lang/StringBuilder;
    //   801: invokevirtual 203	java/lang/StringBuilder:toString	()Ljava/lang/String;
    //   804: invokestatic 62	com/tencent/feedback/common/ELog:debug	(Ljava/lang/String;)V
    //   807: aload 21
    //   809: invokevirtual 381	common/ResponsePackage:c	()[B
    //   812: astore 25
    //   814: aload 25
    //   816: ifnull +50 -> 866
    //   819: aload 21
    //   821: invokevirtual 383	common/ResponsePackage:e	()B
    //   824: istore 26
    //   826: aload 25
    //   828: aload 21
    //   830: invokevirtual 385	common/ResponsePackage:f	()B
    //   833: iload 26
    //   835: ldc_w 387
    //   838: invokestatic 392	com/tencent/feedback/common/g:b	([BIILjava/lang/String;)[B
    //   841: astore 27
    //   843: aload 27
    //   845: ifnull +15 -> 860
    //   848: aload_0
    //   849: aload 21
    //   851: invokevirtual 394	common/ResponsePackage:b	()I
    //   854: aload 27
    //   856: aload_3
    //   857: invokespecial 120	com/tencent/feedback/upload/e:a	(I[BLjava/lang/Object;)V
    //   860: ldc_w 396
    //   863: invokestatic 62	com/tencent/feedback/common/ELog:debug	(Ljava/lang/String;)V
    //   866: aload_2
    //   867: ifnull +22 -> 889
    //   870: aload_1
    //   871: ifnonnull +100 -> 971
    //   874: aconst_null
    //   875: astore 22
    //   877: aload_2
    //   878: aload 22
    //   880: aload 6
    //   882: ldc 230
    //   884: invokeinterface 165 4 0
    //   889: ldc 167
    //   891: invokestatic 62	com/tencent/feedback/common/ELog:debug	(Ljava/lang/String;)V
    //   894: goto -844 -> 50
    //   897: getstatic 185	com/tencent/feedback/upload/OnUploadFinshed$UploadResult:UploadFail	Lcom/tencent/feedback/upload/OnUploadFinshed$UploadResult;
    //   900: astore 6
    //   902: goto -281 -> 621
    //   905: iconst_0
    //   906: istore 23
    //   908: goto -230 -> 678
    //   911: astore 28
    //   913: ldc_w 398
    //   916: invokestatic 151	com/tencent/feedback/common/ELog:error	(Ljava/lang/String;)V
    //   919: aload 28
    //   921: invokevirtual 401	java/lang/Throwable:printStackTrace	()V
    //   924: goto -64 -> 860
    //   927: astore 5
    //   929: aload 5
    //   931: invokevirtual 401	java/lang/Throwable:printStackTrace	()V
    //   934: getstatic 157	com/tencent/feedback/upload/OnUploadFinshed$UploadResult:UploadError	Lcom/tencent/feedback/upload/OnUploadFinshed$UploadResult;
    //   937: astore 10
    //   939: aload_2
    //   940: ifnull +23 -> 963
    //   943: aload_1
    //   944: ifnonnull +36 -> 980
    //   947: aconst_null
    //   948: astore 11
    //   950: aload_2
    //   951: aload 11
    //   953: aload 10
    //   955: ldc_w 403
    //   958: invokeinterface 165 4 0
    //   963: ldc 167
    //   965: invokestatic 62	com/tencent/feedback/common/ELog:debug	(Ljava/lang/String;)V
    //   968: goto -918 -> 50
    //   971: aload_1
    //   972: invokevirtual 173	com/tencent/feedback/upload/AbstractUploadDatas:getmUploadDataType	()Lcom/tencent/feedback/upload/AbstractUploadDatas$UploadDataType;
    //   975: astore 22
    //   977: goto -100 -> 877
    //   980: aload_1
    //   981: invokevirtual 173	com/tencent/feedback/upload/AbstractUploadDatas:getmUploadDataType	()Lcom/tencent/feedback/upload/AbstractUploadDatas$UploadDataType;
    //   984: astore 11
    //   986: goto -36 -> 950
    //   989: astore 12
    //   991: aload 12
    //   993: astore 8
    //   995: aload_2
    //   996: ifnull +22 -> 1018
    //   999: aload_1
    //   1000: ifnonnull +26 -> 1026
    //   1003: aconst_null
    //   1004: astore 9
    //   1006: aload_2
    //   1007: aload 9
    //   1009: aload 4
    //   1011: ldc 230
    //   1013: invokeinterface 165 4 0
    //   1018: ldc 167
    //   1020: invokestatic 62	com/tencent/feedback/common/ELog:debug	(Ljava/lang/String;)V
    //   1023: aload 8
    //   1025: athrow
    //   1026: aload_1
    //   1027: invokevirtual 173	com/tencent/feedback/upload/AbstractUploadDatas:getmUploadDataType	()Lcom/tencent/feedback/upload/AbstractUploadDatas$UploadDataType;
    //   1030: astore 9
    //   1032: goto -26 -> 1006
    //   1035: astore 7
    //   1037: aload 6
    //   1039: astore 4
    //   1041: aload 7
    //   1043: astore 8
    //   1045: goto -50 -> 995
    //   1048: astore 5
    //   1050: aconst_null
    //   1051: astore 6
    //   1053: goto -124 -> 929
    //   1056: aconst_null
    //   1057: astore 17
    //   1059: goto -813 -> 246
    //   1062: aload 36
    //   1064: astore 19
    //   1066: goto -543 -> 523
    //
    // Exception table:
    //   from	to	target	type
    //   848	860	911	java/lang/Throwable
    //   282	307	927	java/lang/Throwable
    //   621	843	927	java/lang/Throwable
    //   860	866	927	java/lang/Throwable
    //   913	924	927	java/lang/Throwable
    //   12	22	989	finally
    //   60	82	989	finally
    //   122	282	989	finally
    //   338	368	989	finally
    //   384	539	989	finally
    //   580	621	989	finally
    //   897	902	989	finally
    //   282	307	1035	finally
    //   621	843	1035	finally
    //   848	860	1035	finally
    //   860	866	1035	finally
    //   913	924	1035	finally
    //   929	939	1035	finally
    //   12	22	1048	java/lang/Throwable
    //   60	82	1048	java/lang/Throwable
    //   122	282	1048	java/lang/Throwable
    //   338	368	1048	java/lang/Throwable
    //   384	539	1048	java/lang/Throwable
    //   580	621	1048	java/lang/Throwable
    //   897	902	1048	java/lang/Throwable
  }

  public static abstract interface a
  {
    public abstract void a(String paramString, long paramLong1, long paramLong2, long paramLong3);
  }

  public static abstract interface b
  {
    public abstract void a(int paramInt, byte[] paramArrayOfByte);
  }
}

/* Location:           C:\Users\sandrocheng.21KUNPENG\Desktop\classes_dex2jar.jar
 * Qualified Name:     com.tencent.feedback.upload.e
 * JD-Core Version:    0.6.2
 */