import java.util.List;

final class tw extends Thread
{
  tw(sy paramsy, List paramList, dv paramdv)
  {
  }

  // ERROR //
  public final void run()
  {
    // Byte code:
    //   0: bipush 10
    //   2: invokestatic 32	android/os/Process:setThreadPriority	(I)V
    //   5: iconst_0
    //   6: istore_1
    //   7: iconst_0
    //   8: istore_2
    //   9: iconst_0
    //   10: istore_3
    //   11: new 34	java/util/ArrayList
    //   14: dup
    //   15: invokespecial 35	java/util/ArrayList:<init>	()V
    //   18: astore 4
    //   20: new 34	java/util/ArrayList
    //   23: dup
    //   24: invokespecial 35	java/util/ArrayList:<init>	()V
    //   27: astore 5
    //   29: new 34	java/util/ArrayList
    //   32: dup
    //   33: invokespecial 35	java/util/ArrayList:<init>	()V
    //   36: astore 6
    //   38: aload 6
    //   40: iconst_1
    //   41: invokestatic 41	java/lang/Integer:valueOf	(I)Ljava/lang/Integer;
    //   44: invokevirtual 45	java/util/ArrayList:add	(Ljava/lang/Object;)Z
    //   47: pop
    //   48: aload_0
    //   49: getfield 14	tw:c	Lsy;
    //   52: getfield 50	sy:b	Z
    //   55: ifeq +13 -> 68
    //   58: aload 6
    //   60: iconst_2
    //   61: invokestatic 41	java/lang/Integer:valueOf	(I)Ljava/lang/Integer;
    //   64: invokevirtual 45	java/util/ArrayList:add	(Ljava/lang/Object;)Z
    //   67: pop
    //   68: aload_0
    //   69: getfield 14	tw:c	Lsy;
    //   72: ldc2_w 51
    //   75: invokestatic 58	java/lang/Math:random	()D
    //   78: dmul
    //   79: d2i
    //   80: putfield 62	sy:k	I
    //   83: aload_0
    //   84: getfield 16	tw:a	Ljava/util/List;
    //   87: invokeinterface 68 1 0
    //   92: astore 17
    //   94: aload 17
    //   96: invokeinterface 74 1 0
    //   101: ifeq +239 -> 340
    //   104: aload 17
    //   106: invokeinterface 78 1 0
    //   111: checkcast 80	java/lang/String
    //   114: astore 95
    //   116: aload 4
    //   118: aload_0
    //   119: getfield 14	tw:c	Lsy;
    //   122: getfield 84	sy:e	Lki;
    //   125: aload 95
    //   127: aload 6
    //   129: invokevirtual 89	ki:a	(Ljava/lang/String;Ljava/util/List;)Ljava/util/List;
    //   132: invokeinterface 93 2 0
    //   137: pop
    //   138: aload 5
    //   140: aload_0
    //   141: getfield 14	tw:c	Lsy;
    //   144: getfield 84	sy:e	Lki;
    //   147: aload 95
    //   149: invokevirtual 96	ki:c	(Ljava/lang/String;)Ljava/util/List;
    //   152: invokeinterface 93 2 0
    //   157: pop
    //   158: goto -64 -> 94
    //   161: astore 8
    //   163: iconst_0
    //   164: istore 9
    //   166: iconst_0
    //   167: istore 10
    //   169: iload_3
    //   170: ifeq +15 -> 185
    //   173: aload_0
    //   174: getfield 14	tw:c	Lsy;
    //   177: getfield 100	sy:l	Landroid/os/Handler;
    //   180: iconst_2
    //   181: invokevirtual 106	android/os/Handler:sendEmptyMessage	(I)Z
    //   184: pop
    //   185: aload 8
    //   187: invokevirtual 109	java/lang/Exception:printStackTrace	()V
    //   190: iconst_1
    //   191: istore 11
    //   193: iload 10
    //   195: istore_1
    //   196: iload 9
    //   198: istore 12
    //   200: iload 12
    //   202: iload_1
    //   203: iadd
    //   204: ifne +1439 -> 1643
    //   207: aload_0
    //   208: getfield 14	tw:c	Lsy;
    //   211: getfield 112	sy:a	Landroid/content/Context;
    //   214: ldc 113
    //   216: invokevirtual 119	android/content/Context:getString	(I)Ljava/lang/String;
    //   219: astore 13
    //   221: aload_0
    //   222: getfield 14	tw:c	Lsy;
    //   225: getfield 112	sy:a	Landroid/content/Context;
    //   228: astore 14
    //   230: iload 11
    //   232: ifeq +10 -> 242
    //   235: iload 12
    //   237: iload_1
    //   238: iadd
    //   239: ifle +1421 -> 1660
    //   242: new 121	java/lang/StringBuilder
    //   245: dup
    //   246: invokespecial 122	java/lang/StringBuilder:<init>	()V
    //   249: aload 13
    //   251: invokevirtual 126	java/lang/StringBuilder:append	(Ljava/lang/String;)Ljava/lang/StringBuilder;
    //   254: iload 12
    //   256: invokevirtual 129	java/lang/StringBuilder:append	(I)Ljava/lang/StringBuilder;
    //   259: aload_0
    //   260: getfield 14	tw:c	Lsy;
    //   263: getfield 112	sy:a	Landroid/content/Context;
    //   266: ldc 130
    //   268: invokevirtual 119	android/content/Context:getString	(I)Ljava/lang/String;
    //   271: invokevirtual 126	java/lang/StringBuilder:append	(Ljava/lang/String;)Ljava/lang/StringBuilder;
    //   274: ldc 132
    //   276: invokevirtual 126	java/lang/StringBuilder:append	(Ljava/lang/String;)Ljava/lang/StringBuilder;
    //   279: iload_1
    //   280: invokevirtual 129	java/lang/StringBuilder:append	(I)Ljava/lang/StringBuilder;
    //   283: aload_0
    //   284: getfield 14	tw:c	Lsy;
    //   287: getfield 112	sy:a	Landroid/content/Context;
    //   290: ldc 133
    //   292: invokevirtual 119	android/content/Context:getString	(I)Ljava/lang/String;
    //   295: invokevirtual 126	java/lang/StringBuilder:append	(Ljava/lang/String;)Ljava/lang/StringBuilder;
    //   298: invokevirtual 137	java/lang/StringBuilder:toString	()Ljava/lang/String;
    //   301: astore 15
    //   303: aload 14
    //   305: aload 15
    //   307: invokestatic 142	ha:a	(Landroid/content/Context;Ljava/lang/String;)V
    //   310: iload 11
    //   312: ifeq +10 -> 322
    //   315: iload 12
    //   317: iload_1
    //   318: iadd
    //   319: ifle +20 -> 339
    //   322: aload_0
    //   323: getfield 18	tw:b	Ldv;
    //   326: ifnull +13 -> 339
    //   329: aload_0
    //   330: getfield 18	tw:b	Ldv;
    //   333: aconst_null
    //   334: invokeinterface 147 2 0
    //   339: return
    //   340: new 121	java/lang/StringBuilder
    //   343: dup
    //   344: ldc 149
    //   346: invokespecial 152	java/lang/StringBuilder:<init>	(Ljava/lang/String;)V
    //   349: aload 4
    //   351: invokeinterface 156 1 0
    //   356: invokevirtual 129	java/lang/StringBuilder:append	(I)Ljava/lang/StringBuilder;
    //   359: invokevirtual 137	java/lang/StringBuilder:toString	()Ljava/lang/String;
    //   362: pop
    //   363: aload 4
    //   365: invokeinterface 156 1 0
    //   370: istore 19
    //   372: iload 19
    //   374: ifle +1353 -> 1727
    //   377: iconst_1
    //   378: istore 20
    //   380: iload 20
    //   382: ifeq +719 -> 1101
    //   385: aload_0
    //   386: getfield 14	tw:c	Lsy;
    //   389: iconst_0
    //   390: putfield 159	sy:i	Z
    //   393: aload_0
    //   394: getfield 14	tw:c	Lsy;
    //   397: getfield 162	sy:j	Z
    //   400: istore 51
    //   402: iconst_0
    //   403: istore_1
    //   404: iload 51
    //   406: iconst_1
    //   407: if_icmpne +17 -> 424
    //   410: aload_0
    //   411: getfield 14	tw:c	Lsy;
    //   414: iconst_0
    //   415: putfield 162	sy:j	Z
    //   418: ldc2_w 163
    //   421: invokestatic 168	java/lang/Thread:sleep	(J)V
    //   424: aload_0
    //   425: getfield 14	tw:c	Lsy;
    //   428: iconst_1
    //   429: putfield 162	sy:j	Z
    //   432: aload_0
    //   433: getfield 14	tw:c	Lsy;
    //   436: getfield 100	sy:l	Landroid/os/Handler;
    //   439: iconst_0
    //   440: invokevirtual 106	android/os/Handler:sendEmptyMessage	(I)Z
    //   443: pop
    //   444: invokestatic 174	java/lang/System:currentTimeMillis	()J
    //   447: lstore 53
    //   449: aload 5
    //   451: invokeinterface 156 1 0
    //   456: istore 55
    //   458: iconst_0
    //   459: istore_1
    //   460: iload 55
    //   462: ifle +252 -> 714
    //   465: aload 5
    //   467: invokeinterface 68 1 0
    //   472: astore 79
    //   474: aconst_null
    //   475: astore 80
    //   477: aconst_null
    //   478: astore 81
    //   480: aload 79
    //   482: invokeinterface 74 1 0
    //   487: istore 82
    //   489: iconst_0
    //   490: istore_1
    //   491: iload 82
    //   493: ifeq +107 -> 600
    //   496: aload 79
    //   498: invokeinterface 78 1 0
    //   503: checkcast 176	ky
    //   506: astore 91
    //   508: iconst_0
    //   509: istore_1
    //   510: aload 80
    //   512: ifnull +22 -> 534
    //   515: aload 80
    //   517: aload 91
    //   519: getfield 180	ky:phonenum	Ljava/lang/String;
    //   522: invokevirtual 183	java/lang/String:equals	(Ljava/lang/Object;)Z
    //   525: istore 93
    //   527: iconst_0
    //   528: istore_1
    //   529: iload 93
    //   531: ifne +22 -> 553
    //   534: aload 91
    //   536: aload 91
    //   538: getfield 186	ky:d	Z
    //   541: invokestatic 191	oo$a:a	(Lcom/tencent/tmsecure/module/aresengine/TelephonyEntity;Z)Ljava/lang/String;
    //   544: astore 81
    //   546: aload 91
    //   548: getfield 180	ky:phonenum	Ljava/lang/String;
    //   551: astore 80
    //   553: iconst_0
    //   554: istore_1
    //   555: aload 81
    //   557: ifnull -77 -> 480
    //   560: ldc 193
    //   562: aload 81
    //   564: invokevirtual 183	java/lang/String:equals	(Ljava/lang/Object;)Z
    //   567: istore 92
    //   569: iconst_0
    //   570: istore_1
    //   571: iload 92
    //   573: ifne -93 -> 480
    //   576: aload 91
    //   578: aload 81
    //   580: putfield 196	ky:name	Ljava/lang/String;
    //   583: iconst_0
    //   584: istore_1
    //   585: goto -105 -> 480
    //   588: astore 94
    //   590: aload 94
    //   592: invokevirtual 197	java/lang/InterruptedException:printStackTrace	()V
    //   595: iconst_0
    //   596: istore_1
    //   597: goto -173 -> 424
    //   600: aload_0
    //   601: getfield 14	tw:c	Lsy;
    //   604: getfield 200	sy:c	Lhi;
    //   607: aload 5
    //   609: invokevirtual 205	hi:b	(Ljava/util/List;)Z
    //   612: pop
    //   613: aconst_null
    //   614: astore 84
    //   616: aload 5
    //   618: invokeinterface 68 1 0
    //   623: astore 85
    //   625: aload 85
    //   627: invokeinterface 74 1 0
    //   632: istore 86
    //   634: iconst_0
    //   635: istore_1
    //   636: iload 86
    //   638: ifeq +66 -> 704
    //   641: aload 85
    //   643: invokeinterface 78 1 0
    //   648: checkcast 176	ky
    //   651: astore 87
    //   653: iconst_0
    //   654: istore_1
    //   655: aload 84
    //   657: ifnull +22 -> 679
    //   660: aload 84
    //   662: aload 87
    //   664: getfield 180	ky:phonenum	Ljava/lang/String;
    //   667: invokevirtual 183	java/lang/String:equals	(Ljava/lang/Object;)Z
    //   670: istore 90
    //   672: iconst_0
    //   673: istore_1
    //   674: iload 90
    //   676: ifne +1030 -> 1706
    //   679: aload 87
    //   681: getfield 180	ky:phonenum	Ljava/lang/String;
    //   684: astore 88
    //   686: aload_0
    //   687: getfield 14	tw:c	Lsy;
    //   690: getfield 84	sy:e	Lki;
    //   693: aload 88
    //   695: invokevirtual 208	ki:d	(Ljava/lang/String;)Z
    //   698: pop
    //   699: iconst_0
    //   700: istore_1
    //   701: goto +1032 -> 1733
    //   704: iconst_0
    //   705: aload 5
    //   707: invokeinterface 156 1 0
    //   712: iadd
    //   713: istore_1
    //   714: aload_0
    //   715: getfield 14	tw:c	Lsy;
    //   718: iconst_5
    //   719: ldc2_w 209
    //   722: invokestatic 58	java/lang/Math:random	()D
    //   725: dmul
    //   726: d2i
    //   727: iadd
    //   728: putfield 62	sy:k	I
    //   731: aload 4
    //   733: invokeinterface 156 1 0
    //   738: ifle +959 -> 1697
    //   741: new 121	java/lang/StringBuilder
    //   744: dup
    //   745: ldc 212
    //   747: invokespecial 152	java/lang/StringBuilder:<init>	(Ljava/lang/String;)V
    //   750: aload 4
    //   752: invokeinterface 156 1 0
    //   757: invokevirtual 129	java/lang/StringBuilder:append	(I)Ljava/lang/StringBuilder;
    //   760: invokevirtual 137	java/lang/StringBuilder:toString	()Ljava/lang/String;
    //   763: pop
    //   764: aload 4
    //   766: invokeinterface 68 1 0
    //   771: astore 66
    //   773: aconst_null
    //   774: astore 67
    //   776: aconst_null
    //   777: astore 68
    //   779: aload 66
    //   781: invokeinterface 74 1 0
    //   786: ifeq +77 -> 863
    //   789: aload 66
    //   791: invokeinterface 78 1 0
    //   796: checkcast 214	mk
    //   799: astore 78
    //   801: aload 67
    //   803: ifnull +16 -> 819
    //   806: aload 67
    //   808: aload 78
    //   810: invokevirtual 216	mk:a	()Ljava/lang/String;
    //   813: invokevirtual 183	java/lang/String:equals	(Ljava/lang/Object;)Z
    //   816: ifne +22 -> 838
    //   819: aload 78
    //   821: aload 78
    //   823: getfield 219	mk:g	Z
    //   826: invokestatic 191	oo$a:a	(Lcom/tencent/tmsecure/module/aresengine/TelephonyEntity;Z)Ljava/lang/String;
    //   829: astore 68
    //   831: aload 78
    //   833: invokevirtual 216	mk:a	()Ljava/lang/String;
    //   836: astore 67
    //   838: aload 68
    //   840: ifnull -61 -> 779
    //   843: ldc 193
    //   845: aload 68
    //   847: invokevirtual 183	java/lang/String:equals	(Ljava/lang/Object;)Z
    //   850: ifne -71 -> 779
    //   853: aload 78
    //   855: aload 68
    //   857: putfield 220	mk:name	Ljava/lang/String;
    //   860: goto -81 -> 779
    //   863: aload_0
    //   864: getfield 14	tw:c	Lsy;
    //   867: getfield 62	sy:k	I
    //   870: istore 69
    //   872: bipush 100
    //   874: aload_0
    //   875: getfield 14	tw:c	Lsy;
    //   878: getfield 62	sy:k	I
    //   881: isub
    //   882: istore 70
    //   884: aload 4
    //   886: invokeinterface 156 1 0
    //   891: istore 71
    //   893: aload 4
    //   895: invokeinterface 68 1 0
    //   900: astore 72
    //   902: iconst_0
    //   903: istore 57
    //   905: iconst_0
    //   906: istore 73
    //   908: aload 72
    //   910: invokeinterface 74 1 0
    //   915: ifeq +849 -> 1764
    //   918: aload 72
    //   920: invokeinterface 78 1 0
    //   925: checkcast 214	mk
    //   928: astore 74
    //   930: aload_0
    //   931: getfield 14	tw:c	Lsy;
    //   934: getfield 162	sy:j	Z
    //   937: ifeq +827 -> 1764
    //   940: iinc 73 1
    //   943: new 121	java/lang/StringBuilder
    //   946: dup
    //   947: ldc 222
    //   949: invokespecial 152	java/lang/StringBuilder:<init>	(Ljava/lang/String;)V
    //   952: aload 74
    //   954: getfield 225	mk:id	I
    //   957: invokevirtual 129	java/lang/StringBuilder:append	(I)Ljava/lang/StringBuilder;
    //   960: invokevirtual 137	java/lang/StringBuilder:toString	()Ljava/lang/String;
    //   963: pop
    //   964: aload_0
    //   965: getfield 14	tw:c	Lsy;
    //   968: getfield 228	sy:d	Ljp;
    //   971: aload 74
    //   973: iconst_0
    //   974: invokevirtual 233	jp:a	(Lmk;Z)J
    //   977: lconst_0
    //   978: lcmp
    //   979: ifle +780 -> 1759
    //   982: new 121	java/lang/StringBuilder
    //   985: dup
    //   986: ldc 235
    //   988: invokespecial 152	java/lang/StringBuilder:<init>	(Ljava/lang/String;)V
    //   991: aload 74
    //   993: getfield 225	mk:id	I
    //   996: invokevirtual 129	java/lang/StringBuilder:append	(I)Ljava/lang/StringBuilder;
    //   999: invokevirtual 137	java/lang/StringBuilder:toString	()Ljava/lang/String;
    //   1002: pop
    //   1003: aload_0
    //   1004: getfield 14	tw:c	Lsy;
    //   1007: getfield 84	sy:e	Lki;
    //   1010: aload 74
    //   1012: invokevirtual 239	ki:remove	(Lcom/tencent/tmsecure/module/aresengine/SmsEntity;)Z
    //   1015: pop
    //   1016: iinc 57 1
    //   1019: aload_0
    //   1020: getfield 14	tw:c	Lsy;
    //   1023: iload 69
    //   1025: i2f
    //   1026: iload 70
    //   1028: i2f
    //   1029: iload 73
    //   1031: i2f
    //   1032: iload 71
    //   1034: i2f
    //   1035: fdiv
    //   1036: fmul
    //   1037: fadd
    //   1038: f2i
    //   1039: putfield 62	sy:k	I
    //   1042: goto -134 -> 908
    //   1045: invokestatic 174	java/lang/System:currentTimeMillis	()J
    //   1048: lstore 58
    //   1050: lload 58
    //   1052: lload 53
    //   1054: lsub
    //   1055: ldc2_w 240
    //   1058: lcmp
    //   1059: ifge +19 -> 1078
    //   1062: ldc2_w 240
    //   1065: lload 53
    //   1067: ladd
    //   1068: lload 58
    //   1070: lsub
    //   1071: lstore 62
    //   1073: lload 62
    //   1075: invokestatic 168	java/lang/Thread:sleep	(J)V
    //   1078: aload_0
    //   1079: getfield 14	tw:c	Lsy;
    //   1082: getfield 100	sy:l	Landroid/os/Handler;
    //   1085: iconst_2
    //   1086: invokevirtual 106	android/os/Handler:sendEmptyMessage	(I)Z
    //   1089: pop
    //   1090: iload 57
    //   1092: istore 12
    //   1094: iload 56
    //   1096: istore 11
    //   1098: goto -898 -> 200
    //   1101: aload 5
    //   1103: invokeinterface 156 1 0
    //   1108: istore 21
    //   1110: iconst_0
    //   1111: istore_1
    //   1112: iload 21
    //   1114: ifle +240 -> 1354
    //   1117: aload 5
    //   1119: invokeinterface 68 1 0
    //   1124: astore 36
    //   1126: aconst_null
    //   1127: astore 37
    //   1129: aconst_null
    //   1130: astore 38
    //   1132: aload 36
    //   1134: invokeinterface 74 1 0
    //   1139: istore 39
    //   1141: iconst_0
    //   1142: istore_1
    //   1143: iload 39
    //   1145: ifeq +95 -> 1240
    //   1148: aload 36
    //   1150: invokeinterface 78 1 0
    //   1155: checkcast 176	ky
    //   1158: astore 48
    //   1160: iconst_0
    //   1161: istore_1
    //   1162: aload 37
    //   1164: ifnull +22 -> 1186
    //   1167: aload 37
    //   1169: aload 48
    //   1171: getfield 180	ky:phonenum	Ljava/lang/String;
    //   1174: invokevirtual 183	java/lang/String:equals	(Ljava/lang/Object;)Z
    //   1177: istore 50
    //   1179: iconst_0
    //   1180: istore_1
    //   1181: iload 50
    //   1183: ifne +22 -> 1205
    //   1186: aload 48
    //   1188: aload 48
    //   1190: getfield 186	ky:d	Z
    //   1193: invokestatic 191	oo$a:a	(Lcom/tencent/tmsecure/module/aresengine/TelephonyEntity;Z)Ljava/lang/String;
    //   1196: astore 38
    //   1198: aload 48
    //   1200: getfield 180	ky:phonenum	Ljava/lang/String;
    //   1203: astore 37
    //   1205: iconst_0
    //   1206: istore_1
    //   1207: aload 38
    //   1209: ifnull -77 -> 1132
    //   1212: ldc 193
    //   1214: aload 38
    //   1216: invokevirtual 183	java/lang/String:equals	(Ljava/lang/Object;)Z
    //   1219: istore 49
    //   1221: iconst_0
    //   1222: istore_1
    //   1223: iload 49
    //   1225: ifne -93 -> 1132
    //   1228: aload 48
    //   1230: aload 38
    //   1232: putfield 196	ky:name	Ljava/lang/String;
    //   1235: iconst_0
    //   1236: istore_1
    //   1237: goto -105 -> 1132
    //   1240: aload_0
    //   1241: getfield 14	tw:c	Lsy;
    //   1244: getfield 200	sy:c	Lhi;
    //   1247: aload 5
    //   1249: invokevirtual 205	hi:b	(Ljava/util/List;)Z
    //   1252: pop
    //   1253: aconst_null
    //   1254: astore 41
    //   1256: aload 5
    //   1258: invokeinterface 68 1 0
    //   1263: astore 42
    //   1265: aload 42
    //   1267: invokeinterface 74 1 0
    //   1272: istore 43
    //   1274: iconst_0
    //   1275: istore_1
    //   1276: iload 43
    //   1278: ifeq +66 -> 1344
    //   1281: aload 42
    //   1283: invokeinterface 78 1 0
    //   1288: checkcast 176	ky
    //   1291: astore 44
    //   1293: iconst_0
    //   1294: istore_1
    //   1295: aload 41
    //   1297: ifnull +22 -> 1319
    //   1300: aload 41
    //   1302: aload 44
    //   1304: getfield 180	ky:phonenum	Ljava/lang/String;
    //   1307: invokevirtual 183	java/lang/String:equals	(Ljava/lang/Object;)Z
    //   1310: istore 47
    //   1312: iconst_0
    //   1313: istore_1
    //   1314: iload 47
    //   1316: ifne +374 -> 1690
    //   1319: aload 44
    //   1321: getfield 180	ky:phonenum	Ljava/lang/String;
    //   1324: astore 45
    //   1326: aload_0
    //   1327: getfield 14	tw:c	Lsy;
    //   1330: getfield 84	sy:e	Lki;
    //   1333: aload 45
    //   1335: invokevirtual 208	ki:d	(Ljava/lang/String;)Z
    //   1338: pop
    //   1339: iconst_0
    //   1340: istore_1
    //   1341: goto +429 -> 1770
    //   1344: iconst_0
    //   1345: aload 5
    //   1347: invokeinterface 156 1 0
    //   1352: iadd
    //   1353: istore_1
    //   1354: aload 4
    //   1356: invokeinterface 156 1 0
    //   1361: ifle +273 -> 1634
    //   1364: aload 4
    //   1366: invokeinterface 68 1 0
    //   1371: astore 22
    //   1373: aconst_null
    //   1374: astore 23
    //   1376: aconst_null
    //   1377: astore 24
    //   1379: aload 22
    //   1381: invokeinterface 74 1 0
    //   1386: ifeq +77 -> 1463
    //   1389: aload 22
    //   1391: invokeinterface 78 1 0
    //   1396: checkcast 214	mk
    //   1399: astore 35
    //   1401: aload 23
    //   1403: ifnull +16 -> 1419
    //   1406: aload 23
    //   1408: aload 35
    //   1410: invokevirtual 216	mk:a	()Ljava/lang/String;
    //   1413: invokevirtual 183	java/lang/String:equals	(Ljava/lang/Object;)Z
    //   1416: ifne +22 -> 1438
    //   1419: aload 35
    //   1421: aload 35
    //   1423: getfield 219	mk:g	Z
    //   1426: invokestatic 191	oo$a:a	(Lcom/tencent/tmsecure/module/aresengine/TelephonyEntity;Z)Ljava/lang/String;
    //   1429: astore 24
    //   1431: aload 35
    //   1433: invokevirtual 216	mk:a	()Ljava/lang/String;
    //   1436: astore 23
    //   1438: aload 24
    //   1440: ifnull -61 -> 1379
    //   1443: ldc 193
    //   1445: aload 24
    //   1447: invokevirtual 183	java/lang/String:equals	(Ljava/lang/Object;)Z
    //   1450: ifne -71 -> 1379
    //   1453: aload 35
    //   1455: aload 24
    //   1457: putfield 220	mk:name	Ljava/lang/String;
    //   1460: goto -81 -> 1379
    //   1463: aload_0
    //   1464: getfield 14	tw:c	Lsy;
    //   1467: getfield 228	sy:d	Ljp;
    //   1470: aload 4
    //   1472: invokevirtual 243	jp:a	(Ljava/util/List;)Z
    //   1475: pop
    //   1476: new 121	java/lang/StringBuilder
    //   1479: dup
    //   1480: ldc 245
    //   1482: invokespecial 152	java/lang/StringBuilder:<init>	(Ljava/lang/String;)V
    //   1485: aload 4
    //   1487: invokeinterface 156 1 0
    //   1492: invokevirtual 129	java/lang/StringBuilder:append	(I)Ljava/lang/StringBuilder;
    //   1495: invokevirtual 137	java/lang/StringBuilder:toString	()Ljava/lang/String;
    //   1498: pop
    //   1499: iconst_m1
    //   1500: istore 27
    //   1502: aload 4
    //   1504: invokeinterface 68 1 0
    //   1509: astore 28
    //   1511: aload 28
    //   1513: invokeinterface 74 1 0
    //   1518: ifeq +95 -> 1613
    //   1521: aload 28
    //   1523: invokeinterface 78 1 0
    //   1528: checkcast 214	mk
    //   1531: astore 30
    //   1533: new 121	java/lang/StringBuilder
    //   1536: dup
    //   1537: ldc 247
    //   1539: invokespecial 152	java/lang/StringBuilder:<init>	(Ljava/lang/String;)V
    //   1542: aload 30
    //   1544: getfield 249	mk:e	I
    //   1547: invokevirtual 129	java/lang/StringBuilder:append	(I)Ljava/lang/StringBuilder;
    //   1550: invokevirtual 137	java/lang/StringBuilder:toString	()Ljava/lang/String;
    //   1553: pop
    //   1554: iload 27
    //   1556: iconst_m1
    //   1557: if_icmpeq +13 -> 1570
    //   1560: iload 27
    //   1562: aload 30
    //   1564: getfield 249	mk:e	I
    //   1567: if_icmpeq +116 -> 1683
    //   1570: aload 30
    //   1572: getfield 249	mk:e	I
    //   1575: istore 32
    //   1577: new 121	java/lang/StringBuilder
    //   1580: dup
    //   1581: ldc 251
    //   1583: invokespecial 152	java/lang/StringBuilder:<init>	(Ljava/lang/String;)V
    //   1586: iload 32
    //   1588: invokevirtual 129	java/lang/StringBuilder:append	(I)Ljava/lang/StringBuilder;
    //   1591: invokevirtual 137	java/lang/StringBuilder:toString	()Ljava/lang/String;
    //   1594: pop
    //   1595: aload_0
    //   1596: getfield 14	tw:c	Lsy;
    //   1599: getfield 84	sy:e	Lki;
    //   1602: iload 32
    //   1604: aload 6
    //   1606: invokevirtual 254	ki:a	(ILjava/util/List;)Z
    //   1609: pop
    //   1610: goto +167 -> 1777
    //   1613: aload 4
    //   1615: invokeinterface 156 1 0
    //   1620: istore 29
    //   1622: iload 29
    //   1624: iconst_0
    //   1625: iadd
    //   1626: istore 12
    //   1628: iconst_0
    //   1629: istore 11
    //   1631: goto -1431 -> 200
    //   1634: iconst_0
    //   1635: istore 11
    //   1637: iconst_0
    //   1638: istore 12
    //   1640: goto -1440 -> 200
    //   1643: aload_0
    //   1644: getfield 14	tw:c	Lsy;
    //   1647: getfield 112	sy:a	Landroid/content/Context;
    //   1650: ldc 255
    //   1652: invokevirtual 119	android/content/Context:getString	(I)Ljava/lang/String;
    //   1655: astore 13
    //   1657: goto -1436 -> 221
    //   1660: aload_0
    //   1661: getfield 14	tw:c	Lsy;
    //   1664: getfield 112	sy:a	Landroid/content/Context;
    //   1667: ldc_w 256
    //   1670: invokevirtual 119	android/content/Context:getString	(I)Ljava/lang/String;
    //   1673: astore 15
    //   1675: goto -1372 -> 303
    //   1678: astore 64
    //   1680: goto -602 -> 1078
    //   1683: iload 27
    //   1685: istore 32
    //   1687: goto +90 -> 1777
    //   1690: aload 41
    //   1692: astore 45
    //   1694: goto +76 -> 1770
    //   1697: iconst_0
    //   1698: istore 56
    //   1700: iconst_0
    //   1701: istore 57
    //   1703: goto -658 -> 1045
    //   1706: aload 84
    //   1708: astore 88
    //   1710: goto +23 -> 1733
    //   1713: astore 8
    //   1715: iload 20
    //   1717: istore_3
    //   1718: iload_1
    //   1719: istore 10
    //   1721: iconst_0
    //   1722: istore 9
    //   1724: goto -1555 -> 169
    //   1727: iconst_0
    //   1728: istore 20
    //   1730: goto -1350 -> 380
    //   1733: aload 88
    //   1735: astore 84
    //   1737: goto -1112 -> 625
    //   1740: astore 8
    //   1742: iload_1
    //   1743: istore 10
    //   1745: iload 57
    //   1747: istore 61
    //   1749: iload 20
    //   1751: istore_3
    //   1752: iload 61
    //   1754: istore 9
    //   1756: goto -1587 -> 169
    //   1759: iconst_1
    //   1760: istore_2
    //   1761: goto -853 -> 908
    //   1764: iload_2
    //   1765: istore 56
    //   1767: goto -722 -> 1045
    //   1770: aload 45
    //   1772: astore 41
    //   1774: goto -509 -> 1265
    //   1777: iload 32
    //   1779: istore 27
    //   1781: goto -270 -> 1511
    //
    // Exception table:
    //   from	to	target	type
    //   68	158	161	java/lang/Exception
    //   340	372	161	java/lang/Exception
    //   418	424	588	java/lang/InterruptedException
    //   1073	1078	1678	java/lang/Exception
    //   385	418	1713	java/lang/Exception
    //   418	424	1713	java/lang/Exception
    //   424	902	1713	java/lang/Exception
    //   1101	1622	1713	java/lang/Exception
    //   908	1050	1740	java/lang/Exception
    //   1078	1090	1740	java/lang/Exception
  }
}

/* Location:           C:\Users\sandrocheng.21KUNPENG\Desktop\classes_dex2jar.jar
 * Qualified Name:     tw
 * JD-Core Version:    0.6.2
 */