final class wj
  implements Runnable
{
  wj(wh paramwh)
  {
  }

  // ERROR //
  public final void run()
  {
    // Byte code:
    //   0: aload_0
    //   1: getfield 12	wj:a	Lwh;
    //   4: getfield 22	wh:e	Ljava/util/HashMap;
    //   7: astore_1
    //   8: aload_1
    //   9: monitorenter
    //   10: aload_0
    //   11: getfield 12	wj:a	Lwh;
    //   14: getfield 25	wh:d	Ljava/util/HashMap;
    //   17: astore_3
    //   18: aload_3
    //   19: monitorenter
    //   20: aload_0
    //   21: getfield 12	wj:a	Lwh;
    //   24: getfield 25	wh:d	Ljava/util/HashMap;
    //   27: invokevirtual 30	java/util/HashMap:clear	()V
    //   30: aload_3
    //   31: monitorexit
    //   32: aload_0
    //   33: getfield 12	wj:a	Lwh;
    //   36: getfield 22	wh:e	Ljava/util/HashMap;
    //   39: ifnull +13 -> 52
    //   42: aload_0
    //   43: getfield 12	wj:a	Lwh;
    //   46: getfield 22	wh:e	Ljava/util/HashMap;
    //   49: invokevirtual 30	java/util/HashMap:clear	()V
    //   52: new 32	java/util/ArrayList
    //   55: dup
    //   56: invokespecial 33	java/util/ArrayList:<init>	()V
    //   59: pop
    //   60: aload_0
    //   61: getfield 12	wj:a	Lwh;
    //   64: getfield 37	wh:b	Landroid/content/Context;
    //   67: ldc 39
    //   69: ldc 41
    //   71: invokestatic 46	fj:a	(Landroid/content/Context;Ljava/lang/String;Ljava/lang/String;)Ljava/lang/Object;
    //   74: checkcast 48	java/util/List
    //   77: astore 6
    //   79: aload 6
    //   81: ifnull +222 -> 303
    //   84: aload 6
    //   86: invokeinterface 52 1 0
    //   91: ifne +212 -> 303
    //   94: iconst_0
    //   95: istore 11
    //   97: iload 11
    //   99: aload 6
    //   101: invokeinterface 56 1 0
    //   106: if_icmpge +197 -> 303
    //   109: aload 6
    //   111: iload 11
    //   113: invokeinterface 60 2 0
    //   118: checkcast 62	QQPIM/STNetLocal
    //   121: astore 12
    //   123: aload 12
    //   125: getfield 66	QQPIM/STNetLocal:nNetType	I
    //   128: istore 13
    //   130: aload_0
    //   131: getfield 12	wj:a	Lwh;
    //   134: pop
    //   135: iload 13
    //   137: getstatic 71	fl:a	Lfl;
    //   140: invokestatic 74	wh:a	(Lfl;)I
    //   143: if_icmpne +34 -> 177
    //   146: aload_0
    //   147: getfield 12	wj:a	Lwh;
    //   150: getfield 22	wh:e	Ljava/util/HashMap;
    //   153: getstatic 71	fl:a	Lfl;
    //   156: aload 12
    //   158: invokevirtual 78	java/util/HashMap:put	(Ljava/lang/Object;Ljava/lang/Object;)Ljava/lang/Object;
    //   161: pop
    //   162: goto +246 -> 408
    //   165: astore 4
    //   167: aload_3
    //   168: monitorexit
    //   169: aload 4
    //   171: athrow
    //   172: astore_2
    //   173: aload_1
    //   174: monitorexit
    //   175: aload_2
    //   176: athrow
    //   177: aload 12
    //   179: getfield 66	QQPIM/STNetLocal:nNetType	I
    //   182: istore 15
    //   184: aload_0
    //   185: getfield 12	wj:a	Lwh;
    //   188: pop
    //   189: iload 15
    //   191: getstatic 81	fl:c	Lfl;
    //   194: invokestatic 74	wh:a	(Lfl;)I
    //   197: if_icmpne +22 -> 219
    //   200: aload_0
    //   201: getfield 12	wj:a	Lwh;
    //   204: getfield 22	wh:e	Ljava/util/HashMap;
    //   207: getstatic 81	fl:c	Lfl;
    //   210: aload 12
    //   212: invokevirtual 78	java/util/HashMap:put	(Ljava/lang/Object;Ljava/lang/Object;)Ljava/lang/Object;
    //   215: pop
    //   216: goto +192 -> 408
    //   219: aload 12
    //   221: getfield 66	QQPIM/STNetLocal:nNetType	I
    //   224: istore 17
    //   226: aload_0
    //   227: getfield 12	wj:a	Lwh;
    //   230: pop
    //   231: iload 17
    //   233: getstatic 83	fl:b	Lfl;
    //   236: invokestatic 74	wh:a	(Lfl;)I
    //   239: if_icmpne +22 -> 261
    //   242: aload_0
    //   243: getfield 12	wj:a	Lwh;
    //   246: getfield 22	wh:e	Ljava/util/HashMap;
    //   249: getstatic 83	fl:b	Lfl;
    //   252: aload 12
    //   254: invokevirtual 78	java/util/HashMap:put	(Ljava/lang/Object;Ljava/lang/Object;)Ljava/lang/Object;
    //   257: pop
    //   258: goto +150 -> 408
    //   261: aload 12
    //   263: getfield 66	QQPIM/STNetLocal:nNetType	I
    //   266: istore 19
    //   268: aload_0
    //   269: getfield 12	wj:a	Lwh;
    //   272: pop
    //   273: iload 19
    //   275: getstatic 85	fl:d	Lfl;
    //   278: invokestatic 74	wh:a	(Lfl;)I
    //   281: if_icmpne +127 -> 408
    //   284: aload_0
    //   285: getfield 12	wj:a	Lwh;
    //   288: getfield 22	wh:e	Ljava/util/HashMap;
    //   291: getstatic 85	fl:d	Lfl;
    //   294: aload 12
    //   296: invokevirtual 78	java/util/HashMap:put	(Ljava/lang/Object;Ljava/lang/Object;)Ljava/lang/Object;
    //   299: pop
    //   300: goto +108 -> 408
    //   303: aload_1
    //   304: monitorexit
    //   305: aload_0
    //   306: getfield 12	wj:a	Lwh;
    //   309: invokestatic 88	wh:a	(Lwh;)Z
    //   312: ifne +95 -> 407
    //   315: aload_0
    //   316: getfield 12	wj:a	Lwh;
    //   319: getfield 91	wh:c	Liy;
    //   322: getfield 96	iy:b	Landroid/content/SharedPreferences$Editor;
    //   325: ldc 98
    //   327: iconst_1
    //   328: invokeinterface 104 3 0
    //   333: invokeinterface 107 1 0
    //   338: pop
    //   339: aload_0
    //   340: getfield 12	wj:a	Lwh;
    //   343: astore 8
    //   345: aload 8
    //   347: getfield 111	wh:g	Landroid/content/BroadcastReceiver;
    //   350: ifnonnull +17 -> 367
    //   353: aload 8
    //   355: new 113	wk
    //   358: dup
    //   359: aload 8
    //   361: invokespecial 115	wk:<init>	(Lwh;)V
    //   364: putfield 111	wh:g	Landroid/content/BroadcastReceiver;
    //   367: aload 8
    //   369: aconst_null
    //   370: putfield 118	wh:f	Lfl;
    //   373: new 120	android/content/IntentFilter
    //   376: dup
    //   377: ldc 122
    //   379: invokespecial 125	android/content/IntentFilter:<init>	(Ljava/lang/String;)V
    //   382: astore 9
    //   384: aload 9
    //   386: ldc 127
    //   388: invokevirtual 130	android/content/IntentFilter:addAction	(Ljava/lang/String;)V
    //   391: aload 8
    //   393: getfield 37	wh:b	Landroid/content/Context;
    //   396: aload 8
    //   398: getfield 111	wh:g	Landroid/content/BroadcastReceiver;
    //   401: aload 9
    //   403: invokevirtual 136	android/content/Context:registerReceiver	(Landroid/content/BroadcastReceiver;Landroid/content/IntentFilter;)Landroid/content/Intent;
    //   406: pop
    //   407: return
    //   408: iinc 11 1
    //   411: goto -314 -> 97
    //
    // Exception table:
    //   from	to	target	type
    //   20	32	165	finally
    //   10	20	172	finally
    //   32	172	172	finally
    //   177	305	172	finally
  }
}

/* Location:           C:\Users\sandrocheng.21KUNPENG\Desktop\classes_dex2jar.jar
 * Qualified Name:     wj
 * JD-Core Version:    0.6.2
 */