final class ww
  implements Runnable
{
  ww(wr paramwr)
  {
  }

  // ERROR //
  public final void run()
  {
    // Byte code:
    //   0: iconst_0
    //   1: istore_1
    //   2: aload_0
    //   3: getfield 12	ww:a	Lwr;
    //   6: invokestatic 24	wr:h	(Lwr;)I
    //   9: ifeq +11 -> 20
    //   12: ldc 26
    //   14: ldc 28
    //   16: invokestatic 33	ff:a	(Ljava/lang/String;Ljava/lang/Object;)V
    //   19: return
    //   20: ldc 26
    //   22: ldc 35
    //   24: invokestatic 33	ff:a	(Ljava/lang/String;Ljava/lang/Object;)V
    //   27: aload_0
    //   28: getfield 12	ww:a	Lwr;
    //   31: invokestatic 39	wr:b	(Lwr;)Ljd;
    //   34: invokevirtual 45	jd:g	()Z
    //   37: istore 5
    //   39: iload 5
    //   41: ifeq +141 -> 182
    //   44: iconst_1
    //   45: istore_3
    //   46: aload_0
    //   47: getfield 12	ww:a	Lwr;
    //   50: invokestatic 48	wr:o	(Lwr;)I
    //   53: pop
    //   54: ldc 26
    //   56: ldc 50
    //   58: invokestatic 33	ff:a	(Ljava/lang/String;Ljava/lang/Object;)V
    //   61: aload_0
    //   62: getfield 12	ww:a	Lwr;
    //   65: invokestatic 54	wr:p	(Lwr;)Z
    //   68: istore_1
    //   69: ldc 26
    //   71: ldc 56
    //   73: invokestatic 33	ff:a	(Ljava/lang/String;Ljava/lang/Object;)V
    //   76: aload_0
    //   77: getfield 12	ww:a	Lwr;
    //   80: invokevirtual 59	wr:i	()Z
    //   83: istore 6
    //   85: iload_3
    //   86: ifne +12 -> 98
    //   89: iload_1
    //   90: ifne +8 -> 98
    //   93: iload 6
    //   95: ifeq -76 -> 19
    //   98: aload_0
    //   99: getfield 12	ww:a	Lwr;
    //   102: invokestatic 39	wr:b	(Lwr;)Ljd;
    //   105: invokestatic 65	java/lang/System:currentTimeMillis	()J
    //   108: invokevirtual 68	jd:b	(J)V
    //   111: goto -92 -> 19
    //   114: astore 4
    //   116: iconst_0
    //   117: istore_3
    //   118: aload 4
    //   120: invokevirtual 71	java/lang/Exception:printStackTrace	()V
    //   123: iload_3
    //   124: ifne +7 -> 131
    //   127: iload_1
    //   128: ifeq -109 -> 19
    //   131: aload_0
    //   132: getfield 12	ww:a	Lwr;
    //   135: invokestatic 39	wr:b	(Lwr;)Ljd;
    //   138: invokestatic 65	java/lang/System:currentTimeMillis	()J
    //   141: invokevirtual 68	jd:b	(J)V
    //   144: goto -125 -> 19
    //   147: astore_2
    //   148: iconst_0
    //   149: istore_3
    //   150: iload_3
    //   151: ifne +7 -> 158
    //   154: iload_1
    //   155: ifeq +16 -> 171
    //   158: aload_0
    //   159: getfield 12	ww:a	Lwr;
    //   162: invokestatic 39	wr:b	(Lwr;)Ljd;
    //   165: invokestatic 65	java/lang/System:currentTimeMillis	()J
    //   168: invokevirtual 68	jd:b	(J)V
    //   171: aload_2
    //   172: athrow
    //   173: astore_2
    //   174: goto -24 -> 150
    //   177: astore 4
    //   179: goto -61 -> 118
    //   182: iconst_0
    //   183: istore_3
    //   184: goto -130 -> 54
    //
    // Exception table:
    //   from	to	target	type
    //   20	39	114	java/lang/Exception
    //   20	39	147	finally
    //   46	85	173	finally
    //   118	123	173	finally
    //   46	85	177	java/lang/Exception
  }
}

/* Location:           C:\Users\sandrocheng.21KUNPENG\Desktop\classes_dex2jar.jar
 * Qualified Name:     ww
 * JD-Core Version:    0.6.2
 */