package kdebug;

import java.io.File;

public final class a
{
  // ERROR //
  public static String a(String paramString, java.util.Map paramMap, c[] paramArrayOfc)
  {
    // Byte code:
    //   0: sipush 1024
    //   3: newarray byte
    //   5: astore_3
    //   6: new 16	java/net/URL
    //   9: dup
    //   10: aload_0
    //   11: invokespecial 19	java/net/URL:<init>	(Ljava/lang/String;)V
    //   14: invokevirtual 23	java/net/URL:openConnection	()Ljava/net/URLConnection;
    //   17: checkcast 25	java/net/HttpURLConnection
    //   20: astore 12
    //   22: aload 12
    //   24: sipush 5000
    //   27: invokevirtual 29	java/net/HttpURLConnection:setConnectTimeout	(I)V
    //   30: aload 12
    //   32: sipush 5000
    //   35: invokevirtual 32	java/net/HttpURLConnection:setReadTimeout	(I)V
    //   38: aload 12
    //   40: iconst_1
    //   41: invokevirtual 36	java/net/HttpURLConnection:setDoInput	(Z)V
    //   44: aload 12
    //   46: iconst_1
    //   47: invokevirtual 39	java/net/HttpURLConnection:setDoOutput	(Z)V
    //   50: aload 12
    //   52: iconst_0
    //   53: invokevirtual 42	java/net/HttpURLConnection:setUseCaches	(Z)V
    //   56: aload 12
    //   58: ldc 44
    //   60: invokevirtual 47	java/net/HttpURLConnection:setRequestMethod	(Ljava/lang/String;)V
    //   63: aload 12
    //   65: ldc 49
    //   67: ldc 51
    //   69: invokevirtual 55	java/net/HttpURLConnection:setRequestProperty	(Ljava/lang/String;Ljava/lang/String;)V
    //   72: aload 12
    //   74: ldc 57
    //   76: ldc 59
    //   78: invokevirtual 55	java/net/HttpURLConnection:setRequestProperty	(Ljava/lang/String;Ljava/lang/String;)V
    //   81: aload 12
    //   83: ldc 61
    //   85: new 63	java/lang/StringBuilder
    //   88: dup
    //   89: invokespecial 64	java/lang/StringBuilder:<init>	()V
    //   92: ldc 66
    //   94: invokevirtual 70	java/lang/StringBuilder:append	(Ljava/lang/String;)Ljava/lang/StringBuilder;
    //   97: ldc 72
    //   99: invokevirtual 70	java/lang/StringBuilder:append	(Ljava/lang/String;)Ljava/lang/StringBuilder;
    //   102: ldc 74
    //   104: invokevirtual 70	java/lang/StringBuilder:append	(Ljava/lang/String;)Ljava/lang/StringBuilder;
    //   107: invokevirtual 78	java/lang/StringBuilder:toString	()Ljava/lang/String;
    //   110: invokevirtual 55	java/net/HttpURLConnection:setRequestProperty	(Ljava/lang/String;Ljava/lang/String;)V
    //   113: new 63	java/lang/StringBuilder
    //   116: dup
    //   117: invokespecial 64	java/lang/StringBuilder:<init>	()V
    //   120: astore 13
    //   122: aload_1
    //   123: invokeinterface 84 1 0
    //   128: invokeinterface 90 1 0
    //   133: astore 14
    //   135: aload 14
    //   137: invokeinterface 96 1 0
    //   142: ifeq +158 -> 300
    //   145: aload 14
    //   147: invokeinterface 100 1 0
    //   152: checkcast 102	java/util/Map$Entry
    //   155: astore 48
    //   157: aload 13
    //   159: ldc 104
    //   161: invokevirtual 70	java/lang/StringBuilder:append	(Ljava/lang/String;)Ljava/lang/StringBuilder;
    //   164: pop
    //   165: aload 13
    //   167: ldc 74
    //   169: invokevirtual 70	java/lang/StringBuilder:append	(Ljava/lang/String;)Ljava/lang/StringBuilder;
    //   172: pop
    //   173: aload 13
    //   175: ldc 106
    //   177: invokevirtual 70	java/lang/StringBuilder:append	(Ljava/lang/String;)Ljava/lang/StringBuilder;
    //   180: pop
    //   181: aload 13
    //   183: new 63	java/lang/StringBuilder
    //   186: dup
    //   187: invokespecial 64	java/lang/StringBuilder:<init>	()V
    //   190: ldc 108
    //   192: invokevirtual 70	java/lang/StringBuilder:append	(Ljava/lang/String;)Ljava/lang/StringBuilder;
    //   195: aload 48
    //   197: invokeinterface 111 1 0
    //   202: checkcast 113	java/lang/String
    //   205: invokevirtual 70	java/lang/StringBuilder:append	(Ljava/lang/String;)Ljava/lang/StringBuilder;
    //   208: ldc 115
    //   210: invokevirtual 70	java/lang/StringBuilder:append	(Ljava/lang/String;)Ljava/lang/StringBuilder;
    //   213: invokevirtual 78	java/lang/StringBuilder:toString	()Ljava/lang/String;
    //   216: invokevirtual 70	java/lang/StringBuilder:append	(Ljava/lang/String;)Ljava/lang/StringBuilder;
    //   219: pop
    //   220: aload 13
    //   222: aload 48
    //   224: invokeinterface 118 1 0
    //   229: checkcast 113	java/lang/String
    //   232: invokevirtual 70	java/lang/StringBuilder:append	(Ljava/lang/String;)Ljava/lang/StringBuilder;
    //   235: pop
    //   236: aload 13
    //   238: ldc 106
    //   240: invokevirtual 70	java/lang/StringBuilder:append	(Ljava/lang/String;)Ljava/lang/StringBuilder;
    //   243: pop
    //   244: goto -109 -> 135
    //   247: astore 4
    //   249: aload 12
    //   251: astore 5
    //   253: aconst_null
    //   254: astore 6
    //   256: aconst_null
    //   257: astore 7
    //   259: aload 4
    //   261: invokevirtual 121	java/lang/Exception:printStackTrace	()V
    //   264: aconst_null
    //   265: astore 8
    //   267: aload 7
    //   269: ifnull +8 -> 277
    //   272: aload 7
    //   274: invokevirtual 126	java/io/DataOutputStream:close	()V
    //   277: aload 6
    //   279: ifnull +8 -> 287
    //   282: aload 6
    //   284: invokevirtual 129	java/io/InputStream:close	()V
    //   287: aload 5
    //   289: ifnull +8 -> 297
    //   292: aload 5
    //   294: invokevirtual 132	java/net/HttpURLConnection:disconnect	()V
    //   297: aload 8
    //   299: areturn
    //   300: iconst_0
    //   301: aload 13
    //   303: invokevirtual 78	java/lang/StringBuilder:toString	()Ljava/lang/String;
    //   306: invokevirtual 136	java/lang/String:getBytes	()[B
    //   309: arraylength
    //   310: iadd
    //   311: istore 15
    //   313: new 63	java/lang/StringBuilder
    //   316: dup
    //   317: invokespecial 64	java/lang/StringBuilder:<init>	()V
    //   320: astore 16
    //   322: aload_2
    //   323: arraylength
    //   324: istore 17
    //   326: iload 15
    //   328: istore 18
    //   330: iconst_0
    //   331: istore 19
    //   333: iload 19
    //   335: iload 17
    //   337: if_icmpge +201 -> 538
    //   340: aload_2
    //   341: iload 19
    //   343: aaload
    //   344: astore 39
    //   346: aload 16
    //   348: iconst_0
    //   349: aload 16
    //   351: invokevirtual 140	java/lang/StringBuilder:length	()I
    //   354: invokevirtual 144	java/lang/StringBuilder:delete	(II)Ljava/lang/StringBuilder;
    //   357: pop
    //   358: aload 16
    //   360: ldc 104
    //   362: invokevirtual 70	java/lang/StringBuilder:append	(Ljava/lang/String;)Ljava/lang/StringBuilder;
    //   365: pop
    //   366: aload 16
    //   368: ldc 74
    //   370: invokevirtual 70	java/lang/StringBuilder:append	(Ljava/lang/String;)Ljava/lang/StringBuilder;
    //   373: pop
    //   374: aload 16
    //   376: ldc 106
    //   378: invokevirtual 70	java/lang/StringBuilder:append	(Ljava/lang/String;)Ljava/lang/StringBuilder;
    //   381: pop
    //   382: aload 16
    //   384: new 63	java/lang/StringBuilder
    //   387: dup
    //   388: invokespecial 64	java/lang/StringBuilder:<init>	()V
    //   391: ldc 146
    //   393: invokevirtual 70	java/lang/StringBuilder:append	(Ljava/lang/String;)Ljava/lang/StringBuilder;
    //   396: aload 39
    //   398: invokevirtual 151	kdebug/c:d	()Ljava/lang/String;
    //   401: invokevirtual 70	java/lang/StringBuilder:append	(Ljava/lang/String;)Ljava/lang/StringBuilder;
    //   404: ldc 153
    //   406: invokevirtual 70	java/lang/StringBuilder:append	(Ljava/lang/String;)Ljava/lang/StringBuilder;
    //   409: aload 39
    //   411: invokevirtual 156	kdebug/c:c	()Ljava/lang/String;
    //   414: invokevirtual 70	java/lang/StringBuilder:append	(Ljava/lang/String;)Ljava/lang/StringBuilder;
    //   417: ldc 158
    //   419: invokevirtual 70	java/lang/StringBuilder:append	(Ljava/lang/String;)Ljava/lang/StringBuilder;
    //   422: invokevirtual 78	java/lang/StringBuilder:toString	()Ljava/lang/String;
    //   425: invokevirtual 70	java/lang/StringBuilder:append	(Ljava/lang/String;)Ljava/lang/StringBuilder;
    //   428: pop
    //   429: aload 16
    //   431: new 63	java/lang/StringBuilder
    //   434: dup
    //   435: invokespecial 64	java/lang/StringBuilder:<init>	()V
    //   438: ldc 160
    //   440: invokevirtual 70	java/lang/StringBuilder:append	(Ljava/lang/String;)Ljava/lang/StringBuilder;
    //   443: aload 39
    //   445: invokevirtual 163	kdebug/c:e	()Ljava/lang/String;
    //   448: invokevirtual 70	java/lang/StringBuilder:append	(Ljava/lang/String;)Ljava/lang/StringBuilder;
    //   451: ldc 165
    //   453: invokevirtual 70	java/lang/StringBuilder:append	(Ljava/lang/String;)Ljava/lang/StringBuilder;
    //   456: invokevirtual 78	java/lang/StringBuilder:toString	()Ljava/lang/String;
    //   459: invokevirtual 70	java/lang/StringBuilder:append	(Ljava/lang/String;)Ljava/lang/StringBuilder;
    //   462: pop
    //   463: iload 18
    //   465: aload 16
    //   467: invokevirtual 78	java/lang/StringBuilder:toString	()Ljava/lang/String;
    //   470: invokevirtual 136	java/lang/String:getBytes	()[B
    //   473: arraylength
    //   474: iadd
    //   475: istore 46
    //   477: aload 39
    //   479: invokevirtual 168	kdebug/c:b	()[B
    //   482: ifnull +31 -> 513
    //   485: iload 46
    //   487: aload 39
    //   489: invokevirtual 168	kdebug/c:b	()[B
    //   492: arraylength
    //   493: iadd
    //   494: istore 47
    //   496: iload 47
    //   498: ldc 106
    //   500: invokevirtual 136	java/lang/String:getBytes	()[B
    //   503: arraylength
    //   504: iadd
    //   505: istore 18
    //   507: iinc 19 1
    //   510: goto -177 -> 333
    //   513: iload 46
    //   515: i2l
    //   516: new 170	java/io/File
    //   519: dup
    //   520: aload 39
    //   522: invokevirtual 172	kdebug/c:a	()Ljava/lang/String;
    //   525: invokespecial 173	java/io/File:<init>	(Ljava/lang/String;)V
    //   528: invokevirtual 176	java/io/File:length	()J
    //   531: ladd
    //   532: l2i
    //   533: istore 47
    //   535: goto -39 -> 496
    //   538: new 63	java/lang/StringBuilder
    //   541: dup
    //   542: invokespecial 64	java/lang/StringBuilder:<init>	()V
    //   545: ldc 104
    //   547: invokevirtual 70	java/lang/StringBuilder:append	(Ljava/lang/String;)Ljava/lang/StringBuilder;
    //   550: ldc 74
    //   552: invokevirtual 70	java/lang/StringBuilder:append	(Ljava/lang/String;)Ljava/lang/StringBuilder;
    //   555: ldc 178
    //   557: invokevirtual 70	java/lang/StringBuilder:append	(Ljava/lang/String;)Ljava/lang/StringBuilder;
    //   560: invokevirtual 78	java/lang/StringBuilder:toString	()Ljava/lang/String;
    //   563: invokevirtual 136	java/lang/String:getBytes	()[B
    //   566: astore 20
    //   568: aload 12
    //   570: iload 18
    //   572: aload 20
    //   574: arraylength
    //   575: iadd
    //   576: invokevirtual 181	java/net/HttpURLConnection:setFixedLengthStreamingMode	(I)V
    //   579: new 123	java/io/DataOutputStream
    //   582: dup
    //   583: aload 12
    //   585: invokevirtual 185	java/net/HttpURLConnection:getOutputStream	()Ljava/io/OutputStream;
    //   588: invokespecial 188	java/io/DataOutputStream:<init>	(Ljava/io/OutputStream;)V
    //   591: astore 21
    //   593: aload 21
    //   595: aload 13
    //   597: invokevirtual 78	java/lang/StringBuilder:toString	()Ljava/lang/String;
    //   600: invokevirtual 136	java/lang/String:getBytes	()[B
    //   603: invokevirtual 192	java/io/DataOutputStream:write	([B)V
    //   606: aload_2
    //   607: arraylength
    //   608: istore 22
    //   610: iconst_0
    //   611: istore 23
    //   613: iload 23
    //   615: iload 22
    //   617: if_icmpge +232 -> 849
    //   620: aload_2
    //   621: iload 23
    //   623: aaload
    //   624: astore 30
    //   626: aload 16
    //   628: iconst_0
    //   629: aload 16
    //   631: invokevirtual 140	java/lang/StringBuilder:length	()I
    //   634: invokevirtual 144	java/lang/StringBuilder:delete	(II)Ljava/lang/StringBuilder;
    //   637: pop
    //   638: aload 16
    //   640: ldc 104
    //   642: invokevirtual 70	java/lang/StringBuilder:append	(Ljava/lang/String;)Ljava/lang/StringBuilder;
    //   645: pop
    //   646: aload 16
    //   648: ldc 74
    //   650: invokevirtual 70	java/lang/StringBuilder:append	(Ljava/lang/String;)Ljava/lang/StringBuilder;
    //   653: pop
    //   654: aload 16
    //   656: ldc 106
    //   658: invokevirtual 70	java/lang/StringBuilder:append	(Ljava/lang/String;)Ljava/lang/StringBuilder;
    //   661: pop
    //   662: aload 16
    //   664: new 63	java/lang/StringBuilder
    //   667: dup
    //   668: invokespecial 64	java/lang/StringBuilder:<init>	()V
    //   671: ldc 146
    //   673: invokevirtual 70	java/lang/StringBuilder:append	(Ljava/lang/String;)Ljava/lang/StringBuilder;
    //   676: aload 30
    //   678: invokevirtual 151	kdebug/c:d	()Ljava/lang/String;
    //   681: invokevirtual 70	java/lang/StringBuilder:append	(Ljava/lang/String;)Ljava/lang/StringBuilder;
    //   684: ldc 153
    //   686: invokevirtual 70	java/lang/StringBuilder:append	(Ljava/lang/String;)Ljava/lang/StringBuilder;
    //   689: aload 30
    //   691: invokevirtual 156	kdebug/c:c	()Ljava/lang/String;
    //   694: invokevirtual 70	java/lang/StringBuilder:append	(Ljava/lang/String;)Ljava/lang/StringBuilder;
    //   697: ldc 158
    //   699: invokevirtual 70	java/lang/StringBuilder:append	(Ljava/lang/String;)Ljava/lang/StringBuilder;
    //   702: invokevirtual 78	java/lang/StringBuilder:toString	()Ljava/lang/String;
    //   705: invokevirtual 70	java/lang/StringBuilder:append	(Ljava/lang/String;)Ljava/lang/StringBuilder;
    //   708: pop
    //   709: aload 16
    //   711: new 63	java/lang/StringBuilder
    //   714: dup
    //   715: invokespecial 64	java/lang/StringBuilder:<init>	()V
    //   718: ldc 160
    //   720: invokevirtual 70	java/lang/StringBuilder:append	(Ljava/lang/String;)Ljava/lang/StringBuilder;
    //   723: aload 30
    //   725: invokevirtual 163	kdebug/c:e	()Ljava/lang/String;
    //   728: invokevirtual 70	java/lang/StringBuilder:append	(Ljava/lang/String;)Ljava/lang/StringBuilder;
    //   731: ldc 165
    //   733: invokevirtual 70	java/lang/StringBuilder:append	(Ljava/lang/String;)Ljava/lang/StringBuilder;
    //   736: invokevirtual 78	java/lang/StringBuilder:toString	()Ljava/lang/String;
    //   739: invokevirtual 70	java/lang/StringBuilder:append	(Ljava/lang/String;)Ljava/lang/StringBuilder;
    //   742: pop
    //   743: aload 21
    //   745: aload 16
    //   747: invokevirtual 78	java/lang/StringBuilder:toString	()Ljava/lang/String;
    //   750: invokevirtual 136	java/lang/String:getBytes	()[B
    //   753: invokevirtual 192	java/io/DataOutputStream:write	([B)V
    //   756: aload 30
    //   758: invokevirtual 168	kdebug/c:b	()[B
    //   761: ifnull +36 -> 797
    //   764: aload 21
    //   766: aload 30
    //   768: invokevirtual 168	kdebug/c:b	()[B
    //   771: iconst_0
    //   772: aload 30
    //   774: invokevirtual 168	kdebug/c:b	()[B
    //   777: arraylength
    //   778: invokevirtual 195	java/io/DataOutputStream:write	([BII)V
    //   781: aload 21
    //   783: ldc 106
    //   785: invokevirtual 136	java/lang/String:getBytes	()[B
    //   788: invokevirtual 192	java/io/DataOutputStream:write	([B)V
    //   791: iinc 23 1
    //   794: goto -181 -> 613
    //   797: new 197	java/io/FileInputStream
    //   800: dup
    //   801: aload 30
    //   803: invokevirtual 172	kdebug/c:a	()Ljava/lang/String;
    //   806: invokespecial 198	java/io/FileInputStream:<init>	(Ljava/lang/String;)V
    //   809: astore 37
    //   811: aload 37
    //   813: aload_3
    //   814: invokevirtual 202	java/io/FileInputStream:read	([B)I
    //   817: istore 38
    //   819: iload 38
    //   821: ifle +20 -> 841
    //   824: aload 21
    //   826: aload_3
    //   827: iconst_0
    //   828: iload 38
    //   830: invokevirtual 195	java/io/DataOutputStream:write	([BII)V
    //   833: aload 21
    //   835: invokevirtual 205	java/io/DataOutputStream:flush	()V
    //   838: goto -27 -> 811
    //   841: aload 37
    //   843: invokevirtual 206	java/io/FileInputStream:close	()V
    //   846: goto -65 -> 781
    //   849: aload 21
    //   851: aload 20
    //   853: invokevirtual 192	java/io/DataOutputStream:write	([B)V
    //   856: aload 21
    //   858: invokevirtual 205	java/io/DataOutputStream:flush	()V
    //   861: aload 12
    //   863: invokevirtual 209	java/net/HttpURLConnection:getResponseCode	()I
    //   866: sipush 200
    //   869: if_icmpne +118 -> 987
    //   872: new 63	java/lang/StringBuilder
    //   875: dup
    //   876: invokespecial 64	java/lang/StringBuilder:<init>	()V
    //   879: astore 24
    //   881: aload 12
    //   883: invokevirtual 213	java/net/HttpURLConnection:getInputStream	()Ljava/io/InputStream;
    //   886: astore 25
    //   888: aload 25
    //   890: astore 26
    //   892: aload 26
    //   894: invokevirtual 215	java/io/InputStream:read	()I
    //   897: istore 27
    //   899: iload 27
    //   901: iconst_m1
    //   902: if_icmpeq +15 -> 917
    //   905: aload 24
    //   907: iload 27
    //   909: i2c
    //   910: invokevirtual 218	java/lang/StringBuilder:append	(C)Ljava/lang/StringBuilder;
    //   913: pop
    //   914: goto -22 -> 892
    //   917: aload 24
    //   919: invokevirtual 78	java/lang/StringBuilder:toString	()Ljava/lang/String;
    //   922: astore 28
    //   924: aload 28
    //   926: astore 8
    //   928: aload 26
    //   930: astore 6
    //   932: aload 21
    //   934: astore 7
    //   936: aload 12
    //   938: astore 5
    //   940: goto -673 -> 267
    //   943: astore 11
    //   945: aload 11
    //   947: invokevirtual 219	java/io/IOException:printStackTrace	()V
    //   950: goto -673 -> 277
    //   953: astore 10
    //   955: aload 10
    //   957: invokevirtual 219	java/io/IOException:printStackTrace	()V
    //   960: goto -673 -> 287
    //   963: astore 9
    //   965: aload 9
    //   967: invokevirtual 121	java/lang/Exception:printStackTrace	()V
    //   970: goto -673 -> 297
    //   973: astore 4
    //   975: aconst_null
    //   976: astore 5
    //   978: aconst_null
    //   979: astore 6
    //   981: aconst_null
    //   982: astore 7
    //   984: goto -725 -> 259
    //   987: aconst_null
    //   988: astore 8
    //   990: aconst_null
    //   991: astore 26
    //   993: goto -65 -> 928
    //   996: astore 4
    //   998: aload 12
    //   1000: astore 5
    //   1002: aload 21
    //   1004: astore 7
    //   1006: aconst_null
    //   1007: astore 6
    //   1009: goto -750 -> 259
    //   1012: astore 4
    //   1014: aload 26
    //   1016: astore 6
    //   1018: aload 21
    //   1020: astore 7
    //   1022: aload 12
    //   1024: astore 5
    //   1026: goto -767 -> 259
    //
    // Exception table:
    //   from	to	target	type
    //   22	244	247	java/lang/Exception
    //   300	593	247	java/lang/Exception
    //   272	277	943	java/io/IOException
    //   282	287	953	java/io/IOException
    //   292	297	963	java/lang/Exception
    //   6	22	973	java/lang/Exception
    //   593	888	996	java/lang/Exception
    //   892	924	1012	java/lang/Exception
  }

  public static c a(String paramString)
  {
    return new c(new File(paramString).getName(), paramString, "file");
  }

  public static c a(byte[] paramArrayOfByte)
  {
    return new c("a.v", paramArrayOfByte, "file");
  }
}

/* Location:           C:\Users\sandrocheng.21KUNPENG\Desktop\classes_dex2jar\
 * Qualified Name:     kdebug.a
 * JD-Core Version:    0.6.2
 */