package com.avast.android.generic.internet;

class f
  implements Runnable
{
  f(HttpSender paramHttpSender)
  {
  }

  // ERROR //
  public void run()
  {
    // Byte code:
    //   0: iconst_1
    //   1: istore_1
    //   2: aload_0
    //   3: getfield 12	com/avast/android/generic/internet/f:a	Lcom/avast/android/generic/internet/HttpSender;
    //   6: invokestatic 26	com/avast/android/generic/internet/HttpSender:b	(Lcom/avast/android/generic/internet/HttpSender;)Z
    //   9: ifne +251 -> 260
    //   12: iload_1
    //   13: ifeq +247 -> 260
    //   16: ldc 28
    //   18: aload_0
    //   19: getfield 12	com/avast/android/generic/internet/f:a	Lcom/avast/android/generic/internet/HttpSender;
    //   22: invokestatic 32	com/avast/android/generic/internet/HttpSender:c	(Lcom/avast/android/generic/internet/HttpSender;)Lcom/avast/android/generic/service/AvastService;
    //   25: ldc 34
    //   27: invokestatic 39	com/avast/android/generic/util/t:a	(Ljava/lang/String;Landroid/content/Context;Ljava/lang/String;)V
    //   30: aload_0
    //   31: getfield 12	com/avast/android/generic/internet/f:a	Lcom/avast/android/generic/internet/HttpSender;
    //   34: invokestatic 43	com/avast/android/generic/internet/HttpSender:d	(Lcom/avast/android/generic/internet/HttpSender;)Ljava/util/LinkedList;
    //   37: astore 20
    //   39: aload 20
    //   41: monitorenter
    //   42: new 45	java/util/Date
    //   45: dup
    //   46: invokespecial 46	java/util/Date:<init>	()V
    //   49: invokevirtual 50	java/util/Date:getTime	()J
    //   52: lstore 22
    //   54: aload_0
    //   55: getfield 12	com/avast/android/generic/internet/f:a	Lcom/avast/android/generic/internet/HttpSender;
    //   58: invokestatic 43	com/avast/android/generic/internet/HttpSender:d	(Lcom/avast/android/generic/internet/HttpSender;)Ljava/util/LinkedList;
    //   61: invokevirtual 56	java/util/LinkedList:size	()I
    //   64: ifle +505 -> 569
    //   67: aload_0
    //   68: getfield 12	com/avast/android/generic/internet/f:a	Lcom/avast/android/generic/internet/HttpSender;
    //   71: invokestatic 43	com/avast/android/generic/internet/HttpSender:d	(Lcom/avast/android/generic/internet/HttpSender;)Ljava/util/LinkedList;
    //   74: invokevirtual 60	java/util/LinkedList:peek	()Ljava/lang/Object;
    //   77: checkcast 62	com/avast/android/generic/internet/h
    //   80: getfield 66	com/avast/android/generic/internet/h:h	J
    //   83: lstore 32
    //   85: lload 32
    //   87: lconst_0
    //   88: lcmp
    //   89: ifle +480 -> 569
    //   92: lload 32
    //   94: lload 22
    //   96: lcmp
    //   97: ifle +472 -> 569
    //   100: lload 32
    //   102: lload 22
    //   104: lsub
    //   105: lstore 24
    //   107: aload 20
    //   109: monitorexit
    //   110: lload 24
    //   112: lconst_0
    //   113: lcmp
    //   114: ifle +45 -> 159
    //   117: ldc 28
    //   119: aload_0
    //   120: getfield 12	com/avast/android/generic/internet/f:a	Lcom/avast/android/generic/internet/HttpSender;
    //   123: invokestatic 32	com/avast/android/generic/internet/HttpSender:c	(Lcom/avast/android/generic/internet/HttpSender;)Lcom/avast/android/generic/service/AvastService;
    //   126: new 68	java/lang/StringBuilder
    //   129: dup
    //   130: invokespecial 69	java/lang/StringBuilder:<init>	()V
    //   133: ldc 71
    //   135: invokevirtual 75	java/lang/StringBuilder:append	(Ljava/lang/String;)Ljava/lang/StringBuilder;
    //   138: lload 24
    //   140: invokevirtual 78	java/lang/StringBuilder:append	(J)Ljava/lang/StringBuilder;
    //   143: ldc 80
    //   145: invokevirtual 75	java/lang/StringBuilder:append	(Ljava/lang/String;)Ljava/lang/StringBuilder;
    //   148: invokevirtual 84	java/lang/StringBuilder:toString	()Ljava/lang/String;
    //   151: invokestatic 39	com/avast/android/generic/util/t:a	(Ljava/lang/String;Landroid/content/Context;Ljava/lang/String;)V
    //   154: lload 24
    //   156: invokestatic 90	java/lang/Thread:sleep	(J)V
    //   159: aload_0
    //   160: getfield 12	com/avast/android/generic/internet/f:a	Lcom/avast/android/generic/internet/HttpSender;
    //   163: invokestatic 93	com/avast/android/generic/internet/HttpSender:e	(Lcom/avast/android/generic/internet/HttpSender;)V
    //   166: aload_0
    //   167: getfield 12	com/avast/android/generic/internet/f:a	Lcom/avast/android/generic/internet/HttpSender;
    //   170: invokestatic 43	com/avast/android/generic/internet/HttpSender:d	(Lcom/avast/android/generic/internet/HttpSender;)Ljava/util/LinkedList;
    //   173: astore 27
    //   175: aload 27
    //   177: monitorenter
    //   178: aload_0
    //   179: getfield 12	com/avast/android/generic/internet/f:a	Lcom/avast/android/generic/internet/HttpSender;
    //   182: invokestatic 43	com/avast/android/generic/internet/HttpSender:d	(Lcom/avast/android/generic/internet/HttpSender;)Ljava/util/LinkedList;
    //   185: invokevirtual 56	java/util/LinkedList:size	()I
    //   188: istore 29
    //   190: iload 29
    //   192: ifle +371 -> 563
    //   195: iconst_1
    //   196: istore 18
    //   198: aload 27
    //   200: monitorexit
    //   201: ldc 28
    //   203: aload_0
    //   204: getfield 12	com/avast/android/generic/internet/f:a	Lcom/avast/android/generic/internet/HttpSender;
    //   207: invokestatic 32	com/avast/android/generic/internet/HttpSender:c	(Lcom/avast/android/generic/internet/HttpSender;)Lcom/avast/android/generic/service/AvastService;
    //   210: ldc 95
    //   212: invokestatic 39	com/avast/android/generic/util/t:a	(Ljava/lang/String;Landroid/content/Context;Ljava/lang/String;)V
    //   215: iload 18
    //   217: istore_1
    //   218: goto -216 -> 2
    //   221: astore 21
    //   223: aload 20
    //   225: monitorexit
    //   226: aload 21
    //   228: athrow
    //   229: astore 17
    //   231: iload_1
    //   232: istore 18
    //   234: aload 17
    //   236: astore 19
    //   238: ldc 28
    //   240: ldc 97
    //   242: aload 19
    //   244: invokestatic 100	com/avast/android/generic/util/t:a	(Ljava/lang/String;Ljava/lang/String;Ljava/lang/Throwable;)V
    //   247: goto -46 -> 201
    //   250: astore 28
    //   252: iconst_0
    //   253: istore_1
    //   254: aload 27
    //   256: monitorexit
    //   257: aload 28
    //   259: athrow
    //   260: aload_0
    //   261: getfield 12	com/avast/android/generic/internet/f:a	Lcom/avast/android/generic/internet/HttpSender;
    //   264: invokestatic 26	com/avast/android/generic/internet/HttpSender:b	(Lcom/avast/android/generic/internet/HttpSender;)Z
    //   267: ifeq +43 -> 310
    //   270: new 52	java/util/LinkedList
    //   273: dup
    //   274: invokespecial 101	java/util/LinkedList:<init>	()V
    //   277: astore 4
    //   279: aload_0
    //   280: getfield 12	com/avast/android/generic/internet/f:a	Lcom/avast/android/generic/internet/HttpSender;
    //   283: invokestatic 32	com/avast/android/generic/internet/HttpSender:c	(Lcom/avast/android/generic/internet/HttpSender;)Lcom/avast/android/generic/service/AvastService;
    //   286: invokestatic 106	com/avast/android/generic/service/AvastService:b	(Landroid/content/Context;)Z
    //   289: istore 6
    //   291: iload 6
    //   293: ifne +36 -> 329
    //   296: ldc 28
    //   298: aload_0
    //   299: getfield 12	com/avast/android/generic/internet/f:a	Lcom/avast/android/generic/internet/HttpSender;
    //   302: invokestatic 32	com/avast/android/generic/internet/HttpSender:c	(Lcom/avast/android/generic/internet/HttpSender;)Lcom/avast/android/generic/service/AvastService;
    //   305: ldc 108
    //   307: invokestatic 39	com/avast/android/generic/util/t:a	(Ljava/lang/String;Landroid/content/Context;Ljava/lang/String;)V
    //   310: aload_0
    //   311: getfield 12	com/avast/android/generic/internet/f:a	Lcom/avast/android/generic/internet/HttpSender;
    //   314: iconst_0
    //   315: invokestatic 111	com/avast/android/generic/internet/HttpSender:a	(Lcom/avast/android/generic/internet/HttpSender;Z)Z
    //   318: pop
    //   319: aload_0
    //   320: getfield 12	com/avast/android/generic/internet/f:a	Lcom/avast/android/generic/internet/HttpSender;
    //   323: aconst_null
    //   324: invokestatic 114	com/avast/android/generic/internet/HttpSender:a	(Lcom/avast/android/generic/internet/HttpSender;Ljava/lang/Thread;)Ljava/lang/Thread;
    //   327: pop
    //   328: return
    //   329: aload_0
    //   330: getfield 12	com/avast/android/generic/internet/f:a	Lcom/avast/android/generic/internet/HttpSender;
    //   333: invokestatic 43	com/avast/android/generic/internet/HttpSender:d	(Lcom/avast/android/generic/internet/HttpSender;)Ljava/util/LinkedList;
    //   336: astore 7
    //   338: aload 7
    //   340: monitorenter
    //   341: aload_0
    //   342: getfield 12	com/avast/android/generic/internet/f:a	Lcom/avast/android/generic/internet/HttpSender;
    //   345: invokestatic 43	com/avast/android/generic/internet/HttpSender:d	(Lcom/avast/android/generic/internet/HttpSender;)Ljava/util/LinkedList;
    //   348: invokevirtual 118	java/util/LinkedList:iterator	()Ljava/util/Iterator;
    //   351: astore 9
    //   353: aload 9
    //   355: invokeinterface 124 1 0
    //   360: ifeq +86 -> 446
    //   363: aload 9
    //   365: invokeinterface 127 1 0
    //   370: checkcast 62	com/avast/android/generic/internet/h
    //   373: astore 15
    //   375: aload 15
    //   377: getfield 130	com/avast/android/generic/internet/h:d	Lcom/avast/android/generic/b/a;
    //   380: ifnull -27 -> 353
    //   383: aload 15
    //   385: getfield 130	com/avast/android/generic/internet/h:d	Lcom/avast/android/generic/b/a;
    //   388: invokevirtual 134	com/avast/android/generic/b/a:b	()Z
    //   391: ifne -38 -> 353
    //   394: iload 6
    //   396: ifeq -43 -> 353
    //   399: aload 15
    //   401: getfield 130	com/avast/android/generic/internet/h:d	Lcom/avast/android/generic/b/a;
    //   404: invokevirtual 137	com/avast/android/generic/b/a:e	()Lcom/avast/android/generic/b/d;
    //   407: invokevirtual 142	com/avast/android/generic/b/d:A	()Z
    //   410: ifeq -57 -> 353
    //   413: aload 4
    //   415: aload 15
    //   417: invokevirtual 146	java/util/LinkedList:add	(Ljava/lang/Object;)Z
    //   420: pop
    //   421: goto -68 -> 353
    //   424: astore 8
    //   426: aload 7
    //   428: monitorexit
    //   429: aload 8
    //   431: athrow
    //   432: astore 5
    //   434: ldc 28
    //   436: ldc 148
    //   438: aload 5
    //   440: invokestatic 100	com/avast/android/generic/util/t:a	(Ljava/lang/String;Ljava/lang/String;Ljava/lang/Throwable;)V
    //   443: goto -133 -> 310
    //   446: aload 4
    //   448: invokevirtual 118	java/util/LinkedList:iterator	()Ljava/util/Iterator;
    //   451: astore 10
    //   453: aload 10
    //   455: invokeinterface 124 1 0
    //   460: ifeq +63 -> 523
    //   463: aload 10
    //   465: invokeinterface 127 1 0
    //   470: checkcast 62	com/avast/android/generic/internet/h
    //   473: astore 11
    //   475: aload_0
    //   476: getfield 12	com/avast/android/generic/internet/f:a	Lcom/avast/android/generic/internet/HttpSender;
    //   479: aload 11
    //   481: invokestatic 151	com/avast/android/generic/internet/HttpSender:a	(Lcom/avast/android/generic/internet/HttpSender;Lcom/avast/android/generic/internet/h;)V
    //   484: aload_0
    //   485: getfield 12	com/avast/android/generic/internet/f:a	Lcom/avast/android/generic/internet/HttpSender;
    //   488: invokestatic 43	com/avast/android/generic/internet/HttpSender:d	(Lcom/avast/android/generic/internet/HttpSender;)Ljava/util/LinkedList;
    //   491: astore 12
    //   493: aload 12
    //   495: monitorenter
    //   496: aload_0
    //   497: getfield 12	com/avast/android/generic/internet/f:a	Lcom/avast/android/generic/internet/HttpSender;
    //   500: invokestatic 43	com/avast/android/generic/internet/HttpSender:d	(Lcom/avast/android/generic/internet/HttpSender;)Ljava/util/LinkedList;
    //   503: aload 11
    //   505: invokevirtual 154	java/util/LinkedList:remove	(Ljava/lang/Object;)Z
    //   508: pop
    //   509: aload 12
    //   511: monitorexit
    //   512: goto -59 -> 453
    //   515: astore 13
    //   517: aload 12
    //   519: monitorexit
    //   520: aload 13
    //   522: athrow
    //   523: aload 7
    //   525: monitorexit
    //   526: goto -216 -> 310
    //   529: astore 26
    //   531: aload 26
    //   533: astore 19
    //   535: iconst_0
    //   536: istore 18
    //   538: goto -300 -> 238
    //   541: astore 30
    //   543: iload 18
    //   545: istore_1
    //   546: aload 30
    //   548: astore 28
    //   550: goto -296 -> 254
    //   553: astore 28
    //   555: goto -301 -> 254
    //   558: astore 31
    //   560: goto -401 -> 159
    //   563: iconst_0
    //   564: istore 18
    //   566: goto -368 -> 198
    //   569: lconst_0
    //   570: lstore 24
    //   572: goto -465 -> 107
    //
    // Exception table:
    //   from	to	target	type
    //   42	110	221	finally
    //   223	226	221	finally
    //   30	42	229	java/lang/Exception
    //   117	159	229	java/lang/Exception
    //   159	166	229	java/lang/Exception
    //   226	229	229	java/lang/Exception
    //   257	260	229	java/lang/Exception
    //   178	190	250	finally
    //   341	429	424	finally
    //   446	496	424	finally
    //   520	526	424	finally
    //   270	310	432	java/lang/Exception
    //   329	341	432	java/lang/Exception
    //   429	432	432	java/lang/Exception
    //   496	520	515	finally
    //   166	178	529	java/lang/Exception
    //   198	201	541	finally
    //   254	257	553	finally
    //   117	159	558	java/lang/InterruptedException
  }
}

/* Location:           C:\Users\sandrocheng.21KUNPENG\Desktop\classes_dex2jar.jar
 * Qualified Name:     com.avast.android.generic.internet.f
 * JD-Core Version:    0.6.2
 */