package com.keniu.security.main;

final class j extends Thread
{
  private j(f paramf, byte paramByte)
  {
  }

  // ERROR //
  public final void run()
  {
    // Byte code:
    //   0: new 23	java/net/URL
    //   3: dup
    //   4: aload_0
    //   5: getfield 13	com/keniu/security/main/j:a	Lcom/keniu/security/main/f;
    //   8: invokestatic 29	com/keniu/security/main/f:h	(Lcom/keniu/security/main/f;)Landroid/content/SharedPreferences;
    //   11: ldc 31
    //   13: ldc 33
    //   15: invokeinterface 39 3 0
    //   20: invokespecial 42	java/net/URL:<init>	(Ljava/lang/String;)V
    //   23: invokevirtual 46	java/net/URL:openConnection	()Ljava/net/URLConnection;
    //   26: astore 17
    //   28: aload 17
    //   30: sipush 30000
    //   33: invokevirtual 52	java/net/URLConnection:setConnectTimeout	(I)V
    //   36: aload 17
    //   38: sipush 30000
    //   41: invokevirtual 55	java/net/URLConnection:setReadTimeout	(I)V
    //   44: aload 17
    //   46: invokevirtual 58	java/net/URLConnection:connect	()V
    //   49: aload 17
    //   51: instanceof 60
    //   54: ifeq +144 -> 198
    //   57: aload 17
    //   59: checkcast 60	java/net/HttpURLConnection
    //   62: invokevirtual 64	java/net/HttpURLConnection:getResponseCode	()I
    //   65: sipush 400
    //   68: if_icmplt +130 -> 198
    //   71: aload_0
    //   72: getfield 13	com/keniu/security/main/j:a	Lcom/keniu/security/main/f;
    //   75: invokestatic 68	com/keniu/security/main/f:g	(Lcom/keniu/security/main/f;)Landroid/os/Handler;
    //   78: iconst_1
    //   79: invokevirtual 74	android/os/Handler:sendEmptyMessage	(I)Z
    //   82: pop
    //   83: aload_0
    //   84: getfield 13	com/keniu/security/main/j:a	Lcom/keniu/security/main/f;
    //   87: invokestatic 78	com/keniu/security/main/f:i	(Lcom/keniu/security/main/f;)Z
    //   90: ifeq +39 -> 129
    //   93: new 80	java/io/File
    //   96: dup
    //   97: new 82	java/lang/StringBuilder
    //   100: dup
    //   101: invokespecial 83	java/lang/StringBuilder:<init>	()V
    //   104: aload_0
    //   105: getfield 13	com/keniu/security/main/j:a	Lcom/keniu/security/main/f;
    //   108: invokestatic 87	com/keniu/security/main/f:d	(Lcom/keniu/security/main/f;)Ljava/lang/String;
    //   111: invokevirtual 91	java/lang/StringBuilder:append	(Ljava/lang/String;)Ljava/lang/StringBuilder;
    //   114: ldc 93
    //   116: invokevirtual 91	java/lang/StringBuilder:append	(Ljava/lang/String;)Ljava/lang/StringBuilder;
    //   119: invokevirtual 97	java/lang/StringBuilder:toString	()Ljava/lang/String;
    //   122: invokespecial 98	java/io/File:<init>	(Ljava/lang/String;)V
    //   125: invokevirtual 102	java/io/File:delete	()Z
    //   128: pop
    //   129: return
    //   130: astore 18
    //   132: aload_0
    //   133: getfield 13	com/keniu/security/main/j:a	Lcom/keniu/security/main/f;
    //   136: invokestatic 68	com/keniu/security/main/f:g	(Lcom/keniu/security/main/f;)Landroid/os/Handler;
    //   139: iconst_1
    //   140: invokevirtual 74	android/os/Handler:sendEmptyMessage	(I)Z
    //   143: pop
    //   144: aload_0
    //   145: getfield 13	com/keniu/security/main/j:a	Lcom/keniu/security/main/f;
    //   148: invokestatic 78	com/keniu/security/main/f:i	(Lcom/keniu/security/main/f;)Z
    //   151: ifeq -22 -> 129
    //   154: new 80	java/io/File
    //   157: dup
    //   158: new 82	java/lang/StringBuilder
    //   161: dup
    //   162: invokespecial 83	java/lang/StringBuilder:<init>	()V
    //   165: aload_0
    //   166: getfield 13	com/keniu/security/main/j:a	Lcom/keniu/security/main/f;
    //   169: invokestatic 87	com/keniu/security/main/f:d	(Lcom/keniu/security/main/f;)Ljava/lang/String;
    //   172: invokevirtual 91	java/lang/StringBuilder:append	(Ljava/lang/String;)Ljava/lang/StringBuilder;
    //   175: ldc 93
    //   177: invokevirtual 91	java/lang/StringBuilder:append	(Ljava/lang/String;)Ljava/lang/StringBuilder;
    //   180: invokevirtual 97	java/lang/StringBuilder:toString	()Ljava/lang/String;
    //   183: invokespecial 98	java/io/File:<init>	(Ljava/lang/String;)V
    //   186: invokevirtual 102	java/io/File:delete	()Z
    //   189: pop
    //   190: goto -61 -> 129
    //   193: astore 20
    //   195: goto -66 -> 129
    //   198: aload 17
    //   200: invokevirtual 105	java/net/URLConnection:getContentLength	()I
    //   203: istore 22
    //   205: invokestatic 111	com/keniu/security/f/f:e	()J
    //   208: iload 22
    //   210: iconst_2
    //   211: imul
    //   212: i2l
    //   213: lcmp
    //   214: ifge +69 -> 283
    //   217: aload_0
    //   218: getfield 13	com/keniu/security/main/j:a	Lcom/keniu/security/main/f;
    //   221: invokestatic 68	com/keniu/security/main/f:g	(Lcom/keniu/security/main/f;)Landroid/os/Handler;
    //   224: iconst_2
    //   225: invokevirtual 74	android/os/Handler:sendEmptyMessage	(I)Z
    //   228: pop
    //   229: aload_0
    //   230: getfield 13	com/keniu/security/main/j:a	Lcom/keniu/security/main/f;
    //   233: invokestatic 78	com/keniu/security/main/f:i	(Lcom/keniu/security/main/f;)Z
    //   236: ifeq -107 -> 129
    //   239: new 80	java/io/File
    //   242: dup
    //   243: new 82	java/lang/StringBuilder
    //   246: dup
    //   247: invokespecial 83	java/lang/StringBuilder:<init>	()V
    //   250: aload_0
    //   251: getfield 13	com/keniu/security/main/j:a	Lcom/keniu/security/main/f;
    //   254: invokestatic 87	com/keniu/security/main/f:d	(Lcom/keniu/security/main/f;)Ljava/lang/String;
    //   257: invokevirtual 91	java/lang/StringBuilder:append	(Ljava/lang/String;)Ljava/lang/StringBuilder;
    //   260: ldc 93
    //   262: invokevirtual 91	java/lang/StringBuilder:append	(Ljava/lang/String;)Ljava/lang/StringBuilder;
    //   265: invokevirtual 97	java/lang/StringBuilder:toString	()Ljava/lang/String;
    //   268: invokespecial 98	java/io/File:<init>	(Ljava/lang/String;)V
    //   271: invokevirtual 102	java/io/File:delete	()Z
    //   274: pop
    //   275: goto -146 -> 129
    //   278: astore 55
    //   280: goto -151 -> 129
    //   283: aload_0
    //   284: getfield 13	com/keniu/security/main/j:a	Lcom/keniu/security/main/f;
    //   287: new 82	java/lang/StringBuilder
    //   290: dup
    //   291: invokespecial 83	java/lang/StringBuilder:<init>	()V
    //   294: invokestatic 114	com/keniu/security/f/f:f	()Ljava/lang/String;
    //   297: invokevirtual 91	java/lang/StringBuilder:append	(Ljava/lang/String;)Ljava/lang/StringBuilder;
    //   300: getstatic 118	java/io/File:separatorChar	C
    //   303: invokevirtual 121	java/lang/StringBuilder:append	(C)Ljava/lang/StringBuilder;
    //   306: ldc 123
    //   308: invokevirtual 91	java/lang/StringBuilder:append	(Ljava/lang/String;)Ljava/lang/StringBuilder;
    //   311: invokevirtual 97	java/lang/StringBuilder:toString	()Ljava/lang/String;
    //   314: invokestatic 126	com/keniu/security/main/f:a	(Lcom/keniu/security/main/f;Ljava/lang/String;)Ljava/lang/String;
    //   317: pop
    //   318: new 80	java/io/File
    //   321: dup
    //   322: aload_0
    //   323: getfield 13	com/keniu/security/main/j:a	Lcom/keniu/security/main/f;
    //   326: invokestatic 87	com/keniu/security/main/f:d	(Lcom/keniu/security/main/f;)Ljava/lang/String;
    //   329: invokespecial 98	java/io/File:<init>	(Ljava/lang/String;)V
    //   332: invokevirtual 129	java/io/File:exists	()Z
    //   335: ifne +21 -> 356
    //   338: new 80	java/io/File
    //   341: dup
    //   342: aload_0
    //   343: getfield 13	com/keniu/security/main/j:a	Lcom/keniu/security/main/f;
    //   346: invokestatic 87	com/keniu/security/main/f:d	(Lcom/keniu/security/main/f;)Ljava/lang/String;
    //   349: invokespecial 98	java/io/File:<init>	(Ljava/lang/String;)V
    //   352: invokevirtual 132	java/io/File:mkdirs	()Z
    //   355: pop
    //   356: aload_0
    //   357: getfield 13	com/keniu/security/main/j:a	Lcom/keniu/security/main/f;
    //   360: new 82	java/lang/StringBuilder
    //   363: dup
    //   364: invokespecial 83	java/lang/StringBuilder:<init>	()V
    //   367: getstatic 118	java/io/File:separatorChar	C
    //   370: invokevirtual 121	java/lang/StringBuilder:append	(C)Ljava/lang/StringBuilder;
    //   373: ldc 134
    //   375: invokevirtual 91	java/lang/StringBuilder:append	(Ljava/lang/String;)Ljava/lang/StringBuilder;
    //   378: invokevirtual 97	java/lang/StringBuilder:toString	()Ljava/lang/String;
    //   381: invokestatic 137	com/keniu/security/main/f:a	(Lcom/keniu/security/main/f;Ljava/lang/Object;)Ljava/lang/String;
    //   384: pop
    //   385: aload_0
    //   386: getfield 13	com/keniu/security/main/j:a	Lcom/keniu/security/main/f;
    //   389: invokestatic 68	com/keniu/security/main/f:g	(Lcom/keniu/security/main/f;)Landroid/os/Handler;
    //   392: invokevirtual 141	android/os/Handler:obtainMessage	()Landroid/os/Message;
    //   395: astore 25
    //   397: aload 25
    //   399: iconst_3
    //   400: putfield 147	android/os/Message:what	I
    //   403: aload 25
    //   405: iload 22
    //   407: putfield 150	android/os/Message:arg1	I
    //   410: aload_0
    //   411: getfield 13	com/keniu/security/main/j:a	Lcom/keniu/security/main/f;
    //   414: invokestatic 68	com/keniu/security/main/f:g	(Lcom/keniu/security/main/f;)Landroid/os/Handler;
    //   417: aload 25
    //   419: invokevirtual 154	android/os/Handler:sendMessage	(Landroid/os/Message;)Z
    //   422: pop
    //   423: aload 17
    //   425: invokevirtual 158	java/net/URLConnection:getInputStream	()Ljava/io/InputStream;
    //   428: astore 27
    //   430: aload 27
    //   432: astore_3
    //   433: sipush 8192
    //   436: newarray byte
    //   438: astore 29
    //   440: new 80	java/io/File
    //   443: dup
    //   444: new 82	java/lang/StringBuilder
    //   447: dup
    //   448: invokespecial 83	java/lang/StringBuilder:<init>	()V
    //   451: aload_0
    //   452: getfield 13	com/keniu/security/main/j:a	Lcom/keniu/security/main/f;
    //   455: invokestatic 87	com/keniu/security/main/f:d	(Lcom/keniu/security/main/f;)Ljava/lang/String;
    //   458: invokevirtual 91	java/lang/StringBuilder:append	(Ljava/lang/String;)Ljava/lang/StringBuilder;
    //   461: ldc 93
    //   463: invokevirtual 91	java/lang/StringBuilder:append	(Ljava/lang/String;)Ljava/lang/StringBuilder;
    //   466: invokevirtual 97	java/lang/StringBuilder:toString	()Ljava/lang/String;
    //   469: invokespecial 98	java/io/File:<init>	(Ljava/lang/String;)V
    //   472: astore 30
    //   474: new 160	java/io/FileOutputStream
    //   477: dup
    //   478: aload 30
    //   480: invokespecial 163	java/io/FileOutputStream:<init>	(Ljava/io/File;)V
    //   483: astore 31
    //   485: iconst_0
    //   486: istore 32
    //   488: aload_0
    //   489: getfield 13	com/keniu/security/main/j:a	Lcom/keniu/security/main/f;
    //   492: invokestatic 78	com/keniu/security/main/f:i	(Lcom/keniu/security/main/f;)Z
    //   495: istore 34
    //   497: iload 34
    //   499: ifeq +70 -> 569
    //   502: aload_3
    //   503: ifnull +7 -> 510
    //   506: aload_3
    //   507: invokevirtual 168	java/io/InputStream:close	()V
    //   510: aload 31
    //   512: invokevirtual 169	java/io/FileOutputStream:close	()V
    //   515: aload_0
    //   516: getfield 13	com/keniu/security/main/j:a	Lcom/keniu/security/main/f;
    //   519: invokestatic 78	com/keniu/security/main/f:i	(Lcom/keniu/security/main/f;)Z
    //   522: ifeq -393 -> 129
    //   525: new 80	java/io/File
    //   528: dup
    //   529: new 82	java/lang/StringBuilder
    //   532: dup
    //   533: invokespecial 83	java/lang/StringBuilder:<init>	()V
    //   536: aload_0
    //   537: getfield 13	com/keniu/security/main/j:a	Lcom/keniu/security/main/f;
    //   540: invokestatic 87	com/keniu/security/main/f:d	(Lcom/keniu/security/main/f;)Ljava/lang/String;
    //   543: invokevirtual 91	java/lang/StringBuilder:append	(Ljava/lang/String;)Ljava/lang/StringBuilder;
    //   546: ldc 93
    //   548: invokevirtual 91	java/lang/StringBuilder:append	(Ljava/lang/String;)Ljava/lang/StringBuilder;
    //   551: invokevirtual 97	java/lang/StringBuilder:toString	()Ljava/lang/String;
    //   554: invokespecial 98	java/io/File:<init>	(Ljava/lang/String;)V
    //   557: invokevirtual 102	java/io/File:delete	()Z
    //   560: pop
    //   561: goto -432 -> 129
    //   564: astore 50
    //   566: goto -437 -> 129
    //   569: aload_3
    //   570: aload 29
    //   572: invokevirtual 173	java/io/InputStream:read	([B)I
    //   575: istore 35
    //   577: iload 35
    //   579: ifle +149 -> 728
    //   582: aload 31
    //   584: aload 29
    //   586: iconst_0
    //   587: iload 35
    //   589: invokevirtual 177	java/io/FileOutputStream:write	([BII)V
    //   592: iload 32
    //   594: iload 35
    //   596: iadd
    //   597: istore 32
    //   599: aload_0
    //   600: getfield 13	com/keniu/security/main/j:a	Lcom/keniu/security/main/f;
    //   603: invokestatic 68	com/keniu/security/main/f:g	(Lcom/keniu/security/main/f;)Landroid/os/Handler;
    //   606: invokevirtual 141	android/os/Handler:obtainMessage	()Landroid/os/Message;
    //   609: astore 47
    //   611: aload 47
    //   613: iconst_5
    //   614: putfield 147	android/os/Message:what	I
    //   617: aload 47
    //   619: iload 32
    //   621: putfield 150	android/os/Message:arg1	I
    //   624: aload_0
    //   625: getfield 13	com/keniu/security/main/j:a	Lcom/keniu/security/main/f;
    //   628: invokestatic 68	com/keniu/security/main/f:g	(Lcom/keniu/security/main/f;)Landroid/os/Handler;
    //   631: aload 47
    //   633: invokevirtual 154	android/os/Handler:sendMessage	(Landroid/os/Message;)Z
    //   636: pop
    //   637: goto -149 -> 488
    //   640: astore 33
    //   642: aload 31
    //   644: astore_2
    //   645: aload_0
    //   646: getfield 13	com/keniu/security/main/j:a	Lcom/keniu/security/main/f;
    //   649: invokestatic 68	com/keniu/security/main/f:g	(Lcom/keniu/security/main/f;)Landroid/os/Handler;
    //   652: bipush 6
    //   654: invokevirtual 74	android/os/Handler:sendEmptyMessage	(I)Z
    //   657: pop
    //   658: aload_3
    //   659: ifnull +7 -> 666
    //   662: aload_3
    //   663: invokevirtual 168	java/io/InputStream:close	()V
    //   666: aload_2
    //   667: ifnull +7 -> 674
    //   670: aload_2
    //   671: invokevirtual 169	java/io/FileOutputStream:close	()V
    //   674: aload_0
    //   675: getfield 13	com/keniu/security/main/j:a	Lcom/keniu/security/main/f;
    //   678: invokestatic 78	com/keniu/security/main/f:i	(Lcom/keniu/security/main/f;)Z
    //   681: ifeq -552 -> 129
    //   684: new 80	java/io/File
    //   687: dup
    //   688: new 82	java/lang/StringBuilder
    //   691: dup
    //   692: invokespecial 83	java/lang/StringBuilder:<init>	()V
    //   695: aload_0
    //   696: getfield 13	com/keniu/security/main/j:a	Lcom/keniu/security/main/f;
    //   699: invokestatic 87	com/keniu/security/main/f:d	(Lcom/keniu/security/main/f;)Ljava/lang/String;
    //   702: invokevirtual 91	java/lang/StringBuilder:append	(Ljava/lang/String;)Ljava/lang/StringBuilder;
    //   705: ldc 93
    //   707: invokevirtual 91	java/lang/StringBuilder:append	(Ljava/lang/String;)Ljava/lang/StringBuilder;
    //   710: invokevirtual 97	java/lang/StringBuilder:toString	()Ljava/lang/String;
    //   713: invokespecial 98	java/io/File:<init>	(Ljava/lang/String;)V
    //   716: invokevirtual 102	java/io/File:delete	()Z
    //   719: pop
    //   720: goto -591 -> 129
    //   723: astore 13
    //   725: goto -596 -> 129
    //   728: aload 30
    //   730: new 80	java/io/File
    //   733: dup
    //   734: aload_0
    //   735: getfield 13	com/keniu/security/main/j:a	Lcom/keniu/security/main/f;
    //   738: invokestatic 87	com/keniu/security/main/f:d	(Lcom/keniu/security/main/f;)Ljava/lang/String;
    //   741: invokespecial 98	java/io/File:<init>	(Ljava/lang/String;)V
    //   744: invokevirtual 181	java/io/File:renameTo	(Ljava/io/File;)Z
    //   747: pop
    //   748: iload 22
    //   750: ifeq +89 -> 839
    //   753: iload 22
    //   755: iload 32
    //   757: if_icmpeq +82 -> 839
    //   760: aload_0
    //   761: getfield 13	com/keniu/security/main/j:a	Lcom/keniu/security/main/f;
    //   764: invokestatic 68	com/keniu/security/main/f:g	(Lcom/keniu/security/main/f;)Landroid/os/Handler;
    //   767: iconst_1
    //   768: invokevirtual 74	android/os/Handler:sendEmptyMessage	(I)Z
    //   771: pop
    //   772: aload_3
    //   773: ifnull +7 -> 780
    //   776: aload_3
    //   777: invokevirtual 168	java/io/InputStream:close	()V
    //   780: aload 31
    //   782: invokevirtual 169	java/io/FileOutputStream:close	()V
    //   785: aload_0
    //   786: getfield 13	com/keniu/security/main/j:a	Lcom/keniu/security/main/f;
    //   789: invokestatic 78	com/keniu/security/main/f:i	(Lcom/keniu/security/main/f;)Z
    //   792: ifeq -663 -> 129
    //   795: new 80	java/io/File
    //   798: dup
    //   799: new 82	java/lang/StringBuilder
    //   802: dup
    //   803: invokespecial 83	java/lang/StringBuilder:<init>	()V
    //   806: aload_0
    //   807: getfield 13	com/keniu/security/main/j:a	Lcom/keniu/security/main/f;
    //   810: invokestatic 87	com/keniu/security/main/f:d	(Lcom/keniu/security/main/f;)Ljava/lang/String;
    //   813: invokevirtual 91	java/lang/StringBuilder:append	(Ljava/lang/String;)Ljava/lang/StringBuilder;
    //   816: ldc 93
    //   818: invokevirtual 91	java/lang/StringBuilder:append	(Ljava/lang/String;)Ljava/lang/StringBuilder;
    //   821: invokevirtual 97	java/lang/StringBuilder:toString	()Ljava/lang/String;
    //   824: invokespecial 98	java/io/File:<init>	(Ljava/lang/String;)V
    //   827: invokevirtual 102	java/io/File:delete	()Z
    //   830: pop
    //   831: goto -702 -> 129
    //   834: astore 44
    //   836: goto -707 -> 129
    //   839: aload_0
    //   840: getfield 13	com/keniu/security/main/j:a	Lcom/keniu/security/main/f;
    //   843: invokestatic 68	com/keniu/security/main/f:g	(Lcom/keniu/security/main/f;)Landroid/os/Handler;
    //   846: bipush 7
    //   848: invokevirtual 74	android/os/Handler:sendEmptyMessage	(I)Z
    //   851: pop
    //   852: aload_3
    //   853: ifnull +7 -> 860
    //   856: aload_3
    //   857: invokevirtual 168	java/io/InputStream:close	()V
    //   860: aload 31
    //   862: invokevirtual 169	java/io/FileOutputStream:close	()V
    //   865: aload_0
    //   866: getfield 13	com/keniu/security/main/j:a	Lcom/keniu/security/main/f;
    //   869: invokestatic 78	com/keniu/security/main/f:i	(Lcom/keniu/security/main/f;)Z
    //   872: ifeq -743 -> 129
    //   875: new 80	java/io/File
    //   878: dup
    //   879: new 82	java/lang/StringBuilder
    //   882: dup
    //   883: invokespecial 83	java/lang/StringBuilder:<init>	()V
    //   886: aload_0
    //   887: getfield 13	com/keniu/security/main/j:a	Lcom/keniu/security/main/f;
    //   890: invokestatic 87	com/keniu/security/main/f:d	(Lcom/keniu/security/main/f;)Ljava/lang/String;
    //   893: invokevirtual 91	java/lang/StringBuilder:append	(Ljava/lang/String;)Ljava/lang/StringBuilder;
    //   896: ldc 93
    //   898: invokevirtual 91	java/lang/StringBuilder:append	(Ljava/lang/String;)Ljava/lang/StringBuilder;
    //   901: invokevirtual 97	java/lang/StringBuilder:toString	()Ljava/lang/String;
    //   904: invokespecial 98	java/io/File:<init>	(Ljava/lang/String;)V
    //   907: invokevirtual 102	java/io/File:delete	()Z
    //   910: pop
    //   911: goto -782 -> 129
    //   914: astore 39
    //   916: goto -787 -> 129
    //   919: astore 7
    //   921: aconst_null
    //   922: astore 6
    //   924: aconst_null
    //   925: astore 5
    //   927: aload 5
    //   929: ifnull +8 -> 937
    //   932: aload 5
    //   934: invokevirtual 168	java/io/InputStream:close	()V
    //   937: aload 6
    //   939: ifnull +8 -> 947
    //   942: aload 6
    //   944: invokevirtual 169	java/io/FileOutputStream:close	()V
    //   947: aload_0
    //   948: getfield 13	com/keniu/security/main/j:a	Lcom/keniu/security/main/f;
    //   951: invokestatic 78	com/keniu/security/main/f:i	(Lcom/keniu/security/main/f;)Z
    //   954: ifeq +39 -> 993
    //   957: new 80	java/io/File
    //   960: dup
    //   961: new 82	java/lang/StringBuilder
    //   964: dup
    //   965: invokespecial 83	java/lang/StringBuilder:<init>	()V
    //   968: aload_0
    //   969: getfield 13	com/keniu/security/main/j:a	Lcom/keniu/security/main/f;
    //   972: invokestatic 87	com/keniu/security/main/f:d	(Lcom/keniu/security/main/f;)Ljava/lang/String;
    //   975: invokevirtual 91	java/lang/StringBuilder:append	(Ljava/lang/String;)Ljava/lang/StringBuilder;
    //   978: ldc 93
    //   980: invokevirtual 91	java/lang/StringBuilder:append	(Ljava/lang/String;)Ljava/lang/StringBuilder;
    //   983: invokevirtual 97	java/lang/StringBuilder:toString	()Ljava/lang/String;
    //   986: invokespecial 98	java/io/File:<init>	(Ljava/lang/String;)V
    //   989: invokevirtual 102	java/io/File:delete	()Z
    //   992: pop
    //   993: aload 7
    //   995: athrow
    //   996: astore 52
    //   998: goto -488 -> 510
    //   1001: astore 49
    //   1003: goto -488 -> 515
    //   1006: astore 46
    //   1008: goto -228 -> 780
    //   1011: astore 43
    //   1013: goto -228 -> 785
    //   1016: astore 41
    //   1018: goto -158 -> 860
    //   1021: astore 38
    //   1023: goto -158 -> 865
    //   1026: astore 16
    //   1028: goto -362 -> 666
    //   1031: astore 15
    //   1033: goto -359 -> 674
    //   1036: astore 11
    //   1038: goto -101 -> 937
    //   1041: astore 10
    //   1043: goto -96 -> 947
    //   1046: astore 8
    //   1048: goto -55 -> 993
    //   1051: astore 7
    //   1053: aload_3
    //   1054: astore 5
    //   1056: aconst_null
    //   1057: astore 6
    //   1059: goto -132 -> 927
    //   1062: astore 7
    //   1064: aload_3
    //   1065: astore 5
    //   1067: aload 31
    //   1069: astore 6
    //   1071: goto -144 -> 927
    //   1074: astore 4
    //   1076: aload_3
    //   1077: astore 5
    //   1079: aload_2
    //   1080: astore 6
    //   1082: aload 4
    //   1084: astore 7
    //   1086: goto -159 -> 927
    //   1089: astore_1
    //   1090: aconst_null
    //   1091: astore_2
    //   1092: aconst_null
    //   1093: astore_3
    //   1094: goto -449 -> 645
    //   1097: astore 28
    //   1099: aconst_null
    //   1100: astore_2
    //   1101: goto -456 -> 645
    //   1104: astore 58
    //   1106: goto -977 -> 129
    //
    // Exception table:
    //   from	to	target	type
    //   44	49	130	java/io/IOException
    //   144	190	193	java/lang/Exception
    //   229	275	278	java/lang/Exception
    //   515	561	564	java/lang/Exception
    //   488	497	640	java/lang/Exception
    //   569	637	640	java/lang/Exception
    //   728	772	640	java/lang/Exception
    //   839	852	640	java/lang/Exception
    //   674	720	723	java/lang/Exception
    //   785	831	834	java/lang/Exception
    //   865	911	914	java/lang/Exception
    //   0	44	919	finally
    //   44	49	919	finally
    //   49	83	919	finally
    //   132	144	919	finally
    //   198	229	919	finally
    //   283	430	919	finally
    //   506	510	996	java/io/IOException
    //   510	515	1001	java/io/IOException
    //   776	780	1006	java/io/IOException
    //   780	785	1011	java/io/IOException
    //   856	860	1016	java/io/IOException
    //   860	865	1021	java/io/IOException
    //   662	666	1026	java/io/IOException
    //   670	674	1031	java/io/IOException
    //   932	937	1036	java/io/IOException
    //   942	947	1041	java/io/IOException
    //   947	993	1046	java/lang/Exception
    //   433	485	1051	finally
    //   488	497	1062	finally
    //   569	637	1062	finally
    //   728	772	1062	finally
    //   839	852	1062	finally
    //   645	658	1074	finally
    //   0	44	1089	java/lang/Exception
    //   44	49	1089	java/lang/Exception
    //   49	83	1089	java/lang/Exception
    //   132	144	1089	java/lang/Exception
    //   198	229	1089	java/lang/Exception
    //   283	430	1089	java/lang/Exception
    //   433	485	1097	java/lang/Exception
    //   83	129	1104	java/lang/Exception
  }
}

/* Location:           C:\Users\sandrocheng.21KUNPENG\Desktop\classes_dex2jar\
 * Qualified Name:     com.keniu.security.main.j
 * JD-Core Version:    0.6.2
 */