package com.keniu.security.f;

public final class p extends ae
{
  private h A;
  private h B;
  private r C = new r();

  public p()
  {
    super(2);
  }

  // ERROR //
  private void b()
  {
    // Byte code:
    //   0: aload_0
    //   1: getfield 27	com/keniu/security/f/p:A	Lcom/keniu/security/f/h;
    //   4: ifnull +89 -> 93
    //   7: invokestatic 32	com/keniu/security/f/ab:a	()Lcom/keniu/security/f/ab;
    //   10: invokevirtual 36	com/keniu/security/f/ab:m	()Ljava/lang/String;
    //   13: astore 39
    //   15: aload_0
    //   16: getfield 27	com/keniu/security/f/p:A	Lcom/keniu/security/f/h;
    //   19: aload 39
    //   21: invokestatic 41	com/keniu/security/f/z:a	(Lcom/keniu/security/f/h;Ljava/lang/String;)I
    //   24: invokestatic 44	com/keniu/security/f/p:a	(I)Z
    //   27: ifeq +66 -> 93
    //   30: aload_0
    //   31: getfield 27	com/keniu/security/f/p:A	Lcom/keniu/security/f/h;
    //   34: ldc 46
    //   36: aload 39
    //   38: invokestatic 49	com/keniu/security/f/p:a	(Lcom/keniu/security/f/h;Ljava/lang/String;Ljava/lang/String;)Z
    //   41: istore 40
    //   43: iload 40
    //   45: ifeq +48 -> 93
    //   48: iconst_1
    //   49: istore 9
    //   51: iload 9
    //   53: ifne +46 -> 99
    //   56: aload_0
    //   57: invokevirtual 53	com/keniu/security/f/p:j	()I
    //   60: ifeq +32 -> 92
    //   63: new 55	java/io/File
    //   66: dup
    //   67: invokestatic 32	com/keniu/security/f/ab:a	()Lcom/keniu/security/f/ab;
    //   70: invokevirtual 57	com/keniu/security/f/ab:j	()Ljava/lang/String;
    //   73: invokespecial 60	java/io/File:<init>	(Ljava/lang/String;)V
    //   76: astore 36
    //   78: aload 36
    //   80: invokevirtual 64	java/io/File:exists	()Z
    //   83: ifeq +9 -> 92
    //   86: aload 36
    //   88: invokevirtual 67	java/io/File:delete	()Z
    //   91: pop
    //   92: return
    //   93: iconst_0
    //   94: istore 9
    //   96: goto -45 -> 51
    //   99: invokestatic 32	com/keniu/security/f/ab:a	()Lcom/keniu/security/f/ab;
    //   102: astore 10
    //   104: aload 10
    //   106: invokevirtual 70	com/keniu/security/f/ab:i	()Z
    //   109: ifne +52 -> 161
    //   112: aload_0
    //   113: iconst_5
    //   114: invokevirtual 73	com/keniu/security/f/p:c	(I)V
    //   117: aload_0
    //   118: invokevirtual 53	com/keniu/security/f/p:j	()I
    //   121: ifeq -29 -> 92
    //   124: new 55	java/io/File
    //   127: dup
    //   128: invokestatic 32	com/keniu/security/f/ab:a	()Lcom/keniu/security/f/ab;
    //   131: invokevirtual 57	com/keniu/security/f/ab:j	()Ljava/lang/String;
    //   134: invokespecial 60	java/io/File:<init>	(Ljava/lang/String;)V
    //   137: astore 33
    //   139: aload 33
    //   141: invokevirtual 64	java/io/File:exists	()Z
    //   144: ifeq -52 -> 92
    //   147: aload 33
    //   149: invokevirtual 67	java/io/File:delete	()Z
    //   152: pop
    //   153: goto -61 -> 92
    //   156: astore 34
    //   158: goto -66 -> 92
    //   161: aload 10
    //   163: invokevirtual 36	com/keniu/security/f/ab:m	()Ljava/lang/String;
    //   166: astore 11
    //   168: aload_0
    //   169: getfield 75	com/keniu/security/f/p:B	Lcom/keniu/security/f/h;
    //   172: ldc 46
    //   174: aload 11
    //   176: invokestatic 78	com/keniu/security/f/z:a	(Lcom/keniu/security/f/h;Ljava/lang/String;Ljava/lang/String;)Ljava/lang/String;
    //   179: astore 12
    //   181: new 80	com/keniu/security/f/aa
    //   184: dup
    //   185: invokespecial 81	com/keniu/security/f/aa:<init>	()V
    //   188: astore 13
    //   190: aload 13
    //   192: aload_0
    //   193: getfield 75	com/keniu/security/f/p:B	Lcom/keniu/security/f/h;
    //   196: aload 12
    //   198: invokevirtual 84	com/keniu/security/f/aa:a	(Lcom/keniu/security/f/h;Ljava/lang/String;)V
    //   201: aload_0
    //   202: getfield 20	com/keniu/security/f/p:C	Lcom/keniu/security/f/r;
    //   205: aload 13
    //   207: getfield 87	com/keniu/security/f/aa:b	I
    //   210: putfield 89	com/keniu/security/f/r:a	I
    //   213: aload_0
    //   214: iconst_4
    //   215: invokevirtual 92	com/keniu/security/f/p:d	(I)V
    //   218: aload 10
    //   220: aload_0
    //   221: getfield 27	com/keniu/security/f/p:A	Lcom/keniu/security/f/h;
    //   224: ldc 94
    //   226: ldc 46
    //   228: invokevirtual 99	com/keniu/security/f/h:a	(Ljava/lang/String;Ljava/lang/String;)Ljava/lang/String;
    //   231: invokevirtual 103	com/keniu/security/f/ab:f	(Ljava/lang/String;)Z
    //   234: ifeq +70 -> 304
    //   237: aload_0
    //   238: getfield 20	com/keniu/security/f/p:C	Lcom/keniu/security/f/r;
    //   241: aload 13
    //   243: getfield 87	com/keniu/security/f/aa:b	I
    //   246: putfield 104	com/keniu/security/f/r:b	I
    //   249: aload_0
    //   250: iconst_5
    //   251: invokevirtual 92	com/keniu/security/f/p:d	(I)V
    //   254: aload_0
    //   255: bipush 7
    //   257: invokevirtual 92	com/keniu/security/f/p:d	(I)V
    //   260: aload_0
    //   261: invokevirtual 53	com/keniu/security/f/p:j	()I
    //   264: ifeq -172 -> 92
    //   267: new 55	java/io/File
    //   270: dup
    //   271: invokestatic 32	com/keniu/security/f/ab:a	()Lcom/keniu/security/f/ab;
    //   274: invokevirtual 57	com/keniu/security/f/ab:j	()Ljava/lang/String;
    //   277: invokespecial 60	java/io/File:<init>	(Ljava/lang/String;)V
    //   280: astore 24
    //   282: aload 24
    //   284: invokevirtual 64	java/io/File:exists	()Z
    //   287: ifeq -195 -> 92
    //   290: aload 24
    //   292: invokevirtual 67	java/io/File:delete	()Z
    //   295: pop
    //   296: goto -204 -> 92
    //   299: astore 25
    //   301: goto -209 -> 92
    //   304: aload 13
    //   306: invokevirtual 106	com/keniu/security/f/aa:b	()I
    //   309: istore 14
    //   311: invokestatic 112	com/keniu/security/f/f:e	()J
    //   314: iload 14
    //   316: i2l
    //   317: lcmp
    //   318: ifge +370 -> 688
    //   321: invokestatic 115	com/keniu/security/f/f:g	()J
    //   324: iload 14
    //   326: i2l
    //   327: lcmp
    //   328: iflt +61 -> 389
    //   331: goto +357 -> 688
    //   334: iload 15
    //   336: ifne +59 -> 395
    //   339: aload_0
    //   340: bipush 8
    //   342: invokevirtual 73	com/keniu/security/f/p:c	(I)V
    //   345: aload_0
    //   346: invokevirtual 53	com/keniu/security/f/p:j	()I
    //   349: ifeq -257 -> 92
    //   352: new 55	java/io/File
    //   355: dup
    //   356: invokestatic 32	com/keniu/security/f/ab:a	()Lcom/keniu/security/f/ab;
    //   359: invokevirtual 57	com/keniu/security/f/ab:j	()Ljava/lang/String;
    //   362: invokespecial 60	java/io/File:<init>	(Ljava/lang/String;)V
    //   365: astore 30
    //   367: aload 30
    //   369: invokevirtual 64	java/io/File:exists	()Z
    //   372: ifeq -280 -> 92
    //   375: aload 30
    //   377: invokevirtual 67	java/io/File:delete	()Z
    //   380: pop
    //   381: goto -289 -> 92
    //   384: astore 31
    //   386: goto -294 -> 92
    //   389: iconst_0
    //   390: istore 15
    //   392: goto -58 -> 334
    //   395: aconst_null
    //   396: astore 16
    //   398: new 117	java/io/FileOutputStream
    //   401: dup
    //   402: aload 10
    //   404: invokevirtual 57	com/keniu/security/f/ab:j	()Ljava/lang/String;
    //   407: invokespecial 118	java/io/FileOutputStream:<init>	(Ljava/lang/String;)V
    //   410: astore 17
    //   412: new 120	com/keniu/security/f/q
    //   415: dup
    //   416: aload_0
    //   417: aload 17
    //   419: invokespecial 123	com/keniu/security/f/q:<init>	(Lcom/keniu/security/f/p;Ljava/io/FileOutputStream;)V
    //   422: astore 18
    //   424: aload_0
    //   425: iconst_5
    //   426: invokevirtual 92	com/keniu/security/f/p:d	(I)V
    //   429: aload 10
    //   431: invokevirtual 125	com/keniu/security/f/ab:b	()Ljava/lang/String;
    //   434: aload 13
    //   436: aload 18
    //   438: invokestatic 128	com/keniu/security/f/p:a	(Ljava/lang/String;Lcom/keniu/security/f/aa;Lcom/keniu/security/f/af;)I
    //   441: istore 20
    //   443: iload 20
    //   445: ifeq +58 -> 503
    //   448: aload_0
    //   449: iload 20
    //   451: invokevirtual 73	com/keniu/security/f/p:c	(I)V
    //   454: aload 17
    //   456: invokevirtual 131	java/io/FileOutputStream:close	()V
    //   459: aload_0
    //   460: invokevirtual 53	com/keniu/security/f/p:j	()I
    //   463: ifeq -371 -> 92
    //   466: new 55	java/io/File
    //   469: dup
    //   470: invokestatic 32	com/keniu/security/f/ab:a	()Lcom/keniu/security/f/ab;
    //   473: invokevirtual 57	com/keniu/security/f/ab:j	()Ljava/lang/String;
    //   476: invokespecial 60	java/io/File:<init>	(Ljava/lang/String;)V
    //   479: astore 27
    //   481: aload 27
    //   483: invokevirtual 64	java/io/File:exists	()Z
    //   486: ifeq -394 -> 92
    //   489: aload 27
    //   491: invokevirtual 67	java/io/File:delete	()Z
    //   494: pop
    //   495: goto -403 -> 92
    //   498: astore 28
    //   500: goto -408 -> 92
    //   503: aload 17
    //   505: invokevirtual 131	java/io/FileOutputStream:close	()V
    //   508: aload 10
    //   510: aload 13
    //   512: invokevirtual 134	com/keniu/security/f/ab:a	(Lcom/keniu/security/f/aa;)Z
    //   515: ifne -261 -> 254
    //   518: aload_0
    //   519: bipush 7
    //   521: invokevirtual 73	com/keniu/security/f/p:c	(I)V
    //   524: aload_0
    //   525: invokevirtual 53	com/keniu/security/f/p:j	()I
    //   528: ifeq -436 -> 92
    //   531: new 55	java/io/File
    //   534: dup
    //   535: invokestatic 32	com/keniu/security/f/ab:a	()Lcom/keniu/security/f/ab;
    //   538: invokevirtual 57	com/keniu/security/f/ab:j	()Ljava/lang/String;
    //   541: invokespecial 60	java/io/File:<init>	(Ljava/lang/String;)V
    //   544: astore 21
    //   546: aload 21
    //   548: invokevirtual 64	java/io/File:exists	()Z
    //   551: ifeq -459 -> 92
    //   554: aload 21
    //   556: invokevirtual 67	java/io/File:delete	()Z
    //   559: pop
    //   560: goto -468 -> 92
    //   563: astore 22
    //   565: goto -473 -> 92
    //   568: astore 19
    //   570: aload 16
    //   572: ifnull +8 -> 580
    //   575: aload 16
    //   577: invokevirtual 131	java/io/FileOutputStream:close	()V
    //   580: aload 19
    //   582: athrow
    //   583: astore 5
    //   585: aload_0
    //   586: iconst_3
    //   587: invokevirtual 73	com/keniu/security/f/p:c	(I)V
    //   590: aload_0
    //   591: invokevirtual 53	com/keniu/security/f/p:j	()I
    //   594: ifeq -502 -> 92
    //   597: new 55	java/io/File
    //   600: dup
    //   601: invokestatic 32	com/keniu/security/f/ab:a	()Lcom/keniu/security/f/ab;
    //   604: invokevirtual 57	com/keniu/security/f/ab:j	()Ljava/lang/String;
    //   607: invokespecial 60	java/io/File:<init>	(Ljava/lang/String;)V
    //   610: astore 6
    //   612: aload 6
    //   614: invokevirtual 64	java/io/File:exists	()Z
    //   617: ifeq -525 -> 92
    //   620: aload 6
    //   622: invokevirtual 67	java/io/File:delete	()Z
    //   625: pop
    //   626: goto -534 -> 92
    //   629: astore 7
    //   631: goto -539 -> 92
    //   634: astore_1
    //   635: aload_0
    //   636: invokevirtual 53	com/keniu/security/f/p:j	()I
    //   639: ifeq +29 -> 668
    //   642: new 55	java/io/File
    //   645: dup
    //   646: invokestatic 32	com/keniu/security/f/ab:a	()Lcom/keniu/security/f/ab;
    //   649: invokevirtual 57	com/keniu/security/f/ab:j	()Ljava/lang/String;
    //   652: invokespecial 60	java/io/File:<init>	(Ljava/lang/String;)V
    //   655: astore_2
    //   656: aload_2
    //   657: invokevirtual 64	java/io/File:exists	()Z
    //   660: ifeq +8 -> 668
    //   663: aload_2
    //   664: invokevirtual 67	java/io/File:delete	()Z
    //   667: pop
    //   668: aload_1
    //   669: athrow
    //   670: astore_3
    //   671: goto -3 -> 668
    //   674: astore 19
    //   676: aload 17
    //   678: astore 16
    //   680: goto -110 -> 570
    //   683: astore 37
    //   685: goto -593 -> 92
    //   688: iconst_1
    //   689: istore 15
    //   691: goto -357 -> 334
    //
    // Exception table:
    //   from	to	target	type
    //   124	153	156	java/lang/Exception
    //   267	296	299	java/lang/Exception
    //   352	381	384	java/lang/Exception
    //   466	495	498	java/lang/Exception
    //   531	560	563	java/lang/Exception
    //   398	412	568	finally
    //   0	43	583	java/lang/Exception
    //   99	117	583	java/lang/Exception
    //   161	260	583	java/lang/Exception
    //   304	345	583	java/lang/Exception
    //   454	459	583	java/lang/Exception
    //   503	524	583	java/lang/Exception
    //   575	583	583	java/lang/Exception
    //   597	626	629	java/lang/Exception
    //   0	43	634	finally
    //   99	117	634	finally
    //   161	260	634	finally
    //   304	345	634	finally
    //   454	459	634	finally
    //   503	524	634	finally
    //   575	583	634	finally
    //   585	590	634	finally
    //   642	668	670	java/lang/Exception
    //   412	454	674	finally
    //   63	92	683	java/lang/Exception
  }

  private boolean c()
  {
    if (this.A != null)
    {
      String str = ab.a().m();
      if ((!a(z.a(this.A, str))) || (!a(this.A, "mosecurity.apk", str)));
    }
    for (boolean bool = true; ; bool = false)
      return bool;
  }

  public final r a()
  {
    return this.C;
  }

  public final void a(h paramh1, h paramh2)
  {
    this.A = paramh1;
    this.B = paramh2;
  }

  // ERROR //
  public final void run()
  {
    // Byte code:
    //   0: aload_0
    //   1: iconst_0
    //   2: invokevirtual 73	com/keniu/security/f/p:c	(I)V
    //   5: aload_0
    //   6: iconst_3
    //   7: invokevirtual 92	com/keniu/security/f/p:d	(I)V
    //   10: aload_0
    //   11: invokevirtual 140	com/keniu/security/f/p:l	()Z
    //   14: ifne +95 -> 109
    //   17: aload_0
    //   18: getfield 27	com/keniu/security/f/p:A	Lcom/keniu/security/f/h;
    //   21: ifnull +95 -> 116
    //   24: invokestatic 32	com/keniu/security/f/ab:a	()Lcom/keniu/security/f/ab;
    //   27: invokevirtual 36	com/keniu/security/f/ab:m	()Ljava/lang/String;
    //   30: astore 39
    //   32: aload_0
    //   33: getfield 27	com/keniu/security/f/p:A	Lcom/keniu/security/f/h;
    //   36: aload 39
    //   38: invokestatic 41	com/keniu/security/f/z:a	(Lcom/keniu/security/f/h;Ljava/lang/String;)I
    //   41: invokestatic 44	com/keniu/security/f/p:a	(I)Z
    //   44: ifeq +72 -> 116
    //   47: aload_0
    //   48: getfield 27	com/keniu/security/f/p:A	Lcom/keniu/security/f/h;
    //   51: ldc 46
    //   53: aload 39
    //   55: invokestatic 49	com/keniu/security/f/p:a	(Lcom/keniu/security/f/h;Ljava/lang/String;Ljava/lang/String;)Z
    //   58: istore 40
    //   60: iload 40
    //   62: ifeq +54 -> 116
    //   65: iconst_1
    //   66: istore 9
    //   68: iload 9
    //   70: ifne +52 -> 122
    //   73: aload_0
    //   74: invokevirtual 53	com/keniu/security/f/p:j	()I
    //   77: ifeq +32 -> 109
    //   80: new 55	java/io/File
    //   83: dup
    //   84: invokestatic 32	com/keniu/security/f/ab:a	()Lcom/keniu/security/f/ab;
    //   87: invokevirtual 57	com/keniu/security/f/ab:j	()Ljava/lang/String;
    //   90: invokespecial 60	java/io/File:<init>	(Ljava/lang/String;)V
    //   93: astore 36
    //   95: aload 36
    //   97: invokevirtual 64	java/io/File:exists	()Z
    //   100: ifeq +9 -> 109
    //   103: aload 36
    //   105: invokevirtual 67	java/io/File:delete	()Z
    //   108: pop
    //   109: aload_0
    //   110: bipush 8
    //   112: invokevirtual 92	com/keniu/security/f/p:d	(I)V
    //   115: return
    //   116: iconst_0
    //   117: istore 9
    //   119: goto -51 -> 68
    //   122: invokestatic 32	com/keniu/security/f/ab:a	()Lcom/keniu/security/f/ab;
    //   125: astore 10
    //   127: aload 10
    //   129: invokevirtual 70	com/keniu/security/f/ab:i	()Z
    //   132: ifne +52 -> 184
    //   135: aload_0
    //   136: iconst_5
    //   137: invokevirtual 73	com/keniu/security/f/p:c	(I)V
    //   140: aload_0
    //   141: invokevirtual 53	com/keniu/security/f/p:j	()I
    //   144: ifeq -35 -> 109
    //   147: new 55	java/io/File
    //   150: dup
    //   151: invokestatic 32	com/keniu/security/f/ab:a	()Lcom/keniu/security/f/ab;
    //   154: invokevirtual 57	com/keniu/security/f/ab:j	()Ljava/lang/String;
    //   157: invokespecial 60	java/io/File:<init>	(Ljava/lang/String;)V
    //   160: astore 33
    //   162: aload 33
    //   164: invokevirtual 64	java/io/File:exists	()Z
    //   167: ifeq -58 -> 109
    //   170: aload 33
    //   172: invokevirtual 67	java/io/File:delete	()Z
    //   175: pop
    //   176: goto -67 -> 109
    //   179: astore 34
    //   181: goto -72 -> 109
    //   184: aload 10
    //   186: invokevirtual 36	com/keniu/security/f/ab:m	()Ljava/lang/String;
    //   189: astore 11
    //   191: aload_0
    //   192: getfield 75	com/keniu/security/f/p:B	Lcom/keniu/security/f/h;
    //   195: ldc 46
    //   197: aload 11
    //   199: invokestatic 78	com/keniu/security/f/z:a	(Lcom/keniu/security/f/h;Ljava/lang/String;Ljava/lang/String;)Ljava/lang/String;
    //   202: astore 12
    //   204: new 80	com/keniu/security/f/aa
    //   207: dup
    //   208: invokespecial 81	com/keniu/security/f/aa:<init>	()V
    //   211: astore 13
    //   213: aload 13
    //   215: aload_0
    //   216: getfield 75	com/keniu/security/f/p:B	Lcom/keniu/security/f/h;
    //   219: aload 12
    //   221: invokevirtual 84	com/keniu/security/f/aa:a	(Lcom/keniu/security/f/h;Ljava/lang/String;)V
    //   224: aload_0
    //   225: getfield 20	com/keniu/security/f/p:C	Lcom/keniu/security/f/r;
    //   228: aload 13
    //   230: getfield 87	com/keniu/security/f/aa:b	I
    //   233: putfield 89	com/keniu/security/f/r:a	I
    //   236: aload_0
    //   237: iconst_4
    //   238: invokevirtual 92	com/keniu/security/f/p:d	(I)V
    //   241: aload 10
    //   243: aload_0
    //   244: getfield 27	com/keniu/security/f/p:A	Lcom/keniu/security/f/h;
    //   247: ldc 94
    //   249: ldc 46
    //   251: invokevirtual 99	com/keniu/security/f/h:a	(Ljava/lang/String;Ljava/lang/String;)Ljava/lang/String;
    //   254: invokevirtual 103	com/keniu/security/f/ab:f	(Ljava/lang/String;)Z
    //   257: ifeq +70 -> 327
    //   260: aload_0
    //   261: getfield 20	com/keniu/security/f/p:C	Lcom/keniu/security/f/r;
    //   264: aload 13
    //   266: getfield 87	com/keniu/security/f/aa:b	I
    //   269: putfield 104	com/keniu/security/f/r:b	I
    //   272: aload_0
    //   273: iconst_5
    //   274: invokevirtual 92	com/keniu/security/f/p:d	(I)V
    //   277: aload_0
    //   278: bipush 7
    //   280: invokevirtual 92	com/keniu/security/f/p:d	(I)V
    //   283: aload_0
    //   284: invokevirtual 53	com/keniu/security/f/p:j	()I
    //   287: ifeq -178 -> 109
    //   290: new 55	java/io/File
    //   293: dup
    //   294: invokestatic 32	com/keniu/security/f/ab:a	()Lcom/keniu/security/f/ab;
    //   297: invokevirtual 57	com/keniu/security/f/ab:j	()Ljava/lang/String;
    //   300: invokespecial 60	java/io/File:<init>	(Ljava/lang/String;)V
    //   303: astore 24
    //   305: aload 24
    //   307: invokevirtual 64	java/io/File:exists	()Z
    //   310: ifeq -201 -> 109
    //   313: aload 24
    //   315: invokevirtual 67	java/io/File:delete	()Z
    //   318: pop
    //   319: goto -210 -> 109
    //   322: astore 25
    //   324: goto -215 -> 109
    //   327: aload 13
    //   329: invokevirtual 106	com/keniu/security/f/aa:b	()I
    //   332: istore 14
    //   334: invokestatic 112	com/keniu/security/f/f:e	()J
    //   337: iload 14
    //   339: i2l
    //   340: lcmp
    //   341: ifge +370 -> 711
    //   344: invokestatic 115	com/keniu/security/f/f:g	()J
    //   347: iload 14
    //   349: i2l
    //   350: lcmp
    //   351: iflt +61 -> 412
    //   354: goto +357 -> 711
    //   357: iload 15
    //   359: ifne +59 -> 418
    //   362: aload_0
    //   363: bipush 8
    //   365: invokevirtual 73	com/keniu/security/f/p:c	(I)V
    //   368: aload_0
    //   369: invokevirtual 53	com/keniu/security/f/p:j	()I
    //   372: ifeq -263 -> 109
    //   375: new 55	java/io/File
    //   378: dup
    //   379: invokestatic 32	com/keniu/security/f/ab:a	()Lcom/keniu/security/f/ab;
    //   382: invokevirtual 57	com/keniu/security/f/ab:j	()Ljava/lang/String;
    //   385: invokespecial 60	java/io/File:<init>	(Ljava/lang/String;)V
    //   388: astore 30
    //   390: aload 30
    //   392: invokevirtual 64	java/io/File:exists	()Z
    //   395: ifeq -286 -> 109
    //   398: aload 30
    //   400: invokevirtual 67	java/io/File:delete	()Z
    //   403: pop
    //   404: goto -295 -> 109
    //   407: astore 31
    //   409: goto -300 -> 109
    //   412: iconst_0
    //   413: istore 15
    //   415: goto -58 -> 357
    //   418: aconst_null
    //   419: astore 16
    //   421: new 117	java/io/FileOutputStream
    //   424: dup
    //   425: aload 10
    //   427: invokevirtual 57	com/keniu/security/f/ab:j	()Ljava/lang/String;
    //   430: invokespecial 118	java/io/FileOutputStream:<init>	(Ljava/lang/String;)V
    //   433: astore 17
    //   435: new 120	com/keniu/security/f/q
    //   438: dup
    //   439: aload_0
    //   440: aload 17
    //   442: invokespecial 123	com/keniu/security/f/q:<init>	(Lcom/keniu/security/f/p;Ljava/io/FileOutputStream;)V
    //   445: astore 18
    //   447: aload_0
    //   448: iconst_5
    //   449: invokevirtual 92	com/keniu/security/f/p:d	(I)V
    //   452: aload 10
    //   454: invokevirtual 125	com/keniu/security/f/ab:b	()Ljava/lang/String;
    //   457: aload 13
    //   459: aload 18
    //   461: invokestatic 128	com/keniu/security/f/p:a	(Ljava/lang/String;Lcom/keniu/security/f/aa;Lcom/keniu/security/f/af;)I
    //   464: istore 20
    //   466: iload 20
    //   468: ifeq +58 -> 526
    //   471: aload_0
    //   472: iload 20
    //   474: invokevirtual 73	com/keniu/security/f/p:c	(I)V
    //   477: aload 17
    //   479: invokevirtual 131	java/io/FileOutputStream:close	()V
    //   482: aload_0
    //   483: invokevirtual 53	com/keniu/security/f/p:j	()I
    //   486: ifeq -377 -> 109
    //   489: new 55	java/io/File
    //   492: dup
    //   493: invokestatic 32	com/keniu/security/f/ab:a	()Lcom/keniu/security/f/ab;
    //   496: invokevirtual 57	com/keniu/security/f/ab:j	()Ljava/lang/String;
    //   499: invokespecial 60	java/io/File:<init>	(Ljava/lang/String;)V
    //   502: astore 27
    //   504: aload 27
    //   506: invokevirtual 64	java/io/File:exists	()Z
    //   509: ifeq -400 -> 109
    //   512: aload 27
    //   514: invokevirtual 67	java/io/File:delete	()Z
    //   517: pop
    //   518: goto -409 -> 109
    //   521: astore 28
    //   523: goto -414 -> 109
    //   526: aload 17
    //   528: invokevirtual 131	java/io/FileOutputStream:close	()V
    //   531: aload 10
    //   533: aload 13
    //   535: invokevirtual 134	com/keniu/security/f/ab:a	(Lcom/keniu/security/f/aa;)Z
    //   538: ifne -261 -> 277
    //   541: aload_0
    //   542: bipush 7
    //   544: invokevirtual 73	com/keniu/security/f/p:c	(I)V
    //   547: aload_0
    //   548: invokevirtual 53	com/keniu/security/f/p:j	()I
    //   551: ifeq -442 -> 109
    //   554: new 55	java/io/File
    //   557: dup
    //   558: invokestatic 32	com/keniu/security/f/ab:a	()Lcom/keniu/security/f/ab;
    //   561: invokevirtual 57	com/keniu/security/f/ab:j	()Ljava/lang/String;
    //   564: invokespecial 60	java/io/File:<init>	(Ljava/lang/String;)V
    //   567: astore 21
    //   569: aload 21
    //   571: invokevirtual 64	java/io/File:exists	()Z
    //   574: ifeq -465 -> 109
    //   577: aload 21
    //   579: invokevirtual 67	java/io/File:delete	()Z
    //   582: pop
    //   583: goto -474 -> 109
    //   586: astore 22
    //   588: goto -479 -> 109
    //   591: astore 19
    //   593: aload 16
    //   595: ifnull +8 -> 603
    //   598: aload 16
    //   600: invokevirtual 131	java/io/FileOutputStream:close	()V
    //   603: aload 19
    //   605: athrow
    //   606: astore 5
    //   608: aload_0
    //   609: iconst_3
    //   610: invokevirtual 73	com/keniu/security/f/p:c	(I)V
    //   613: aload_0
    //   614: invokevirtual 53	com/keniu/security/f/p:j	()I
    //   617: ifeq -508 -> 109
    //   620: new 55	java/io/File
    //   623: dup
    //   624: invokestatic 32	com/keniu/security/f/ab:a	()Lcom/keniu/security/f/ab;
    //   627: invokevirtual 57	com/keniu/security/f/ab:j	()Ljava/lang/String;
    //   630: invokespecial 60	java/io/File:<init>	(Ljava/lang/String;)V
    //   633: astore 6
    //   635: aload 6
    //   637: invokevirtual 64	java/io/File:exists	()Z
    //   640: ifeq -531 -> 109
    //   643: aload 6
    //   645: invokevirtual 67	java/io/File:delete	()Z
    //   648: pop
    //   649: goto -540 -> 109
    //   652: astore 7
    //   654: goto -545 -> 109
    //   657: astore_1
    //   658: aload_0
    //   659: invokevirtual 53	com/keniu/security/f/p:j	()I
    //   662: ifeq +29 -> 691
    //   665: new 55	java/io/File
    //   668: dup
    //   669: invokestatic 32	com/keniu/security/f/ab:a	()Lcom/keniu/security/f/ab;
    //   672: invokevirtual 57	com/keniu/security/f/ab:j	()Ljava/lang/String;
    //   675: invokespecial 60	java/io/File:<init>	(Ljava/lang/String;)V
    //   678: astore_2
    //   679: aload_2
    //   680: invokevirtual 64	java/io/File:exists	()Z
    //   683: ifeq +8 -> 691
    //   686: aload_2
    //   687: invokevirtual 67	java/io/File:delete	()Z
    //   690: pop
    //   691: aload_1
    //   692: athrow
    //   693: astore_3
    //   694: goto -3 -> 691
    //   697: astore 19
    //   699: aload 17
    //   701: astore 16
    //   703: goto -110 -> 593
    //   706: astore 37
    //   708: goto -599 -> 109
    //   711: iconst_1
    //   712: istore 15
    //   714: goto -357 -> 357
    //
    // Exception table:
    //   from	to	target	type
    //   147	176	179	java/lang/Exception
    //   290	319	322	java/lang/Exception
    //   375	404	407	java/lang/Exception
    //   489	518	521	java/lang/Exception
    //   554	583	586	java/lang/Exception
    //   421	435	591	finally
    //   17	60	606	java/lang/Exception
    //   122	140	606	java/lang/Exception
    //   184	283	606	java/lang/Exception
    //   327	368	606	java/lang/Exception
    //   477	482	606	java/lang/Exception
    //   526	547	606	java/lang/Exception
    //   598	606	606	java/lang/Exception
    //   620	649	652	java/lang/Exception
    //   17	60	657	finally
    //   122	140	657	finally
    //   184	283	657	finally
    //   327	368	657	finally
    //   477	482	657	finally
    //   526	547	657	finally
    //   598	606	657	finally
    //   608	613	657	finally
    //   665	691	693	java/lang/Exception
    //   435	477	697	finally
    //   80	109	706	java/lang/Exception
  }
}

/* Location:           C:\Users\sandrocheng.21KUNPENG\Desktop\classes_dex2jar\
 * Qualified Name:     com.keniu.security.f.p
 * JD-Core Version:    0.6.2
 */