package com.keniu.security.f;

public final class w extends ae
{
  private h A;
  private h B;
  private y C = new y();

  public w()
  {
    super(3);
  }

  // ERROR //
  private void b()
  {
    // Byte code:
    //   0: aload_0
    //   1: getfield 27	com/keniu/security/f/w:A	Lcom/keniu/security/f/h;
    //   4: ifnull +892 -> 896
    //   7: invokestatic 32	com/keniu/security/f/ab:a	()Lcom/keniu/security/f/ab;
    //   10: invokevirtual 36	com/keniu/security/f/ab:n	()Ljava/lang/String;
    //   13: astore 40
    //   15: aload_0
    //   16: getfield 27	com/keniu/security/f/w:A	Lcom/keniu/security/f/h;
    //   19: ldc 38
    //   21: aload 40
    //   23: invokestatic 41	com/keniu/security/f/w:a	(Lcom/keniu/security/f/h;Ljava/lang/String;Ljava/lang/String;)Z
    //   26: ifeq +870 -> 896
    //   29: iconst_1
    //   30: istore_2
    //   31: goto +860 -> 891
    //   34: new 43	com/keniu/security/f/aa
    //   37: dup
    //   38: invokespecial 44	com/keniu/security/f/aa:<init>	()V
    //   41: astore_3
    //   42: invokestatic 32	com/keniu/security/f/ab:a	()Lcom/keniu/security/f/ab;
    //   45: astore 4
    //   47: new 46	java/util/HashMap
    //   50: dup
    //   51: invokespecial 47	java/util/HashMap:<init>	()V
    //   54: astore 5
    //   56: aload_0
    //   57: getfield 27	com/keniu/security/f/w:A	Lcom/keniu/security/f/h;
    //   60: ldc 49
    //   62: invokevirtual 54	com/keniu/security/f/h:a	(Ljava/lang/String;)Ljava/util/Collection;
    //   65: astore 6
    //   67: aload 6
    //   69: invokeinterface 60 1 0
    //   74: astore 7
    //   76: iconst_0
    //   77: istore 8
    //   79: aload 7
    //   81: invokeinterface 66 1 0
    //   86: ifeq +100 -> 186
    //   89: aload 7
    //   91: invokeinterface 70 1 0
    //   96: checkcast 72	java/lang/String
    //   99: astore 36
    //   101: aload 4
    //   103: aload 36
    //   105: invokevirtual 75	com/keniu/security/f/ab:a	(Ljava/lang/String;)Z
    //   108: ifeq -29 -> 79
    //   111: aload 4
    //   113: aload 36
    //   115: invokevirtual 79	com/keniu/security/f/ab:c	(Ljava/lang/String;)Ljava/lang/String;
    //   118: astore 37
    //   120: aload_0
    //   121: getfield 27	com/keniu/security/f/w:A	Lcom/keniu/security/f/h;
    //   124: aload 36
    //   126: aload 37
    //   128: invokestatic 41	com/keniu/security/f/w:a	(Lcom/keniu/security/f/h;Ljava/lang/String;Ljava/lang/String;)Z
    //   131: ifeq -52 -> 79
    //   134: aload 5
    //   136: aload 36
    //   138: aload 37
    //   140: invokeinterface 85 3 0
    //   145: pop
    //   146: aload_0
    //   147: getfield 87	com/keniu/security/f/w:B	Lcom/keniu/security/f/h;
    //   150: aload 36
    //   152: aload 4
    //   154: aload 36
    //   156: invokevirtual 79	com/keniu/security/f/ab:c	(Ljava/lang/String;)Ljava/lang/String;
    //   159: invokestatic 92	com/keniu/security/f/z:a	(Lcom/keniu/security/f/h;Ljava/lang/String;Ljava/lang/String;)Ljava/lang/String;
    //   162: astore 39
    //   164: aload_3
    //   165: aload_0
    //   166: getfield 87	com/keniu/security/f/w:B	Lcom/keniu/security/f/h;
    //   169: aload 39
    //   171: invokevirtual 95	com/keniu/security/f/aa:a	(Lcom/keniu/security/f/h;Ljava/lang/String;)V
    //   174: iload 8
    //   176: aload_3
    //   177: invokevirtual 98	com/keniu/security/f/aa:b	()I
    //   180: iadd
    //   181: istore 8
    //   183: goto -104 -> 79
    //   186: invokestatic 104	com/keniu/security/f/f:g	()J
    //   189: iload 8
    //   191: i2l
    //   192: lcmp
    //   193: iflt +29 -> 222
    //   196: iconst_1
    //   197: istore 9
    //   199: iload 9
    //   201: ifne +27 -> 228
    //   204: aload_0
    //   205: bipush 8
    //   207: invokevirtual 106	com/keniu/security/f/w:c	(I)V
    //   210: goto +685 -> 895
    //   213: astore_1
    //   214: aload_0
    //   215: iconst_3
    //   216: invokevirtual 106	com/keniu/security/f/w:c	(I)V
    //   219: goto +676 -> 895
    //   222: iconst_0
    //   223: istore 9
    //   225: goto -26 -> 199
    //   228: aload 6
    //   230: invokeinterface 60 1 0
    //   235: astore 10
    //   237: aload 4
    //   239: invokevirtual 108	com/keniu/security/f/ab:b	()Ljava/lang/String;
    //   242: astore 11
    //   244: aload 10
    //   246: invokeinterface 66 1 0
    //   251: ifeq +597 -> 848
    //   254: aload_0
    //   255: invokevirtual 111	com/keniu/security/f/w:l	()Z
    //   258: ifne +590 -> 848
    //   261: aload 10
    //   263: invokeinterface 70 1 0
    //   268: checkcast 72	java/lang/String
    //   271: astore 12
    //   273: aload 4
    //   275: aload 12
    //   277: invokevirtual 75	com/keniu/security/f/ab:a	(Ljava/lang/String;)Z
    //   280: ifeq -36 -> 244
    //   283: aload 5
    //   285: aload 12
    //   287: invokeinterface 115 2 0
    //   292: checkcast 72	java/lang/String
    //   295: astore 13
    //   297: aload 13
    //   299: ifnull -55 -> 244
    //   302: aload_0
    //   303: getfield 27	com/keniu/security/f/w:A	Lcom/keniu/security/f/h;
    //   306: aload 12
    //   308: aload 13
    //   310: invokestatic 41	com/keniu/security/f/w:a	(Lcom/keniu/security/f/h;Ljava/lang/String;Ljava/lang/String;)Z
    //   313: ifeq -69 -> 244
    //   316: aload_0
    //   317: getfield 87	com/keniu/security/f/w:B	Lcom/keniu/security/f/h;
    //   320: aload 12
    //   322: aload 4
    //   324: aload 12
    //   326: invokevirtual 79	com/keniu/security/f/ab:c	(Ljava/lang/String;)Ljava/lang/String;
    //   329: invokestatic 92	com/keniu/security/f/z:a	(Lcom/keniu/security/f/h;Ljava/lang/String;Ljava/lang/String;)Ljava/lang/String;
    //   332: astore 14
    //   334: aload_3
    //   335: aload_0
    //   336: getfield 87	com/keniu/security/f/w:B	Lcom/keniu/security/f/h;
    //   339: aload 14
    //   341: invokevirtual 95	com/keniu/security/f/aa:a	(Lcom/keniu/security/f/h;Ljava/lang/String;)V
    //   344: aload_0
    //   345: getfield 20	com/keniu/security/f/w:C	Lcom/keniu/security/f/y;
    //   348: aload 12
    //   350: putfield 118	com/keniu/security/f/y:a	Ljava/lang/String;
    //   353: aload_0
    //   354: getfield 20	com/keniu/security/f/w:C	Lcom/keniu/security/f/y;
    //   357: aload_3
    //   358: getfield 121	com/keniu/security/f/aa:b	I
    //   361: putfield 122	com/keniu/security/f/y:b	I
    //   364: aload_0
    //   365: getfield 20	com/keniu/security/f/w:C	Lcom/keniu/security/f/y;
    //   368: iconst_0
    //   369: putfield 124	com/keniu/security/f/y:c	I
    //   372: aload_0
    //   373: getfield 20	com/keniu/security/f/w:C	Lcom/keniu/security/f/y;
    //   376: aload 4
    //   378: aload 12
    //   380: invokevirtual 127	com/keniu/security/f/ab:d	(Ljava/lang/String;)Ljava/lang/String;
    //   383: putfield 129	com/keniu/security/f/y:d	Ljava/lang/String;
    //   386: aload_0
    //   387: iconst_4
    //   388: invokevirtual 131	com/keniu/security/f/w:d	(I)V
    //   391: new 133	java/io/FileOutputStream
    //   394: dup
    //   395: aload 4
    //   397: aload 12
    //   399: invokevirtual 136	com/keniu/security/f/ab:e	(Ljava/lang/String;)Ljava/lang/String;
    //   402: invokespecial 139	java/io/FileOutputStream:<init>	(Ljava/lang/String;)V
    //   405: astore 15
    //   407: new 141	com/keniu/security/f/x
    //   410: dup
    //   411: aload_0
    //   412: aload 15
    //   414: invokespecial 144	com/keniu/security/f/x:<init>	(Lcom/keniu/security/f/w;Ljava/io/FileOutputStream;)V
    //   417: astore 16
    //   419: aload_0
    //   420: iconst_5
    //   421: invokevirtual 131	com/keniu/security/f/w:d	(I)V
    //   424: aload 11
    //   426: aload_3
    //   427: aload 16
    //   429: invokestatic 147	com/keniu/security/f/w:a	(Ljava/lang/String;Lcom/keniu/security/f/aa;Lcom/keniu/security/f/af;)I
    //   432: istore 22
    //   434: iload 22
    //   436: ifeq +54 -> 490
    //   439: aload_0
    //   440: iload 22
    //   442: invokevirtual 106	com/keniu/security/f/w:c	(I)V
    //   445: aload 15
    //   447: invokevirtual 150	java/io/FileOutputStream:close	()V
    //   450: aload_0
    //   451: invokevirtual 153	com/keniu/security/f/w:j	()I
    //   454: ifeq +441 -> 895
    //   457: new 155	java/io/File
    //   460: dup
    //   461: aload 4
    //   463: aload 12
    //   465: invokevirtual 136	com/keniu/security/f/ab:e	(Ljava/lang/String;)Ljava/lang/String;
    //   468: invokespecial 156	java/io/File:<init>	(Ljava/lang/String;)V
    //   471: astore 34
    //   473: aload 34
    //   475: invokevirtual 159	java/io/File:exists	()Z
    //   478: ifeq +417 -> 895
    //   481: aload 34
    //   483: invokevirtual 162	java/io/File:delete	()Z
    //   486: pop
    //   487: goto +408 -> 895
    //   490: aload 15
    //   492: invokevirtual 150	java/io/FileOutputStream:close	()V
    //   495: aload_0
    //   496: invokevirtual 153	com/keniu/security/f/w:j	()I
    //   499: ifeq +33 -> 532
    //   502: new 155	java/io/File
    //   505: dup
    //   506: aload 4
    //   508: aload 12
    //   510: invokevirtual 136	com/keniu/security/f/ab:e	(Ljava/lang/String;)Ljava/lang/String;
    //   513: invokespecial 156	java/io/File:<init>	(Ljava/lang/String;)V
    //   516: astore 23
    //   518: aload 23
    //   520: invokevirtual 159	java/io/File:exists	()Z
    //   523: ifeq +9 -> 532
    //   526: aload 23
    //   528: invokevirtual 162	java/io/File:delete	()Z
    //   531: pop
    //   532: aload 4
    //   534: aload 12
    //   536: invokevirtual 164	com/keniu/security/f/ab:b	(Ljava/lang/String;)Ljava/lang/String;
    //   539: astore 24
    //   541: aload 4
    //   543: aload 12
    //   545: invokevirtual 136	com/keniu/security/f/ab:e	(Ljava/lang/String;)Ljava/lang/String;
    //   548: astore 25
    //   550: aload_3
    //   551: getfield 168	com/keniu/security/f/aa:f	Z
    //   554: ifeq +81 -> 635
    //   557: aload_3
    //   558: getfield 170	com/keniu/security/f/aa:e	I
    //   561: ifne +324 -> 885
    //   564: aload_3
    //   565: getfield 171	com/keniu/security/f/aa:d	Ljava/lang/String;
    //   568: astore 31
    //   570: aload 25
    //   572: new 173	java/lang/StringBuilder
    //   575: dup
    //   576: invokespecial 174	java/lang/StringBuilder:<init>	()V
    //   579: aload 24
    //   581: invokevirtual 178	java/lang/StringBuilder:append	(Ljava/lang/String;)Ljava/lang/StringBuilder;
    //   584: ldc 180
    //   586: invokevirtual 178	java/lang/StringBuilder:append	(Ljava/lang/String;)Ljava/lang/StringBuilder;
    //   589: invokevirtual 183	java/lang/StringBuilder:toString	()Ljava/lang/String;
    //   592: aload 31
    //   594: invokestatic 186	com/keniu/security/f/f:a	(Ljava/lang/String;Ljava/lang/String;Ljava/lang/String;)Z
    //   597: ifeq +278 -> 875
    //   600: new 155	java/io/File
    //   603: dup
    //   604: aload 25
    //   606: invokespecial 156	java/io/File:<init>	(Ljava/lang/String;)V
    //   609: invokevirtual 162	java/io/File:delete	()Z
    //   612: pop
    //   613: new 173	java/lang/StringBuilder
    //   616: dup
    //   617: invokespecial 174	java/lang/StringBuilder:<init>	()V
    //   620: aload 24
    //   622: invokevirtual 178	java/lang/StringBuilder:append	(Ljava/lang/String;)Ljava/lang/StringBuilder;
    //   625: ldc 180
    //   627: invokevirtual 178	java/lang/StringBuilder:append	(Ljava/lang/String;)Ljava/lang/StringBuilder;
    //   630: invokevirtual 183	java/lang/StringBuilder:toString	()Ljava/lang/String;
    //   633: astore 25
    //   635: aload_3
    //   636: getfield 170	com/keniu/security/f/aa:e	I
    //   639: iconst_1
    //   640: if_icmpne +171 -> 811
    //   643: aload 24
    //   645: aload 25
    //   647: new 173	java/lang/StringBuilder
    //   650: dup
    //   651: invokespecial 174	java/lang/StringBuilder:<init>	()V
    //   654: aload 24
    //   656: invokevirtual 178	java/lang/StringBuilder:append	(Ljava/lang/String;)Ljava/lang/StringBuilder;
    //   659: ldc 188
    //   661: invokevirtual 178	java/lang/StringBuilder:append	(Ljava/lang/String;)Ljava/lang/StringBuilder;
    //   664: invokevirtual 183	java/lang/StringBuilder:toString	()Ljava/lang/String;
    //   667: aload_3
    //   668: getfield 171	com/keniu/security/f/aa:d	Ljava/lang/String;
    //   671: invokestatic 191	com/keniu/security/f/f:a	(Ljava/lang/String;Ljava/lang/String;Ljava/lang/String;Ljava/lang/String;)Z
    //   674: ifeq +201 -> 875
    //   677: new 155	java/io/File
    //   680: dup
    //   681: aload 25
    //   683: invokespecial 156	java/io/File:<init>	(Ljava/lang/String;)V
    //   686: invokevirtual 162	java/io/File:delete	()Z
    //   689: pop
    //   690: new 173	java/lang/StringBuilder
    //   693: dup
    //   694: invokespecial 174	java/lang/StringBuilder:<init>	()V
    //   697: aload 24
    //   699: invokevirtual 178	java/lang/StringBuilder:append	(Ljava/lang/String;)Ljava/lang/StringBuilder;
    //   702: ldc 188
    //   704: invokevirtual 178	java/lang/StringBuilder:append	(Ljava/lang/String;)Ljava/lang/StringBuilder;
    //   707: invokevirtual 183	java/lang/StringBuilder:toString	()Ljava/lang/String;
    //   710: astore 25
    //   712: aload 25
    //   714: aload 24
    //   716: invokestatic 194	com/keniu/security/f/f:b	(Ljava/lang/String;Ljava/lang/String;)Z
    //   719: istore 29
    //   721: aload 25
    //   723: astore 26
    //   725: iload 29
    //   727: istore 27
    //   729: iload 27
    //   731: ifne +16 -> 747
    //   734: new 155	java/io/File
    //   737: dup
    //   738: aload 26
    //   740: invokespecial 156	java/io/File:<init>	(Ljava/lang/String;)V
    //   743: invokevirtual 162	java/io/File:delete	()Z
    //   746: pop
    //   747: iload 27
    //   749: ifne +90 -> 839
    //   752: aload_0
    //   753: bipush 7
    //   755: invokevirtual 106	com/keniu/security/f/w:c	(I)V
    //   758: goto +137 -> 895
    //   761: aload 18
    //   763: ifnull +8 -> 771
    //   766: aload 18
    //   768: invokevirtual 150	java/io/FileOutputStream:close	()V
    //   771: aload_0
    //   772: invokevirtual 153	com/keniu/security/f/w:j	()I
    //   775: ifeq +33 -> 808
    //   778: new 155	java/io/File
    //   781: dup
    //   782: aload 4
    //   784: aload 12
    //   786: invokevirtual 136	com/keniu/security/f/ab:e	(Ljava/lang/String;)Ljava/lang/String;
    //   789: invokespecial 156	java/io/File:<init>	(Ljava/lang/String;)V
    //   792: astore 20
    //   794: aload 20
    //   796: invokevirtual 159	java/io/File:exists	()Z
    //   799: ifeq +9 -> 808
    //   802: aload 20
    //   804: invokevirtual 162	java/io/File:delete	()Z
    //   807: pop
    //   808: aload 19
    //   810: athrow
    //   811: aload_3
    //   812: getfield 170	com/keniu/security/f/aa:e	I
    //   815: iconst_2
    //   816: if_icmpne -104 -> 712
    //   819: aload 25
    //   821: aload 24
    //   823: invokestatic 198	com/keniu/security/f/l:a	(Ljava/lang/String;Ljava/lang/String;)Z
    //   826: ifeq +49 -> 875
    //   829: aload 25
    //   831: astore 26
    //   833: iconst_1
    //   834: istore 27
    //   836: goto -107 -> 729
    //   839: aload_0
    //   840: bipush 7
    //   842: invokevirtual 131	com/keniu/security/f/w:d	(I)V
    //   845: goto -601 -> 244
    //   848: aload 4
    //   850: aload_0
    //   851: getfield 27	com/keniu/security/f/w:A	Lcom/keniu/security/f/h;
    //   854: ldc 49
    //   856: ldc 38
    //   858: invokevirtual 201	com/keniu/security/f/h:a	(Ljava/lang/String;Ljava/lang/String;)Ljava/lang/String;
    //   861: invokevirtual 203	com/keniu/security/f/ab:g	(Ljava/lang/String;)V
    //   864: goto +31 -> 895
    //   867: astore 19
    //   869: aconst_null
    //   870: astore 18
    //   872: goto -111 -> 761
    //   875: aload 25
    //   877: astore 26
    //   879: iconst_0
    //   880: istore 27
    //   882: goto -153 -> 729
    //   885: aconst_null
    //   886: astore 31
    //   888: goto -318 -> 570
    //   891: iload_2
    //   892: ifne -858 -> 34
    //   895: return
    //   896: iconst_0
    //   897: istore_2
    //   898: goto -7 -> 891
    //   901: astore 17
    //   903: aload 15
    //   905: astore 18
    //   907: aload 17
    //   909: astore 19
    //   911: goto -150 -> 761
    //
    // Exception table:
    //   from	to	target	type
    //   0	210	213	java/lang/Exception
    //   228	391	213	java/lang/Exception
    //   445	864	213	java/lang/Exception
    //   391	407	867	finally
    //   407	445	901	finally
  }

  private boolean c()
  {
    if (this.A != null)
    {
      String str = ab.a().n();
      if (!a(this.A, "data", str));
    }
    for (boolean bool = true; ; bool = false)
      return bool;
  }

  public final y a()
  {
    return this.C;
  }

  public final void a(h paramh1, h paramh2)
  {
    this.A = paramh1;
    this.B = paramh2;
  }

  // ERROR //
  public final void run()
  {
    // Byte code:
    //   0: aload_0
    //   1: iconst_0
    //   2: invokevirtual 106	com/keniu/security/f/w:c	(I)V
    //   5: aload_0
    //   6: iconst_3
    //   7: invokevirtual 131	com/keniu/security/f/w:d	(I)V
    //   10: aload_0
    //   11: invokevirtual 111	com/keniu/security/f/w:l	()Z
    //   14: ifne +42 -> 56
    //   17: aload_0
    //   18: getfield 27	com/keniu/security/f/w:A	Lcom/keniu/security/f/h;
    //   21: ifnull +42 -> 63
    //   24: invokestatic 32	com/keniu/security/f/ab:a	()Lcom/keniu/security/f/ab;
    //   27: invokevirtual 36	com/keniu/security/f/ab:n	()Ljava/lang/String;
    //   30: astore 41
    //   32: aload_0
    //   33: getfield 27	com/keniu/security/f/w:A	Lcom/keniu/security/f/h;
    //   36: ldc 38
    //   38: aload 41
    //   40: invokestatic 41	com/keniu/security/f/w:a	(Lcom/keniu/security/f/h;Ljava/lang/String;Ljava/lang/String;)Z
    //   43: istore 42
    //   45: iload 42
    //   47: ifeq +16 -> 63
    //   50: iconst_1
    //   51: istore_2
    //   52: iload_2
    //   53: ifne +15 -> 68
    //   56: aload_0
    //   57: bipush 8
    //   59: invokevirtual 131	com/keniu/security/f/w:d	(I)V
    //   62: return
    //   63: iconst_0
    //   64: istore_2
    //   65: goto -13 -> 52
    //   68: new 43	com/keniu/security/f/aa
    //   71: dup
    //   72: invokespecial 44	com/keniu/security/f/aa:<init>	()V
    //   75: astore_3
    //   76: invokestatic 32	com/keniu/security/f/ab:a	()Lcom/keniu/security/f/ab;
    //   79: astore 4
    //   81: new 46	java/util/HashMap
    //   84: dup
    //   85: invokespecial 47	java/util/HashMap:<init>	()V
    //   88: astore 5
    //   90: aload_0
    //   91: getfield 27	com/keniu/security/f/w:A	Lcom/keniu/security/f/h;
    //   94: ldc 49
    //   96: invokevirtual 54	com/keniu/security/f/h:a	(Ljava/lang/String;)Ljava/util/Collection;
    //   99: astore 6
    //   101: aload 6
    //   103: invokeinterface 60 1 0
    //   108: astore 7
    //   110: iconst_0
    //   111: istore 8
    //   113: aload 7
    //   115: invokeinterface 66 1 0
    //   120: ifeq +100 -> 220
    //   123: aload 7
    //   125: invokeinterface 70 1 0
    //   130: checkcast 72	java/lang/String
    //   133: astore 37
    //   135: aload 4
    //   137: aload 37
    //   139: invokevirtual 75	com/keniu/security/f/ab:a	(Ljava/lang/String;)Z
    //   142: ifeq -29 -> 113
    //   145: aload 4
    //   147: aload 37
    //   149: invokevirtual 79	com/keniu/security/f/ab:c	(Ljava/lang/String;)Ljava/lang/String;
    //   152: astore 38
    //   154: aload_0
    //   155: getfield 27	com/keniu/security/f/w:A	Lcom/keniu/security/f/h;
    //   158: aload 37
    //   160: aload 38
    //   162: invokestatic 41	com/keniu/security/f/w:a	(Lcom/keniu/security/f/h;Ljava/lang/String;Ljava/lang/String;)Z
    //   165: ifeq -52 -> 113
    //   168: aload 5
    //   170: aload 37
    //   172: aload 38
    //   174: invokeinterface 85 3 0
    //   179: pop
    //   180: aload_0
    //   181: getfield 87	com/keniu/security/f/w:B	Lcom/keniu/security/f/h;
    //   184: aload 37
    //   186: aload 4
    //   188: aload 37
    //   190: invokevirtual 79	com/keniu/security/f/ab:c	(Ljava/lang/String;)Ljava/lang/String;
    //   193: invokestatic 92	com/keniu/security/f/z:a	(Lcom/keniu/security/f/h;Ljava/lang/String;Ljava/lang/String;)Ljava/lang/String;
    //   196: astore 40
    //   198: aload_3
    //   199: aload_0
    //   200: getfield 87	com/keniu/security/f/w:B	Lcom/keniu/security/f/h;
    //   203: aload 40
    //   205: invokevirtual 95	com/keniu/security/f/aa:a	(Lcom/keniu/security/f/h;Ljava/lang/String;)V
    //   208: iload 8
    //   210: aload_3
    //   211: invokevirtual 98	com/keniu/security/f/aa:b	()I
    //   214: iadd
    //   215: istore 8
    //   217: goto -104 -> 113
    //   220: invokestatic 104	com/keniu/security/f/f:g	()J
    //   223: iload 8
    //   225: i2l
    //   226: lcmp
    //   227: iflt +29 -> 256
    //   230: iconst_1
    //   231: istore 9
    //   233: iload 9
    //   235: ifne +27 -> 262
    //   238: aload_0
    //   239: bipush 8
    //   241: invokevirtual 106	com/keniu/security/f/w:c	(I)V
    //   244: goto -188 -> 56
    //   247: astore_1
    //   248: aload_0
    //   249: iconst_3
    //   250: invokevirtual 106	com/keniu/security/f/w:c	(I)V
    //   253: goto -197 -> 56
    //   256: iconst_0
    //   257: istore 9
    //   259: goto -26 -> 233
    //   262: aload 6
    //   264: invokeinterface 60 1 0
    //   269: astore 10
    //   271: aload 4
    //   273: invokevirtual 108	com/keniu/security/f/ab:b	()Ljava/lang/String;
    //   276: astore 11
    //   278: aload 10
    //   280: invokeinterface 66 1 0
    //   285: ifeq +604 -> 889
    //   288: aload_0
    //   289: invokevirtual 111	com/keniu/security/f/w:l	()Z
    //   292: ifne +597 -> 889
    //   295: aload 10
    //   297: invokeinterface 70 1 0
    //   302: checkcast 72	java/lang/String
    //   305: astore 12
    //   307: aload 4
    //   309: aload 12
    //   311: invokevirtual 75	com/keniu/security/f/ab:a	(Ljava/lang/String;)Z
    //   314: ifeq -36 -> 278
    //   317: aload 5
    //   319: aload 12
    //   321: invokeinterface 115 2 0
    //   326: checkcast 72	java/lang/String
    //   329: astore 13
    //   331: aload 13
    //   333: ifnull -55 -> 278
    //   336: aload_0
    //   337: getfield 27	com/keniu/security/f/w:A	Lcom/keniu/security/f/h;
    //   340: aload 12
    //   342: aload 13
    //   344: invokestatic 41	com/keniu/security/f/w:a	(Lcom/keniu/security/f/h;Ljava/lang/String;Ljava/lang/String;)Z
    //   347: ifeq -69 -> 278
    //   350: aload_0
    //   351: getfield 87	com/keniu/security/f/w:B	Lcom/keniu/security/f/h;
    //   354: aload 12
    //   356: aload 4
    //   358: aload 12
    //   360: invokevirtual 79	com/keniu/security/f/ab:c	(Ljava/lang/String;)Ljava/lang/String;
    //   363: invokestatic 92	com/keniu/security/f/z:a	(Lcom/keniu/security/f/h;Ljava/lang/String;Ljava/lang/String;)Ljava/lang/String;
    //   366: astore 14
    //   368: aload_3
    //   369: aload_0
    //   370: getfield 87	com/keniu/security/f/w:B	Lcom/keniu/security/f/h;
    //   373: aload 14
    //   375: invokevirtual 95	com/keniu/security/f/aa:a	(Lcom/keniu/security/f/h;Ljava/lang/String;)V
    //   378: aload_0
    //   379: getfield 20	com/keniu/security/f/w:C	Lcom/keniu/security/f/y;
    //   382: aload 12
    //   384: putfield 118	com/keniu/security/f/y:a	Ljava/lang/String;
    //   387: aload_0
    //   388: getfield 20	com/keniu/security/f/w:C	Lcom/keniu/security/f/y;
    //   391: aload_3
    //   392: getfield 121	com/keniu/security/f/aa:b	I
    //   395: putfield 122	com/keniu/security/f/y:b	I
    //   398: aload_0
    //   399: getfield 20	com/keniu/security/f/w:C	Lcom/keniu/security/f/y;
    //   402: iconst_0
    //   403: putfield 124	com/keniu/security/f/y:c	I
    //   406: aload_0
    //   407: getfield 20	com/keniu/security/f/w:C	Lcom/keniu/security/f/y;
    //   410: aload 4
    //   412: aload 12
    //   414: invokevirtual 127	com/keniu/security/f/ab:d	(Ljava/lang/String;)Ljava/lang/String;
    //   417: putfield 129	com/keniu/security/f/y:d	Ljava/lang/String;
    //   420: aload_0
    //   421: iconst_4
    //   422: invokevirtual 131	com/keniu/security/f/w:d	(I)V
    //   425: new 133	java/io/FileOutputStream
    //   428: dup
    //   429: aload 4
    //   431: aload 12
    //   433: invokevirtual 136	com/keniu/security/f/ab:e	(Ljava/lang/String;)Ljava/lang/String;
    //   436: invokespecial 139	java/io/FileOutputStream:<init>	(Ljava/lang/String;)V
    //   439: astore 15
    //   441: new 141	com/keniu/security/f/x
    //   444: dup
    //   445: aload_0
    //   446: aload 15
    //   448: invokespecial 144	com/keniu/security/f/x:<init>	(Lcom/keniu/security/f/w;Ljava/io/FileOutputStream;)V
    //   451: astore 16
    //   453: aload_0
    //   454: iconst_5
    //   455: invokevirtual 131	com/keniu/security/f/w:d	(I)V
    //   458: aload 11
    //   460: aload_3
    //   461: aload 16
    //   463: invokestatic 147	com/keniu/security/f/w:a	(Ljava/lang/String;Lcom/keniu/security/f/aa;Lcom/keniu/security/f/af;)I
    //   466: istore 21
    //   468: iload 21
    //   470: ifeq +54 -> 524
    //   473: aload_0
    //   474: iload 21
    //   476: invokevirtual 106	com/keniu/security/f/w:c	(I)V
    //   479: aload 15
    //   481: invokevirtual 150	java/io/FileOutputStream:close	()V
    //   484: aload_0
    //   485: invokevirtual 153	com/keniu/security/f/w:j	()I
    //   488: ifeq -432 -> 56
    //   491: new 155	java/io/File
    //   494: dup
    //   495: aload 4
    //   497: aload 12
    //   499: invokevirtual 136	com/keniu/security/f/ab:e	(Ljava/lang/String;)Ljava/lang/String;
    //   502: invokespecial 156	java/io/File:<init>	(Ljava/lang/String;)V
    //   505: astore 34
    //   507: aload 34
    //   509: invokevirtual 159	java/io/File:exists	()Z
    //   512: ifeq -456 -> 56
    //   515: aload 34
    //   517: invokevirtual 162	java/io/File:delete	()Z
    //   520: pop
    //   521: goto -465 -> 56
    //   524: aload 15
    //   526: invokevirtual 150	java/io/FileOutputStream:close	()V
    //   529: aload_0
    //   530: invokevirtual 153	com/keniu/security/f/w:j	()I
    //   533: ifeq +33 -> 566
    //   536: new 155	java/io/File
    //   539: dup
    //   540: aload 4
    //   542: aload 12
    //   544: invokevirtual 136	com/keniu/security/f/ab:e	(Ljava/lang/String;)Ljava/lang/String;
    //   547: invokespecial 156	java/io/File:<init>	(Ljava/lang/String;)V
    //   550: astore 22
    //   552: aload 22
    //   554: invokevirtual 159	java/io/File:exists	()Z
    //   557: ifeq +9 -> 566
    //   560: aload 22
    //   562: invokevirtual 162	java/io/File:delete	()Z
    //   565: pop
    //   566: aload 4
    //   568: aload 12
    //   570: invokevirtual 164	com/keniu/security/f/ab:b	(Ljava/lang/String;)Ljava/lang/String;
    //   573: astore 23
    //   575: aload 4
    //   577: aload 12
    //   579: invokevirtual 136	com/keniu/security/f/ab:e	(Ljava/lang/String;)Ljava/lang/String;
    //   582: astore 24
    //   584: aload_3
    //   585: getfield 168	com/keniu/security/f/aa:f	Z
    //   588: ifeq +88 -> 676
    //   591: aload_3
    //   592: getfield 170	com/keniu/security/f/aa:e	I
    //   595: istore 30
    //   597: aconst_null
    //   598: astore 31
    //   600: iload 30
    //   602: ifne +9 -> 611
    //   605: aload_3
    //   606: getfield 171	com/keniu/security/f/aa:d	Ljava/lang/String;
    //   609: astore 31
    //   611: aload 24
    //   613: new 173	java/lang/StringBuilder
    //   616: dup
    //   617: invokespecial 174	java/lang/StringBuilder:<init>	()V
    //   620: aload 23
    //   622: invokevirtual 178	java/lang/StringBuilder:append	(Ljava/lang/String;)Ljava/lang/StringBuilder;
    //   625: ldc 180
    //   627: invokevirtual 178	java/lang/StringBuilder:append	(Ljava/lang/String;)Ljava/lang/StringBuilder;
    //   630: invokevirtual 183	java/lang/StringBuilder:toString	()Ljava/lang/String;
    //   633: aload 31
    //   635: invokestatic 186	com/keniu/security/f/f:a	(Ljava/lang/String;Ljava/lang/String;Ljava/lang/String;)Z
    //   638: ifeq +282 -> 920
    //   641: new 155	java/io/File
    //   644: dup
    //   645: aload 24
    //   647: invokespecial 156	java/io/File:<init>	(Ljava/lang/String;)V
    //   650: invokevirtual 162	java/io/File:delete	()Z
    //   653: pop
    //   654: new 173	java/lang/StringBuilder
    //   657: dup
    //   658: invokespecial 174	java/lang/StringBuilder:<init>	()V
    //   661: aload 23
    //   663: invokevirtual 178	java/lang/StringBuilder:append	(Ljava/lang/String;)Ljava/lang/StringBuilder;
    //   666: ldc 180
    //   668: invokevirtual 178	java/lang/StringBuilder:append	(Ljava/lang/String;)Ljava/lang/StringBuilder;
    //   671: invokevirtual 183	java/lang/StringBuilder:toString	()Ljava/lang/String;
    //   674: astore 24
    //   676: aload_3
    //   677: getfield 170	com/keniu/security/f/aa:e	I
    //   680: iconst_1
    //   681: if_icmpne +171 -> 852
    //   684: aload 23
    //   686: aload 24
    //   688: new 173	java/lang/StringBuilder
    //   691: dup
    //   692: invokespecial 174	java/lang/StringBuilder:<init>	()V
    //   695: aload 23
    //   697: invokevirtual 178	java/lang/StringBuilder:append	(Ljava/lang/String;)Ljava/lang/StringBuilder;
    //   700: ldc 188
    //   702: invokevirtual 178	java/lang/StringBuilder:append	(Ljava/lang/String;)Ljava/lang/StringBuilder;
    //   705: invokevirtual 183	java/lang/StringBuilder:toString	()Ljava/lang/String;
    //   708: aload_3
    //   709: getfield 171	com/keniu/security/f/aa:d	Ljava/lang/String;
    //   712: invokestatic 191	com/keniu/security/f/f:a	(Ljava/lang/String;Ljava/lang/String;Ljava/lang/String;Ljava/lang/String;)Z
    //   715: ifeq +205 -> 920
    //   718: new 155	java/io/File
    //   721: dup
    //   722: aload 24
    //   724: invokespecial 156	java/io/File:<init>	(Ljava/lang/String;)V
    //   727: invokevirtual 162	java/io/File:delete	()Z
    //   730: pop
    //   731: new 173	java/lang/StringBuilder
    //   734: dup
    //   735: invokespecial 174	java/lang/StringBuilder:<init>	()V
    //   738: aload 23
    //   740: invokevirtual 178	java/lang/StringBuilder:append	(Ljava/lang/String;)Ljava/lang/StringBuilder;
    //   743: ldc 188
    //   745: invokevirtual 178	java/lang/StringBuilder:append	(Ljava/lang/String;)Ljava/lang/StringBuilder;
    //   748: invokevirtual 183	java/lang/StringBuilder:toString	()Ljava/lang/String;
    //   751: astore 24
    //   753: aload 24
    //   755: aload 23
    //   757: invokestatic 194	com/keniu/security/f/f:b	(Ljava/lang/String;Ljava/lang/String;)Z
    //   760: istore 28
    //   762: aload 24
    //   764: astore 25
    //   766: iload 28
    //   768: istore 26
    //   770: iload 26
    //   772: ifne +16 -> 788
    //   775: new 155	java/io/File
    //   778: dup
    //   779: aload 25
    //   781: invokespecial 156	java/io/File:<init>	(Ljava/lang/String;)V
    //   784: invokevirtual 162	java/io/File:delete	()Z
    //   787: pop
    //   788: iload 26
    //   790: ifne +90 -> 880
    //   793: aload_0
    //   794: bipush 7
    //   796: invokevirtual 106	com/keniu/security/f/w:c	(I)V
    //   799: goto -743 -> 56
    //   802: aload 18
    //   804: ifnull +8 -> 812
    //   807: aload 18
    //   809: invokevirtual 150	java/io/FileOutputStream:close	()V
    //   812: aload_0
    //   813: invokevirtual 153	com/keniu/security/f/w:j	()I
    //   816: ifeq +33 -> 849
    //   819: new 155	java/io/File
    //   822: dup
    //   823: aload 4
    //   825: aload 12
    //   827: invokevirtual 136	com/keniu/security/f/ab:e	(Ljava/lang/String;)Ljava/lang/String;
    //   830: invokespecial 156	java/io/File:<init>	(Ljava/lang/String;)V
    //   833: astore 19
    //   835: aload 19
    //   837: invokevirtual 159	java/io/File:exists	()Z
    //   840: ifeq +9 -> 849
    //   843: aload 19
    //   845: invokevirtual 162	java/io/File:delete	()Z
    //   848: pop
    //   849: aload 17
    //   851: athrow
    //   852: aload_3
    //   853: getfield 170	com/keniu/security/f/aa:e	I
    //   856: iconst_2
    //   857: if_icmpne -104 -> 753
    //   860: aload 24
    //   862: aload 23
    //   864: invokestatic 198	com/keniu/security/f/l:a	(Ljava/lang/String;Ljava/lang/String;)Z
    //   867: ifeq +53 -> 920
    //   870: aload 24
    //   872: astore 25
    //   874: iconst_1
    //   875: istore 26
    //   877: goto -107 -> 770
    //   880: aload_0
    //   881: bipush 7
    //   883: invokevirtual 131	com/keniu/security/f/w:d	(I)V
    //   886: goto -608 -> 278
    //   889: aload 4
    //   891: aload_0
    //   892: getfield 27	com/keniu/security/f/w:A	Lcom/keniu/security/f/h;
    //   895: ldc 49
    //   897: ldc 38
    //   899: invokevirtual 201	com/keniu/security/f/h:a	(Ljava/lang/String;Ljava/lang/String;)Ljava/lang/String;
    //   902: invokevirtual 203	com/keniu/security/f/ab:g	(Ljava/lang/String;)V
    //   905: goto -849 -> 56
    //   908: astore 36
    //   910: aload 36
    //   912: astore 17
    //   914: aconst_null
    //   915: astore 18
    //   917: goto -115 -> 802
    //   920: aload 24
    //   922: astore 25
    //   924: iconst_0
    //   925: istore 26
    //   927: goto -157 -> 770
    //   930: astore 17
    //   932: aload 15
    //   934: astore 18
    //   936: goto -134 -> 802
    //
    // Exception table:
    //   from	to	target	type
    //   17	45	247	java/lang/Exception
    //   68	244	247	java/lang/Exception
    //   262	425	247	java/lang/Exception
    //   479	905	247	java/lang/Exception
    //   425	441	908	finally
    //   441	479	930	finally
  }
}

/* Location:           C:\Users\sandrocheng.21KUNPENG\Desktop\classes_dex2jar\
 * Qualified Name:     com.keniu.security.f.w
 * JD-Core Version:    0.6.2
 */